Workbook
Name DATA: [1]SO_QUY!$B$10:$I$46
Name DMNV: '[1]DMNV '!$A$4:$G$23
Name DSCBNV: '[2]Du lieu'!$AA$5:$AA$18
Name du_an: '[3]Không xóa'!$E$5:$E$9
Name Gio_cong_tieu_chuan: '[4]Du lieu'!$P$4:$S$4
Name he_so: '[4]Du lieu'!$E$4:$E$7
Name Ho_ten: '[5]Du lieu'!$AA$5:$AA$18
Name Lam_sach: '[6]khong xoa'!$A$1:$A$12

Sheet Data
E1: SỔ QUỸ NỘI BỘ | K1: Updated by: | L1: Nga.tt
K2: Date: | L2: =TODAY() -> 44882
A3: Số hiệu chứng từ | B3: Ngày | C3: Người nhận or nộp tiền | D3: Tên khách hàng/ nhà thầu | E3: Diễn giải | F3: Mã dự án | G3: Phân loại chứng từ | H3: Mã khoản tiền | I3: Hình thức Thu / Chi | J3: Số tiền Amount | L3: Ghi chú | N3: Đối chiếu
B4: Date | C4: Recipients or payers | D4: Client's name/ Contractor's name | E4: Items | F4: Project's code | G4: Thuế (TAX) / Nội bộ (Internal) | H4: Value Code | I4: Cash/ BIDV/ TCB/ I-TCB | J4: Thu Value of receiving | K4: Chi Value of payment | L4: Remarks | N4: Tiền mặt

Sheet Report
H1: BÁO CÁO TÌNH HÌNH THU CHI QUỸ NỘI BỘ | Q1: Prepared by Thuong.dt
A2: Ghi chú: Thống kê số liệu 12 tháng gần nhất | P2: Updated | Q2: =TODAY() -> 44882
A3: Phân loại Classification | C3: Mã Code | D3: =EOMONTH($Q$2,-11) -> 44561 | E3: =EOMONTH($Q$2,-10) -> 44592 | F3: =EOMONTH($Q$2,-9) -> 44620 | G3: =EOMONTH($Q$2,-8) -> 44651 | H3: =EOMONTH($Q$2,-7) -> 44681 | I3: =EOMONTH($Q$2,-6) -> 44712 | J3: =EOMONTH($Q$2,-5) -> 44742 | K3: =EOMONTH($Q$2,-4) -> 44773 | L3: =EOMONTH($Q$2,-3) -> 44804 | M3: =EOMONTH($Q$2,-2) -> 44834 | N3: =EOMONTH($Q$2,-1) -> 44865 | O3: =EOMONTH($Q$2,0) -> 44895 | P3: Total | Q3: Tỉ lệ %
A4: Công thức trung gian lọc ra năm | D4: =YEAR(D3) -> 2021 | E4: =YEAR(E3) -> 2022 | F4: =YEAR(F3) -> 2022 | G4: =YEAR(G3) -> 2022 | H4: =YEAR(H3) -> 2022 | I4: =YEAR(I3) -> 2022 | J4: =YEAR(J3) -> 2022 | K4: =YEAR(K3) -> 2022 | ... O4: =YEAR(O3) -> 2022
A5: Công thức trung gian lọc ra tháng | D5: =MONTH(D3) -> 12 | E5: =MONTH(E3) -> 1 | F5: =MONTH(F3) -> 2 | G5: =MONTH(G3) -> 3 | H5: =MONTH(H3) -> 4 | I5: =MONTH(I3) -> 5 | J5: =MONTH(J3) -> 6 | K5: =MONTH(K3) -> 7 | ... O5: =MONTH(O3) -> 11
A6: Công thức trung gian lọc ra ngày | D6: =DAY(D3) -> 31 | E6: =DAY(E3) -> 31 | F6: =DAY(F3) -> 28 | G6: =DAY(G3) -> 31 | H6: =DAY(H3) -> 30 | I6: =DAY(I3) -> 31 | J6: =DAY(J3) -> 30 | K6: =DAY(K3) -> 31 | ... N6: =DAY(N3) -> 31 | O6: =DAY(Q2) -> 17
A7: Tổng tiền thu: | D7: =SUMIFS(Data!$J:$J,Data!$B:$B,">="&DATE(D4,D5,1),Data!$B:$B,"<="&DATE(D4,D5,D6)) -> 0 | E7: =SUMIFS(Data!$J:$J,Data!$B:$B,">"&DATE(D4,D5,D6),Data!$B:$B,"<="&DATE(E4,E5,E6)) -> 0 | F7: =SUMIFS(Data!$J:$J,Data!$B:$B,">"&DATE(E4,E5,E6),Data!$B:$B,"<="&DATE(F4,F5,F6)) -> 0 | G7: =SUMIFS(Data!$J:$J,Data!$B:$B,">"&DATE(F4,F5,F6),Data!$B:$B,"<="&DATE(G4,G5,G6)) -> 0 | H7: =SUMIFS(Data!$J:$J,Data!$B:$B,">"&DATE(G4,G5,G6),Data!$B:$B,"<="&DATE(H4,H5,H6)) -> 0 | I7: =SUMIFS(Data!$J:$J,Data!$B:$B,">"&DATE(H4,H5,H6),Data!$B:$B,"<="&DATE(I4,I5,I6)) -> 0 | J7: =SUMIFS(Data!$J:$J,Data!$B:$B,">"&DATE(I4,I5,I6),Data!$B:$B,"<="&DATE(J4,J5,J6)) -> 0 | K7: =SUMIFS(Data!$J:$J,Data!$B:$B,">"&DATE(J4,J5,J6),Data!$B:$B,"<="&DATE(K4,K5,K6)) -> 0 | L7: =SUMIFS(Data!$J:$J,Data!$B:$B,">"&DATE(K4,K5,K6),Data!$B:$B,"<="&DATE(L4,L5,L6)) -> 0 | ... O7: =SUMIFS(Data!$J:$J,Data!$B:$B,">"&DATE(N4,N5,N6),Data!$B:$B,"<="&DATE(O4,O5,O6)) -> 0 | P7: =SUM(D7:O7) -> 0 | Q7: 1
B8: =Classification!A28 -> Tiền mặt quỹ | C8: =Classification!C28 -> Cash | D8: =SUMIFS(Data!$J:$J,Data!$B:$B,">="&DATE(D4,D5,1),Data!$B:$B,"<="&DATE(D4,D5,D6),Data!$I:$I,$C$8) -> 0 | E8: =SUMIFS(Data!$J:$J,Data!$B:$B,">="&DATE(E4,E5,1),Data!$B:$B,"<="&DATE(E4,E5,E6),Data!$I:$I,$C8) -> 0 | F8: =SUMIFS(Data!$J:$J,Data!$B:$B,">="&DATE(F4,F5,1),Data!$B:$B,"<="&DATE(F4,F5,F6),Data!$I:$I,$C8) -> 0 | G8: =SUMIFS(Data!$J:$J,Data!$B:$B,">="&DATE(G4,G5,1),Data!$B:$B,"<="&DATE(G4,G5,G6),Data!$I:$I,$C8) -> 0 | H8: =SUMIFS(Data!$J:$J,Data!$B:$B,">="&DATE(H4,H5,1),Data!$B:$B,"<="&DATE(H4,H5,H6),Data!$I:$I,$C8) -> 0 | I8: =SUMIFS(Data!$J:$J,Data!$B:$B,">="&DATE(I4,I5,1),Data!$B:$B,"<="&DATE(I4,I5,I6),Data!$I:$I,$C8) -> 0 | J8: =SUMIFS(Data!$J:$J,Data!$B:$B,">="&DATE(J4,J5,1),Data!$B:$B,"<="&DATE(J4,J5,J6),Data!$I:$I,$C8) -> 0 | K8: =SUMIFS(Data!$J:$J,Data!$B:$B,">="&DATE(K4,K5,1),Data!$B:$B,"<="&DATE(K4,K5,K6),Data!$I:$I,$C8) -> 0 | L8: =SUMIFS(Data!$J:$J,Data!$B:$B,">="&DATE(L4,L5,1),Data!$B:$B,"<="&DATE(L4,L5,L6),Data!$I:$I,$C8) -> 0 | ... O8: =SUMIFS(Data!$J:$J,Data!$B:$B,">="&DATE(O4,O5,1),Data!$B:$B,"<="&DATE(O4,O5,O6),Data!$I:$I,$C8) -> 0 | P8: =SUM(D8:O8) -> 0 | Q8: =P8/$P$7 -> #DIV/0!
B9: =Classification!A29 -> Ngân hàng nội bộ | C9: =Classification!C29 -> I-TCB | D9: =SUMIFS(Data!$J:$J,Data!$B:$B,">="&DATE(D4,D5,1),Data!$B:$B,"<="&DATE(D4,D5,D6),Data!$I:$I,$C$9) -> 0 | E9: =SUMIFS(Data!$J:$J,Data!$B:$B,">="&DATE(E4,E5,1),Data!$B:$B,"<="&DATE(E4,E5,E6),Data!$I:$I,$C9) -> 0 | F9: =SUMIFS(Data!$J:$J,Data!$B:$B,">="&DATE(F4,F5,1),Data!$B:$B,"<="&DATE(F4,F5,F6),Data!$I:$I,$C9) -> 0 | G9: =SUMIFS(Data!$J:$J,Data!$B:$B,">="&DATE(G4,G5,1),Data!$B:$B,"<="&DATE(G4,G5,G6),Data!$I:$I,$C9) -> 0 | H9: =SUMIFS(Data!$J:$J,Data!$B:$B,">="&DATE(H4,H5,1),Data!$B:$B,"<="&DATE(H4,H5,H6),Data!$I:$I,$C9) -> 0 | I9: =SUMIFS(Data!$J:$J,Data!$B:$B,">="&DATE(I4,I5,1),Data!$B:$B,"<="&DATE(I4,I5,I6),Data!$I:$I,$C9) -> 0 | J9: =SUMIFS(Data!$J:$J,Data!$B:$B,">="&DATE(J4,J5,1),Data!$B:$B,"<="&DATE(J4,J5,J6),Data!$I:$I,$C9) -> 0 | K9: =SUMIFS(Data!$J:$J,Data!$B:$B,">="&DATE(K4,K5,1),Data!$B:$B,"<="&DATE(K4,K5,K6),Data!$I:$I,$C9) -> 0 | L9: =SUMIFS(Data!$J:$J,Data!$B:$B,">="&DATE(L4,L5,1),Data!$B:$B,"<="&DATE(L4,L5,L6),Data!$I:$I,$C9) -> 0 | ... O9: =SUMIFS(Data!$J:$J,Data!$B:$B,">="&DATE(O4,O5,1),Data!$B:$B,"<="&DATE(O4,O5,O6),Data!$I:$I,$C9) -> 0 | P9: =SUM(D9:O9) -> 0 | Q9: =P9/$P$7 -> #DIV/0!
A10: Tổng tiền chi: | D10: =SUMIFS(Data!$K:$K,Data!$B:$B,">="&DATE(D4,D5,1),Data!$B:$B,"<="&DATE(D4,D5,D6)) -> 0 | E10: =SUMIFS(Data!$K:$K,Data!$B:$B,">"&DATE(D4,D5,D6),Data!$B:$B,"<="&DATE(E4,E5,E6)) -> 0 | F10: =SUMIFS(Data!$K:$K,Data!$B:$B,">"&DATE(E4,E5,E6),Data!$B:$B,"<="&DATE(F4,F5,F6)) -> 0 | G10: =SUMIFS(Data!$K:$K,Data!$B:$B,">"&DATE(F4,F5,F6),Data!$B:$B,"<="&DATE(G4,G5,G6)) -> 0 | H10: =SUMIFS(Data!$K:$K,Data!$B:$B,">"&DATE(G4,G5,G6),Data!$B:$B,"<="&DATE(H4,H5,H6)) -> 0 | I10: =SUMIFS(Data!$K:$K,Data!$B:$B,">"&DATE(H4,H5,H6),Data!$B:$B,"<="&DATE(I4,I5,I6)) -> 0 | J10: =SUMIFS(Data!$K:$K,Data!$B:$B,">"&DATE(I4,I5,I6),Data!$B:$B,"<="&DATE(J4,J5,J6)) -> 0 | K10: =SUMIFS(Data!$K:$K,Data!$B:$B,">"&DATE(J4,J5,J6),Data!$B:$B,"<="&DATE(K4,K5,K6)) -> 0 | L10: =SUMIFS(Data!$K:$K,Data!$B:$B,">"&DATE(K4,K5,K6),Data!$B:$B,"<="&DATE(L4,L5,L6)) -> 0 | ... O10: =SUMIFS(Data!$K:$K,Data!$B:$B,">"&DATE(N4,N5,N6),Data!$B:$B,"<="&DATE(O4,O5,O6)) -> 0 | P10: =SUM(D10:O10) -> 0 | Q10: 1
B11: Chi tiền mặt | C11: =Classification!C28 -> Cash | D11: =SUMIFS(Data!$K:$K,Data!$B:$B,">="&DATE(D4,D5,1),Data!$B:$B,"<="&DATE(D4,D5,D6),Data!$I:$I,$C$11) -> 0 | E11: =SUMIFS(Data!$K:$K,Data!$B:$B,">="&DATE(E4,E5,1),Data!$B:$B,"<="&DATE(E4,E5,E6),Data!$I:$I,$C$11) -> 0 | F11: =SUMIFS(Data!$K:$K,Data!$B:$B,">="&DATE(F4,F5,1),Data!$B:$B,"<="&DATE(F4,F5,F6),Data!$I:$I,$C$11) -> 0 | G11: =SUMIFS(Data!$K:$K,Data!$B:$B,">="&DATE(G4,G5,1),Data!$B:$B,"<="&DATE(G4,G5,G6),Data!$I:$I,$C$11) -> 0 | H11: =SUMIFS(Data!$K:$K,Data!$B:$B,">="&DATE(H4,H5,1),Data!$B:$B,"<="&DATE(H4,H5,H6),Data!$I:$I,$C$11) -> 0 | I11: =SUMIFS(Data!$K:$K,Data!$B:$B,">="&DATE(I4,I5,1),Data!$B:$B,"<="&DATE(I4,I5,I6),Data!$I:$I,$C$11) -> 0 | J11: =SUMIFS(Data!$K:$K,Data!$B:$B,">="&DATE(J4,J5,1),Data!$B:$B,"<="&DATE(J4,J5,J6),Data!$I:$I,$C$11) -> 0 | K11: =SUMIFS(Data!$K:$K,Data!$B:$B,">="&DATE(K4,K5,1),Data!$B:$B,"<="&DATE(K4,K5,K6),Data!$I:$I,$C$11) -> 0 | ... O11: =SUMIFS(Data!$K:$K,Data!$B:$B,">="&DATE(O4,O5,1),Data!$B:$B,"<="&DATE(O4,O5,O6),Data!$I:$I,$C$11) -> 0 | P11: =SUM(D11:O11) -> 0 | Q11: =P11/$P$10 -> #DIV/0!
B12: Chi chuyển khoản | C12: =Classification!C29 -> I-TCB | D12: =SUMIFS(Data!$K:$K,Data!$B:$B,">="&DATE(D4,D5,1),Data!$B:$B,"<="&DATE(D4,D5,D6),Data!$I:$I,$C$12) -> 0 | E12: =SUMIFS(Data!$K:$K,Data!$B:$B,">="&DATE(E4,E5,1),Data!$B:$B,"<="&DATE(E4,E5,E6),Data!$I:$I,$C$12) -> 0 | F12: =SUMIFS(Data!$K:$K,Data!$B:$B,">="&DATE(F4,F5,1),Data!$B:$B,"<="&DATE(F4,F5,F6),Data!$I:$I,$C$12) -> 0 | G12: =SUMIFS(Data!$K:$K,Data!$B:$B,">="&DATE(G4,G5,1),Data!$B:$B,"<="&DATE(G4,G5,G6),Data!$I:$I,$C$12) -> 0 | H12: =SUMIFS(Data!$K:$K,Data!$B:$B,">="&DATE(H4,H5,1),Data!$B:$B,"<="&DATE(H4,H5,H6),Data!$I:$I,$C$12) -> 0 | I12: =SUMIFS(Data!$K:$K,Data!$B:$B,">="&DATE(I4,I5,1),Data!$B:$B,"<="&DATE(I4,I5,I6),Data!$I:$I,$C$12) -> 0 | J12: =SUMIFS(Data!$K:$K,Data!$B:$B,">="&DATE(J4,J5,1),Data!$B:$B,"<="&DATE(J4,J5,J6),Data!$I:$I,$C$12) -> 0 | K12: =SUMIFS(Data!$K:$K,Data!$B:$B,">="&DATE(K4,K5,1),Data!$B:$B,"<="&DATE(K4,K5,K6),Data!$I:$I,$C$12) -> 0 | ... O12: =SUMIFS(Data!$K:$K,Data!$B:$B,">="&DATE(O4,O5,1),Data!$B:$B,"<="&DATE(O4,O5,O6),Data!$I:$I,$C$12) -> 0 | P12: =SUM(D12:O12) -> 0 | Q12: =P12/$P$10 -> #DIV/0!
B13: Các khoản chi có HĐ | C13: =Classification!C25 -> TAX | D13: =SUMIFS(Data!$K:$K,Data!$B:$B,">="&DATE(D4,D5,1),Data!$B:$B,"<="&DATE(D4,D5,D6),Data!$G:$G,$C$13) -> 0 | E13: =SUMIFS(Data!$K:$K,Data!$B:$B,">="&DATE(E4,E5,1),Data!$B:$B,"<="&DATE(E4,E5,E6),Data!$G:$G,$C$13) -> 0 | F13: =SUMIFS(Data!$K:$K,Data!$B:$B,">="&DATE(F4,F5,1),Data!$B:$B,"<="&DATE(F4,F5,F6),Data!$G:$G,$C$13) -> 0 | G13: =SUMIFS(Data!$K:$K,Data!$B:$B,">="&DATE(G4,G5,1),Data!$B:$B,"<="&DATE(G4,G5,G6),Data!$G:$G,$C$13) -> 0 | H13: =SUMIFS(Data!$K:$K,Data!$B:$B,">="&DATE(H4,H5,1),Data!$B:$B,"<="&DATE(H4,H5,H6),Data!$G:$G,$C$13) -> 0 | I13: =SUMIFS(Data!$K:$K,Data!$B:$B,">="&DATE(I4,I5,1),Data!$B:$B,"<="&DATE(I4,I5,I6),Data!$G:$G,$C$13) -> 0 | J13: =SUMIFS(Data!$K:$K,Data!$B:$B,">="&DATE(J4,J5,1),Data!$B:$B,"<="&DATE(J4,J5,J6),Data!$G:$G,$C$13) -> 0 | K13: =SUMIFS(Data!$K:$K,Data!$B:$B,">="&DATE(K4,K5,1),Data!$B:$B,"<="&DATE(K4,K5,K6),Data!$G:$G,$C$13) -> 0 | ... O13: =SUMIFS(Data!$K:$K,Data!$B:$B,">="&DATE(O4,O5,1),Data!$B:$B,"<="&DATE(O4,O5,O6),Data!$G:$G,$C$13) -> 0 | P13: =SUM(D13:O13) -> 0 | Q13: =P13/$P$10 -> #DIV/0!
B14: Các khoản chi không có HĐ | C14: =Classification!C26 -> Internal | D14: =SUMIFS(Data!$K:$K,Data!$B:$B,">="&DATE(D4,D5,1),Data!$B:$B,"<="&DATE(D4,D5,D6),Data!$G:$G,$C$14) -> 0 | E14: =SUMIFS(Data!$K:$K,Data!$B:$B,">="&DATE(E4,E5,1),Data!$B:$B,"<="&DATE(E4,E5,E6),Data!$G:$G,$C$14) -> 0 | F14: =SUMIFS(Data!$K:$K,Data!$B:$B,">="&DATE(F4,F5,1),Data!$B:$B,"<="&DATE(F4,F5,F6),Data!$G:$G,$C$14) -> 0 | G14: =SUMIFS(Data!$K:$K,Data!$B:$B,">="&DATE(G4,G5,1),Data!$B:$B,"<="&DATE(G4,G5,G6),Data!$G:$G,$C$14) -> 0 | H14: =SUMIFS(Data!$K:$K,Data!$B:$B,">="&DATE(H4,H5,1),Data!$B:$B,"<="&DATE(H4,H5,H6),Data!$G:$G,$C$14) -> 0 | I14: =SUMIFS(Data!$K:$K,Data!$B:$B,">="&DATE(I4,I5,1),Data!$B:$B,"<="&DATE(I4,I5,I6),Data!$G:$G,$C$14) -> 0 | J14: =SUMIFS(Data!$K:$K,Data!$B:$B,">="&DATE(J4,J5,1),Data!$B:$B,"<="&DATE(J4,J5,J6),Data!$G:$G,$C$14) -> 0 | K14: =SUMIFS(Data!$K:$K,Data!$B:$B,">="&DATE(K4,K5,1),Data!$B:$B,"<="&DATE(K4,K5,K6),Data!$G:$G,$C$14) -> 0 | ... O14: =SUMIFS(Data!$K:$K,Data!$B:$B,">="&DATE(O4,O5,1),Data!$B:$B,"<="&DATE(O4,O5,O6),Data!$G:$G,$C$14) -> 0 | P14: =SUM(D14:O14) -> 0 | Q14: =P14/$P$10 -> #DIV/0!
B15: =Classification!A10 -> Các khoản chi cho các dự án Bảo trì & Dịch vụ | C15: =Classification!C10 -> MS | D15: =SUMIFS(Data!$K:$K,Data!$B:$B,">="&DATE(D$4,D$5,1),Data!$B:$B,"<="&DATE(D$4,D$5,D$6),Data!$G:$G,$C$14,Data!$H:$H,$C15) -> 0 | E15: =SUMIFS(Data!$K:$K,Data!$B:$B,">="&DATE(E$4,E$5,1),Data!$B:$B,"<="&DATE(E$4,E$5,E$6),Data!$G:$G,$C$14,Data!$H:$H,$C15) -> 0 | F15: =SUMIFS(Data!$K:$K,Data!$B:$B,">="&DATE(F$4,F$5,1),Data!$B:$B,"<="&DATE(F$4,F$5,F$6),Data!$G:$G,$C$14,Data!$H:$H,$C15) -> 0 | G15: =SUMIFS(Data!$K:$K,Data!$B:$B,">="&DATE(G$4,G$5,1),Data!$B:$B,"<="&DATE(G$4,G$5,G$6),Data!$G:$G,$C$14,Data!$H:$H,$C15) -> 0 | H15: =SUMIFS(Data!$K:$K,Data!$B:$B,">="&DATE(H$4,H$5,1),Data!$B:$B,"<="&DATE(H$4,H$5,H$6),Data!$G:$G,$C$14,Data!$H:$H,$C15) -> 0 | I15: =SUMIFS(Data!$K:$K,Data!$B:$B,">="&DATE(I$4,I$5,1),Data!$B:$B,"<="&DATE(I$4,I$5,I$6),Data!$G:$G,$C$14,Data!$H:$H,$C15) -> 0 | J15: =SUMIFS(Data!$K:$K,Data!$B:$B,">="&DATE(J$4,J$5,1),Data!$B:$B,"<="&DATE(J$4,J$5,J$6),Data!$G:$G,$C$14,Data!$H:$H,$C15) -> 0 | K15: =SUMIFS(Data!$K:$K,Data!$B:$B,">="&DATE(K$4,K$5,1),Data!$B:$B,"<="&DATE(K$4,K$5,K$6),Data!$G:$G,$C$14,Data!$H:$H,$C15) -> 0 | ... O15: =SUMIFS(Data!$K:$K,Data!$B:$B,">="&DATE(O$4,O$5,1),Data!$B:$B,"<="&DATE(O$4,O$5,O$6),Data!$G:$G,$C$14,Data!$H:$H,$C15) -> 0 | P15: =SUM(D15:O15) -> 0 | Q15: =P15/($P$13+$P$14) -> #DIV/0!
B16: =Classification!A11 -> Các khoản chi liên quan tới dự án vận hành tòa nhà | C16: =Classification!C11 -> FM | D16: =SUMIFS(Data!$K:$K,Data!$B:$B,">="&DATE(D$4,D$5,1),Data!$B:$B,"<="&DATE(D$4,D$5,D$6),Data!$G:$G,$C$14,Data!$H:$H,$C16) -> 0 | E16: =SUMIFS(Data!$K:$K,Data!$B:$B,">="&DATE(E$4,E$5,1),Data!$B:$B,"<="&DATE(E$4,E$5,E$6),Data!$G:$G,$C$14,Data!$H:$H,$C16) -> 0 | F16: =SUMIFS(Data!$K:$K,Data!$B:$B,">="&DATE(F$4,F$5,1),Data!$B:$B,"<="&DATE(F$4,F$5,F$6),Data!$G:$G,$C$14,Data!$H:$H,$C16) -> 0 | G16: =SUMIFS(Data!$K:$K,Data!$B:$B,">="&DATE(G$4,G$5,1),Data!$B:$B,"<="&DATE(G$4,G$5,G$6),Data!$G:$G,$C$14,Data!$H:$H,$C16) -> 0 | H16: =SUMIFS(Data!$K:$K,Data!$B:$B,">="&DATE(H$4,H$5,1),Data!$B:$B,"<="&DATE(H$4,H$5,H$6),Data!$G:$G,$C$14,Data!$H:$H,$C16) -> 0 | I16: =SUMIFS(Data!$K:$K,Data!$B:$B,">="&DATE(I$4,I$5,1),Data!$B:$B,"<="&DATE(I$4,I$5,I$6),Data!$G:$G,$C$14,Data!$H:$H,$C16) -> 0 | J16: =SUMIFS(Data!$K:$K,Data!$B:$B,">="&DATE(J$4,J$5,1),Data!$B:$B,"<="&DATE(J$4,J$5,J$6),Data!$G:$G,$C$14,Data!$H:$H,$C16) -> 0 | K16: =SUMIFS(Data!$K:$K,Data!$B:$B,">="&DATE(K$4,K$5,1),Data!$B:$B,"<="&DATE(K$4,K$5,K$6),Data!$G:$G,$C$14,Data!$H:$H,$C16) -> 0 | ... O16: =SUMIFS(Data!$K:$K,Data!$B:$B,">="&DATE(O$4,O$5,1),Data!$B:$B,"<="&DATE(O$4,O$5,O$6),Data!$G:$G,$C$14,Data!$H:$H,$C16) -> 0 | P16: =SUM(D16:O16) -> 0 | Q16: =P16/($P$13+$P$14) -> #DIV/0!
B17: =Classification!A15 -> Lương nhân viên & BHXH, BHYT, đồng phục, giày, trợ cấp điện thoại | C17: =Classification!C15 -> LC | D17: =SUMIFS(Data!$K:$K,Data!$B:$B,">="&DATE(D$4,D$5,1),Data!$B:$B,"<="&DATE(D$4,D$5,D$6),Data!$G:$G,$C$14,Data!$H:$H,$C17) -> 0 | E17: =SUMIFS(Data!$K:$K,Data!$B:$B,">="&DATE(E$4,E$5,1),Data!$B:$B,"<="&DATE(E$4,E$5,E$6),Data!$G:$G,$C$14,Data!$H:$H,$C17) -> 0 | F17: =SUMIFS(Data!$K:$K,Data!$B:$B,">="&DATE(F$4,F$5,1),Data!$B:$B,"<="&DATE(F$4,F$5,F$6),Data!$G:$G,$C$14,Data!$H:$H,$C17) -> 0 | G17: =SUMIFS(Data!$K:$K,Data!$B:$B,">="&DATE(G$4,G$5,1),Data!$B:$B,"<="&DATE(G$4,G$5,G$6),Data!$G:$G,$C$14,Data!$H:$H,$C17) -> 0 | H17: =SUMIFS(Data!$K:$K,Data!$B:$B,">="&DATE(H$4,H$5,1),Data!$B:$B,"<="&DATE(H$4,H$5,H$6),Data!$G:$G,$C$14,Data!$H:$H,$C17) -> 0 | I17: =SUMIFS(Data!$K:$K,Data!$B:$B,">="&DATE(I$4,I$5,1),Data!$B:$B,"<="&DATE(I$4,I$5,I$6),Data!$G:$G,$C$14,Data!$H:$H,$C17) -> 0 | J17: =SUMIFS(Data!$K:$K,Data!$B:$B,">="&DATE(J$4,J$5,1),Data!$B:$B,"<="&DATE(J$4,J$5,J$6),Data!$G:$G,$C$14,Data!$H:$H,$C17) -> 0 | K17: =SUMIFS(Data!$K:$K,Data!$B:$B,">="&DATE(K$4,K$5,1),Data!$B:$B,"<="&DATE(K$4,K$5,K$6),Data!$G:$G,$C$14,Data!$H:$H,$C17) -> 0 | ... O17: =SUMIFS(Data!$K:$K,Data!$B:$B,">="&DATE(O$4,O$5,1),Data!$B:$B,"<="&DATE(O$4,O$5,O$6),Data!$G:$G,$C$14,Data!$H:$H,$C17) -> 0 | P17: =SUM(D17:O17) -> 0 | Q17: =P17/($P$13+$P$14) -> #DIV/0!
B18: =Classification!A16 -> Chi phí quan hệ khách hàng | C18: =Classification!C16 -> CR | D18: =SUMIFS(Data!$K:$K,Data!$B:$B,">="&DATE(D$4,D$5,1),Data!$B:$B,"<="&DATE(D$4,D$5,D$6),Data!$G:$G,$C$14,Data!$H:$H,$C18) -> 0 | E18: =SUMIFS(Data!$K:$K,Data!$B:$B,">="&DATE(E$4,E$5,1),Data!$B:$B,"<="&DATE(E$4,E$5,E$6),Data!$G:$G,$C$14,Data!$H:$H,$C18) -> 0 | F18: =SUMIFS(Data!$K:$K,Data!$B:$B,">="&DATE(F$4,F$5,1),Data!$B:$B,"<="&DATE(F$4,F$5,F$6),Data!$G:$G,$C$14,Data!$H:$H,$C18) -> 0 | G18: =SUMIFS(Data!$K:$K,Data!$B:$B,">="&DATE(G$4,G$5,1),Data!$B:$B,"<="&DATE(G$4,G$5,G$6),Data!$G:$G,$C$14,Data!$H:$H,$C18) -> 0 | H18: =SUMIFS(Data!$K:$K,Data!$B:$B,">="&DATE(H$4,H$5,1),Data!$B:$B,"<="&DATE(H$4,H$5,H$6),Data!$G:$G,$C$14,Data!$H:$H,$C18) -> 0 | I18: =SUMIFS(Data!$K:$K,Data!$B:$B,">="&DATE(I$4,I$5,1),Data!$B:$B,"<="&DATE(I$4,I$5,I$6),Data!$G:$G,$C$14,Data!$H:$H,$C18) -> 0 | J18: =SUMIFS(Data!$K:$K,Data!$B:$B,">="&DATE(J$4,J$5,1),Data!$B:$B,"<="&DATE(J$4,J$5,J$6),Data!$G:$G,$C$14,Data!$H:$H,$C18) -> 0 | K18: =SUMIFS(Data!$K:$K,Data!$B:$B,">="&DATE(K$4,K$5,1),Data!$B:$B,"<="&DATE(K$4,K$5,K$6),Data!$G:$G,$C$14,Data!$H:$H,$C18) -> 0 | ... O18: =SUMIFS(Data!$K:$K,Data!$B:$B,">="&DATE(O$4,O$5,1),Data!$B:$B,"<="&DATE(O$4,O$5,O$6),Data!$G:$G,$C$14,Data!$H:$H,$C18) -> 0 | P18: =SUM(D18:O18) -> 0 | Q18: =P18/($P$13+$P$14) -> #DIV/0!
B19: =Classification!A17 -> Vật tư tiêu hao dùng chung | C19: =Classification!C17 -> GC | D19: =SUMIFS(Data!$K:$K,Data!$B:$B,">="&DATE(D$4,D$5,1),Data!$B:$B,"<="&DATE(D$4,D$5,D$6),Data!$G:$G,$C$14,Data!$H:$H,$C19) -> 0 | E19: =SUMIFS(Data!$K:$K,Data!$B:$B,">="&DATE(E$4,E$5,1),Data!$B:$B,"<="&DATE(E$4,E$5,E$6),Data!$G:$G,$C$14,Data!$H:$H,$C19) -> 0 | F19: =SUMIFS(Data!$K:$K,Data!$B:$B,">="&DATE(F$4,F$5,1),Data!$B:$B,"<="&DATE(F$4,F$5,F$6),Data!$G:$G,$C$14,Data!$H:$H,$C19) -> 0 | G19: =SUMIFS(Data!$K:$K,Data!$B:$B,">="&DATE(G$4,G$5,1),Data!$B:$B,"<="&DATE(G$4,G$5,G$6),Data!$G:$G,$C$14,Data!$H:$H,$C19) -> 0 | H19: =SUMIFS(Data!$K:$K,Data!$B:$B,">="&DATE(H$4,H$5,1),Data!$B:$B,"<="&DATE(H$4,H$5,H$6),Data!$G:$G,$C$14,Data!$H:$H,$C19) -> 0 | I19: =SUMIFS(Data!$K:$K,Data!$B:$B,">="&DATE(I$4,I$5,1),Data!$B:$B,"<="&DATE(I$4,I$5,I$6),Data!$G:$G,$C$14,Data!$H:$H,$C19) -> 0 | J19: =SUMIFS(Data!$K:$K,Data!$B:$B,">="&DATE(J$4,J$5,1),Data!$B:$B,"<="&DATE(J$4,J$5,J$6),Data!$G:$G,$C$14,Data!$H:$H,$C19) -> 0 | K19: =SUMIFS(Data!$K:$K,Data!$B:$B,">="&DATE(K$4,K$5,1),Data!$B:$B,"<="&DATE(K$4,K$5,K$6),Data!$G:$G,$C$14,Data!$H:$H,$C19) -> 0 | ... O19: =SUMIFS(Data!$K:$K,Data!$B:$B,">="&DATE(O$4,O$5,1),Data!$B:$B,"<="&DATE(O$4,O$5,O$6),Data!$G:$G,$C$14,Data!$H:$H,$C19) -> 0 | P19: =SUM(D19:O19) -> 0 | Q19: =P19/($P$13+$P$14) -> #DIV/0!
B20: =Classification!A18 -> Tài sản, công cụ dụng cụ, máy tính, trang thiết bị văn phòng, trang bị an toàn (mũ, kính, đai an toàn…) | C20: =Classification!C18 -> AT | D20: =SUMIFS(Data!$K:$K,Data!$B:$B,">="&DATE(D$4,D$5,1),Data!$B:$B,"<="&DATE(D$4,D$5,D$6),Data!$G:$G,$C$14,Data!$H:$H,$C20) -> 0 | E20: =SUMIFS(Data!$K:$K,Data!$B:$B,">="&DATE(E$4,E$5,1),Data!$B:$B,"<="&DATE(E$4,E$5,E$6),Data!$G:$G,$C$14,Data!$H:$H,$C20) -> 0 | F20: =SUMIFS(Data!$K:$K,Data!$B:$B,">="&DATE(F$4,F$5,1),Data!$B:$B,"<="&DATE(F$4,F$5,F$6),Data!$G:$G,$C$14,Data!$H:$H,$C20) -> 0 | G20: =SUMIFS(Data!$K:$K,Data!$B:$B,">="&DATE(G$4,G$5,1),Data!$B:$B,"<="&DATE(G$4,G$5,G$6),Data!$G:$G,$C$14,Data!$H:$H,$C20) -> 0 | H20: =SUMIFS(Data!$K:$K,Data!$B:$B,">="&DATE(H$4,H$5,1),Data!$B:$B,"<="&DATE(H$4,H$5,H$6),Data!$G:$G,$C$14,Data!$H:$H,$C20) -> 0 | I20: =SUMIFS(Data!$K:$K,Data!$B:$B,">="&DATE(I$4,I$5,1),Data!$B:$B,"<="&DATE(I$4,I$5,I$6),Data!$G:$G,$C$14,Data!$H:$H,$C20) -> 0 | J20: =SUMIFS(Data!$K:$K,Data!$B:$B,">="&DATE(J$4,J$5,1),Data!$B:$B,"<="&DATE(J$4,J$5,J$6),Data!$G:$G,$C$14,Data!$H:$H,$C20) -> 0 | K20: =SUMIFS(Data!$K:$K,Data!$B:$B,">="&DATE(K$4,K$5,1),Data!$B:$B,"<="&DATE(K$4,K$5,K$6),Data!$G:$G,$C$14,Data!$H:$H,$C20) -> 0 | ... O20: =SUMIFS(Data!$K:$K,Data!$B:$B,">="&DATE(O$4,O$5,1),Data!$B:$B,"<="&DATE(O$4,O$5,O$6),Data!$G:$G,$C$14,Data!$H:$H,$C20) -> 0 | P20: =SUM(D20:O20) -> 0 | Q20: =P20/($P$13+$P$14) -> #DIV/0!
B21: =Classification!A19 -> Chi phí quản lý: Chi phí văn phòng, phí ngân hàng, tiếp khách, liên hoan, bảo hiểm TNNN, tai nạn… | C21: =Classification!C19 -> OH | D21: =SUMIFS(Data!$K:$K,Data!$B:$B,">="&DATE(D$4,D$5,1),Data!$B:$B,"<="&DATE(D$4,D$5,D$6),Data!$G:$G,$C$14,Data!$H:$H,$C21) -> 0 | E21: =SUMIFS(Data!$K:$K,Data!$B:$B,">="&DATE(E$4,E$5,1),Data!$B:$B,"<="&DATE(E$4,E$5,E$6),Data!$G:$G,$C$14,Data!$H:$H,$C21) -> 0 | F21: =SUMIFS(Data!$K:$K,Data!$B:$B,">="&DATE(F$4,F$5,1),Data!$B:$B,"<="&DATE(F$4,F$5,F$6),Data!$G:$G,$C$14,Data!$H:$H,$C21) -> 0 | G21: =SUMIFS(Data!$K:$K,Data!$B:$B,">="&DATE(G$4,G$5,1),Data!$B:$B,"<="&DATE(G$4,G$5,G$6),Data!$G:$G,$C$14,Data!$H:$H,$C21) -> 0 | H21: =SUMIFS(Data!$K:$K,Data!$B:$B,">="&DATE(H$4,H$5,1),Data!$B:$B,"<="&DATE(H$4,H$5,H$6),Data!$G:$G,$C$14,Data!$H:$H,$C21) -> 0 | I21: =SUMIFS(Data!$K:$K,Data!$B:$B,">="&DATE(I$4,I$5,1),Data!$B:$B,"<="&DATE(I$4,I$5,I$6),Data!$G:$G,$C$14,Data!$H:$H,$C21) -> 0 | J21: =SUMIFS(Data!$K:$K,Data!$B:$B,">="&DATE(J$4,J$5,1),Data!$B:$B,"<="&DATE(J$4,J$5,J$6),Data!$G:$G,$C$14,Data!$H:$H,$C21) -> 0 | K21: =SUMIFS(Data!$K:$K,Data!$B:$B,">="&DATE(K$4,K$5,1),Data!$B:$B,"<="&DATE(K$4,K$5,K$6),Data!$G:$G,$C$14,Data!$H:$H,$C21) -> 0 | ... O21: =SUMIFS(Data!$K:$K,Data!$B:$B,">="&DATE(O$4,O$5,1),Data!$B:$B,"<="&DATE(O$4,O$5,O$6),Data!$G:$G,$C$14,Data!$H:$H,$C21) -> 0 | P21: =SUM(D21:O21) -> 0 | Q21: =P21/($P$13+$P$14) -> #DIV/0!
B22: =Classification!A22 -> XLHĐ | C22: =Classification!C22 -> IV | D22: =SUMIFS(Data!$K:$K,Data!$B:$B,">="&DATE(D$4,D$5,1),Data!$B:$B,"<="&DATE(D$4,D$5,D$6),Data!$G:$G,$C$14,Data!$H:$H,$C22) -> 0 | E22: =SUMIFS(Data!$K:$K,Data!$B:$B,">="&DATE(E$4,E$5,1),Data!$B:$B,"<="&DATE(E$4,E$5,E$6),Data!$G:$G,$C$14,Data!$H:$H,$C22) -> 0 | F22: =SUMIFS(Data!$K:$K,Data!$B:$B,">="&DATE(F$4,F$5,1),Data!$B:$B,"<="&DATE(F$4,F$5,F$6),Data!$G:$G,$C$14,Data!$H:$H,$C22) -> 0 | G22: =SUMIFS(Data!$K:$K,Data!$B:$B,">="&DATE(G$4,G$5,1),Data!$B:$B,"<="&DATE(G$4,G$5,G$6),Data!$G:$G,$C$14,Data!$H:$H,$C22) -> 0 | H22: =SUMIFS(Data!$K:$K,Data!$B:$B,">="&DATE(H$4,H$5,1),Data!$B:$B,"<="&DATE(H$4,H$5,H$6),Data!$G:$G,$C$14,Data!$H:$H,$C22) -> 0 | I22: =SUMIFS(Data!$K:$K,Data!$B:$B,">="&DATE(I$4,I$5,1),Data!$B:$B,"<="&DATE(I$4,I$5,I$6),Data!$G:$G,$C$14,Data!$H:$H,$C22) -> 0 | J22: =SUMIFS(Data!$K:$K,Data!$B:$B,">="&DATE(J$4,J$5,1),Data!$B:$B,"<="&DATE(J$4,J$5,J$6),Data!$G:$G,$C$14,Data!$H:$H,$C22) -> 0 | K22: =SUMIFS(Data!$K:$K,Data!$B:$B,">="&DATE(K$4,K$5,1),Data!$B:$B,"<="&DATE(K$4,K$5,K$6),Data!$G:$G,$C$14,Data!$H:$H,$C22) -> 0 | ... O22: =SUMIFS(Data!$K:$K,Data!$B:$B,">="&DATE(O$4,O$5,1),Data!$B:$B,"<="&DATE(O$4,O$5,O$6),Data!$G:$G,$C$14,Data!$H:$H,$C22) -> 0 | P22: =SUM(D22:O22) -> 0 | Q22: =P22/($P$13+$P$14) -> #DIV/0!
B23: =Classification!A23 -> Chuyển tiền giữa các TK, đổi tiền, chi mua bán hộ, vay/tạm ứng (có trả lại) … | C23: =Classification!C23 -> BA | D23: =SUMIFS(Data!$K:$K,Data!$B:$B,">="&DATE(D$4,D$5,1),Data!$B:$B,"<="&DATE(D$4,D$5,D$6),Data!$G:$G,$C$14,Data!$H:$H,$C23) -> 0 | E23: =SUMIFS(Data!$K:$K,Data!$B:$B,">="&DATE(E$4,E$5,1),Data!$B:$B,"<="&DATE(E$4,E$5,E$6),Data!$G:$G,$C$14,Data!$H:$H,$C23) -> 0 | F23: =SUMIFS(Data!$K:$K,Data!$B:$B,">="&DATE(F$4,F$5,1),Data!$B:$B,"<="&DATE(F$4,F$5,F$6),Data!$G:$G,$C$14,Data!$H:$H,$C23) -> 0 | G23: =SUMIFS(Data!$K:$K,Data!$B:$B,">="&DATE(G$4,G$5,1),Data!$B:$B,"<="&DATE(G$4,G$5,G$6),Data!$G:$G,$C$14,Data!$H:$H,$C23) -> 0 | H23: =SUMIFS(Data!$K:$K,Data!$B:$B,">="&DATE(H$4,H$5,1),Data!$B:$B,"<="&DATE(H$4,H$5,H$6),Data!$G:$G,$C$14,Data!$H:$H,$C23) -> 0 | I23: =SUMIFS(Data!$K:$K,Data!$B:$B,">="&DATE(I$4,I$5,1),Data!$B:$B,"<="&DATE(I$4,I$5,I$6),Data!$G:$G,$C$14,Data!$H:$H,$C23) -> 0 | J23: =SUMIFS(Data!$K:$K,Data!$B:$B,">="&DATE(J$4,J$5,1),Data!$B:$B,"<="&DATE(J$4,J$5,J$6),Data!$G:$G,$C$14,Data!$H:$H,$C23) -> 0 | K23: =SUMIFS(Data!$K:$K,Data!$B:$B,">="&DATE(K$4,K$5,1),Data!$B:$B,"<="&DATE(K$4,K$5,K$6),Data!$G:$G,$C$14,Data!$H:$H,$C23) -> 0 | ... O23: =SUMIFS(Data!$K:$K,Data!$B:$B,">="&DATE(O$4,O$5,1),Data!$B:$B,"<="&DATE(O$4,O$5,O$6),Data!$G:$G,$C$14,Data!$H:$H,$C23) -> 0 | P23: =SUM(D23:O23) -> 0 | Q23: =P23/($P$13+$P$14) -> #DIV/0!
A24: Tổng tiền còn tồn | D24: =D25+D26 -> 0 | E24: =E25+E26 -> 0 | F24: =F25+F26 -> 0 | G24: =G25+G26 -> 0 | H24: =H25+H26 -> 0 | I24: =I25+I26 -> 0 | J24: =J25+J26 -> 0 | K24: =K25+K26 -> 0 | ... O24: =O25+O26 -> 0 | P24: =O24 -> 0 | Q24: =P24/($P$13+$P$14) -> #DIV/0!
B25: =Classification!A28 -> Tiền mặt quỹ | C25: =Classification!C28 -> Cash | D25: =SUMIFS(Data!$J:$J,Data!$B:$B,"<="&DATE(D$4,D$5,D$6),Data!$I:$I,$C25)-SUMIFS(Data!$K:$K,Data!$B:$B,"<="&DATE(D$4,D$5,D$6),Data!$I:$I,$C25) -> 0 | E25: =SUMIFS(Data!$J:$J,Data!$B:$B,"<="&DATE(E4,E5,E6),Data!$I:$I,$C25)-SUMIFS(Data!$K:$K,Data!$B:$B,"<="&DATE(E4,E5,E6),Data!$I:$I,$C25) -> 0 | F25: =SUMIFS(Data!$J:$J,Data!$B:$B,"<="&DATE(F4,F5,F6),Data!$I:$I,$C25)-SUMIFS(Data!$K:$K,Data!$B:$B,"<="&DATE(F4,F5,F6),Data!$I:$I,$C25) -> 0 | G25: =SUMIFS(Data!$J:$J,Data!$B:$B,"<="&DATE(G4,G5,G6),Data!$I:$I,$C25)-SUMIFS(Data!$K:$K,Data!$B:$B,"<="&DATE(G4,G5,G6),Data!$I:$I,$C25) -> 0 | H25: =SUMIFS(Data!$J:$J,Data!$B:$B,"<="&DATE(H4,H5,H6),Data!$I:$I,$C25)-SUMIFS(Data!$K:$K,Data!$B:$B,"<="&DATE(H4,H5,H6),Data!$I:$I,$C25) -> 0 | I25: =SUMIFS(Data!$J:$J,Data!$B:$B,"<="&DATE(I4,I5,I6),Data!$I:$I,$C25)-SUMIFS(Data!$K:$K,Data!$B:$B,"<="&DATE(I4,I5,I6),Data!$I:$I,$C25) -> 0 | J25: =SUMIFS(Data!$J:$J,Data!$B:$B,"<="&DATE(J4,J5,J6),Data!$I:$I,$C25)-SUMIFS(Data!$K:$K,Data!$B:$B,"<="&DATE(J4,J5,J6),Data!$I:$I,$C25) -> 0 | K25: =SUMIFS(Data!$J:$J,Data!$B:$B,"<="&DATE(K4,K5,K6),Data!$I:$I,$C25)-SUMIFS(Data!$K:$K,Data!$B:$B,"<="&DATE(K4,K5,K6),Data!$I:$I,$C25) -> 0 | L25: =SUMIFS(Data!$J:$J,Data!$B:$B,"<="&DATE(L4,L5,L6),Data!$I:$I,$C25)-SUMIFS(Data!$K:$K,Data!$B:$B,"<="&DATE(L4,L5,L6),Data!$I:$I,$C25) -> 0 | ... O25: =SUMIFS(Data!$J:$J,Data!$B:$B,"<="&DATE(O4,O5,O6),Data!$I:$I,$C25)-SUMIFS(Data!$K:$K,Data!$B:$B,"<="&DATE(O4,O5,O6),Data!$I:$I,$C25) -> 0 | P25: =O25 -> 0
B26: =Classification!A29 -> Ngân hàng nội bộ | C26: =Classification!C29 -> I-TCB | D26: =SUMIFS(Data!$J:$J,Data!$B:$B,"<="&DATE(D$4,D$5,D$6),Data!$I:$I,$C26)-SUMIFS(Data!$K:$K,Data!$B:$B,"<="&DATE(D$4,D$5,D$6),Data!$I:$I,$C26) -> 0 | E26: =SUMIFS(Data!$J:$J,Data!$B:$B,"<="&DATE(E$4,E$5,E$6),Data!$I:$I,$C26)-SUMIFS(Data!$K:$K,Data!$B:$B,"<="&DATE(E$4,E$5,E$6),Data!$I:$I,$C26) -> 0 | F26: =SUMIFS(Data!$J:$J,Data!$B:$B,"<="&DATE(F$4,F$5,F$6),Data!$I:$I,$C26)-SUMIFS(Data!$K:$K,Data!$B:$B,"<="&DATE(F$4,F$5,F$6),Data!$I:$I,$C26) -> 0 | G26: =SUMIFS(Data!$J:$J,Data!$B:$B,"<="&DATE(G$4,G$5,G$6),Data!$I:$I,$C26)-SUMIFS(Data!$K:$K,Data!$B:$B,"<="&DATE(G$4,G$5,G$6),Data!$I:$I,$C26) -> 0 | H26: =SUMIFS(Data!$J:$J,Data!$B:$B,"<="&DATE(H$4,H$5,H$6),Data!$I:$I,$C26)-SUMIFS(Data!$K:$K,Data!$B:$B,"<="&DATE(H$4,H$5,H$6),Data!$I:$I,$C26) -> 0 | I26: =SUMIFS(Data!$J:$J,Data!$B:$B,"<="&DATE(I$4,I$5,I$6),Data!$I:$I,$C26)-SUMIFS(Data!$K:$K,Data!$B:$B,"<="&DATE(I$4,I$5,I$6),Data!$I:$I,$C26) -> 0 | J26: =SUMIFS(Data!$J:$J,Data!$B:$B,"<="&DATE(J$4,J$5,J$6),Data!$I:$I,$C26)-SUMIFS(Data!$K:$K,Data!$B:$B,"<="&DATE(J$4,J$5,J$6),Data!$I:$I,$C26) -> 0 | K26: =SUMIFS(Data!$J:$J,Data!$B:$B,"<="&DATE(K$4,K$5,K$6),Data!$I:$I,$C26)-SUMIFS(Data!$K:$K,Data!$B:$B,"<="&DATE(K$4,K$5,K$6),Data!$I:$I,$C26) -> 0 | ... O26: =SUMIFS(Data!$J:$J,Data!$B:$B,"<="&DATE(O$4,O$5,O$6),Data!$I:$I,$C26)-SUMIFS(Data!$K:$K,Data!$B:$B,"<="&DATE(O$4,O$5,O$6),Data!$I:$I,$C26) -> 0 | P26: =O26 -> 0

Sheet Phieuthu_chi
A1: CÔNG TY CỔ PHẦN DỊCH VỤ SPS | M1: ="Mẫu số 0"&IF(LEFT($L$7,2)="PT",1,2)&"-TT" -> Mẫu số 02-TT
M2: (Ban hành theo TT số 200/2014/TT-BTC ngày 22/12/2014 của BTC)
F4: ="PHIẾU "&IF(MID($L$7,3,2)="PT","THU","CHI") -> PHIẾU CHI
E5: =IF(MID($L$7,3,2)="PT",INDEX(Data!$B:$B,MATCH($L$7,Data!$A:$A,0)),INDEX(Data!$B:$B,MATCH($L$7,Data!A:A,0))) -> #N/A
K6: Quyển số: | L6: ………
K7: Số: | L7: 22PC06_28
K8: Nợ:
A9: ="Họ và tên người "&IF(MID($L$7,3,2)="PT","nộp","nhận")&" tiền:" -> Họ và tên người nhận tiền: | D9: =IF(MID($L$7,3,2)="PT",INDEX(Data!C:C,MATCH($L$7,Data!$A:$A,0)),INDEX(Data!C:C,MATCH($L$7,Data!A:A,0))) -> #N/A | K9: Có:
A10: Địa chỉ: | C10: =IF(MID($L$7,3,2)="PT",INDEX(Data!$D:$D,MATCH($L$7,Data!$A:$A,0)),INDEX(Data!$D:$D,MATCH($L$7,Data!A:A,0))) -> #N/A
A11: ="Lý do "&IF(MID($L$7,3,2)="PT","nộp:","chi:") -> Lý do chi: | C11: =IF(MID($L$7,3,2)="PT",INDEX(Data!$E:$E,MATCH($L$7,Data!$A:$A,0)),INDEX(Data!$E:$E,MATCH($L$7,Data!A:A,0))) -> #N/A
A12: Số tiền: | C12: =IF(MID($L$7,3,2)="PT",INDEX(Data!$J:$J,MATCH($L$7,Data!$A:$A,0)),INDEX(Data!$K:$K,MATCH($L$7,Data!A:A,0))) -> #N/A
A13: Viết bằng chữ: | C13: =[7]!VND(C12) -> #NAME?
A14: Kèm theo: | B14: ………….. | C14: Chứng từ gốc: | E14: ……………………………………………………………………………………
J15: =E5 -> #N/A
A16: Giám đốc | C16: Phụ trách kế toán | F16: ="Người "&IF(MID($L$7,3,2)="PT","nộp","nhận")&" tiền" -> Người nhận tiền | I16: Người lập phiếu | L16: Thủ quỹ
A17: (Ký, họ tên, đóng dấu) | D17: (Ký, họ tên) | F17: (Ký, họ tên) | I17: (Ký, họ tên) | L17: (Ký, họ tên)
A21: Hoàng Văn Phong | C21: Đỗ Thị Loan | F21: =D9 -> #N/A | I21: Trần Thị Nga | L21: Trần Thị Nga
A23: Đã nhận đủ số tiền (viết bằng chữ): | E23: …………………………………………………………..……………………………
A24: + Tỷ giá ngoại tệ (vàng bạc, đá quý): | E24: …………………………………………………………..……………………………
A25: + Số tiền quy đổi: | E25: …………………………………………………………..……………………………
A29: CÔNG TY CỔ PHẦN DỊCH VỤ SPS | M29: ="Mẫu số 0"&IF(LEFT($L$7,2)="PT",1,2)&"-TT" -> Mẫu số 02-TT
M30: (Ban hành theo TT số 200/2014/TT-BTC ngày 22/12/2014 của BTC)
F33: ="PHIẾU "&IF(MID($L$35,3,2)="PT","THU","CHI") -> PHIẾU CHI
E34: =IF(MID($L$35,3,2)="PT",INDEX(Data!$B:$B,MATCH($L$35,Data!$A:$A,0)),INDEX(Data!$B:$B,MATCH($L$35,Data!A:A,0))) -> #N/A | K34: Quyển số: | L34: ………
K35: Số: | L35: 22PC06_28
K36: Nợ: | L36: ……….
A37: ="Họ và tên người "&IF(MID($L$35,3,2)="PT","nộp","nhận")&" tiền:" -> Họ và tên người nhận tiền: | D37: =IF(MID($L$35,3,2)="PT",INDEX(Data!C:C,MATCH($L$35,Data!$A:$A,0)),INDEX(Data!C:C,MATCH($L$35,Data!A:A,0))) -> #N/A | K37: Có: | L37: ……..
A38: Địa chỉ: | C38: =IF(MID($L$35,3,2)="PT",INDEX(Data!$D:$D,MATCH($L$35,Data!$A:$A,0)),INDEX(Data!$D:$D,MATCH($L$35,Data!A:A,0))) -> #N/A
A39: ="Lý do "&IF(MID(L35,3,2)="PT","nộp:","chi:") -> Lý do chi: | C39: =IF(MID($L$35,3,2)="PT",INDEX(Data!$E:$E,MATCH($L$35,Data!$A:$A,0)),INDEX(Data!$E:$E,MATCH($L$35,Data!A:A,0))) -> #N/A
A40: Số tiền: | C40: =IF(MID($L$35,3,2)="PT",INDEX(Data!$J:$J,MATCH($L$35,Data!$A:$A,0)),INDEX(Data!$K:$K,MATCH($L$35,Data!A:A,0))) -> #N/A
A41: Viết bằng chữ: | C41: =[7]!VND(C40) -> #NAME?
A42: Kèm theo: | B42: ………….. | C42: Chứng từ gốc: | E42: ……………………………………………………………………………………
J43: =E34 -> #N/A
A44: Giám đốc | D44: Phụ trách kế toán | F44: ="Người "&IF(MID($L$7,3,2)="PT","nộp","nhận")&" tiền" -> Người nhận tiền | I44: Người lập phiếu | L44: Thủ quỹ
A45: (Ký, họ tên, đóng dấu) | D45: (Ký, họ tên) | F45: (Ký, họ tên) | I45: (Ký, họ tên) | L45: (Ký, họ tên)
A49: Hoàng Văn Phong | C49: Đỗ Thị Loan | F49: =D37 -> #N/A | I49: Trần Thị Nga | L49: Trần Thị Nga
A51: Đã nhận đủ số tiền (viết bằng chữ): | E51: …………………………………………………………..……………………………
A52: + Tỷ giá ngoại tệ (vàng bạc, đá quý): | E52: …………………………………………………………..……………………………
A53: + Số tiền quy đổi: | E53: …………………………………………………………..……………………………

Sheet Classification
A1: PHÂN LOẠI & MÃ KHOẢN MỤC:
A2: I. Phân loại các khoản thu:
A3: Thu từ Bảo trì & Dịch vụ | B3: Revenue from Maintenance & Services | C3: RMS
A4: Thu từ quản lý vận hành tòa nhà | B4: Revenue from Facility Management | C4: RFM
A5: Thu từ lãi tiền gửi hoặc lãi đầu tư tài chính, thanh lý tài sản | B5: Revenue from financial INvestment, deposit interest, liquidation of assets | C5: RIN
A6: Thu khác: thu tạm ứng thừa, tiền chuyển sai, thu từ XLHĐ, thu tiền mua hộ | B6: Revenue from OThers Income: excess advance, return money… | C6: ROT
A7: Vốn góp hoặc các khoản vay | B7: Capital Contribution or Loan | C7: CCL
A8: II. Tiền gửi tiết kiệm: bao gồm cả khoản gửi và rút | B8: Saving Cash | C8: SC
A9: III. Phân loại chi phí:
A10: Các khoản chi cho các dự án Bảo trì & Dịch vụ | B10: Maintenance & Services | C10: MS
A11: Các khoản chi liên quan tới dự án vận hành tòa nhà | B11: FM related costs | C11: FM
A12: Phí dịch vụ bảo vệ thuộc quản lý vận hành tòa nhà | B12: Sercurity Service | C12: SS
A13: Phí làm sạch thuộc quản lý vận hành tòa nhà | B13: Cleaning Service | C13: CS
A14: Kiểm soát côn trùng, chăm sóc cây xanh thuộc quản lý vận hành tòa nhà | B14: Pest control, Gardening | C14: PG
A15: Lương nhân viên & BHXH, BHYT, đồng phục, giày, trợ cấp điện thoại | B15: Labor Cost | C15: LC
A16: Chi phí quan hệ khách hàng | B16: Customer Relationship | C16: CR
A17: Vật tư tiêu hao dùng chung | B17: General Consumables | C17: GC
A18: Tài sản, công cụ dụng cụ, máy tính, trang thiết bị văn phòng, trang bị an toàn (mũ, kính, đai an toàn…) | B18: Asset & Tools fees | C18: AT
A19: Chi phí quản lý: Chi phí văn phòng, phí ngân hàng, tiếp khách, liên hoan, bảo hiểm TNNN, tai nạn… | B19: OverHead cost | C19: OH
A20: Thuế VAT, TNDN, phí nộp nhà nước | B20: TAx, fee | C20: TA
A21: Thanh toán khoản vay, trả tiền cổ đông, chi trả cổ tức | B21: Debt & dividends Payment | C21: DP
... A23: Chuyển tiền giữa các TK, đổi tiền, chi mua bán hộ, vay/tạm ứng (có trả lại) … | B23: Money transfer Between Accounts, | C23: BA
A24: IV. Phân loại chứng từ:
A25: Chứng từ thuế | B25: TAX document | C25: TAX
A26: Chứng từ nội bộ | B26: Internal document | C26: Internal
A27: V. Hình thức thu chi:
A28: Tiền mặt quỹ | B28: Cash in hand | C28: Cash
A29: Ngân hàng nội bộ | B29: Internal bank account TCB | C29: I-TCB
A30: Ngân hàng BIDV | B30: BIDV bank account | C30: BIDV
A31: Ngân hàng Techcombank | B31: TechComBank account | C31: TCB
A32: VI. Khác:
A33: Chỉnh sửa, hiệu chỉnh số liệu | B33: Data correction (No Available) | C33: N/A

Sheet Lãi tiền gửi
A1: TT | B1: Thời gian | C1: Nội dung | D1: Số tiền
A2: 1 | B2: 44044 | C2: Lãi tiền gửi | D2: 3271
A3: 2 | B3: 44075 | C3: Lãi tiền gửi | D3: 3635
A4: 3 | B4: 44105 | C4: Lãi tiền gửi | D4: 6088
A5: 4 | C5: Tiết kiệm | D5: 177261
A6: 5 | B6: 44136 | C6: Lãi tiền gửi tháng 11/2020 | D6: 7617
A7: 6 | B7: 44166 | C7: Lãi tiền gửi tháng 12/2020 | D7: 3031
A8: 7 | B8: 44197 | C8: Lãi tiền gửi tháng 01/2021 | D8: 3782
A9: 8 | B9: 44228 | C9: Lãi tiền gửi tháng 02/2021 | D9: 2734
A10: 9 | B10: 44256 | C10: Lãi tiền gửi tháng 03/2021 | D10: 459
A11: =A10+1 -> 10 | B11: 44287 | C11: Lãi tiền gửi tháng 04/2021
A12: =A11+1 -> 11 | B12: 44317 | C12: Lãi tiền gửi tháng 05/2021 | D12: 698
A13: =A12+1 -> 12 | B13: 44348 | C13: Lãi tiền gửi tháng 06/2021 | D13: 1967
A14: =A13+1 -> 13
A15: =A14+1 -> 14
A16: =A15+1 -> 15
