Workbook

Sheet DATA
I1: BÁO CÁO DOANH THU DỰ ÁN | V1: Người lập: | W1: N.T.T.Hằng
I2: TURNOVER REPORT | V2: Ngày báo cáo: | W2: =TODAY()
W3: Đơn vị tính: đồng
A4: TT No | B4: Tên đơn vị nhận hóa đơn Company's name | C4: Tên khách hàng Client name | D4: Số hợp đồng/ dự án Contract/ Prj number | E4: Tên dự án Project name | F4: Phân loại Classification | G4: Thời hạn hợp đồng Contract duration | I4: Giá trị hợp đồng (tạm tính/tháng) Total contract | J4: Tháng-Năm Month-Year | K4: KL nghiệm thu đã xuất hóa đơn/ giá trị tạm ứng Invoice amount/ Advance amount | L4: CĐT trừ tiền (Phạt, cung cấp thiếu...) Deduct | M4: Khoản đã thu Received amount | O4: Còn phải thu Remain amount | P4: Tình trạng dự án Project status | Q4: Payment document submit date/ Ngày gửi HSTT cho KH | R4: Số hóa đơn GTGT Invoice no. | S4: Điều khoản thanh toán /Nội dung TT Payment term /Content payment | T4: Tần suất thanh toán/ Payment frequency | U4: Thời gian dự kiến phát hành hóa đơn/ Est. issuing invoice | V4: Contract status/ (Yes/ Pending/NA) | W4: Ghi chú Remark
G5: Từ From | H5: Đến To | M5: Số tiền Amount | N5: Ngày thu Received date

Sheet Status
E1: BÁO CÁO TÌNH TRẠNG DOANH THU
E2: STATUS OF TURNOVER REPORT
E3: =YEAR(TODAY())
C4: Reviewed date: | D4: =TODAY() | G4: VND | H4: Ratio (%)
B5: A. Tổng giá trị còn lại các dự án đã ký hợp đồng đang thực hiện chưa thanh toán Value of ongoing projects | G5: =SUMIF(DATA!$P:$P,"Ongoing",DATA!$I:$I)
A6: Sent | B6: B. Tổng giá trị đã thực hiện xong, đợi thanh toán Value of waiting for payment projects | G6: =SUM(G7:G10) | H6: =G6/G13
C7: Giá trị đợi thanh toán đã quá thời hạn (các dự án đã gửi hồ sơ thanh toán cho KH) Waiting for payment out time (submitted the document payment to clients ) | G7: =SUMIF(DATA!$P:$P,"Waiting for payment out time",DATA!$O:$O) | H7: =G7/G13
C8: Giá trị đợi thanh toán trong thời hạn (các dự án đã gửi hồ sơ thanh toán cho KH) Waiting for payment in time (submitted the document payment to clients ) | G8: =SUMIF(DATA!$P:$P,"Waiting for payment in time",DATA!$O:$O) | H8: =G8/G13
C9: Giá trị đợi thanh toán (các dự án đã xong, đã gửi bản nháp hóa đơn/ Hồ sơ nghiệm thu cho KH & đang chờ KH xác nhận để gửi hồ sơ thanh toán chính thức) Pending Payment (work done & sent the draft invoice/ Work completion for checking & waiting client's confirmation) | G9: =SUMIF(DATA!$P:$P,"Pending Payment",DATA!$I:$I) | H9: =G9/G13
C10: Giá trị thanh toán thiếu (khoản "còn phải thu": Bảo hành, Xử lý bồi thường, KH giữ lại,...) Total remaining debt (Warranty, Compensation amount,...) | G10: =SUMIF(DATA!$P:$P,"Remaining",DATA!$I:$I) | H10: =G10/G13
B11: C. Tổng giá trị dự án triển khai chậm hoặc hoàn tất hồ sơ chậm Delay amount | G11: =SUMIF(DATA!$P:$P,"Delay",DATA!$I:$I) | H11: =G11/G13
A12: Y | B12: D. Tổng giá trị các dự án KH phạt vi phạm Penalty amount in year | G12: =SUMIFS(DATA!L:L,DATA!J:J,">="&DATE(Status!E3,1,1),DATA!J:J,"<="&DATE(Status!E3,12,31)) | H12: =G12/G13
A13: Y | B13: E. Giá trị đã thu các dự án trong năm Revenue of done job in year | G13: =SUMIFS(DATA!M:M,DATA!N:N,">="&DATE(Status!E3,1,1),DATA!N:N,"<="&DATE(Status!E3,12,31)) | H13: =G13/G13
G14: =PlanActual!P1009
G15: =G13-G14 | H15: Diff

Sheet PlanActual
I1: KẾ HOẠCH & THỰC TẾ DOANH THU TRONG NĂM | P1: Prepared by Nguyễn Thị Thu Hằng
H2: YEAR: | I2: =YEAR(TODAY()) | O2: Date: | P2: =TODAY()
A4: No | B4: Tên Khách hàng Client Name | D4: 1 | E4: 2 | F4: 3 | G4: 4 | H4: 5 | I4: 6 | J4: 7 | K4: 8 | L4: 9 | M4: 10 | N4: 11 | O4: 12 | P4: Total | Q4: Ratio
A5: Trung gian tính ngày cuối của tháng | D5: 31 | E5: =DAY(EOMONTH(DATE(I2,E4,1),0)) | F5: 31 | G5: 30 | H5: 31 | I5: 30 | J5: 31 | K5: 31 | L5: 30 | M5: 31 | N5: 30 | O5: 31
A6: 1 | B6: VNPT IDC - NAM THANG LONG(Inactive) | C6: Kế hoạch | D6: =SUMIFS(DATA!$I:$I,DATA!$C:$C,$B6,DATA!$J:$J,">="&DATE($I$2,D$4,1),DATA!$J:$J,"<="&DATE($I$2,D$4,D$5)) | E6: =SUMIFS(DATA!$I:$I,DATA!$C:$C,$B6,DATA!$J:$J,">="&DATE($I$2,E$4,1),DATA!$J:$J,"<="&DATE($I$2,E$4,E$5)) | F6: =SUMIFS(DATA!$I:$I,DATA!$C:$C,$B6,DATA!$J:$J,">="&DATE($I$2,F$4,1),DATA!$J:$J,"<="&DATE($I$2,F$4,F$5)) | G6: =SUMIFS(DATA!$I:$I,DATA!$C:$C,$B6,DATA!$J:$J,">="&DATE($I$2,G$4,1),DATA!$J:$J,"<="&DATE($I$2,G$4,G$5)) | H6: =SUMIFS(DATA!$I:$I,DATA!$C:$C,$B6,DATA!$J:$J,">="&DATE($I$2,H$4,1),DATA!$J:$J,"<="&DATE($I$2,H$4,H$5)) | I6: =SUMIFS(DATA!$I:$I,DATA!$C:$C,$B6,DATA!$J:$J,">="&DATE($I$2,I$4,1),DATA!$J:$J,"<="&DATE($I$2,I$4,I$5)) | J6: =SUMIFS(DATA!$I:$I,DATA!$C:$C,$B6,DATA!$J:$J,">="&DATE($I$2,J$4,1),DATA!$J:$J,"<="&DATE($I$2,J$4,J$5)) | K6: =SUMIFS(DATA!$I:$I,DATA!$C:$C,$B6,DATA!$J:$J,">="&DATE($I$2,K$4,1),DATA!$J:$J,"<="&DATE($I$2,K$4,K$5)) | ... O6: =SUMIFS(DATA!$I:$I,DATA!$C:$C,$B6,DATA!$J:$J,">="&DATE($I$2,O$4,1),DATA!$J:$J,"<="&DATE($I$2,O$4,O$5)) | P6: =SUM(D6:O6)
C7: Thực tế | D7: =SUMIFS(DATA!$M:$M,DATA!$C:$C,$B6,DATA!$N:$N,">="&DATE($I$2,D$4,1),DATA!$N:$N,"<="&DATE($I$2,D$4,D$5)) | E7: =SUMIFS(DATA!$M:$M,DATA!$C:$C,$B6,DATA!$N:$N,">="&DATE($I$2,E$4,1),DATA!$N:$N,"<="&DATE($I$2,E$4,E$5)) | F7: =SUMIFS(DATA!$M:$M,DATA!$C:$C,$B6,DATA!$N:$N,">="&DATE($I$2,F$4,1),DATA!$N:$N,"<="&DATE($I$2,F$4,F$5)) | G7: =SUMIFS(DATA!$M:$M,DATA!$C:$C,$B6,DATA!$N:$N,">="&DATE($I$2,G$4,1),DATA!$N:$N,"<="&DATE($I$2,G$4,G$5)) | H7: =SUMIFS(DATA!$M:$M,DATA!$C:$C,$B6,DATA!$N:$N,">="&DATE($I$2,H$4,1),DATA!$N:$N,"<="&DATE($I$2,H$4,H$5)) | I7: =SUMIFS(DATA!$M:$M,DATA!$C:$C,$B6,DATA!$N:$N,">="&DATE($I$2,I$4,1),DATA!$N:$N,"<="&DATE($I$2,I$4,I$5)) | J7: =SUMIFS(DATA!$M:$M,DATA!$C:$C,$B6,DATA!$N:$N,">="&DATE($I$2,J$4,1),DATA!$N:$N,"<="&DATE($I$2,J$4,J$5)) | K7: =SUMIFS(DATA!$M:$M,DATA!$C:$C,$B6,DATA!$N:$N,">="&DATE($I$2,K$4,1),DATA!$N:$N,"<="&DATE($I$2,K$4,K$5)) | ... O7: =SUMIFS(DATA!$M:$M,DATA!$C:$C,$B6,DATA!$N:$N,">="&DATE($I$2,O$4,1),DATA!$N:$N,"<="&DATE($I$2,O$4,O$5)) | P7: =SUM(D7:O7)
A8: 2 | B8: EMBASSY OF AUSTRALIA | C8: Kế hoạch | D8: =SUMIFS(DATA!$I:$I,DATA!$C:$C,$B8,DATA!$J:$J,">="&DATE($I$2,D$4,1),DATA!$J:$J,"<="&DATE($I$2,D$4,D$5)) | E8: =SUMIFS(DATA!$I:$I,DATA!$C:$C,$B8,DATA!$J:$J,">="&DATE($I$2,E$4,1),DATA!$J:$J,"<="&DATE($I$2,E$4,E$5)) | F8: =SUMIFS(DATA!$I:$I,DATA!$C:$C,$B8,DATA!$J:$J,">="&DATE($I$2,F$4,1),DATA!$J:$J,"<="&DATE($I$2,F$4,F$5)) | G8: =SUMIFS(DATA!$I:$I,DATA!$C:$C,$B8,DATA!$J:$J,">="&DATE($I$2,G$4,1),DATA!$J:$J,"<="&DATE($I$2,G$4,G$5)) | H8: =SUMIFS(DATA!$I:$I,DATA!$C:$C,$B8,DATA!$J:$J,">="&DATE($I$2,H$4,1),DATA!$J:$J,"<="&DATE($I$2,H$4,H$5)) | I8: =SUMIFS(DATA!$I:$I,DATA!$C:$C,$B8,DATA!$J:$J,">="&DATE($I$2,I$4,1),DATA!$J:$J,"<="&DATE($I$2,I$4,I$5)) | J8: =SUMIFS(DATA!$I:$I,DATA!$C:$C,$B8,DATA!$J:$J,">="&DATE($I$2,J$4,1),DATA!$J:$J,"<="&DATE($I$2,J$4,J$5)) | K8: =SUMIFS(DATA!$I:$I,DATA!$C:$C,$B8,DATA!$J:$J,">="&DATE($I$2,K$4,1),DATA!$J:$J,"<="&DATE($I$2,K$4,K$5)) | ... O8: =SUMIFS(DATA!$I:$I,DATA!$C:$C,$B8,DATA!$J:$J,">="&DATE($I$2,O$4,1),DATA!$J:$J,"<="&DATE($I$2,O$4,O$5)) | P8: =SUM(D8:O8)
C9: Thực tế | D9: =SUMIFS(DATA!$M:$M,DATA!$C:$C,$B8,DATA!$N:$N,">="&DATE($I$2,D$4,1),DATA!$N:$N,"<="&DATE($I$2,D$4,D$5)) | E9: =SUMIFS(DATA!$M:$M,DATA!$C:$C,$B8,DATA!$N:$N,">="&DATE($I$2,E$4,1),DATA!$N:$N,"<="&DATE($I$2,E$4,E$5)) | F9: =SUMIFS(DATA!$M:$M,DATA!$C:$C,$B8,DATA!$N:$N,">="&DATE($I$2,F$4,1),DATA!$N:$N,"<="&DATE($I$2,F$4,F$5)) | G9: =SUMIFS(DATA!$M:$M,DATA!$C:$C,$B8,DATA!$N:$N,">="&DATE($I$2,G$4,1),DATA!$N:$N,"<="&DATE($I$2,G$4,G$5)) | H9: =SUMIFS(DATA!$M:$M,DATA!$C:$C,$B8,DATA!$N:$N,">="&DATE($I$2,H$4,1),DATA!$N:$N,"<="&DATE($I$2,H$4,H$5)) | I9: =SUMIFS(DATA!$M:$M,DATA!$C:$C,$B8,DATA!$N:$N,">="&DATE($I$2,I$4,1),DATA!$N:$N,"<="&DATE($I$2,I$4,I$5)) | J9: =SUMIFS(DATA!$M:$M,DATA!$C:$C,$B8,DATA!$N:$N,">="&DATE($I$2,J$4,1),DATA!$N:$N,"<="&DATE($I$2,J$4,J$5)) | K9: =SUMIFS(DATA!$M:$M,DATA!$C:$C,$B8,DATA!$N:$N,">="&DATE($I$2,K$4,1),DATA!$N:$N,"<="&DATE($I$2,K$4,K$5)) | ... O9: =SUMIFS(DATA!$M:$M,DATA!$C:$C,$B8,DATA!$N:$N,">="&DATE($I$2,O$4,1),DATA!$N:$N,"<="&DATE($I$2,O$4,O$5)) | P9: =SUM(D9:O9)
A10: 3 | B10: YAMAHA MOTOR VIETNAM | C10: Kế hoạch | D10: =SUMIFS(DATA!$I:$I,DATA!$C:$C,$B10,DATA!$J:$J,">="&DATE($I$2,D$4,1),DATA!$J:$J,"<="&DATE($I$2,D$4,D$5)) | E10: =SUMIFS(DATA!$I:$I,DATA!$C:$C,$B10,DATA!$J:$J,">="&DATE($I$2,E$4,1),DATA!$J:$J,"<="&DATE($I$2,E$4,E$5)) | F10: =SUMIFS(DATA!$I:$I,DATA!$C:$C,$B10,DATA!$J:$J,">="&DATE($I$2,F$4,1),DATA!$J:$J,"<="&DATE($I$2,F$4,F$5)) | G10: =SUMIFS(DATA!$I:$I,DATA!$C:$C,$B10,DATA!$J:$J,">="&DATE($I$2,G$4,1),DATA!$J:$J,"<="&DATE($I$2,G$4,G$5)) | H10: =SUMIFS(DATA!$I:$I,DATA!$C:$C,$B10,DATA!$J:$J,">="&DATE($I$2,H$4,1),DATA!$J:$J,"<="&DATE($I$2,H$4,H$5)) | I10: =SUMIFS(DATA!$I:$I,DATA!$C:$C,$B10,DATA!$J:$J,">="&DATE($I$2,I$4,1),DATA!$J:$J,"<="&DATE($I$2,I$4,I$5)) | J10: =SUMIFS(DATA!$I:$I,DATA!$C:$C,$B10,DATA!$J:$J,">="&DATE($I$2,J$4,1),DATA!$J:$J,"<="&DATE($I$2,J$4,J$5)) | K10: =SUMIFS(DATA!$I:$I,DATA!$C:$C,$B10,DATA!$J:$J,">="&DATE($I$2,K$4,1),DATA!$J:$J,"<="&DATE($I$2,K$4,K$5)) | ... O10: =SUMIFS(DATA!$I:$I,DATA!$C:$C,$B10,DATA!$J:$J,">="&DATE($I$2,O$4,1),DATA!$J:$J,"<="&DATE($I$2,O$4,O$5)) | P10: =SUM(D10:O10)
C11: Thực tế | D11: =SUMIFS(DATA!$M:$M,DATA!$C:$C,$B10,DATA!$N:$N,">="&DATE($I$2,D$4,1),DATA!$N:$N,"<="&DATE($I$2,D$4,D$5)) | E11: =SUMIFS(DATA!$M:$M,DATA!$C:$C,$B10,DATA!$N:$N,">="&DATE($I$2,E$4,1),DATA!$N:$N,"<="&DATE($I$2,E$4,E$5)) | F11: =SUMIFS(DATA!$M:$M,DATA!$C:$C,$B10,DATA!$N:$N,">="&DATE($I$2,F$4,1),DATA!$N:$N,"<="&DATE($I$2,F$4,F$5)) | G11: =SUMIFS(DATA!$M:$M,DATA!$C:$C,$B10,DATA!$N:$N,">="&DATE($I$2,G$4,1),DATA!$N:$N,"<="&DATE($I$2,G$4,G$5)) | H11: =SUMIFS(DATA!$M:$M,DATA!$C:$C,$B10,DATA!$N:$N,">="&DATE($I$2,H$4,1),DATA!$N:$N,"<="&DATE($I$2,H$4,H$5)) | I11: =SUMIFS(DATA!$M:$M,DATA!$C:$C,$B10,DATA!$N:$N,">="&DATE($I$2,I$4,1),DATA!$N:$N,"<="&DATE($I$2,I$4,I$5)) | J11: =SUMIFS(DATA!$M:$M,DATA!$C:$C,$B10,DATA!$N:$N,">="&DATE($I$2,J$4,1),DATA!$N:$N,"<="&DATE($I$2,J$4,J$5)) | K11: =SUMIFS(DATA!$M:$M,DATA!$C:$C,$B10,DATA!$N:$N,">="&DATE($I$2,K$4,1),DATA!$N:$N,"<="&DATE($I$2,K$4,K$5)) | ... O11: =SUMIFS(DATA!$M:$M,DATA!$C:$C,$B10,DATA!$N:$N,">="&DATE($I$2,O$4,1),DATA!$N:$N,"<="&DATE($I$2,O$4,O$5)) | P11: =SUM(D11:O11)
A12: 4 | B12: CÔNG TY TNHH THÁP LÁNG HẠ | C12: Kế hoạch | D12: =SUMIFS(DATA!$I:$I,DATA!$C:$C,$B12,DATA!$J:$J,">="&DATE($I$2,D$4,1),DATA!$J:$J,"<="&DATE($I$2,D$4,D$5)) | E12: =SUMIFS(DATA!$I:$I,DATA!$C:$C,$B12,DATA!$J:$J,">="&DATE($I$2,E$4,1),DATA!$J:$J,"<="&DATE($I$2,E$4,E$5)) | F12: =SUMIFS(DATA!$I:$I,DATA!$C:$C,$B12,DATA!$J:$J,">="&DATE($I$2,F$4,1),DATA!$J:$J,"<="&DATE($I$2,F$4,F$5)) | G12: =SUMIFS(DATA!$I:$I,DATA!$C:$C,$B12,DATA!$J:$J,">="&DATE($I$2,G$4,1),DATA!$J:$J,"<="&DATE($I$2,G$4,G$5)) | H12: =SUMIFS(DATA!$I:$I,DATA!$C:$C,$B12,DATA!$J:$J,">="&DATE($I$2,H$4,1),DATA!$J:$J,"<="&DATE($I$2,H$4,H$5)) | I12: =SUMIFS(DATA!$I:$I,DATA!$C:$C,$B12,DATA!$J:$J,">="&DATE($I$2,I$4,1),DATA!$J:$J,"<="&DATE($I$2,I$4,I$5)) | J12: =SUMIFS(DATA!$I:$I,DATA!$C:$C,$B12,DATA!$J:$J,">="&DATE($I$2,J$4,1),DATA!$J:$J,"<="&DATE($I$2,J$4,J$5)) | K12: =SUMIFS(DATA!$I:$I,DATA!$C:$C,$B12,DATA!$J:$J,">="&DATE($I$2,K$4,1),DATA!$J:$J,"<="&DATE($I$2,K$4,K$5)) | ... O12: =SUMIFS(DATA!$I:$I,DATA!$C:$C,$B12,DATA!$J:$J,">="&DATE($I$2,O$4,1),DATA!$J:$J,"<="&DATE($I$2,O$4,O$5)) | P12: =SUM(D12:O12)
C13: Thực tế | D13: =SUMIFS(DATA!$M:$M,DATA!$C:$C,$B12,DATA!$N:$N,">="&DATE($I$2,D$4,1),DATA!$N:$N,"<="&DATE($I$2,D$4,D$5)) | E13: =SUMIFS(DATA!$M:$M,DATA!$C:$C,$B12,DATA!$N:$N,">="&DATE($I$2,E$4,1),DATA!$N:$N,"<="&DATE($I$2,E$4,E$5)) | F13: =SUMIFS(DATA!$M:$M,DATA!$C:$C,$B12,DATA!$N:$N,">="&DATE($I$2,F$4,1),DATA!$N:$N,"<="&DATE($I$2,F$4,F$5)) | G13: =SUMIFS(DATA!$M:$M,DATA!$C:$C,$B12,DATA!$N:$N,">="&DATE($I$2,G$4,1),DATA!$N:$N,"<="&DATE($I$2,G$4,G$5)) | H13: =SUMIFS(DATA!$M:$M,DATA!$C:$C,$B12,DATA!$N:$N,">="&DATE($I$2,H$4,1),DATA!$N:$N,"<="&DATE($I$2,H$4,H$5)) | I13: =SUMIFS(DATA!$M:$M,DATA!$C:$C,$B12,DATA!$N:$N,">="&DATE($I$2,I$4,1),DATA!$N:$N,"<="&DATE($I$2,I$4,I$5)) | J13: =SUMIFS(DATA!$M:$M,DATA!$C:$C,$B12,DATA!$N:$N,">="&DATE($I$2,J$4,1),DATA!$N:$N,"<="&DATE($I$2,J$4,J$5)) | K13: =SUMIFS(DATA!$M:$M,DATA!$C:$C,$B12,DATA!$N:$N,">="&DATE($I$2,K$4,1),DATA!$N:$N,"<="&DATE($I$2,K$4,K$5)) | ... O13: =SUMIFS(DATA!$M:$M,DATA!$C:$C,$B12,DATA!$N:$N,">="&DATE($I$2,O$4,1),DATA!$N:$N,"<="&DATE($I$2,O$4,O$5)) | P13: =SUM(D13:O13)
A14: 5 | B14: TRUNG TÂM HẠ TẦNG IDC - CÔNG TY CÔNG NGHỆ THÔNG TIN VNPT (VNPT-IT) | C14: Kế hoạch | D14: =SUMIFS(DATA!$I:$I,DATA!$C:$C,$B14,DATA!$J:$J,">="&DATE($I$2,D$4,1),DATA!$J:$J,"<="&DATE($I$2,D$4,D$5)) | E14: =SUMIFS(DATA!$I:$I,DATA!$C:$C,$B14,DATA!$J:$J,">="&DATE($I$2,E$4,1),DATA!$J:$J,"<="&DATE($I$2,E$4,E$5)) | F14: =SUMIFS(DATA!$I:$I,DATA!$C:$C,$B14,DATA!$J:$J,">="&DATE($I$2,F$4,1),DATA!$J:$J,"<="&DATE($I$2,F$4,F$5)) | G14: =SUMIFS(DATA!$I:$I,DATA!$C:$C,$B14,DATA!$J:$J,">="&DATE($I$2,G$4,1),DATA!$J:$J,"<="&DATE($I$2,G$4,G$5)) | H14: =SUMIFS(DATA!$I:$I,DATA!$C:$C,$B14,DATA!$J:$J,">="&DATE($I$2,H$4,1),DATA!$J:$J,"<="&DATE($I$2,H$4,H$5)) | I14: =SUMIFS(DATA!$I:$I,DATA!$C:$C,$B14,DATA!$J:$J,">="&DATE($I$2,I$4,1),DATA!$J:$J,"<="&DATE($I$2,I$4,I$5)) | J14: =SUMIFS(DATA!$I:$I,DATA!$C:$C,$B14,DATA!$J:$J,">="&DATE($I$2,J$4,1),DATA!$J:$J,"<="&DATE($I$2,J$4,J$5)) | K14: =SUMIFS(DATA!$I:$I,DATA!$C:$C,$B14,DATA!$J:$J,">="&DATE($I$2,K$4,1),DATA!$J:$J,"<="&DATE($I$2,K$4,K$5)) | ... O14: =SUMIFS(DATA!$I:$I,DATA!$C:$C,$B14,DATA!$J:$J,">="&DATE($I$2,O$4,1),DATA!$J:$J,"<="&DATE($I$2,O$4,O$5)) | P14: =SUM(D14:O14)
C15: Thực tế | D15: =SUMIFS(DATA!$M:$M,DATA!$C:$C,$B14,DATA!$N:$N,">="&DATE($I$2,D$4,1),DATA!$N:$N,"<="&DATE($I$2,D$4,D$5)) | E15: =SUMIFS(DATA!$M:$M,DATA!$C:$C,$B14,DATA!$N:$N,">="&DATE($I$2,E$4,1),DATA!$N:$N,"<="&DATE($I$2,E$4,E$5)) | F15: =SUMIFS(DATA!$M:$M,DATA!$C:$C,$B14,DATA!$N:$N,">="&DATE($I$2,F$4,1),DATA!$N:$N,"<="&DATE($I$2,F$4,F$5)) | G15: =SUMIFS(DATA!$M:$M,DATA!$C:$C,$B14,DATA!$N:$N,">="&DATE($I$2,G$4,1),DATA!$N:$N,"<="&DATE($I$2,G$4,G$5)) | H15: =SUMIFS(DATA!$M:$M,DATA!$C:$C,$B14,DATA!$N:$N,">="&DATE($I$2,H$4,1),DATA!$N:$N,"<="&DATE($I$2,H$4,H$5)) | I15: =SUMIFS(DATA!$M:$M,DATA!$C:$C,$B14,DATA!$N:$N,">="&DATE($I$2,I$4,1),DATA!$N:$N,"<="&DATE($I$2,I$4,I$5)) | J15: =SUMIFS(DATA!$M:$M,DATA!$C:$C,$B14,DATA!$N:$N,">="&DATE($I$2,J$4,1),DATA!$N:$N,"<="&DATE($I$2,J$4,J$5)) | K15: =SUMIFS(DATA!$M:$M,DATA!$C:$C,$B14,DATA!$N:$N,">="&DATE($I$2,K$4,1),DATA!$N:$N,"<="&DATE($I$2,K$4,K$5)) | ... O15: =SUMIFS(DATA!$M:$M,DATA!$C:$C,$B14,DATA!$N:$N,">="&DATE($I$2,O$4,1),DATA!$N:$N,"<="&DATE($I$2,O$4,O$5)) | P15: =SUM(D15:O15)
A16: 6 | B16: CRYSTAL MARTIN VIETNAM | C16: Kế hoạch | D16: =SUMIFS(DATA!$I:$I,DATA!$C:$C,$B16,DATA!$J:$J,">="&DATE($I$2,D$4,1),DATA!$J:$J,"<="&DATE($I$2,D$4,D$5)) | E16: =SUMIFS(DATA!$I:$I,DATA!$C:$C,$B16,DATA!$J:$J,">="&DATE($I$2,E$4,1),DATA!$J:$J,"<="&DATE($I$2,E$4,E$5)) | F16: =SUMIFS(DATA!$I:$I,DATA!$C:$C,$B16,DATA!$J:$J,">="&DATE($I$2,F$4,1),DATA!$J:$J,"<="&DATE($I$2,F$4,F$5)) | G16: =SUMIFS(DATA!$I:$I,DATA!$C:$C,$B16,DATA!$J:$J,">="&DATE($I$2,G$4,1),DATA!$J:$J,"<="&DATE($I$2,G$4,G$5)) | H16: =SUMIFS(DATA!$I:$I,DATA!$C:$C,$B16,DATA!$J:$J,">="&DATE($I$2,H$4,1),DATA!$J:$J,"<="&DATE($I$2,H$4,H$5)) | I16: =SUMIFS(DATA!$I:$I,DATA!$C:$C,$B16,DATA!$J:$J,">="&DATE($I$2,I$4,1),DATA!$J:$J,"<="&DATE($I$2,I$4,I$5)) | J16: =SUMIFS(DATA!$I:$I,DATA!$C:$C,$B16,DATA!$J:$J,">="&DATE($I$2,J$4,1),DATA!$J:$J,"<="&DATE($I$2,J$4,J$5)) | K16: =SUMIFS(DATA!$I:$I,DATA!$C:$C,$B16,DATA!$J:$J,">="&DATE($I$2,K$4,1),DATA!$J:$J,"<="&DATE($I$2,K$4,K$5)) | ... O16: =SUMIFS(DATA!$I:$I,DATA!$C:$C,$B16,DATA!$J:$J,">="&DATE($I$2,O$4,1),DATA!$J:$J,"<="&DATE($I$2,O$4,O$5)) | P16: =SUM(D16:O16)
C17: Thực tế | D17: =SUMIFS(DATA!$M:$M,DATA!$C:$C,$B16,DATA!$N:$N,">="&DATE($I$2,D$4,1),DATA!$N:$N,"<="&DATE($I$2,D$4,D$5)) | E17: =SUMIFS(DATA!$M:$M,DATA!$C:$C,$B16,DATA!$N:$N,">="&DATE($I$2,E$4,1),DATA!$N:$N,"<="&DATE($I$2,E$4,E$5)) | F17: =SUMIFS(DATA!$M:$M,DATA!$C:$C,$B16,DATA!$N:$N,">="&DATE($I$2,F$4,1),DATA!$N:$N,"<="&DATE($I$2,F$4,F$5)) | G17: =SUMIFS(DATA!$M:$M,DATA!$C:$C,$B16,DATA!$N:$N,">="&DATE($I$2,G$4,1),DATA!$N:$N,"<="&DATE($I$2,G$4,G$5)) | H17: =SUMIFS(DATA!$M:$M,DATA!$C:$C,$B16,DATA!$N:$N,">="&DATE($I$2,H$4,1),DATA!$N:$N,"<="&DATE($I$2,H$4,H$5)) | I17: =SUMIFS(DATA!$M:$M,DATA!$C:$C,$B16,DATA!$N:$N,">="&DATE($I$2,I$4,1),DATA!$N:$N,"<="&DATE($I$2,I$4,I$5)) | J17: =SUMIFS(DATA!$M:$M,DATA!$C:$C,$B16,DATA!$N:$N,">="&DATE($I$2,J$4,1),DATA!$N:$N,"<="&DATE($I$2,J$4,J$5)) | K17: =SUMIFS(DATA!$M:$M,DATA!$C:$C,$B16,DATA!$N:$N,">="&DATE($I$2,K$4,1),DATA!$N:$N,"<="&DATE($I$2,K$4,K$5)) | ... O17: =SUMIFS(DATA!$M:$M,DATA!$C:$C,$B16,DATA!$N:$N,">="&DATE($I$2,O$4,1),DATA!$N:$N,"<="&DATE($I$2,O$4,O$5)) | P17: =SUM(D17:O17)
A18: 7 | B18: RMIT UNIVERSITY | C18: Kế hoạch | D18: =SUMIFS(DATA!$I:$I,DATA!$C:$C,$B18,DATA!$J:$J,">="&DATE($I$2,D$4,1),DATA!$J:$J,"<="&DATE($I$2,D$4,D$5)) | E18: =SUMIFS(DATA!$I:$I,DATA!$C:$C,$B18,DATA!$J:$J,">="&DATE($I$2,E$4,1),DATA!$J:$J,"<="&DATE($I$2,E$4,E$5)) | F18: =SUMIFS(DATA!$I:$I,DATA!$C:$C,$B18,DATA!$J:$J,">="&DATE($I$2,F$4,1),DATA!$J:$J,"<="&DATE($I$2,F$4,F$5)) | G18: =SUMIFS(DATA!$I:$I,DATA!$C:$C,$B18,DATA!$J:$J,">="&DATE($I$2,G$4,1),DATA!$J:$J,"<="&DATE($I$2,G$4,G$5)) | H18: =SUMIFS(DATA!$I:$I,DATA!$C:$C,$B18,DATA!$J:$J,">="&DATE($I$2,H$4,1),DATA!$J:$J,"<="&DATE($I$2,H$4,H$5)) | I18: =SUMIFS(DATA!$I:$I,DATA!$C:$C,$B18,DATA!$J:$J,">="&DATE($I$2,I$4,1),DATA!$J:$J,"<="&DATE($I$2,I$4,I$5)) | J18: =SUMIFS(DATA!$I:$I,DATA!$C:$C,$B18,DATA!$J:$J,">="&DATE($I$2,J$4,1),DATA!$J:$J,"<="&DATE($I$2,J$4,J$5)) | K18: =SUMIFS(DATA!$I:$I,DATA!$C:$C,$B18,DATA!$J:$J,">="&DATE($I$2,K$4,1),DATA!$J:$J,"<="&DATE($I$2,K$4,K$5)) | ... O18: =SUMIFS(DATA!$I:$I,DATA!$C:$C,$B18,DATA!$J:$J,">="&DATE($I$2,O$4,1),DATA!$J:$J,"<="&DATE($I$2,O$4,O$5)) | P18: =SUM(D18:O18)
C19: Thực tế | D19: =SUMIFS(DATA!$M:$M,DATA!$C:$C,$B18,DATA!$N:$N,">="&DATE($I$2,D$4,1),DATA!$N:$N,"<="&DATE($I$2,D$4,D$5)) | E19: =SUMIFS(DATA!$M:$M,DATA!$C:$C,$B18,DATA!$N:$N,">="&DATE($I$2,E$4,1),DATA!$N:$N,"<="&DATE($I$2,E$4,E$5)) | F19: =SUMIFS(DATA!$M:$M,DATA!$C:$C,$B18,DATA!$N:$N,">="&DATE($I$2,F$4,1),DATA!$N:$N,"<="&DATE($I$2,F$4,F$5)) | G19: =SUMIFS(DATA!$M:$M,DATA!$C:$C,$B18,DATA!$N:$N,">="&DATE($I$2,G$4,1),DATA!$N:$N,"<="&DATE($I$2,G$4,G$5)) | H19: =SUMIFS(DATA!$M:$M,DATA!$C:$C,$B18,DATA!$N:$N,">="&DATE($I$2,H$4,1),DATA!$N:$N,"<="&DATE($I$2,H$4,H$5)) | I19: =SUMIFS(DATA!$M:$M,DATA!$C:$C,$B18,DATA!$N:$N,">="&DATE($I$2,I$4,1),DATA!$N:$N,"<="&DATE($I$2,I$4,I$5)) | J19: =SUMIFS(DATA!$M:$M,DATA!$C:$C,$B18,DATA!$N:$N,">="&DATE($I$2,J$4,1),DATA!$N:$N,"<="&DATE($I$2,J$4,J$5)) | K19: =SUMIFS(DATA!$M:$M,DATA!$C:$C,$B18,DATA!$N:$N,">="&DATE($I$2,K$4,1),DATA!$N:$N,"<="&DATE($I$2,K$4,K$5)) | ... O19: =SUMIFS(DATA!$M:$M,DATA!$C:$C,$B18,DATA!$N:$N,">="&DATE($I$2,O$4,1),DATA!$N:$N,"<="&DATE($I$2,O$4,O$5)) | P19: =SUM(D19:O19)
A20: 8 | B20: GOLDEN PALACE MỄ TRÌ | C20: Kế hoạch | D20: =SUMIFS(DATA!$I:$I,DATA!$C:$C,$B20,DATA!$J:$J,">="&DATE($I$2,D$4,1),DATA!$J:$J,"<="&DATE($I$2,D$4,D$5)) | E20: =SUMIFS(DATA!$I:$I,DATA!$C:$C,$B20,DATA!$J:$J,">="&DATE($I$2,E$4,1),DATA!$J:$J,"<="&DATE($I$2,E$4,E$5)) | F20: =SUMIFS(DATA!$I:$I,DATA!$C:$C,$B20,DATA!$J:$J,">="&DATE($I$2,F$4,1),DATA!$J:$J,"<="&DATE($I$2,F$4,F$5)) | G20: =SUMIFS(DATA!$I:$I,DATA!$C:$C,$B20,DATA!$J:$J,">="&DATE($I$2,G$4,1),DATA!$J:$J,"<="&DATE($I$2,G$4,G$5)) | H20: =SUMIFS(DATA!$I:$I,DATA!$C:$C,$B20,DATA!$J:$J,">="&DATE($I$2,H$4,1),DATA!$J:$J,"<="&DATE($I$2,H$4,H$5)) | I20: =SUMIFS(DATA!$I:$I,DATA!$C:$C,$B20,DATA!$J:$J,">="&DATE($I$2,I$4,1),DATA!$J:$J,"<="&DATE($I$2,I$4,I$5)) | J20: =SUMIFS(DATA!$I:$I,DATA!$C:$C,$B20,DATA!$J:$J,">="&DATE($I$2,J$4,1),DATA!$J:$J,"<="&DATE($I$2,J$4,J$5)) | K20: =SUMIFS(DATA!$I:$I,DATA!$C:$C,$B20,DATA!$J:$J,">="&DATE($I$2,K$4,1),DATA!$J:$J,"<="&DATE($I$2,K$4,K$5)) | ... O20: =SUMIFS(DATA!$I:$I,DATA!$C:$C,$B20,DATA!$J:$J,">="&DATE($I$2,O$4,1),DATA!$J:$J,"<="&DATE($I$2,O$4,O$5)) | P20: =SUM(D20:O20)
C21: Thực tế | D21: =SUMIFS(DATA!$M:$M,DATA!$C:$C,$B20,DATA!$N:$N,">="&DATE($I$2,D$4,1),DATA!$N:$N,"<="&DATE($I$2,D$4,D$5)) | E21: =SUMIFS(DATA!$M:$M,DATA!$C:$C,$B20,DATA!$N:$N,">="&DATE($I$2,E$4,1),DATA!$N:$N,"<="&DATE($I$2,E$4,E$5)) | F21: =SUMIFS(DATA!$M:$M,DATA!$C:$C,$B20,DATA!$N:$N,">="&DATE($I$2,F$4,1),DATA!$N:$N,"<="&DATE($I$2,F$4,F$5)) | G21: =SUMIFS(DATA!$M:$M,DATA!$C:$C,$B20,DATA!$N:$N,">="&DATE($I$2,G$4,1),DATA!$N:$N,"<="&DATE($I$2,G$4,G$5)) | H21: =SUMIFS(DATA!$M:$M,DATA!$C:$C,$B20,DATA!$N:$N,">="&DATE($I$2,H$4,1),DATA!$N:$N,"<="&DATE($I$2,H$4,H$5)) | I21: =SUMIFS(DATA!$M:$M,DATA!$C:$C,$B20,DATA!$N:$N,">="&DATE($I$2,I$4,1),DATA!$N:$N,"<="&DATE($I$2,I$4,I$5)) | J21: =SUMIFS(DATA!$M:$M,DATA!$C:$C,$B20,DATA!$N:$N,">="&DATE($I$2,J$4,1),DATA!$N:$N,"<="&DATE($I$2,J$4,J$5)) | K21: =SUMIFS(DATA!$M:$M,DATA!$C:$C,$B20,DATA!$N:$N,">="&DATE($I$2,K$4,1),DATA!$N:$N,"<="&DATE($I$2,K$4,K$5)) | ... O21: =SUMIFS(DATA!$M:$M,DATA!$C:$C,$B20,DATA!$N:$N,">="&DATE($I$2,O$4,1),DATA!$N:$N,"<="&DATE($I$2,O$4,O$5)) | P21: =SUM(D21:O21)
A22: 9 | B22: U.S. PEACE CORPS | C22: Kế hoạch | D22: =SUMIFS(DATA!$I:$I,DATA!$C:$C,$B22,DATA!$J:$J,">="&DATE($I$2,D$4,1),DATA!$J:$J,"<="&DATE($I$2,D$4,D$5)) | E22: =SUMIFS(DATA!$I:$I,DATA!$C:$C,$B22,DATA!$J:$J,">="&DATE($I$2,E$4,1),DATA!$J:$J,"<="&DATE($I$2,E$4,E$5)) | F22: =SUMIFS(DATA!$I:$I,DATA!$C:$C,$B22,DATA!$J:$J,">="&DATE($I$2,F$4,1),DATA!$J:$J,"<="&DATE($I$2,F$4,F$5)) | G22: =SUMIFS(DATA!$I:$I,DATA!$C:$C,$B22,DATA!$J:$J,">="&DATE($I$2,G$4,1),DATA!$J:$J,"<="&DATE($I$2,G$4,G$5)) | H22: =SUMIFS(DATA!$I:$I,DATA!$C:$C,$B22,DATA!$J:$J,">="&DATE($I$2,H$4,1),DATA!$J:$J,"<="&DATE($I$2,H$4,H$5)) | I22: =SUMIFS(DATA!$I:$I,DATA!$C:$C,$B22,DATA!$J:$J,">="&DATE($I$2,I$4,1),DATA!$J:$J,"<="&DATE($I$2,I$4,I$5)) | J22: =SUMIFS(DATA!$I:$I,DATA!$C:$C,$B22,DATA!$J:$J,">="&DATE($I$2,J$4,1),DATA!$J:$J,"<="&DATE($I$2,J$4,J$5)) | K22: =SUMIFS(DATA!$I:$I,DATA!$C:$C,$B22,DATA!$J:$J,">="&DATE($I$2,K$4,1),DATA!$J:$J,"<="&DATE($I$2,K$4,K$5)) | ... O22: =SUMIFS(DATA!$I:$I,DATA!$C:$C,$B22,DATA!$J:$J,">="&DATE($I$2,O$4,1),DATA!$J:$J,"<="&DATE($I$2,O$4,O$5)) | P22: =SUM(D22:O22)
C23: Thực tế | D23: =SUMIFS(DATA!$M:$M,DATA!$C:$C,$B22,DATA!$N:$N,">="&DATE($I$2,D$4,1),DATA!$N:$N,"<="&DATE($I$2,D$4,D$5)) | E23: =SUMIFS(DATA!$M:$M,DATA!$C:$C,$B22,DATA!$N:$N,">="&DATE($I$2,E$4,1),DATA!$N:$N,"<="&DATE($I$2,E$4,E$5)) | F23: =SUMIFS(DATA!$M:$M,DATA!$C:$C,$B22,DATA!$N:$N,">="&DATE($I$2,F$4,1),DATA!$N:$N,"<="&DATE($I$2,F$4,F$5)) | G23: =SUMIFS(DATA!$M:$M,DATA!$C:$C,$B22,DATA!$N:$N,">="&DATE($I$2,G$4,1),DATA!$N:$N,"<="&DATE($I$2,G$4,G$5)) | H23: =SUMIFS(DATA!$M:$M,DATA!$C:$C,$B22,DATA!$N:$N,">="&DATE($I$2,H$4,1),DATA!$N:$N,"<="&DATE($I$2,H$4,H$5)) | I23: =SUMIFS(DATA!$M:$M,DATA!$C:$C,$B22,DATA!$N:$N,">="&DATE($I$2,I$4,1),DATA!$N:$N,"<="&DATE($I$2,I$4,I$5)) | J23: =SUMIFS(DATA!$M:$M,DATA!$C:$C,$B22,DATA!$N:$N,">="&DATE($I$2,J$4,1),DATA!$N:$N,"<="&DATE($I$2,J$4,J$5)) | K23: =SUMIFS(DATA!$M:$M,DATA!$C:$C,$B22,DATA!$N:$N,">="&DATE($I$2,K$4,1),DATA!$N:$N,"<="&DATE($I$2,K$4,K$5)) | ... O23: =SUMIFS(DATA!$M:$M,DATA!$C:$C,$B22,DATA!$N:$N,">="&DATE($I$2,O$4,1),DATA!$N:$N,"<="&DATE($I$2,O$4,O$5)) | P23: =SUM(D23:O23)
A24: 10 | B24: DETECH TOWER II | C24: Kế hoạch | D24: =SUMIFS(DATA!$I:$I,DATA!$C:$C,$B24,DATA!$J:$J,">="&DATE($I$2,D$4,1),DATA!$J:$J,"<="&DATE($I$2,D$4,D$5)) | E24: =SUMIFS(DATA!$I:$I,DATA!$C:$C,$B24,DATA!$J:$J,">="&DATE($I$2,E$4,1),DATA!$J:$J,"<="&DATE($I$2,E$4,E$5)) | F24: =SUMIFS(DATA!$I:$I,DATA!$C:$C,$B24,DATA!$J:$J,">="&DATE($I$2,F$4,1),DATA!$J:$J,"<="&DATE($I$2,F$4,F$5)) | G24: =SUMIFS(DATA!$I:$I,DATA!$C:$C,$B24,DATA!$J:$J,">="&DATE($I$2,G$4,1),DATA!$J:$J,"<="&DATE($I$2,G$4,G$5)) | H24: =SUMIFS(DATA!$I:$I,DATA!$C:$C,$B24,DATA!$J:$J,">="&DATE($I$2,H$4,1),DATA!$J:$J,"<="&DATE($I$2,H$4,H$5)) | I24: =SUMIFS(DATA!$I:$I,DATA!$C:$C,$B24,DATA!$J:$J,">="&DATE($I$2,I$4,1),DATA!$J:$J,"<="&DATE($I$2,I$4,I$5)) | J24: =SUMIFS(DATA!$I:$I,DATA!$C:$C,$B24,DATA!$J:$J,">="&DATE($I$2,J$4,1),DATA!$J:$J,"<="&DATE($I$2,J$4,J$5)) | K24: =SUMIFS(DATA!$I:$I,DATA!$C:$C,$B24,DATA!$J:$J,">="&DATE($I$2,K$4,1),DATA!$J:$J,"<="&DATE($I$2,K$4,K$5)) | ... O24: =SUMIFS(DATA!$I:$I,DATA!$C:$C,$B24,DATA!$J:$J,">="&DATE($I$2,O$4,1),DATA!$J:$J,"<="&DATE($I$2,O$4,O$5)) | P24: =SUM(D24:O24)
C25: Thực tế | D25: =SUMIFS(DATA!$M:$M,DATA!$C:$C,$B24,DATA!$N:$N,">="&DATE($I$2,D$4,1),DATA!$N:$N,"<="&DATE($I$2,D$4,D$5)) | E25: =SUMIFS(DATA!$M:$M,DATA!$C:$C,$B24,DATA!$N:$N,">="&DATE($I$2,E$4,1),DATA!$N:$N,"<="&DATE($I$2,E$4,E$5)) | F25: =SUMIFS(DATA!$M:$M,DATA!$C:$C,$B24,DATA!$N:$N,">="&DATE($I$2,F$4,1),DATA!$N:$N,"<="&DATE($I$2,F$4,F$5)) | G25: =SUMIFS(DATA!$M:$M,DATA!$C:$C,$B24,DATA!$N:$N,">="&DATE($I$2,G$4,1),DATA!$N:$N,"<="&DATE($I$2,G$4,G$5)) | H25: =SUMIFS(DATA!$M:$M,DATA!$C:$C,$B24,DATA!$N:$N,">="&DATE($I$2,H$4,1),DATA!$N:$N,"<="&DATE($I$2,H$4,H$5)) | I25: =SUMIFS(DATA!$M:$M,DATA!$C:$C,$B24,DATA!$N:$N,">="&DATE($I$2,I$4,1),DATA!$N:$N,"<="&DATE($I$2,I$4,I$5)) | J25: =SUMIFS(DATA!$M:$M,DATA!$C:$C,$B24,DATA!$N:$N,">="&DATE($I$2,J$4,1),DATA!$N:$N,"<="&DATE($I$2,J$4,J$5)) | K25: =SUMIFS(DATA!$M:$M,DATA!$C:$C,$B24,DATA!$N:$N,">="&DATE($I$2,K$4,1),DATA!$N:$N,"<="&DATE($I$2,K$4,K$5)) | ... O25: =SUMIFS(DATA!$M:$M,DATA!$C:$C,$B24,DATA!$N:$N,">="&DATE($I$2,O$4,1),DATA!$N:$N,"<="&DATE($I$2,O$4,O$5)) | P25: =SUM(D25:O25)
A26: 11 | B26: WIDIA SHINKI VIETNAM | C26: Kế hoạch | D26: =SUMIFS(DATA!$I:$I,DATA!$C:$C,$B26,DATA!$J:$J,">="&DATE($I$2,D$4,1),DATA!$J:$J,"<="&DATE($I$2,D$4,D$5)) | E26: =SUMIFS(DATA!$I:$I,DATA!$C:$C,$B26,DATA!$J:$J,">="&DATE($I$2,E$4,1),DATA!$J:$J,"<="&DATE($I$2,E$4,E$5)) | F26: =SUMIFS(DATA!$I:$I,DATA!$C:$C,$B26,DATA!$J:$J,">="&DATE($I$2,F$4,1),DATA!$J:$J,"<="&DATE($I$2,F$4,F$5)) | G26: =SUMIFS(DATA!$I:$I,DATA!$C:$C,$B26,DATA!$J:$J,">="&DATE($I$2,G$4,1),DATA!$J:$J,"<="&DATE($I$2,G$4,G$5)) | H26: =SUMIFS(DATA!$I:$I,DATA!$C:$C,$B26,DATA!$J:$J,">="&DATE($I$2,H$4,1),DATA!$J:$J,"<="&DATE($I$2,H$4,H$5)) | I26: =SUMIFS(DATA!$I:$I,DATA!$C:$C,$B26,DATA!$J:$J,">="&DATE($I$2,I$4,1),DATA!$J:$J,"<="&DATE($I$2,I$4,I$5)) | J26: =SUMIFS(DATA!$I:$I,DATA!$C:$C,$B26,DATA!$J:$J,">="&DATE($I$2,J$4,1),DATA!$J:$J,"<="&DATE($I$2,J$4,J$5)) | K26: =SUMIFS(DATA!$I:$I,DATA!$C:$C,$B26,DATA!$J:$J,">="&DATE($I$2,K$4,1),DATA!$J:$J,"<="&DATE($I$2,K$4,K$5)) | ... O26: =SUMIFS(DATA!$I:$I,DATA!$C:$C,$B26,DATA!$J:$J,">="&DATE($I$2,O$4,1),DATA!$J:$J,"<="&DATE($I$2,O$4,O$5)) | P26: =SUM(D26:O26)
C27: Thực tế | D27: =SUMIFS(DATA!$M:$M,DATA!$C:$C,$B26,DATA!$N:$N,">="&DATE($I$2,D$4,1),DATA!$N:$N,"<="&DATE($I$2,D$4,D$5)) | E27: =SUMIFS(DATA!$M:$M,DATA!$C:$C,$B26,DATA!$N:$N,">="&DATE($I$2,E$4,1),DATA!$N:$N,"<="&DATE($I$2,E$4,E$5)) | F27: =SUMIFS(DATA!$M:$M,DATA!$C:$C,$B26,DATA!$N:$N,">="&DATE($I$2,F$4,1),DATA!$N:$N,"<="&DATE($I$2,F$4,F$5)) | G27: =SUMIFS(DATA!$M:$M,DATA!$C:$C,$B26,DATA!$N:$N,">="&DATE($I$2,G$4,1),DATA!$N:$N,"<="&DATE($I$2,G$4,G$5)) | H27: =SUMIFS(DATA!$M:$M,DATA!$C:$C,$B26,DATA!$N:$N,">="&DATE($I$2,H$4,1),DATA!$N:$N,"<="&DATE($I$2,H$4,H$5)) | I27: =SUMIFS(DATA!$M:$M,DATA!$C:$C,$B26,DATA!$N:$N,">="&DATE($I$2,I$4,1),DATA!$N:$N,"<="&DATE($I$2,I$4,I$5)) | J27: =SUMIFS(DATA!$M:$M,DATA!$C:$C,$B26,DATA!$N:$N,">="&DATE($I$2,J$4,1),DATA!$N:$N,"<="&DATE($I$2,J$4,J$5)) | K27: =SUMIFS(DATA!$M:$M,DATA!$C:$C,$B26,DATA!$N:$N,">="&DATE($I$2,K$4,1),DATA!$N:$N,"<="&DATE($I$2,K$4,K$5)) | ... O27: =SUMIFS(DATA!$M:$M,DATA!$C:$C,$B26,DATA!$N:$N,">="&DATE($I$2,O$4,1),DATA!$N:$N,"<="&DATE($I$2,O$4,O$5)) | P27: =SUM(D27:O27)
A28: 12 | B28: GENTHERM VIETNAM CO., LTD | C28: Kế hoạch | D28: =SUMIFS(DATA!$I:$I,DATA!$C:$C,$B28,DATA!$J:$J,">="&DATE($I$2,D$4,1),DATA!$J:$J,"<="&DATE($I$2,D$4,D$5)) | E28: =SUMIFS(DATA!$I:$I,DATA!$C:$C,$B28,DATA!$J:$J,">="&DATE($I$2,E$4,1),DATA!$J:$J,"<="&DATE($I$2,E$4,E$5)) | F28: =SUMIFS(DATA!$I:$I,DATA!$C:$C,$B28,DATA!$J:$J,">="&DATE($I$2,F$4,1),DATA!$J:$J,"<="&DATE($I$2,F$4,F$5)) | G28: =SUMIFS(DATA!$I:$I,DATA!$C:$C,$B28,DATA!$J:$J,">="&DATE($I$2,G$4,1),DATA!$J:$J,"<="&DATE($I$2,G$4,G$5)) | H28: =SUMIFS(DATA!$I:$I,DATA!$C:$C,$B28,DATA!$J:$J,">="&DATE($I$2,H$4,1),DATA!$J:$J,"<="&DATE($I$2,H$4,H$5)) | I28: =SUMIFS(DATA!$I:$I,DATA!$C:$C,$B28,DATA!$J:$J,">="&DATE($I$2,I$4,1),DATA!$J:$J,"<="&DATE($I$2,I$4,I$5)) | J28: =SUMIFS(DATA!$I:$I,DATA!$C:$C,$B28,DATA!$J:$J,">="&DATE($I$2,J$4,1),DATA!$J:$J,"<="&DATE($I$2,J$4,J$5)) | K28: =SUMIFS(DATA!$I:$I,DATA!$C:$C,$B28,DATA!$J:$J,">="&DATE($I$2,K$4,1),DATA!$J:$J,"<="&DATE($I$2,K$4,K$5)) | ... O28: =SUMIFS(DATA!$I:$I,DATA!$C:$C,$B28,DATA!$J:$J,">="&DATE($I$2,O$4,1),DATA!$J:$J,"<="&DATE($I$2,O$4,O$5)) | P28: =SUM(D28:O28)
C29: Thực tế | D29: =SUMIFS(DATA!$M:$M,DATA!$C:$C,$B28,DATA!$N:$N,">="&DATE($I$2,D$4,1),DATA!$N:$N,"<="&DATE($I$2,D$4,D$5)) | E29: =SUMIFS(DATA!$M:$M,DATA!$C:$C,$B28,DATA!$N:$N,">="&DATE($I$2,E$4,1),DATA!$N:$N,"<="&DATE($I$2,E$4,E$5)) | F29: =SUMIFS(DATA!$M:$M,DATA!$C:$C,$B28,DATA!$N:$N,">="&DATE($I$2,F$4,1),DATA!$N:$N,"<="&DATE($I$2,F$4,F$5)) | G29: =SUMIFS(DATA!$M:$M,DATA!$C:$C,$B28,DATA!$N:$N,">="&DATE($I$2,G$4,1),DATA!$N:$N,"<="&DATE($I$2,G$4,G$5)) | H29: =SUMIFS(DATA!$M:$M,DATA!$C:$C,$B28,DATA!$N:$N,">="&DATE($I$2,H$4,1),DATA!$N:$N,"<="&DATE($I$2,H$4,H$5)) | I29: =SUMIFS(DATA!$M:$M,DATA!$C:$C,$B28,DATA!$N:$N,">="&DATE($I$2,I$4,1),DATA!$N:$N,"<="&DATE($I$2,I$4,I$5)) | J29: =SUMIFS(DATA!$M:$M,DATA!$C:$C,$B28,DATA!$N:$N,">="&DATE($I$2,J$4,1),DATA!$N:$N,"<="&DATE($I$2,J$4,J$5)) | K29: =SUMIFS(DATA!$M:$M,DATA!$C:$C,$B28,DATA!$N:$N,">="&DATE($I$2,K$4,1),DATA!$N:$N,"<="&DATE($I$2,K$4,K$5)) | ... O29: =SUMIFS(DATA!$M:$M,DATA!$C:$C,$B28,DATA!$N:$N,">="&DATE($I$2,O$4,1),DATA!$N:$N,"<="&DATE($I$2,O$4,O$5)) | P29: =SUM(D29:O29)
A30: 13 | B30: FALCON VIETNAM | C30: Kế hoạch | D30: =SUMIFS(DATA!$I:$I,DATA!$C:$C,$B30,DATA!$J:$J,">="&DATE($I$2,D$4,1),DATA!$J:$J,"<="&DATE($I$2,D$4,D$5)) | E30: =SUMIFS(DATA!$I:$I,DATA!$C:$C,$B30,DATA!$J:$J,">="&DATE($I$2,E$4,1),DATA!$J:$J,"<="&DATE($I$2,E$4,E$5)) | F30: =SUMIFS(DATA!$I:$I,DATA!$C:$C,$B30,DATA!$J:$J,">="&DATE($I$2,F$4,1),DATA!$J:$J,"<="&DATE($I$2,F$4,F$5)) | G30: =SUMIFS(DATA!$I:$I,DATA!$C:$C,$B30,DATA!$J:$J,">="&DATE($I$2,G$4,1),DATA!$J:$J,"<="&DATE($I$2,G$4,G$5)) | H30: =SUMIFS(DATA!$I:$I,DATA!$C:$C,$B30,DATA!$J:$J,">="&DATE($I$2,H$4,1),DATA!$J:$J,"<="&DATE($I$2,H$4,H$5)) | I30: =SUMIFS(DATA!$I:$I,DATA!$C:$C,$B30,DATA!$J:$J,">="&DATE($I$2,I$4,1),DATA!$J:$J,"<="&DATE($I$2,I$4,I$5)) | J30: =SUMIFS(DATA!$I:$I,DATA!$C:$C,$B30,DATA!$J:$J,">="&DATE($I$2,J$4,1),DATA!$J:$J,"<="&DATE($I$2,J$4,J$5)) | K30: =SUMIFS(DATA!$I:$I,DATA!$C:$C,$B30,DATA!$J:$J,">="&DATE($I$2,K$4,1),DATA!$J:$J,"<="&DATE($I$2,K$4,K$5)) | ... O30: =SUMIFS(DATA!$I:$I,DATA!$C:$C,$B30,DATA!$J:$J,">="&DATE($I$2,O$4,1),DATA!$J:$J,"<="&DATE($I$2,O$4,O$5)) | P30: =SUM(D30:O30)
C31: Thực tế | D31: =SUMIFS(DATA!$M:$M,DATA!$C:$C,$B30,DATA!$N:$N,">="&DATE($I$2,D$4,1),DATA!$N:$N,"<="&DATE($I$2,D$4,D$5)) | E31: =SUMIFS(DATA!$M:$M,DATA!$C:$C,$B30,DATA!$N:$N,">="&DATE($I$2,E$4,1),DATA!$N:$N,"<="&DATE($I$2,E$4,E$5)) | F31: =SUMIFS(DATA!$M:$M,DATA!$C:$C,$B30,DATA!$N:$N,">="&DATE($I$2,F$4,1),DATA!$N:$N,"<="&DATE($I$2,F$4,F$5)) | G31: =SUMIFS(DATA!$M:$M,DATA!$C:$C,$B30,DATA!$N:$N,">="&DATE($I$2,G$4,1),DATA!$N:$N,"<="&DATE($I$2,G$4,G$5)) | H31: =SUMIFS(DATA!$M:$M,DATA!$C:$C,$B30,DATA!$N:$N,">="&DATE($I$2,H$4,1),DATA!$N:$N,"<="&DATE($I$2,H$4,H$5)) | I31: =SUMIFS(DATA!$M:$M,DATA!$C:$C,$B30,DATA!$N:$N,">="&DATE($I$2,I$4,1),DATA!$N:$N,"<="&DATE($I$2,I$4,I$5)) | J31: =SUMIFS(DATA!$M:$M,DATA!$C:$C,$B30,DATA!$N:$N,">="&DATE($I$2,J$4,1),DATA!$N:$N,"<="&DATE($I$2,J$4,J$5)) | K31: =SUMIFS(DATA!$M:$M,DATA!$C:$C,$B30,DATA!$N:$N,">="&DATE($I$2,K$4,1),DATA!$N:$N,"<="&DATE($I$2,K$4,K$5)) | ... O31: =SUMIFS(DATA!$M:$M,DATA!$C:$C,$B30,DATA!$N:$N,">="&DATE($I$2,O$4,1),DATA!$N:$N,"<="&DATE($I$2,O$4,O$5)) | P31: =SUM(D31:O31)
A32: 14 | B32: HORISON TOWER | C32: Kế hoạch | D32: =SUMIFS(DATA!$I:$I,DATA!$C:$C,$B32,DATA!$J:$J,">="&DATE($I$2,D$4,1),DATA!$J:$J,"<="&DATE($I$2,D$4,D$5)) | E32: =SUMIFS(DATA!$I:$I,DATA!$C:$C,$B32,DATA!$J:$J,">="&DATE($I$2,E$4,1),DATA!$J:$J,"<="&DATE($I$2,E$4,E$5)) | F32: =SUMIFS(DATA!$I:$I,DATA!$C:$C,$B32,DATA!$J:$J,">="&DATE($I$2,F$4,1),DATA!$J:$J,"<="&DATE($I$2,F$4,F$5)) | G32: =SUMIFS(DATA!$I:$I,DATA!$C:$C,$B32,DATA!$J:$J,">="&DATE($I$2,G$4,1),DATA!$J:$J,"<="&DATE($I$2,G$4,G$5)) | H32: =SUMIFS(DATA!$I:$I,DATA!$C:$C,$B32,DATA!$J:$J,">="&DATE($I$2,H$4,1),DATA!$J:$J,"<="&DATE($I$2,H$4,H$5)) | I32: =SUMIFS(DATA!$I:$I,DATA!$C:$C,$B32,DATA!$J:$J,">="&DATE($I$2,I$4,1),DATA!$J:$J,"<="&DATE($I$2,I$4,I$5)) | J32: =SUMIFS(DATA!$I:$I,DATA!$C:$C,$B32,DATA!$J:$J,">="&DATE($I$2,J$4,1),DATA!$J:$J,"<="&DATE($I$2,J$4,J$5)) | K32: =SUMIFS(DATA!$I:$I,DATA!$C:$C,$B32,DATA!$J:$J,">="&DATE($I$2,K$4,1),DATA!$J:$J,"<="&DATE($I$2,K$4,K$5)) | ... O32: =SUMIFS(DATA!$I:$I,DATA!$C:$C,$B32,DATA!$J:$J,">="&DATE($I$2,O$4,1),DATA!$J:$J,"<="&DATE($I$2,O$4,O$5)) | P32: =SUM(D32:O32)
C33: Thực tế | D33: =SUMIFS(DATA!$M:$M,DATA!$C:$C,$B32,DATA!$N:$N,">="&DATE($I$2,D$4,1),DATA!$N:$N,"<="&DATE($I$2,D$4,D$5)) | E33: =SUMIFS(DATA!$M:$M,DATA!$C:$C,$B32,DATA!$N:$N,">="&DATE($I$2,E$4,1),DATA!$N:$N,"<="&DATE($I$2,E$4,E$5)) | F33: =SUMIFS(DATA!$M:$M,DATA!$C:$C,$B32,DATA!$N:$N,">="&DATE($I$2,F$4,1),DATA!$N:$N,"<="&DATE($I$2,F$4,F$5)) | G33: =SUMIFS(DATA!$M:$M,DATA!$C:$C,$B32,DATA!$N:$N,">="&DATE($I$2,G$4,1),DATA!$N:$N,"<="&DATE($I$2,G$4,G$5)) | H33: =SUMIFS(DATA!$M:$M,DATA!$C:$C,$B32,DATA!$N:$N,">="&DATE($I$2,H$4,1),DATA!$N:$N,"<="&DATE($I$2,H$4,H$5)) | I33: =SUMIFS(DATA!$M:$M,DATA!$C:$C,$B32,DATA!$N:$N,">="&DATE($I$2,I$4,1),DATA!$N:$N,"<="&DATE($I$2,I$4,I$5)) | J33: =SUMIFS(DATA!$M:$M,DATA!$C:$C,$B32,DATA!$N:$N,">="&DATE($I$2,J$4,1),DATA!$N:$N,"<="&DATE($I$2,J$4,J$5)) | K33: =SUMIFS(DATA!$M:$M,DATA!$C:$C,$B32,DATA!$N:$N,">="&DATE($I$2,K$4,1),DATA!$N:$N,"<="&DATE($I$2,K$4,K$5)) | ... O33: =SUMIFS(DATA!$M:$M,DATA!$C:$C,$B32,DATA!$N:$N,">="&DATE($I$2,O$4,1),DATA!$N:$N,"<="&DATE($I$2,O$4,O$5)) | P33: =SUM(D33:O33)
A34: 15 | B34: EMBASSY OF FRANCE | C34: Kế hoạch | D34: =SUMIFS(DATA!$I:$I,DATA!$C:$C,$B34,DATA!$J:$J,">="&DATE($I$2,D$4,1),DATA!$J:$J,"<="&DATE($I$2,D$4,D$5)) | E34: =SUMIFS(DATA!$I:$I,DATA!$C:$C,$B34,DATA!$J:$J,">="&DATE($I$2,E$4,1),DATA!$J:$J,"<="&DATE($I$2,E$4,E$5)) | F34: =SUMIFS(DATA!$I:$I,DATA!$C:$C,$B34,DATA!$J:$J,">="&DATE($I$2,F$4,1),DATA!$J:$J,"<="&DATE($I$2,F$4,F$5)) | G34: =SUMIFS(DATA!$I:$I,DATA!$C:$C,$B34,DATA!$J:$J,">="&DATE($I$2,G$4,1),DATA!$J:$J,"<="&DATE($I$2,G$4,G$5)) | H34: =SUMIFS(DATA!$I:$I,DATA!$C:$C,$B34,DATA!$J:$J,">="&DATE($I$2,H$4,1),DATA!$J:$J,"<="&DATE($I$2,H$4,H$5)) | I34: =SUMIFS(DATA!$I:$I,DATA!$C:$C,$B34,DATA!$J:$J,">="&DATE($I$2,I$4,1),DATA!$J:$J,"<="&DATE($I$2,I$4,I$5)) | J34: =SUMIFS(DATA!$I:$I,DATA!$C:$C,$B34,DATA!$J:$J,">="&DATE($I$2,J$4,1),DATA!$J:$J,"<="&DATE($I$2,J$4,J$5)) | K34: =SUMIFS(DATA!$I:$I,DATA!$C:$C,$B34,DATA!$J:$J,">="&DATE($I$2,K$4,1),DATA!$J:$J,"<="&DATE($I$2,K$4,K$5)) | ... O34: =SUMIFS(DATA!$I:$I,DATA!$C:$C,$B34,DATA!$J:$J,">="&DATE($I$2,O$4,1),DATA!$J:$J,"<="&DATE($I$2,O$4,O$5)) | P34: =SUM(D34:O34)
C35: Thực tế | D35: =SUMIFS(DATA!$M:$M,DATA!$C:$C,$B34,DATA!$N:$N,">="&DATE($I$2,D$4,1),DATA!$N:$N,"<="&DATE($I$2,D$4,D$5)) | E35: =SUMIFS(DATA!$M:$M,DATA!$C:$C,$B34,DATA!$N:$N,">="&DATE($I$2,E$4,1),DATA!$N:$N,"<="&DATE($I$2,E$4,E$5)) | F35: =SUMIFS(DATA!$M:$M,DATA!$C:$C,$B34,DATA!$N:$N,">="&DATE($I$2,F$4,1),DATA!$N:$N,"<="&DATE($I$2,F$4,F$5)) | G35: =SUMIFS(DATA!$M:$M,DATA!$C:$C,$B34,DATA!$N:$N,">="&DATE($I$2,G$4,1),DATA!$N:$N,"<="&DATE($I$2,G$4,G$5)) | H35: =SUMIFS(DATA!$M:$M,DATA!$C:$C,$B34,DATA!$N:$N,">="&DATE($I$2,H$4,1),DATA!$N:$N,"<="&DATE($I$2,H$4,H$5)) | I35: =SUMIFS(DATA!$M:$M,DATA!$C:$C,$B34,DATA!$N:$N,">="&DATE($I$2,I$4,1),DATA!$N:$N,"<="&DATE($I$2,I$4,I$5)) | J35: =SUMIFS(DATA!$M:$M,DATA!$C:$C,$B34,DATA!$N:$N,">="&DATE($I$2,J$4,1),DATA!$N:$N,"<="&DATE($I$2,J$4,J$5)) | K35: =SUMIFS(DATA!$M:$M,DATA!$C:$C,$B34,DATA!$N:$N,">="&DATE($I$2,K$4,1),DATA!$N:$N,"<="&DATE($I$2,K$4,K$5)) | ... O35: =SUMIFS(DATA!$M:$M,DATA!$C:$C,$B34,DATA!$N:$N,">="&DATE($I$2,O$4,1),DATA!$N:$N,"<="&DATE($I$2,O$4,O$5)) | P35: =SUM(D35:O35)
A36: 16 | B36: PHC COMPLEX | C36: Kế hoạch | D36: =SUMIFS(DATA!$I:$I,DATA!$C:$C,$B36,DATA!$J:$J,">="&DATE($I$2,D$4,1),DATA!$J:$J,"<="&DATE($I$2,D$4,D$5)) | E36: =SUMIFS(DATA!$I:$I,DATA!$C:$C,$B36,DATA!$J:$J,">="&DATE($I$2,E$4,1),DATA!$J:$J,"<="&DATE($I$2,E$4,E$5)) | F36: =SUMIFS(DATA!$I:$I,DATA!$C:$C,$B36,DATA!$J:$J,">="&DATE($I$2,F$4,1),DATA!$J:$J,"<="&DATE($I$2,F$4,F$5)) | G36: =SUMIFS(DATA!$I:$I,DATA!$C:$C,$B36,DATA!$J:$J,">="&DATE($I$2,G$4,1),DATA!$J:$J,"<="&DATE($I$2,G$4,G$5)) | H36: =SUMIFS(DATA!$I:$I,DATA!$C:$C,$B36,DATA!$J:$J,">="&DATE($I$2,H$4,1),DATA!$J:$J,"<="&DATE($I$2,H$4,H$5)) | I36: =SUMIFS(DATA!$I:$I,DATA!$C:$C,$B36,DATA!$J:$J,">="&DATE($I$2,I$4,1),DATA!$J:$J,"<="&DATE($I$2,I$4,I$5)) | J36: =SUMIFS(DATA!$I:$I,DATA!$C:$C,$B36,DATA!$J:$J,">="&DATE($I$2,J$4,1),DATA!$J:$J,"<="&DATE($I$2,J$4,J$5)) | K36: =SUMIFS(DATA!$I:$I,DATA!$C:$C,$B36,DATA!$J:$J,">="&DATE($I$2,K$4,1),DATA!$J:$J,"<="&DATE($I$2,K$4,K$5)) | ... O36: =SUMIFS(DATA!$I:$I,DATA!$C:$C,$B36,DATA!$J:$J,">="&DATE($I$2,O$4,1),DATA!$J:$J,"<="&DATE($I$2,O$4,O$5)) | P36: =SUM(D36:O36)
C37: Thực tế | D37: =SUMIFS(DATA!$M:$M,DATA!$C:$C,$B36,DATA!$N:$N,">="&DATE($I$2,D$4,1),DATA!$N:$N,"<="&DATE($I$2,D$4,D$5)) | E37: =SUMIFS(DATA!$M:$M,DATA!$C:$C,$B36,DATA!$N:$N,">="&DATE($I$2,E$4,1),DATA!$N:$N,"<="&DATE($I$2,E$4,E$5)) | F37: =SUMIFS(DATA!$M:$M,DATA!$C:$C,$B36,DATA!$N:$N,">="&DATE($I$2,F$4,1),DATA!$N:$N,"<="&DATE($I$2,F$4,F$5)) | G37: =SUMIFS(DATA!$M:$M,DATA!$C:$C,$B36,DATA!$N:$N,">="&DATE($I$2,G$4,1),DATA!$N:$N,"<="&DATE($I$2,G$4,G$5)) | H37: =SUMIFS(DATA!$M:$M,DATA!$C:$C,$B36,DATA!$N:$N,">="&DATE($I$2,H$4,1),DATA!$N:$N,"<="&DATE($I$2,H$4,H$5)) | I37: =SUMIFS(DATA!$M:$M,DATA!$C:$C,$B36,DATA!$N:$N,">="&DATE($I$2,I$4,1),DATA!$N:$N,"<="&DATE($I$2,I$4,I$5)) | J37: =SUMIFS(DATA!$M:$M,DATA!$C:$C,$B36,DATA!$N:$N,">="&DATE($I$2,J$4,1),DATA!$N:$N,"<="&DATE($I$2,J$4,J$5)) | K37: =SUMIFS(DATA!$M:$M,DATA!$C:$C,$B36,DATA!$N:$N,">="&DATE($I$2,K$4,1),DATA!$N:$N,"<="&DATE($I$2,K$4,K$5)) | ... O37: =SUMIFS(DATA!$M:$M,DATA!$C:$C,$B36,DATA!$N:$N,">="&DATE($I$2,O$4,1),DATA!$N:$N,"<="&DATE($I$2,O$4,O$5)) | P37: =SUM(D37:O37)
A38: 17 | B38: FSOFT - DUY TÂN | C38: Kế hoạch | D38: =SUMIFS(DATA!$I:$I,DATA!$C:$C,$B38,DATA!$J:$J,">="&DATE($I$2,D$4,1),DATA!$J:$J,"<="&DATE($I$2,D$4,D$5)) | E38: =SUMIFS(DATA!$I:$I,DATA!$C:$C,$B38,DATA!$J:$J,">="&DATE($I$2,E$4,1),DATA!$J:$J,"<="&DATE($I$2,E$4,E$5)) | F38: =SUMIFS(DATA!$I:$I,DATA!$C:$C,$B38,DATA!$J:$J,">="&DATE($I$2,F$4,1),DATA!$J:$J,"<="&DATE($I$2,F$4,F$5)) | G38: =SUMIFS(DATA!$I:$I,DATA!$C:$C,$B38,DATA!$J:$J,">="&DATE($I$2,G$4,1),DATA!$J:$J,"<="&DATE($I$2,G$4,G$5)) | H38: =SUMIFS(DATA!$I:$I,DATA!$C:$C,$B38,DATA!$J:$J,">="&DATE($I$2,H$4,1),DATA!$J:$J,"<="&DATE($I$2,H$4,H$5)) | I38: =SUMIFS(DATA!$I:$I,DATA!$C:$C,$B38,DATA!$J:$J,">="&DATE($I$2,I$4,1),DATA!$J:$J,"<="&DATE($I$2,I$4,I$5)) | J38: =SUMIFS(DATA!$I:$I,DATA!$C:$C,$B38,DATA!$J:$J,">="&DATE($I$2,J$4,1),DATA!$J:$J,"<="&DATE($I$2,J$4,J$5)) | K38: =SUMIFS(DATA!$I:$I,DATA!$C:$C,$B38,DATA!$J:$J,">="&DATE($I$2,K$4,1),DATA!$J:$J,"<="&DATE($I$2,K$4,K$5)) | ... O38: =SUMIFS(DATA!$I:$I,DATA!$C:$C,$B38,DATA!$J:$J,">="&DATE($I$2,O$4,1),DATA!$J:$J,"<="&DATE($I$2,O$4,O$5)) | P38: =SUM(D38:O38)
C39: Thực tế | D39: =SUMIFS(DATA!$M:$M,DATA!$C:$C,$B38,DATA!$N:$N,">="&DATE($I$2,D$4,1),DATA!$N:$N,"<="&DATE($I$2,D$4,D$5)) | E39: =SUMIFS(DATA!$M:$M,DATA!$C:$C,$B38,DATA!$N:$N,">="&DATE($I$2,E$4,1),DATA!$N:$N,"<="&DATE($I$2,E$4,E$5)) | F39: =SUMIFS(DATA!$M:$M,DATA!$C:$C,$B38,DATA!$N:$N,">="&DATE($I$2,F$4,1),DATA!$N:$N,"<="&DATE($I$2,F$4,F$5)) | G39: =SUMIFS(DATA!$M:$M,DATA!$C:$C,$B38,DATA!$N:$N,">="&DATE($I$2,G$4,1),DATA!$N:$N,"<="&DATE($I$2,G$4,G$5)) | H39: =SUMIFS(DATA!$M:$M,DATA!$C:$C,$B38,DATA!$N:$N,">="&DATE($I$2,H$4,1),DATA!$N:$N,"<="&DATE($I$2,H$4,H$5)) | I39: =SUMIFS(DATA!$M:$M,DATA!$C:$C,$B38,DATA!$N:$N,">="&DATE($I$2,I$4,1),DATA!$N:$N,"<="&DATE($I$2,I$4,I$5)) | J39: =SUMIFS(DATA!$M:$M,DATA!$C:$C,$B38,DATA!$N:$N,">="&DATE($I$2,J$4,1),DATA!$N:$N,"<="&DATE($I$2,J$4,J$5)) | K39: =SUMIFS(DATA!$M:$M,DATA!$C:$C,$B38,DATA!$N:$N,">="&DATE($I$2,K$4,1),DATA!$N:$N,"<="&DATE($I$2,K$4,K$5)) | ... O39: =SUMIFS(DATA!$M:$M,DATA!$C:$C,$B38,DATA!$N:$N,">="&DATE($I$2,O$4,1),DATA!$N:$N,"<="&DATE($I$2,O$4,O$5)) | P39: =SUM(D39:O39)
A40: 18 | B40: US EMBASSY HANOI | C40: Kế hoạch | D40: =SUMIFS(DATA!$I:$I,DATA!$C:$C,$B40,DATA!$J:$J,">="&DATE($I$2,D$4,1),DATA!$J:$J,"<="&DATE($I$2,D$4,D$5)) | E40: =SUMIFS(DATA!$I:$I,DATA!$C:$C,$B40,DATA!$J:$J,">="&DATE($I$2,E$4,1),DATA!$J:$J,"<="&DATE($I$2,E$4,E$5)) | F40: =SUMIFS(DATA!$I:$I,DATA!$C:$C,$B40,DATA!$J:$J,">="&DATE($I$2,F$4,1),DATA!$J:$J,"<="&DATE($I$2,F$4,F$5)) | G40: =SUMIFS(DATA!$I:$I,DATA!$C:$C,$B40,DATA!$J:$J,">="&DATE($I$2,G$4,1),DATA!$J:$J,"<="&DATE($I$2,G$4,G$5)) | H40: =SUMIFS(DATA!$I:$I,DATA!$C:$C,$B40,DATA!$J:$J,">="&DATE($I$2,H$4,1),DATA!$J:$J,"<="&DATE($I$2,H$4,H$5)) | I40: =SUMIFS(DATA!$I:$I,DATA!$C:$C,$B40,DATA!$J:$J,">="&DATE($I$2,I$4,1),DATA!$J:$J,"<="&DATE($I$2,I$4,I$5)) | J40: =SUMIFS(DATA!$I:$I,DATA!$C:$C,$B40,DATA!$J:$J,">="&DATE($I$2,J$4,1),DATA!$J:$J,"<="&DATE($I$2,J$4,J$5)) | K40: =SUMIFS(DATA!$I:$I,DATA!$C:$C,$B40,DATA!$J:$J,">="&DATE($I$2,K$4,1),DATA!$J:$J,"<="&DATE($I$2,K$4,K$5)) | ... O40: =SUMIFS(DATA!$I:$I,DATA!$C:$C,$B40,DATA!$J:$J,">="&DATE($I$2,O$4,1),DATA!$J:$J,"<="&DATE($I$2,O$4,O$5)) | P40: =SUM(D40:O40)
C41: Thực tế | D41: =SUMIFS(DATA!$M:$M,DATA!$C:$C,$B40,DATA!$N:$N,">="&DATE($I$2,D$4,1),DATA!$N:$N,"<="&DATE($I$2,D$4,D$5)) | E41: =SUMIFS(DATA!$M:$M,DATA!$C:$C,$B40,DATA!$N:$N,">="&DATE($I$2,E$4,1),DATA!$N:$N,"<="&DATE($I$2,E$4,E$5)) | F41: =SUMIFS(DATA!$M:$M,DATA!$C:$C,$B40,DATA!$N:$N,">="&DATE($I$2,F$4,1),DATA!$N:$N,"<="&DATE($I$2,F$4,F$5)) | G41: =SUMIFS(DATA!$M:$M,DATA!$C:$C,$B40,DATA!$N:$N,">="&DATE($I$2,G$4,1),DATA!$N:$N,"<="&DATE($I$2,G$4,G$5)) | H41: =SUMIFS(DATA!$M:$M,DATA!$C:$C,$B40,DATA!$N:$N,">="&DATE($I$2,H$4,1),DATA!$N:$N,"<="&DATE($I$2,H$4,H$5)) | I41: =SUMIFS(DATA!$M:$M,DATA!$C:$C,$B40,DATA!$N:$N,">="&DATE($I$2,I$4,1),DATA!$N:$N,"<="&DATE($I$2,I$4,I$5)) | J41: =SUMIFS(DATA!$M:$M,DATA!$C:$C,$B40,DATA!$N:$N,">="&DATE($I$2,J$4,1),DATA!$N:$N,"<="&DATE($I$2,J$4,J$5)) | K41: =SUMIFS(DATA!$M:$M,DATA!$C:$C,$B40,DATA!$N:$N,">="&DATE($I$2,K$4,1),DATA!$N:$N,"<="&DATE($I$2,K$4,K$5)) | ... O41: =SUMIFS(DATA!$M:$M,DATA!$C:$C,$B40,DATA!$N:$N,">="&DATE($I$2,O$4,1),DATA!$N:$N,"<="&DATE($I$2,O$4,O$5)) | P41: =SUM(D41:O41)
A42: 19 | B42: FIVE STAR GARDEN | C42: Kế hoạch | D42: =SUMIFS(DATA!$I:$I,DATA!$C:$C,$B42,DATA!$J:$J,">="&DATE($I$2,D$4,1),DATA!$J:$J,"<="&DATE($I$2,D$4,D$5)) | E42: =SUMIFS(DATA!$I:$I,DATA!$C:$C,$B42,DATA!$J:$J,">="&DATE($I$2,E$4,1),DATA!$J:$J,"<="&DATE($I$2,E$4,E$5)) | F42: =SUMIFS(DATA!$I:$I,DATA!$C:$C,$B42,DATA!$J:$J,">="&DATE($I$2,F$4,1),DATA!$J:$J,"<="&DATE($I$2,F$4,F$5)) | G42: =SUMIFS(DATA!$I:$I,DATA!$C:$C,$B42,DATA!$J:$J,">="&DATE($I$2,G$4,1),DATA!$J:$J,"<="&DATE($I$2,G$4,G$5)) | H42: =SUMIFS(DATA!$I:$I,DATA!$C:$C,$B42,DATA!$J:$J,">="&DATE($I$2,H$4,1),DATA!$J:$J,"<="&DATE($I$2,H$4,H$5)) | I42: =SUMIFS(DATA!$I:$I,DATA!$C:$C,$B42,DATA!$J:$J,">="&DATE($I$2,I$4,1),DATA!$J:$J,"<="&DATE($I$2,I$4,I$5)) | J42: =SUMIFS(DATA!$I:$I,DATA!$C:$C,$B42,DATA!$J:$J,">="&DATE($I$2,J$4,1),DATA!$J:$J,"<="&DATE($I$2,J$4,J$5)) | K42: =SUMIFS(DATA!$I:$I,DATA!$C:$C,$B42,DATA!$J:$J,">="&DATE($I$2,K$4,1),DATA!$J:$J,"<="&DATE($I$2,K$4,K$5)) | ... O42: =SUMIFS(DATA!$I:$I,DATA!$C:$C,$B42,DATA!$J:$J,">="&DATE($I$2,O$4,1),DATA!$J:$J,"<="&DATE($I$2,O$4,O$5)) | P42: =SUM(D42:O42)
C43: Thực tế | D43: =SUMIFS(DATA!$M:$M,DATA!$C:$C,$B42,DATA!$N:$N,">="&DATE($I$2,D$4,1),DATA!$N:$N,"<="&DATE($I$2,D$4,D$5)) | E43: =SUMIFS(DATA!$M:$M,DATA!$C:$C,$B42,DATA!$N:$N,">="&DATE($I$2,E$4,1),DATA!$N:$N,"<="&DATE($I$2,E$4,E$5)) | F43: =SUMIFS(DATA!$M:$M,DATA!$C:$C,$B42,DATA!$N:$N,">="&DATE($I$2,F$4,1),DATA!$N:$N,"<="&DATE($I$2,F$4,F$5)) | G43: =SUMIFS(DATA!$M:$M,DATA!$C:$C,$B42,DATA!$N:$N,">="&DATE($I$2,G$4,1),DATA!$N:$N,"<="&DATE($I$2,G$4,G$5)) | H43: =SUMIFS(DATA!$M:$M,DATA!$C:$C,$B42,DATA!$N:$N,">="&DATE($I$2,H$4,1),DATA!$N:$N,"<="&DATE($I$2,H$4,H$5)) | I43: =SUMIFS(DATA!$M:$M,DATA!$C:$C,$B42,DATA!$N:$N,">="&DATE($I$2,I$4,1),DATA!$N:$N,"<="&DATE($I$2,I$4,I$5)) | J43: =SUMIFS(DATA!$M:$M,DATA!$C:$C,$B42,DATA!$N:$N,">="&DATE($I$2,J$4,1),DATA!$N:$N,"<="&DATE($I$2,J$4,J$5)) | K43: =SUMIFS(DATA!$M:$M,DATA!$C:$C,$B42,DATA!$N:$N,">="&DATE($I$2,K$4,1),DATA!$N:$N,"<="&DATE($I$2,K$4,K$5)) | ... O43: =SUMIFS(DATA!$M:$M,DATA!$C:$C,$B42,DATA!$N:$N,">="&DATE($I$2,O$4,1),DATA!$N:$N,"<="&DATE($I$2,O$4,O$5)) | P43: =SUM(D43:O43)
A44: 20 | B44: EMBASSY OF CANADA | C44: Kế hoạch | D44: =SUMIFS(DATA!$I:$I,DATA!$C:$C,$B44,DATA!$J:$J,">="&DATE($I$2,D$4,1),DATA!$J:$J,"<="&DATE($I$2,D$4,D$5)) | E44: =SUMIFS(DATA!$I:$I,DATA!$C:$C,$B44,DATA!$J:$J,">="&DATE($I$2,E$4,1),DATA!$J:$J,"<="&DATE($I$2,E$4,E$5)) | F44: =SUMIFS(DATA!$I:$I,DATA!$C:$C,$B44,DATA!$J:$J,">="&DATE($I$2,F$4,1),DATA!$J:$J,"<="&DATE($I$2,F$4,F$5)) | G44: =SUMIFS(DATA!$I:$I,DATA!$C:$C,$B44,DATA!$J:$J,">="&DATE($I$2,G$4,1),DATA!$J:$J,"<="&DATE($I$2,G$4,G$5)) | H44: =SUMIFS(DATA!$I:$I,DATA!$C:$C,$B44,DATA!$J:$J,">="&DATE($I$2,H$4,1),DATA!$J:$J,"<="&DATE($I$2,H$4,H$5)) | I44: =SUMIFS(DATA!$I:$I,DATA!$C:$C,$B44,DATA!$J:$J,">="&DATE($I$2,I$4,1),DATA!$J:$J,"<="&DATE($I$2,I$4,I$5)) | J44: =SUMIFS(DATA!$I:$I,DATA!$C:$C,$B44,DATA!$J:$J,">="&DATE($I$2,J$4,1),DATA!$J:$J,"<="&DATE($I$2,J$4,J$5)) | K44: =SUMIFS(DATA!$I:$I,DATA!$C:$C,$B44,DATA!$J:$J,">="&DATE($I$2,K$4,1),DATA!$J:$J,"<="&DATE($I$2,K$4,K$5)) | ... O44: =SUMIFS(DATA!$I:$I,DATA!$C:$C,$B44,DATA!$J:$J,">="&DATE($I$2,O$4,1),DATA!$J:$J,"<="&DATE($I$2,O$4,O$5)) | P44: =SUM(D44:O44)
C45: Thực tế | D45: =SUMIFS(DATA!$M:$M,DATA!$C:$C,$B44,DATA!$N:$N,">="&DATE($I$2,D$4,1),DATA!$N:$N,"<="&DATE($I$2,D$4,D$5)) | E45: =SUMIFS(DATA!$M:$M,DATA!$C:$C,$B44,DATA!$N:$N,">="&DATE($I$2,E$4,1),DATA!$N:$N,"<="&DATE($I$2,E$4,E$5)) | F45: =SUMIFS(DATA!$M:$M,DATA!$C:$C,$B44,DATA!$N:$N,">="&DATE($I$2,F$4,1),DATA!$N:$N,"<="&DATE($I$2,F$4,F$5)) | G45: =SUMIFS(DATA!$M:$M,DATA!$C:$C,$B44,DATA!$N:$N,">="&DATE($I$2,G$4,1),DATA!$N:$N,"<="&DATE($I$2,G$4,G$5)) | H45: =SUMIFS(DATA!$M:$M,DATA!$C:$C,$B44,DATA!$N:$N,">="&DATE($I$2,H$4,1),DATA!$N:$N,"<="&DATE($I$2,H$4,H$5)) | I45: =SUMIFS(DATA!$M:$M,DATA!$C:$C,$B44,DATA!$N:$N,">="&DATE($I$2,I$4,1),DATA!$N:$N,"<="&DATE($I$2,I$4,I$5)) | J45: =SUMIFS(DATA!$M:$M,DATA!$C:$C,$B44,DATA!$N:$N,">="&DATE($I$2,J$4,1),DATA!$N:$N,"<="&DATE($I$2,J$4,J$5)) | K45: =SUMIFS(DATA!$M:$M,DATA!$C:$C,$B44,DATA!$N:$N,">="&DATE($I$2,K$4,1),DATA!$N:$N,"<="&DATE($I$2,K$4,K$5)) | ... O45: =SUMIFS(DATA!$M:$M,DATA!$C:$C,$B44,DATA!$N:$N,">="&DATE($I$2,O$4,1),DATA!$N:$N,"<="&DATE($I$2,O$4,O$5)) | P45: =SUM(D45:O45)
A46: 21 | B46: TOYOTA MOTOR VIETNAM | C46: Kế hoạch | D46: =SUMIFS(DATA!$I:$I,DATA!$C:$C,$B46,DATA!$J:$J,">="&DATE($I$2,D$4,1),DATA!$J:$J,"<="&DATE($I$2,D$4,D$5)) | E46: =SUMIFS(DATA!$I:$I,DATA!$C:$C,$B46,DATA!$J:$J,">="&DATE($I$2,E$4,1),DATA!$J:$J,"<="&DATE($I$2,E$4,E$5)) | F46: =SUMIFS(DATA!$I:$I,DATA!$C:$C,$B46,DATA!$J:$J,">="&DATE($I$2,F$4,1),DATA!$J:$J,"<="&DATE($I$2,F$4,F$5)) | G46: =SUMIFS(DATA!$I:$I,DATA!$C:$C,$B46,DATA!$J:$J,">="&DATE($I$2,G$4,1),DATA!$J:$J,"<="&DATE($I$2,G$4,G$5)) | H46: =SUMIFS(DATA!$I:$I,DATA!$C:$C,$B46,DATA!$J:$J,">="&DATE($I$2,H$4,1),DATA!$J:$J,"<="&DATE($I$2,H$4,H$5)) | I46: =SUMIFS(DATA!$I:$I,DATA!$C:$C,$B46,DATA!$J:$J,">="&DATE($I$2,I$4,1),DATA!$J:$J,"<="&DATE($I$2,I$4,I$5)) | J46: =SUMIFS(DATA!$I:$I,DATA!$C:$C,$B46,DATA!$J:$J,">="&DATE($I$2,J$4,1),DATA!$J:$J,"<="&DATE($I$2,J$4,J$5)) | K46: =SUMIFS(DATA!$I:$I,DATA!$C:$C,$B46,DATA!$J:$J,">="&DATE($I$2,K$4,1),DATA!$J:$J,"<="&DATE($I$2,K$4,K$5)) | ... O46: =SUMIFS(DATA!$I:$I,DATA!$C:$C,$B46,DATA!$J:$J,">="&DATE($I$2,O$4,1),DATA!$J:$J,"<="&DATE($I$2,O$4,O$5)) | P46: =SUM(D46:O46)
C47: Thực tế | D47: =SUMIFS(DATA!$M:$M,DATA!$C:$C,$B46,DATA!$N:$N,">="&DATE($I$2,D$4,1),DATA!$N:$N,"<="&DATE($I$2,D$4,D$5)) | E47: =SUMIFS(DATA!$M:$M,DATA!$C:$C,$B46,DATA!$N:$N,">="&DATE($I$2,E$4,1),DATA!$N:$N,"<="&DATE($I$2,E$4,E$5)) | F47: =SUMIFS(DATA!$M:$M,DATA!$C:$C,$B46,DATA!$N:$N,">="&DATE($I$2,F$4,1),DATA!$N:$N,"<="&DATE($I$2,F$4,F$5)) | G47: =SUMIFS(DATA!$M:$M,DATA!$C:$C,$B46,DATA!$N:$N,">="&DATE($I$2,G$4,1),DATA!$N:$N,"<="&DATE($I$2,G$4,G$5)) | H47: =SUMIFS(DATA!$M:$M,DATA!$C:$C,$B46,DATA!$N:$N,">="&DATE($I$2,H$4,1),DATA!$N:$N,"<="&DATE($I$2,H$4,H$5)) | I47: =SUMIFS(DATA!$M:$M,DATA!$C:$C,$B46,DATA!$N:$N,">="&DATE($I$2,I$4,1),DATA!$N:$N,"<="&DATE($I$2,I$4,I$5)) | J47: =SUMIFS(DATA!$M:$M,DATA!$C:$C,$B46,DATA!$N:$N,">="&DATE($I$2,J$4,1),DATA!$N:$N,"<="&DATE($I$2,J$4,J$5)) | K47: =SUMIFS(DATA!$M:$M,DATA!$C:$C,$B46,DATA!$N:$N,">="&DATE($I$2,K$4,1),DATA!$N:$N,"<="&DATE($I$2,K$4,K$5)) | ... O47: =SUMIFS(DATA!$M:$M,DATA!$C:$C,$B46,DATA!$N:$N,">="&DATE($I$2,O$4,1),DATA!$N:$N,"<="&DATE($I$2,O$4,O$5)) | P47: =SUM(D47:O47)
A48: 22 | B48: DUY HUNG CO.,LTD | C48: Kế hoạch | D48: =SUMIFS(DATA!$I:$I,DATA!$C:$C,$B48,DATA!$J:$J,">="&DATE($I$2,D$4,1),DATA!$J:$J,"<="&DATE($I$2,D$4,D$5)) | E48: =SUMIFS(DATA!$I:$I,DATA!$C:$C,$B48,DATA!$J:$J,">="&DATE($I$2,E$4,1),DATA!$J:$J,"<="&DATE($I$2,E$4,E$5)) | F48: =SUMIFS(DATA!$I:$I,DATA!$C:$C,$B48,DATA!$J:$J,">="&DATE($I$2,F$4,1),DATA!$J:$J,"<="&DATE($I$2,F$4,F$5)) | G48: =SUMIFS(DATA!$I:$I,DATA!$C:$C,$B48,DATA!$J:$J,">="&DATE($I$2,G$4,1),DATA!$J:$J,"<="&DATE($I$2,G$4,G$5)) | H48: =SUMIFS(DATA!$I:$I,DATA!$C:$C,$B48,DATA!$J:$J,">="&DATE($I$2,H$4,1),DATA!$J:$J,"<="&DATE($I$2,H$4,H$5)) | I48: =SUMIFS(DATA!$I:$I,DATA!$C:$C,$B48,DATA!$J:$J,">="&DATE($I$2,I$4,1),DATA!$J:$J,"<="&DATE($I$2,I$4,I$5)) | J48: =SUMIFS(DATA!$I:$I,DATA!$C:$C,$B48,DATA!$J:$J,">="&DATE($I$2,J$4,1),DATA!$J:$J,"<="&DATE($I$2,J$4,J$5)) | K48: =SUMIFS(DATA!$I:$I,DATA!$C:$C,$B48,DATA!$J:$J,">="&DATE($I$2,K$4,1),DATA!$J:$J,"<="&DATE($I$2,K$4,K$5)) | ... O48: =SUMIFS(DATA!$I:$I,DATA!$C:$C,$B48,DATA!$J:$J,">="&DATE($I$2,O$4,1),DATA!$J:$J,"<="&DATE($I$2,O$4,O$5)) | P48: =SUM(D48:O48)
C49: Thực tế | D49: =SUMIFS(DATA!$M:$M,DATA!$C:$C,$B48,DATA!$N:$N,">="&DATE($I$2,D$4,1),DATA!$N:$N,"<="&DATE($I$2,D$4,D$5)) | E49: =SUMIFS(DATA!$M:$M,DATA!$C:$C,$B48,DATA!$N:$N,">="&DATE($I$2,E$4,1),DATA!$N:$N,"<="&DATE($I$2,E$4,E$5)) | F49: =SUMIFS(DATA!$M:$M,DATA!$C:$C,$B48,DATA!$N:$N,">="&DATE($I$2,F$4,1),DATA!$N:$N,"<="&DATE($I$2,F$4,F$5)) | G49: =SUMIFS(DATA!$M:$M,DATA!$C:$C,$B48,DATA!$N:$N,">="&DATE($I$2,G$4,1),DATA!$N:$N,"<="&DATE($I$2,G$4,G$5)) | H49: =SUMIFS(DATA!$M:$M,DATA!$C:$C,$B48,DATA!$N:$N,">="&DATE($I$2,H$4,1),DATA!$N:$N,"<="&DATE($I$2,H$4,H$5)) | I49: =SUMIFS(DATA!$M:$M,DATA!$C:$C,$B48,DATA!$N:$N,">="&DATE($I$2,I$4,1),DATA!$N:$N,"<="&DATE($I$2,I$4,I$5)) | J49: =SUMIFS(DATA!$M:$M,DATA!$C:$C,$B48,DATA!$N:$N,">="&DATE($I$2,J$4,1),DATA!$N:$N,"<="&DATE($I$2,J$4,J$5)) | K49: =SUMIFS(DATA!$M:$M,DATA!$C:$C,$B48,DATA!$N:$N,">="&DATE($I$2,K$4,1),DATA!$N:$N,"<="&DATE($I$2,K$4,K$5)) | ... O49: =SUMIFS(DATA!$M:$M,DATA!$C:$C,$B48,DATA!$N:$N,">="&DATE($I$2,O$4,1),DATA!$N:$N,"<="&DATE($I$2,O$4,O$5)) | P49: =SUM(D49:O49)
A50: 23 | B50: ĐIỆN LỰC BẮC GIANG | C50: Kế hoạch | D50: =SUMIFS(DATA!$I:$I,DATA!$C:$C,$B50,DATA!$J:$J,">="&DATE($I$2,D$4,1),DATA!$J:$J,"<="&DATE($I$2,D$4,D$5)) | E50: =SUMIFS(DATA!$I:$I,DATA!$C:$C,$B50,DATA!$J:$J,">="&DATE($I$2,E$4,1),DATA!$J:$J,"<="&DATE($I$2,E$4,E$5)) | F50: =SUMIFS(DATA!$I:$I,DATA!$C:$C,$B50,DATA!$J:$J,">="&DATE($I$2,F$4,1),DATA!$J:$J,"<="&DATE($I$2,F$4,F$5)) | G50: =SUMIFS(DATA!$I:$I,DATA!$C:$C,$B50,DATA!$J:$J,">="&DATE($I$2,G$4,1),DATA!$J:$J,"<="&DATE($I$2,G$4,G$5)) | H50: =SUMIFS(DATA!$I:$I,DATA!$C:$C,$B50,DATA!$J:$J,">="&DATE($I$2,H$4,1),DATA!$J:$J,"<="&DATE($I$2,H$4,H$5)) | I50: =SUMIFS(DATA!$I:$I,DATA!$C:$C,$B50,DATA!$J:$J,">="&DATE($I$2,I$4,1),DATA!$J:$J,"<="&DATE($I$2,I$4,I$5)) | J50: =SUMIFS(DATA!$I:$I,DATA!$C:$C,$B50,DATA!$J:$J,">="&DATE($I$2,J$4,1),DATA!$J:$J,"<="&DATE($I$2,J$4,J$5)) | K50: =SUMIFS(DATA!$I:$I,DATA!$C:$C,$B50,DATA!$J:$J,">="&DATE($I$2,K$4,1),DATA!$J:$J,"<="&DATE($I$2,K$4,K$5)) | ... O50: =SUMIFS(DATA!$I:$I,DATA!$C:$C,$B50,DATA!$J:$J,">="&DATE($I$2,O$4,1),DATA!$J:$J,"<="&DATE($I$2,O$4,O$5)) | P50: =SUM(D50:O50)
C51: Thực tế | D51: =SUMIFS(DATA!$M:$M,DATA!$C:$C,$B50,DATA!$N:$N,">="&DATE($I$2,D$4,1),DATA!$N:$N,"<="&DATE($I$2,D$4,D$5)) | E51: =SUMIFS(DATA!$M:$M,DATA!$C:$C,$B50,DATA!$N:$N,">="&DATE($I$2,E$4,1),DATA!$N:$N,"<="&DATE($I$2,E$4,E$5)) | F51: =SUMIFS(DATA!$M:$M,DATA!$C:$C,$B50,DATA!$N:$N,">="&DATE($I$2,F$4,1),DATA!$N:$N,"<="&DATE($I$2,F$4,F$5)) | G51: =SUMIFS(DATA!$M:$M,DATA!$C:$C,$B50,DATA!$N:$N,">="&DATE($I$2,G$4,1),DATA!$N:$N,"<="&DATE($I$2,G$4,G$5)) | H51: =SUMIFS(DATA!$M:$M,DATA!$C:$C,$B50,DATA!$N:$N,">="&DATE($I$2,H$4,1),DATA!$N:$N,"<="&DATE($I$2,H$4,H$5)) | I51: =SUMIFS(DATA!$M:$M,DATA!$C:$C,$B50,DATA!$N:$N,">="&DATE($I$2,I$4,1),DATA!$N:$N,"<="&DATE($I$2,I$4,I$5)) | J51: =SUMIFS(DATA!$M:$M,DATA!$C:$C,$B50,DATA!$N:$N,">="&DATE($I$2,J$4,1),DATA!$N:$N,"<="&DATE($I$2,J$4,J$5)) | K51: =SUMIFS(DATA!$M:$M,DATA!$C:$C,$B50,DATA!$N:$N,">="&DATE($I$2,K$4,1),DATA!$N:$N,"<="&DATE($I$2,K$4,K$5)) | ... O51: =SUMIFS(DATA!$M:$M,DATA!$C:$C,$B50,DATA!$N:$N,">="&DATE($I$2,O$4,1),DATA!$N:$N,"<="&DATE($I$2,O$4,O$5)) | P51: =SUM(D51:O51)
A52: 24 | B52: TOYOTA BOSHOKU HANOI CO., LTD | C52: Kế hoạch | D52: =SUMIFS(DATA!$I:$I,DATA!$C:$C,$B52,DATA!$J:$J,">="&DATE($I$2,D$4,1),DATA!$J:$J,"<="&DATE($I$2,D$4,D$5)) | E52: =SUMIFS(DATA!$I:$I,DATA!$C:$C,$B52,DATA!$J:$J,">="&DATE($I$2,E$4,1),DATA!$J:$J,"<="&DATE($I$2,E$4,E$5)) | F52: =SUMIFS(DATA!$I:$I,DATA!$C:$C,$B52,DATA!$J:$J,">="&DATE($I$2,F$4,1),DATA!$J:$J,"<="&DATE($I$2,F$4,F$5)) | G52: =SUMIFS(DATA!$I:$I,DATA!$C:$C,$B52,DATA!$J:$J,">="&DATE($I$2,G$4,1),DATA!$J:$J,"<="&DATE($I$2,G$4,G$5)) | H52: =SUMIFS(DATA!$I:$I,DATA!$C:$C,$B52,DATA!$J:$J,">="&DATE($I$2,H$4,1),DATA!$J:$J,"<="&DATE($I$2,H$4,H$5)) | I52: =SUMIFS(DATA!$I:$I,DATA!$C:$C,$B52,DATA!$J:$J,">="&DATE($I$2,I$4,1),DATA!$J:$J,"<="&DATE($I$2,I$4,I$5)) | J52: =SUMIFS(DATA!$I:$I,DATA!$C:$C,$B52,DATA!$J:$J,">="&DATE($I$2,J$4,1),DATA!$J:$J,"<="&DATE($I$2,J$4,J$5)) | K52: =SUMIFS(DATA!$I:$I,DATA!$C:$C,$B52,DATA!$J:$J,">="&DATE($I$2,K$4,1),DATA!$J:$J,"<="&DATE($I$2,K$4,K$5)) | ... O52: =SUMIFS(DATA!$I:$I,DATA!$C:$C,$B52,DATA!$J:$J,">="&DATE($I$2,O$4,1),DATA!$J:$J,"<="&DATE($I$2,O$4,O$5)) | P52: =SUM(D52:O52)
C53: Thực tế | D53: =SUMIFS(DATA!$M:$M,DATA!$C:$C,$B52,DATA!$N:$N,">="&DATE($I$2,D$4,1),DATA!$N:$N,"<="&DATE($I$2,D$4,D$5)) | E53: =SUMIFS(DATA!$M:$M,DATA!$C:$C,$B52,DATA!$N:$N,">="&DATE($I$2,E$4,1),DATA!$N:$N,"<="&DATE($I$2,E$4,E$5)) | F53: =SUMIFS(DATA!$M:$M,DATA!$C:$C,$B52,DATA!$N:$N,">="&DATE($I$2,F$4,1),DATA!$N:$N,"<="&DATE($I$2,F$4,F$5)) | G53: =SUMIFS(DATA!$M:$M,DATA!$C:$C,$B52,DATA!$N:$N,">="&DATE($I$2,G$4,1),DATA!$N:$N,"<="&DATE($I$2,G$4,G$5)) | H53: =SUMIFS(DATA!$M:$M,DATA!$C:$C,$B52,DATA!$N:$N,">="&DATE($I$2,H$4,1),DATA!$N:$N,"<="&DATE($I$2,H$4,H$5)) | I53: =SUMIFS(DATA!$M:$M,DATA!$C:$C,$B52,DATA!$N:$N,">="&DATE($I$2,I$4,1),DATA!$N:$N,"<="&DATE($I$2,I$4,I$5)) | J53: =SUMIFS(DATA!$M:$M,DATA!$C:$C,$B52,DATA!$N:$N,">="&DATE($I$2,J$4,1),DATA!$N:$N,"<="&DATE($I$2,J$4,J$5)) | K53: =SUMIFS(DATA!$M:$M,DATA!$C:$C,$B52,DATA!$N:$N,">="&DATE($I$2,K$4,1),DATA!$N:$N,"<="&DATE($I$2,K$4,K$5)) | ... O53: =SUMIFS(DATA!$M:$M,DATA!$C:$C,$B52,DATA!$N:$N,">="&DATE($I$2,O$4,1),DATA!$N:$N,"<="&DATE($I$2,O$4,O$5)) | P53: =SUM(D53:O53)
A54: 25 | B54: TOYOTA BOSHOKU HANOI CO., LTD(Inactive) | C54: Kế hoạch | D54: =SUMIFS(DATA!$I:$I,DATA!$C:$C,$B54,DATA!$J:$J,">="&DATE($I$2,D$4,1),DATA!$J:$J,"<="&DATE($I$2,D$4,D$5)) | E54: =SUMIFS(DATA!$I:$I,DATA!$C:$C,$B54,DATA!$J:$J,">="&DATE($I$2,E$4,1),DATA!$J:$J,"<="&DATE($I$2,E$4,E$5)) | F54: =SUMIFS(DATA!$I:$I,DATA!$C:$C,$B54,DATA!$J:$J,">="&DATE($I$2,F$4,1),DATA!$J:$J,"<="&DATE($I$2,F$4,F$5)) | G54: =SUMIFS(DATA!$I:$I,DATA!$C:$C,$B54,DATA!$J:$J,">="&DATE($I$2,G$4,1),DATA!$J:$J,"<="&DATE($I$2,G$4,G$5)) | H54: =SUMIFS(DATA!$I:$I,DATA!$C:$C,$B54,DATA!$J:$J,">="&DATE($I$2,H$4,1),DATA!$J:$J,"<="&DATE($I$2,H$4,H$5)) | I54: =SUMIFS(DATA!$I:$I,DATA!$C:$C,$B54,DATA!$J:$J,">="&DATE($I$2,I$4,1),DATA!$J:$J,"<="&DATE($I$2,I$4,I$5)) | J54: =SUMIFS(DATA!$I:$I,DATA!$C:$C,$B54,DATA!$J:$J,">="&DATE($I$2,J$4,1),DATA!$J:$J,"<="&DATE($I$2,J$4,J$5)) | K54: =SUMIFS(DATA!$I:$I,DATA!$C:$C,$B54,DATA!$J:$J,">="&DATE($I$2,K$4,1),DATA!$J:$J,"<="&DATE($I$2,K$4,K$5)) | ... O54: =SUMIFS(DATA!$I:$I,DATA!$C:$C,$B54,DATA!$J:$J,">="&DATE($I$2,O$4,1),DATA!$J:$J,"<="&DATE($I$2,O$4,O$5)) | P54: =SUM(D54:O54)
C55: Thực tế | D55: =SUMIFS(DATA!$M:$M,DATA!$C:$C,$B54,DATA!$N:$N,">="&DATE($I$2,D$4,1),DATA!$N:$N,"<="&DATE($I$2,D$4,D$5)) | E55: =SUMIFS(DATA!$M:$M,DATA!$C:$C,$B54,DATA!$N:$N,">="&DATE($I$2,E$4,1),DATA!$N:$N,"<="&DATE($I$2,E$4,E$5)) | F55: =SUMIFS(DATA!$M:$M,DATA!$C:$C,$B54,DATA!$N:$N,">="&DATE($I$2,F$4,1),DATA!$N:$N,"<="&DATE($I$2,F$4,F$5)) | G55: =SUMIFS(DATA!$M:$M,DATA!$C:$C,$B54,DATA!$N:$N,">="&DATE($I$2,G$4,1),DATA!$N:$N,"<="&DATE($I$2,G$4,G$5)) | H55: =SUMIFS(DATA!$M:$M,DATA!$C:$C,$B54,DATA!$N:$N,">="&DATE($I$2,H$4,1),DATA!$N:$N,"<="&DATE($I$2,H$4,H$5)) | I55: =SUMIFS(DATA!$M:$M,DATA!$C:$C,$B54,DATA!$N:$N,">="&DATE($I$2,I$4,1),DATA!$N:$N,"<="&DATE($I$2,I$4,I$5)) | J55: =SUMIFS(DATA!$M:$M,DATA!$C:$C,$B54,DATA!$N:$N,">="&DATE($I$2,J$4,1),DATA!$N:$N,"<="&DATE($I$2,J$4,J$5)) | K55: =SUMIFS(DATA!$M:$M,DATA!$C:$C,$B54,DATA!$N:$N,">="&DATE($I$2,K$4,1),DATA!$N:$N,"<="&DATE($I$2,K$4,K$5)) | ... O55: =SUMIFS(DATA!$M:$M,DATA!$C:$C,$B54,DATA!$N:$N,">="&DATE($I$2,O$4,1),DATA!$N:$N,"<="&DATE($I$2,O$4,O$5)) | P55: =SUM(D55:O55)
A56: 26 | B56: DETECH TOWER | C56: Kế hoạch | D56: =SUMIFS(DATA!$I:$I,DATA!$C:$C,$B56,DATA!$J:$J,">="&DATE($I$2,D$4,1),DATA!$J:$J,"<="&DATE($I$2,D$4,D$5)) | E56: =SUMIFS(DATA!$I:$I,DATA!$C:$C,$B56,DATA!$J:$J,">="&DATE($I$2,E$4,1),DATA!$J:$J,"<="&DATE($I$2,E$4,E$5)) | F56: =SUMIFS(DATA!$I:$I,DATA!$C:$C,$B56,DATA!$J:$J,">="&DATE($I$2,F$4,1),DATA!$J:$J,"<="&DATE($I$2,F$4,F$5)) | G56: =SUMIFS(DATA!$I:$I,DATA!$C:$C,$B56,DATA!$J:$J,">="&DATE($I$2,G$4,1),DATA!$J:$J,"<="&DATE($I$2,G$4,G$5)) | H56: =SUMIFS(DATA!$I:$I,DATA!$C:$C,$B56,DATA!$J:$J,">="&DATE($I$2,H$4,1),DATA!$J:$J,"<="&DATE($I$2,H$4,H$5)) | I56: =SUMIFS(DATA!$I:$I,DATA!$C:$C,$B56,DATA!$J:$J,">="&DATE($I$2,I$4,1),DATA!$J:$J,"<="&DATE($I$2,I$4,I$5)) | J56: =SUMIFS(DATA!$I:$I,DATA!$C:$C,$B56,DATA!$J:$J,">="&DATE($I$2,J$4,1),DATA!$J:$J,"<="&DATE($I$2,J$4,J$5)) | K56: =SUMIFS(DATA!$I:$I,DATA!$C:$C,$B56,DATA!$J:$J,">="&DATE($I$2,K$4,1),DATA!$J:$J,"<="&DATE($I$2,K$4,K$5)) | ... O56: =SUMIFS(DATA!$I:$I,DATA!$C:$C,$B56,DATA!$J:$J,">="&DATE($I$2,O$4,1),DATA!$J:$J,"<="&DATE($I$2,O$4,O$5)) | P56: =SUM(D56:O56)
C57: Thực tế | D57: =SUMIFS(DATA!$M:$M,DATA!$C:$C,$B56,DATA!$N:$N,">="&DATE($I$2,D$4,1),DATA!$N:$N,"<="&DATE($I$2,D$4,D$5)) | E57: =SUMIFS(DATA!$M:$M,DATA!$C:$C,$B56,DATA!$N:$N,">="&DATE($I$2,E$4,1),DATA!$N:$N,"<="&DATE($I$2,E$4,E$5)) | F57: =SUMIFS(DATA!$M:$M,DATA!$C:$C,$B56,DATA!$N:$N,">="&DATE($I$2,F$4,1),DATA!$N:$N,"<="&DATE($I$2,F$4,F$5)) | G57: =SUMIFS(DATA!$M:$M,DATA!$C:$C,$B56,DATA!$N:$N,">="&DATE($I$2,G$4,1),DATA!$N:$N,"<="&DATE($I$2,G$4,G$5)) | H57: =SUMIFS(DATA!$M:$M,DATA!$C:$C,$B56,DATA!$N:$N,">="&DATE($I$2,H$4,1),DATA!$N:$N,"<="&DATE($I$2,H$4,H$5)) | I57: =SUMIFS(DATA!$M:$M,DATA!$C:$C,$B56,DATA!$N:$N,">="&DATE($I$2,I$4,1),DATA!$N:$N,"<="&DATE($I$2,I$4,I$5)) | J57: =SUMIFS(DATA!$M:$M,DATA!$C:$C,$B56,DATA!$N:$N,">="&DATE($I$2,J$4,1),DATA!$N:$N,"<="&DATE($I$2,J$4,J$5)) | K57: =SUMIFS(DATA!$M:$M,DATA!$C:$C,$B56,DATA!$N:$N,">="&DATE($I$2,K$4,1),DATA!$N:$N,"<="&DATE($I$2,K$4,K$5)) | ... O57: =SUMIFS(DATA!$M:$M,DATA!$C:$C,$B56,DATA!$N:$N,">="&DATE($I$2,O$4,1),DATA!$N:$N,"<="&DATE($I$2,O$4,O$5)) | P57: =SUM(D57:O57)
A58: 27 | B58: THĂNG LONG INVEST | C58: Kế hoạch | D58: =SUMIFS(DATA!$I:$I,DATA!$C:$C,$B58,DATA!$J:$J,">="&DATE($I$2,D$4,1),DATA!$J:$J,"<="&DATE($I$2,D$4,D$5)) | E58: =SUMIFS(DATA!$I:$I,DATA!$C:$C,$B58,DATA!$J:$J,">="&DATE($I$2,E$4,1),DATA!$J:$J,"<="&DATE($I$2,E$4,E$5)) | F58: =SUMIFS(DATA!$I:$I,DATA!$C:$C,$B58,DATA!$J:$J,">="&DATE($I$2,F$4,1),DATA!$J:$J,"<="&DATE($I$2,F$4,F$5)) | G58: =SUMIFS(DATA!$I:$I,DATA!$C:$C,$B58,DATA!$J:$J,">="&DATE($I$2,G$4,1),DATA!$J:$J,"<="&DATE($I$2,G$4,G$5)) | H58: =SUMIFS(DATA!$I:$I,DATA!$C:$C,$B58,DATA!$J:$J,">="&DATE($I$2,H$4,1),DATA!$J:$J,"<="&DATE($I$2,H$4,H$5)) | I58: =SUMIFS(DATA!$I:$I,DATA!$C:$C,$B58,DATA!$J:$J,">="&DATE($I$2,I$4,1),DATA!$J:$J,"<="&DATE($I$2,I$4,I$5)) | J58: =SUMIFS(DATA!$I:$I,DATA!$C:$C,$B58,DATA!$J:$J,">="&DATE($I$2,J$4,1),DATA!$J:$J,"<="&DATE($I$2,J$4,J$5)) | K58: =SUMIFS(DATA!$I:$I,DATA!$C:$C,$B58,DATA!$J:$J,">="&DATE($I$2,K$4,1),DATA!$J:$J,"<="&DATE($I$2,K$4,K$5)) | ... O58: =SUMIFS(DATA!$I:$I,DATA!$C:$C,$B58,DATA!$J:$J,">="&DATE($I$2,O$4,1),DATA!$J:$J,"<="&DATE($I$2,O$4,O$5)) | P58: =SUM(D58:O58)
C59: Thực tế | D59: =SUMIFS(DATA!$M:$M,DATA!$C:$C,$B58,DATA!$N:$N,">="&DATE($I$2,D$4,1),DATA!$N:$N,"<="&DATE($I$2,D$4,D$5)) | E59: =SUMIFS(DATA!$M:$M,DATA!$C:$C,$B58,DATA!$N:$N,">="&DATE($I$2,E$4,1),DATA!$N:$N,"<="&DATE($I$2,E$4,E$5)) | F59: =SUMIFS(DATA!$M:$M,DATA!$C:$C,$B58,DATA!$N:$N,">="&DATE($I$2,F$4,1),DATA!$N:$N,"<="&DATE($I$2,F$4,F$5)) | G59: =SUMIFS(DATA!$M:$M,DATA!$C:$C,$B58,DATA!$N:$N,">="&DATE($I$2,G$4,1),DATA!$N:$N,"<="&DATE($I$2,G$4,G$5)) | H59: =SUMIFS(DATA!$M:$M,DATA!$C:$C,$B58,DATA!$N:$N,">="&DATE($I$2,H$4,1),DATA!$N:$N,"<="&DATE($I$2,H$4,H$5)) | I59: =SUMIFS(DATA!$M:$M,DATA!$C:$C,$B58,DATA!$N:$N,">="&DATE($I$2,I$4,1),DATA!$N:$N,"<="&DATE($I$2,I$4,I$5)) | J59: =SUMIFS(DATA!$M:$M,DATA!$C:$C,$B58,DATA!$N:$N,">="&DATE($I$2,J$4,1),DATA!$N:$N,"<="&DATE($I$2,J$4,J$5)) | K59: =SUMIFS(DATA!$M:$M,DATA!$C:$C,$B58,DATA!$N:$N,">="&DATE($I$2,K$4,1),DATA!$N:$N,"<="&DATE($I$2,K$4,K$5)) | ... O59: =SUMIFS(DATA!$M:$M,DATA!$C:$C,$B58,DATA!$N:$N,">="&DATE($I$2,O$4,1),DATA!$N:$N,"<="&DATE($I$2,O$4,O$5)) | P59: =SUM(D59:O59)
A60: 28 | B60: BAN QUẢN TRỊ KHU CĂN HỘ INDOCHINA PLAZA HÀ NỘI_(Lưu trữ) | C60: Kế hoạch | D60: =SUMIFS(DATA!$I:$I,DATA!$C:$C,$B60,DATA!$J:$J,">="&DATE($I$2,D$4,1),DATA!$J:$J,"<="&DATE($I$2,D$4,D$5)) | E60: =SUMIFS(DATA!$I:$I,DATA!$C:$C,$B60,DATA!$J:$J,">="&DATE($I$2,E$4,1),DATA!$J:$J,"<="&DATE($I$2,E$4,E$5)) | F60: =SUMIFS(DATA!$I:$I,DATA!$C:$C,$B60,DATA!$J:$J,">="&DATE($I$2,F$4,1),DATA!$J:$J,"<="&DATE($I$2,F$4,F$5)) | G60: =SUMIFS(DATA!$I:$I,DATA!$C:$C,$B60,DATA!$J:$J,">="&DATE($I$2,G$4,1),DATA!$J:$J,"<="&DATE($I$2,G$4,G$5)) | H60: =SUMIFS(DATA!$I:$I,DATA!$C:$C,$B60,DATA!$J:$J,">="&DATE($I$2,H$4,1),DATA!$J:$J,"<="&DATE($I$2,H$4,H$5)) | I60: =SUMIFS(DATA!$I:$I,DATA!$C:$C,$B60,DATA!$J:$J,">="&DATE($I$2,I$4,1),DATA!$J:$J,"<="&DATE($I$2,I$4,I$5)) | J60: =SUMIFS(DATA!$I:$I,DATA!$C:$C,$B60,DATA!$J:$J,">="&DATE($I$2,J$4,1),DATA!$J:$J,"<="&DATE($I$2,J$4,J$5)) | K60: =SUMIFS(DATA!$I:$I,DATA!$C:$C,$B60,DATA!$J:$J,">="&DATE($I$2,K$4,1),DATA!$J:$J,"<="&DATE($I$2,K$4,K$5)) | ... O60: =SUMIFS(DATA!$I:$I,DATA!$C:$C,$B60,DATA!$J:$J,">="&DATE($I$2,O$4,1),DATA!$J:$J,"<="&DATE($I$2,O$4,O$5)) | P60: =SUM(D60:O60)
C61: Thực tế | D61: =SUMIFS(DATA!$M:$M,DATA!$C:$C,$B60,DATA!$N:$N,">="&DATE($I$2,D$4,1),DATA!$N:$N,"<="&DATE($I$2,D$4,D$5)) | E61: =SUMIFS(DATA!$M:$M,DATA!$C:$C,$B60,DATA!$N:$N,">="&DATE($I$2,E$4,1),DATA!$N:$N,"<="&DATE($I$2,E$4,E$5)) | F61: =SUMIFS(DATA!$M:$M,DATA!$C:$C,$B60,DATA!$N:$N,">="&DATE($I$2,F$4,1),DATA!$N:$N,"<="&DATE($I$2,F$4,F$5)) | G61: =SUMIFS(DATA!$M:$M,DATA!$C:$C,$B60,DATA!$N:$N,">="&DATE($I$2,G$4,1),DATA!$N:$N,"<="&DATE($I$2,G$4,G$5)) | H61: =SUMIFS(DATA!$M:$M,DATA!$C:$C,$B60,DATA!$N:$N,">="&DATE($I$2,H$4,1),DATA!$N:$N,"<="&DATE($I$2,H$4,H$5)) | I61: =SUMIFS(DATA!$M:$M,DATA!$C:$C,$B60,DATA!$N:$N,">="&DATE($I$2,I$4,1),DATA!$N:$N,"<="&DATE($I$2,I$4,I$5)) | J61: =SUMIFS(DATA!$M:$M,DATA!$C:$C,$B60,DATA!$N:$N,">="&DATE($I$2,J$4,1),DATA!$N:$N,"<="&DATE($I$2,J$4,J$5)) | K61: =SUMIFS(DATA!$M:$M,DATA!$C:$C,$B60,DATA!$N:$N,">="&DATE($I$2,K$4,1),DATA!$N:$N,"<="&DATE($I$2,K$4,K$5)) | ... O61: =SUMIFS(DATA!$M:$M,DATA!$C:$C,$B60,DATA!$N:$N,">="&DATE($I$2,O$4,1),DATA!$N:$N,"<="&DATE($I$2,O$4,O$5)) | P61: =SUM(D61:O61)
A62: 29 | B62: BIG C MÊ LINH | C62: Kế hoạch | D62: =SUMIFS(DATA!$I:$I,DATA!$C:$C,$B62,DATA!$J:$J,">="&DATE($I$2,D$4,1),DATA!$J:$J,"<="&DATE($I$2,D$4,D$5)) | E62: =SUMIFS(DATA!$I:$I,DATA!$C:$C,$B62,DATA!$J:$J,">="&DATE($I$2,E$4,1),DATA!$J:$J,"<="&DATE($I$2,E$4,E$5)) | F62: =SUMIFS(DATA!$I:$I,DATA!$C:$C,$B62,DATA!$J:$J,">="&DATE($I$2,F$4,1),DATA!$J:$J,"<="&DATE($I$2,F$4,F$5)) | G62: =SUMIFS(DATA!$I:$I,DATA!$C:$C,$B62,DATA!$J:$J,">="&DATE($I$2,G$4,1),DATA!$J:$J,"<="&DATE($I$2,G$4,G$5)) | H62: =SUMIFS(DATA!$I:$I,DATA!$C:$C,$B62,DATA!$J:$J,">="&DATE($I$2,H$4,1),DATA!$J:$J,"<="&DATE($I$2,H$4,H$5)) | I62: =SUMIFS(DATA!$I:$I,DATA!$C:$C,$B62,DATA!$J:$J,">="&DATE($I$2,I$4,1),DATA!$J:$J,"<="&DATE($I$2,I$4,I$5)) | J62: =SUMIFS(DATA!$I:$I,DATA!$C:$C,$B62,DATA!$J:$J,">="&DATE($I$2,J$4,1),DATA!$J:$J,"<="&DATE($I$2,J$4,J$5)) | K62: =SUMIFS(DATA!$I:$I,DATA!$C:$C,$B62,DATA!$J:$J,">="&DATE($I$2,K$4,1),DATA!$J:$J,"<="&DATE($I$2,K$4,K$5)) | ... O62: =SUMIFS(DATA!$I:$I,DATA!$C:$C,$B62,DATA!$J:$J,">="&DATE($I$2,O$4,1),DATA!$J:$J,"<="&DATE($I$2,O$4,O$5)) | P62: =SUM(D62:O62)
C63: Thực tế | D63: =SUMIFS(DATA!$M:$M,DATA!$C:$C,$B62,DATA!$N:$N,">="&DATE($I$2,D$4,1),DATA!$N:$N,"<="&DATE($I$2,D$4,D$5)) | E63: =SUMIFS(DATA!$M:$M,DATA!$C:$C,$B62,DATA!$N:$N,">="&DATE($I$2,E$4,1),DATA!$N:$N,"<="&DATE($I$2,E$4,E$5)) | F63: =SUMIFS(DATA!$M:$M,DATA!$C:$C,$B62,DATA!$N:$N,">="&DATE($I$2,F$4,1),DATA!$N:$N,"<="&DATE($I$2,F$4,F$5)) | G63: =SUMIFS(DATA!$M:$M,DATA!$C:$C,$B62,DATA!$N:$N,">="&DATE($I$2,G$4,1),DATA!$N:$N,"<="&DATE($I$2,G$4,G$5)) | H63: =SUMIFS(DATA!$M:$M,DATA!$C:$C,$B62,DATA!$N:$N,">="&DATE($I$2,H$4,1),DATA!$N:$N,"<="&DATE($I$2,H$4,H$5)) | I63: =SUMIFS(DATA!$M:$M,DATA!$C:$C,$B62,DATA!$N:$N,">="&DATE($I$2,I$4,1),DATA!$N:$N,"<="&DATE($I$2,I$4,I$5)) | J63: =SUMIFS(DATA!$M:$M,DATA!$C:$C,$B62,DATA!$N:$N,">="&DATE($I$2,J$4,1),DATA!$N:$N,"<="&DATE($I$2,J$4,J$5)) | K63: =SUMIFS(DATA!$M:$M,DATA!$C:$C,$B62,DATA!$N:$N,">="&DATE($I$2,K$4,1),DATA!$N:$N,"<="&DATE($I$2,K$4,K$5)) | ... O63: =SUMIFS(DATA!$M:$M,DATA!$C:$C,$B62,DATA!$N:$N,">="&DATE($I$2,O$4,1),DATA!$N:$N,"<="&DATE($I$2,O$4,O$5)) | P63: =SUM(D63:O63)
A64: 30 | B64: DETECH TOWER_(Lưu trữ) | C64: Kế hoạch | D64: =SUMIFS(DATA!$I:$I,DATA!$C:$C,$B64,DATA!$J:$J,">="&DATE($I$2,D$4,1),DATA!$J:$J,"<="&DATE($I$2,D$4,D$5)) | E64: =SUMIFS(DATA!$I:$I,DATA!$C:$C,$B64,DATA!$J:$J,">="&DATE($I$2,E$4,1),DATA!$J:$J,"<="&DATE($I$2,E$4,E$5)) | F64: =SUMIFS(DATA!$I:$I,DATA!$C:$C,$B64,DATA!$J:$J,">="&DATE($I$2,F$4,1),DATA!$J:$J,"<="&DATE($I$2,F$4,F$5)) | G64: =SUMIFS(DATA!$I:$I,DATA!$C:$C,$B64,DATA!$J:$J,">="&DATE($I$2,G$4,1),DATA!$J:$J,"<="&DATE($I$2,G$4,G$5)) | H64: =SUMIFS(DATA!$I:$I,DATA!$C:$C,$B64,DATA!$J:$J,">="&DATE($I$2,H$4,1),DATA!$J:$J,"<="&DATE($I$2,H$4,H$5)) | I64: =SUMIFS(DATA!$I:$I,DATA!$C:$C,$B64,DATA!$J:$J,">="&DATE($I$2,I$4,1),DATA!$J:$J,"<="&DATE($I$2,I$4,I$5)) | J64: =SUMIFS(DATA!$I:$I,DATA!$C:$C,$B64,DATA!$J:$J,">="&DATE($I$2,J$4,1),DATA!$J:$J,"<="&DATE($I$2,J$4,J$5)) | K64: =SUMIFS(DATA!$I:$I,DATA!$C:$C,$B64,DATA!$J:$J,">="&DATE($I$2,K$4,1),DATA!$J:$J,"<="&DATE($I$2,K$4,K$5)) | ... O64: =SUMIFS(DATA!$I:$I,DATA!$C:$C,$B64,DATA!$J:$J,">="&DATE($I$2,O$4,1),DATA!$J:$J,"<="&DATE($I$2,O$4,O$5)) | P64: =SUM(D64:O64)
C65: Thực tế | D65: =SUMIFS(DATA!$M:$M,DATA!$C:$C,$B64,DATA!$N:$N,">="&DATE($I$2,D$4,1),DATA!$N:$N,"<="&DATE($I$2,D$4,D$5)) | E65: =SUMIFS(DATA!$M:$M,DATA!$C:$C,$B64,DATA!$N:$N,">="&DATE($I$2,E$4,1),DATA!$N:$N,"<="&DATE($I$2,E$4,E$5)) | F65: =SUMIFS(DATA!$M:$M,DATA!$C:$C,$B64,DATA!$N:$N,">="&DATE($I$2,F$4,1),DATA!$N:$N,"<="&DATE($I$2,F$4,F$5)) | G65: =SUMIFS(DATA!$M:$M,DATA!$C:$C,$B64,DATA!$N:$N,">="&DATE($I$2,G$4,1),DATA!$N:$N,"<="&DATE($I$2,G$4,G$5)) | H65: =SUMIFS(DATA!$M:$M,DATA!$C:$C,$B64,DATA!$N:$N,">="&DATE($I$2,H$4,1),DATA!$N:$N,"<="&DATE($I$2,H$4,H$5)) | I65: =SUMIFS(DATA!$M:$M,DATA!$C:$C,$B64,DATA!$N:$N,">="&DATE($I$2,I$4,1),DATA!$N:$N,"<="&DATE($I$2,I$4,I$5)) | J65: =SUMIFS(DATA!$M:$M,DATA!$C:$C,$B64,DATA!$N:$N,">="&DATE($I$2,J$4,1),DATA!$N:$N,"<="&DATE($I$2,J$4,J$5)) | K65: =SUMIFS(DATA!$M:$M,DATA!$C:$C,$B64,DATA!$N:$N,">="&DATE($I$2,K$4,1),DATA!$N:$N,"<="&DATE($I$2,K$4,K$5)) | ... O65: =SUMIFS(DATA!$M:$M,DATA!$C:$C,$B64,DATA!$N:$N,">="&DATE($I$2,O$4,1),DATA!$N:$N,"<="&DATE($I$2,O$4,O$5)) | P65: =SUM(D65:O65)
A66: 31 | B66: BỘ TƯ LỆNH PHÁO BINH_(Lưu Trữ) | C66: Kế hoạch | D66: =SUMIFS(DATA!$I:$I,DATA!$C:$C,$B66,DATA!$J:$J,">="&DATE($I$2,D$4,1),DATA!$J:$J,"<="&DATE($I$2,D$4,D$5)) | E66: =SUMIFS(DATA!$I:$I,DATA!$C:$C,$B66,DATA!$J:$J,">="&DATE($I$2,E$4,1),DATA!$J:$J,"<="&DATE($I$2,E$4,E$5)) | F66: =SUMIFS(DATA!$I:$I,DATA!$C:$C,$B66,DATA!$J:$J,">="&DATE($I$2,F$4,1),DATA!$J:$J,"<="&DATE($I$2,F$4,F$5)) | G66: =SUMIFS(DATA!$I:$I,DATA!$C:$C,$B66,DATA!$J:$J,">="&DATE($I$2,G$4,1),DATA!$J:$J,"<="&DATE($I$2,G$4,G$5)) | H66: =SUMIFS(DATA!$I:$I,DATA!$C:$C,$B66,DATA!$J:$J,">="&DATE($I$2,H$4,1),DATA!$J:$J,"<="&DATE($I$2,H$4,H$5)) | I66: =SUMIFS(DATA!$I:$I,DATA!$C:$C,$B66,DATA!$J:$J,">="&DATE($I$2,I$4,1),DATA!$J:$J,"<="&DATE($I$2,I$4,I$5)) | J66: =SUMIFS(DATA!$I:$I,DATA!$C:$C,$B66,DATA!$J:$J,">="&DATE($I$2,J$4,1),DATA!$J:$J,"<="&DATE($I$2,J$4,J$5)) | K66: =SUMIFS(DATA!$I:$I,DATA!$C:$C,$B66,DATA!$J:$J,">="&DATE($I$2,K$4,1),DATA!$J:$J,"<="&DATE($I$2,K$4,K$5)) | ... O66: =SUMIFS(DATA!$I:$I,DATA!$C:$C,$B66,DATA!$J:$J,">="&DATE($I$2,O$4,1),DATA!$J:$J,"<="&DATE($I$2,O$4,O$5)) | P66: =SUM(D66:O66)
C67: Thực tế | D67: =SUMIFS(DATA!$M:$M,DATA!$C:$C,$B66,DATA!$N:$N,">="&DATE($I$2,D$4,1),DATA!$N:$N,"<="&DATE($I$2,D$4,D$5)) | E67: =SUMIFS(DATA!$M:$M,DATA!$C:$C,$B66,DATA!$N:$N,">="&DATE($I$2,E$4,1),DATA!$N:$N,"<="&DATE($I$2,E$4,E$5)) | F67: =SUMIFS(DATA!$M:$M,DATA!$C:$C,$B66,DATA!$N:$N,">="&DATE($I$2,F$4,1),DATA!$N:$N,"<="&DATE($I$2,F$4,F$5)) | G67: =SUMIFS(DATA!$M:$M,DATA!$C:$C,$B66,DATA!$N:$N,">="&DATE($I$2,G$4,1),DATA!$N:$N,"<="&DATE($I$2,G$4,G$5)) | H67: =SUMIFS(DATA!$M:$M,DATA!$C:$C,$B66,DATA!$N:$N,">="&DATE($I$2,H$4,1),DATA!$N:$N,"<="&DATE($I$2,H$4,H$5)) | I67: =SUMIFS(DATA!$M:$M,DATA!$C:$C,$B66,DATA!$N:$N,">="&DATE($I$2,I$4,1),DATA!$N:$N,"<="&DATE($I$2,I$4,I$5)) | J67: =SUMIFS(DATA!$M:$M,DATA!$C:$C,$B66,DATA!$N:$N,">="&DATE($I$2,J$4,1),DATA!$N:$N,"<="&DATE($I$2,J$4,J$5)) | K67: =SUMIFS(DATA!$M:$M,DATA!$C:$C,$B66,DATA!$N:$N,">="&DATE($I$2,K$4,1),DATA!$N:$N,"<="&DATE($I$2,K$4,K$5)) | ... O67: =SUMIFS(DATA!$M:$M,DATA!$C:$C,$B66,DATA!$N:$N,">="&DATE($I$2,O$4,1),DATA!$N:$N,"<="&DATE($I$2,O$4,O$5)) | P67: =SUM(D67:O67)
A68: 32 | B68: HC GOLDEN CITY | C68: Kế hoạch | D68: =SUMIFS(DATA!$I:$I,DATA!$C:$C,$B68,DATA!$J:$J,">="&DATE($I$2,D$4,1),DATA!$J:$J,"<="&DATE($I$2,D$4,D$5)) | E68: =SUMIFS(DATA!$I:$I,DATA!$C:$C,$B68,DATA!$J:$J,">="&DATE($I$2,E$4,1),DATA!$J:$J,"<="&DATE($I$2,E$4,E$5)) | F68: =SUMIFS(DATA!$I:$I,DATA!$C:$C,$B68,DATA!$J:$J,">="&DATE($I$2,F$4,1),DATA!$J:$J,"<="&DATE($I$2,F$4,F$5)) | G68: =SUMIFS(DATA!$I:$I,DATA!$C:$C,$B68,DATA!$J:$J,">="&DATE($I$2,G$4,1),DATA!$J:$J,"<="&DATE($I$2,G$4,G$5)) | H68: =SUMIFS(DATA!$I:$I,DATA!$C:$C,$B68,DATA!$J:$J,">="&DATE($I$2,H$4,1),DATA!$J:$J,"<="&DATE($I$2,H$4,H$5)) | I68: =SUMIFS(DATA!$I:$I,DATA!$C:$C,$B68,DATA!$J:$J,">="&DATE($I$2,I$4,1),DATA!$J:$J,"<="&DATE($I$2,I$4,I$5)) | J68: =SUMIFS(DATA!$I:$I,DATA!$C:$C,$B68,DATA!$J:$J,">="&DATE($I$2,J$4,1),DATA!$J:$J,"<="&DATE($I$2,J$4,J$5)) | K68: =SUMIFS(DATA!$I:$I,DATA!$C:$C,$B68,DATA!$J:$J,">="&DATE($I$2,K$4,1),DATA!$J:$J,"<="&DATE($I$2,K$4,K$5)) | ... O68: =SUMIFS(DATA!$I:$I,DATA!$C:$C,$B68,DATA!$J:$J,">="&DATE($I$2,O$4,1),DATA!$J:$J,"<="&DATE($I$2,O$4,O$5)) | P68: =SUM(D68:O68)
C69: Thực tế | D69: =SUMIFS(DATA!$M:$M,DATA!$C:$C,$B68,DATA!$N:$N,">="&DATE($I$2,D$4,1),DATA!$N:$N,"<="&DATE($I$2,D$4,D$5)) | E69: =SUMIFS(DATA!$M:$M,DATA!$C:$C,$B68,DATA!$N:$N,">="&DATE($I$2,E$4,1),DATA!$N:$N,"<="&DATE($I$2,E$4,E$5)) | F69: =SUMIFS(DATA!$M:$M,DATA!$C:$C,$B68,DATA!$N:$N,">="&DATE($I$2,F$4,1),DATA!$N:$N,"<="&DATE($I$2,F$4,F$5)) | G69: =SUMIFS(DATA!$M:$M,DATA!$C:$C,$B68,DATA!$N:$N,">="&DATE($I$2,G$4,1),DATA!$N:$N,"<="&DATE($I$2,G$4,G$5)) | H69: =SUMIFS(DATA!$M:$M,DATA!$C:$C,$B68,DATA!$N:$N,">="&DATE($I$2,H$4,1),DATA!$N:$N,"<="&DATE($I$2,H$4,H$5)) | I69: =SUMIFS(DATA!$M:$M,DATA!$C:$C,$B68,DATA!$N:$N,">="&DATE($I$2,I$4,1),DATA!$N:$N,"<="&DATE($I$2,I$4,I$5)) | J69: =SUMIFS(DATA!$M:$M,DATA!$C:$C,$B68,DATA!$N:$N,">="&DATE($I$2,J$4,1),DATA!$N:$N,"<="&DATE($I$2,J$4,J$5)) | K69: =SUMIFS(DATA!$M:$M,DATA!$C:$C,$B68,DATA!$N:$N,">="&DATE($I$2,K$4,1),DATA!$N:$N,"<="&DATE($I$2,K$4,K$5)) | ... O69: =SUMIFS(DATA!$M:$M,DATA!$C:$C,$B68,DATA!$N:$N,">="&DATE($I$2,O$4,1),DATA!$N:$N,"<="&DATE($I$2,O$4,O$5)) | P69: =SUM(D69:O69)
A70: 33 | B70: WORLD BANK | C70: Kế hoạch | D70: =SUMIFS(DATA!$I:$I,DATA!$C:$C,$B70,DATA!$J:$J,">="&DATE($I$2,D$4,1),DATA!$J:$J,"<="&DATE($I$2,D$4,D$5)) | E70: =SUMIFS(DATA!$I:$I,DATA!$C:$C,$B70,DATA!$J:$J,">="&DATE($I$2,E$4,1),DATA!$J:$J,"<="&DATE($I$2,E$4,E$5)) | F70: =SUMIFS(DATA!$I:$I,DATA!$C:$C,$B70,DATA!$J:$J,">="&DATE($I$2,F$4,1),DATA!$J:$J,"<="&DATE($I$2,F$4,F$5)) | G70: =SUMIFS(DATA!$I:$I,DATA!$C:$C,$B70,DATA!$J:$J,">="&DATE($I$2,G$4,1),DATA!$J:$J,"<="&DATE($I$2,G$4,G$5)) | H70: =SUMIFS(DATA!$I:$I,DATA!$C:$C,$B70,DATA!$J:$J,">="&DATE($I$2,H$4,1),DATA!$J:$J,"<="&DATE($I$2,H$4,H$5)) | I70: =SUMIFS(DATA!$I:$I,DATA!$C:$C,$B70,DATA!$J:$J,">="&DATE($I$2,I$4,1),DATA!$J:$J,"<="&DATE($I$2,I$4,I$5)) | J70: =SUMIFS(DATA!$I:$I,DATA!$C:$C,$B70,DATA!$J:$J,">="&DATE($I$2,J$4,1),DATA!$J:$J,"<="&DATE($I$2,J$4,J$5)) | K70: =SUMIFS(DATA!$I:$I,DATA!$C:$C,$B70,DATA!$J:$J,">="&DATE($I$2,K$4,1),DATA!$J:$J,"<="&DATE($I$2,K$4,K$5)) | ... O70: =SUMIFS(DATA!$I:$I,DATA!$C:$C,$B70,DATA!$J:$J,">="&DATE($I$2,O$4,1),DATA!$J:$J,"<="&DATE($I$2,O$4,O$5)) | P70: =SUM(D70:O70)
C71: Thực tế | D71: =SUMIFS(DATA!$M:$M,DATA!$C:$C,$B70,DATA!$N:$N,">="&DATE($I$2,D$4,1),DATA!$N:$N,"<="&DATE($I$2,D$4,D$5)) | E71: =SUMIFS(DATA!$M:$M,DATA!$C:$C,$B70,DATA!$N:$N,">="&DATE($I$2,E$4,1),DATA!$N:$N,"<="&DATE($I$2,E$4,E$5)) | F71: =SUMIFS(DATA!$M:$M,DATA!$C:$C,$B70,DATA!$N:$N,">="&DATE($I$2,F$4,1),DATA!$N:$N,"<="&DATE($I$2,F$4,F$5)) | G71: =SUMIFS(DATA!$M:$M,DATA!$C:$C,$B70,DATA!$N:$N,">="&DATE($I$2,G$4,1),DATA!$N:$N,"<="&DATE($I$2,G$4,G$5)) | H71: =SUMIFS(DATA!$M:$M,DATA!$C:$C,$B70,DATA!$N:$N,">="&DATE($I$2,H$4,1),DATA!$N:$N,"<="&DATE($I$2,H$4,H$5)) | I71: =SUMIFS(DATA!$M:$M,DATA!$C:$C,$B70,DATA!$N:$N,">="&DATE($I$2,I$4,1),DATA!$N:$N,"<="&DATE($I$2,I$4,I$5)) | J71: =SUMIFS(DATA!$M:$M,DATA!$C:$C,$B70,DATA!$N:$N,">="&DATE($I$2,J$4,1),DATA!$N:$N,"<="&DATE($I$2,J$4,J$5)) | K71: =SUMIFS(DATA!$M:$M,DATA!$C:$C,$B70,DATA!$N:$N,">="&DATE($I$2,K$4,1),DATA!$N:$N,"<="&DATE($I$2,K$4,K$5)) | ... O71: =SUMIFS(DATA!$M:$M,DATA!$C:$C,$B70,DATA!$N:$N,">="&DATE($I$2,O$4,1),DATA!$N:$N,"<="&DATE($I$2,O$4,O$5)) | P71: =SUM(D71:O71)
A72: 34 | B72: US PEACE CORPS(Inactive) | C72: Kế hoạch | D72: =SUMIFS(DATA!$I:$I,DATA!$C:$C,$B72,DATA!$J:$J,">="&DATE($I$2,D$4,1),DATA!$J:$J,"<="&DATE($I$2,D$4,D$5)) | E72: =SUMIFS(DATA!$I:$I,DATA!$C:$C,$B72,DATA!$J:$J,">="&DATE($I$2,E$4,1),DATA!$J:$J,"<="&DATE($I$2,E$4,E$5)) | F72: =SUMIFS(DATA!$I:$I,DATA!$C:$C,$B72,DATA!$J:$J,">="&DATE($I$2,F$4,1),DATA!$J:$J,"<="&DATE($I$2,F$4,F$5)) | G72: =SUMIFS(DATA!$I:$I,DATA!$C:$C,$B72,DATA!$J:$J,">="&DATE($I$2,G$4,1),DATA!$J:$J,"<="&DATE($I$2,G$4,G$5)) | H72: =SUMIFS(DATA!$I:$I,DATA!$C:$C,$B72,DATA!$J:$J,">="&DATE($I$2,H$4,1),DATA!$J:$J,"<="&DATE($I$2,H$4,H$5)) | I72: =SUMIFS(DATA!$I:$I,DATA!$C:$C,$B72,DATA!$J:$J,">="&DATE($I$2,I$4,1),DATA!$J:$J,"<="&DATE($I$2,I$4,I$5)) | J72: =SUMIFS(DATA!$I:$I,DATA!$C:$C,$B72,DATA!$J:$J,">="&DATE($I$2,J$4,1),DATA!$J:$J,"<="&DATE($I$2,J$4,J$5)) | K72: =SUMIFS(DATA!$I:$I,DATA!$C:$C,$B72,DATA!$J:$J,">="&DATE($I$2,K$4,1),DATA!$J:$J,"<="&DATE($I$2,K$4,K$5)) | ... O72: =SUMIFS(DATA!$I:$I,DATA!$C:$C,$B72,DATA!$J:$J,">="&DATE($I$2,O$4,1),DATA!$J:$J,"<="&DATE($I$2,O$4,O$5)) | P72: =SUM(D72:O72)
C73: Thực tế | D73: =SUMIFS(DATA!$M:$M,DATA!$C:$C,$B72,DATA!$N:$N,">="&DATE($I$2,D$4,1),DATA!$N:$N,"<="&DATE($I$2,D$4,D$5)) | E73: =SUMIFS(DATA!$M:$M,DATA!$C:$C,$B72,DATA!$N:$N,">="&DATE($I$2,E$4,1),DATA!$N:$N,"<="&DATE($I$2,E$4,E$5)) | F73: =SUMIFS(DATA!$M:$M,DATA!$C:$C,$B72,DATA!$N:$N,">="&DATE($I$2,F$4,1),DATA!$N:$N,"<="&DATE($I$2,F$4,F$5)) | G73: =SUMIFS(DATA!$M:$M,DATA!$C:$C,$B72,DATA!$N:$N,">="&DATE($I$2,G$4,1),DATA!$N:$N,"<="&DATE($I$2,G$4,G$5)) | H73: =SUMIFS(DATA!$M:$M,DATA!$C:$C,$B72,DATA!$N:$N,">="&DATE($I$2,H$4,1),DATA!$N:$N,"<="&DATE($I$2,H$4,H$5)) | I73: =SUMIFS(DATA!$M:$M,DATA!$C:$C,$B72,DATA!$N:$N,">="&DATE($I$2,I$4,1),DATA!$N:$N,"<="&DATE($I$2,I$4,I$5)) | J73: =SUMIFS(DATA!$M:$M,DATA!$C:$C,$B72,DATA!$N:$N,">="&DATE($I$2,J$4,1),DATA!$N:$N,"<="&DATE($I$2,J$4,J$5)) | K73: =SUMIFS(DATA!$M:$M,DATA!$C:$C,$B72,DATA!$N:$N,">="&DATE($I$2,K$4,1),DATA!$N:$N,"<="&DATE($I$2,K$4,K$5)) | ... O73: =SUMIFS(DATA!$M:$M,DATA!$C:$C,$B72,DATA!$N:$N,">="&DATE($I$2,O$4,1),DATA!$N:$N,"<="&DATE($I$2,O$4,O$5)) | P73: =SUM(D73:O73)
A74: 35 | B74: TH BẮC GIANG | C74: Kế hoạch | D74: =SUMIFS(DATA!$I:$I,DATA!$C:$C,$B74,DATA!$J:$J,">="&DATE($I$2,D$4,1),DATA!$J:$J,"<="&DATE($I$2,D$4,D$5)) | E74: =SUMIFS(DATA!$I:$I,DATA!$C:$C,$B74,DATA!$J:$J,">="&DATE($I$2,E$4,1),DATA!$J:$J,"<="&DATE($I$2,E$4,E$5)) | F74: =SUMIFS(DATA!$I:$I,DATA!$C:$C,$B74,DATA!$J:$J,">="&DATE($I$2,F$4,1),DATA!$J:$J,"<="&DATE($I$2,F$4,F$5)) | G74: =SUMIFS(DATA!$I:$I,DATA!$C:$C,$B74,DATA!$J:$J,">="&DATE($I$2,G$4,1),DATA!$J:$J,"<="&DATE($I$2,G$4,G$5)) | H74: =SUMIFS(DATA!$I:$I,DATA!$C:$C,$B74,DATA!$J:$J,">="&DATE($I$2,H$4,1),DATA!$J:$J,"<="&DATE($I$2,H$4,H$5)) | I74: =SUMIFS(DATA!$I:$I,DATA!$C:$C,$B74,DATA!$J:$J,">="&DATE($I$2,I$4,1),DATA!$J:$J,"<="&DATE($I$2,I$4,I$5)) | J74: =SUMIFS(DATA!$I:$I,DATA!$C:$C,$B74,DATA!$J:$J,">="&DATE($I$2,J$4,1),DATA!$J:$J,"<="&DATE($I$2,J$4,J$5)) | K74: =SUMIFS(DATA!$I:$I,DATA!$C:$C,$B74,DATA!$J:$J,">="&DATE($I$2,K$4,1),DATA!$J:$J,"<="&DATE($I$2,K$4,K$5)) | ... O74: =SUMIFS(DATA!$I:$I,DATA!$C:$C,$B74,DATA!$J:$J,">="&DATE($I$2,O$4,1),DATA!$J:$J,"<="&DATE($I$2,O$4,O$5)) | P74: =SUM(D74:O74)
C75: Thực tế | D75: =SUMIFS(DATA!$M:$M,DATA!$C:$C,$B74,DATA!$N:$N,">="&DATE($I$2,D$4,1),DATA!$N:$N,"<="&DATE($I$2,D$4,D$5)) | E75: =SUMIFS(DATA!$M:$M,DATA!$C:$C,$B74,DATA!$N:$N,">="&DATE($I$2,E$4,1),DATA!$N:$N,"<="&DATE($I$2,E$4,E$5)) | F75: =SUMIFS(DATA!$M:$M,DATA!$C:$C,$B74,DATA!$N:$N,">="&DATE($I$2,F$4,1),DATA!$N:$N,"<="&DATE($I$2,F$4,F$5)) | G75: =SUMIFS(DATA!$M:$M,DATA!$C:$C,$B74,DATA!$N:$N,">="&DATE($I$2,G$4,1),DATA!$N:$N,"<="&DATE($I$2,G$4,G$5)) | H75: =SUMIFS(DATA!$M:$M,DATA!$C:$C,$B74,DATA!$N:$N,">="&DATE($I$2,H$4,1),DATA!$N:$N,"<="&DATE($I$2,H$4,H$5)) | I75: =SUMIFS(DATA!$M:$M,DATA!$C:$C,$B74,DATA!$N:$N,">="&DATE($I$2,I$4,1),DATA!$N:$N,"<="&DATE($I$2,I$4,I$5)) | J75: =SUMIFS(DATA!$M:$M,DATA!$C:$C,$B74,DATA!$N:$N,">="&DATE($I$2,J$4,1),DATA!$N:$N,"<="&DATE($I$2,J$4,J$5)) | K75: =SUMIFS(DATA!$M:$M,DATA!$C:$C,$B74,DATA!$N:$N,">="&DATE($I$2,K$4,1),DATA!$N:$N,"<="&DATE($I$2,K$4,K$5)) | ... O75: =SUMIFS(DATA!$M:$M,DATA!$C:$C,$B74,DATA!$N:$N,">="&DATE($I$2,O$4,1),DATA!$N:$N,"<="&DATE($I$2,O$4,O$5)) | P75: =SUM(D75:O75)
A76: 36 | B76: KENNAMETAL VIETNAM | C76: Kế hoạch | D76: =SUMIFS(DATA!$I:$I,DATA!$C:$C,$B76,DATA!$J:$J,">="&DATE($I$2,D$4,1),DATA!$J:$J,"<="&DATE($I$2,D$4,D$5)) | E76: =SUMIFS(DATA!$I:$I,DATA!$C:$C,$B76,DATA!$J:$J,">="&DATE($I$2,E$4,1),DATA!$J:$J,"<="&DATE($I$2,E$4,E$5)) | F76: =SUMIFS(DATA!$I:$I,DATA!$C:$C,$B76,DATA!$J:$J,">="&DATE($I$2,F$4,1),DATA!$J:$J,"<="&DATE($I$2,F$4,F$5)) | G76: =SUMIFS(DATA!$I:$I,DATA!$C:$C,$B76,DATA!$J:$J,">="&DATE($I$2,G$4,1),DATA!$J:$J,"<="&DATE($I$2,G$4,G$5)) | H76: =SUMIFS(DATA!$I:$I,DATA!$C:$C,$B76,DATA!$J:$J,">="&DATE($I$2,H$4,1),DATA!$J:$J,"<="&DATE($I$2,H$4,H$5)) | I76: =SUMIFS(DATA!$I:$I,DATA!$C:$C,$B76,DATA!$J:$J,">="&DATE($I$2,I$4,1),DATA!$J:$J,"<="&DATE($I$2,I$4,I$5)) | J76: =SUMIFS(DATA!$I:$I,DATA!$C:$C,$B76,DATA!$J:$J,">="&DATE($I$2,J$4,1),DATA!$J:$J,"<="&DATE($I$2,J$4,J$5)) | K76: =SUMIFS(DATA!$I:$I,DATA!$C:$C,$B76,DATA!$J:$J,">="&DATE($I$2,K$4,1),DATA!$J:$J,"<="&DATE($I$2,K$4,K$5)) | ... O76: =SUMIFS(DATA!$I:$I,DATA!$C:$C,$B76,DATA!$J:$J,">="&DATE($I$2,O$4,1),DATA!$J:$J,"<="&DATE($I$2,O$4,O$5)) | P76: =SUM(D76:O76)
C77: Thực tế | D77: =SUMIFS(DATA!$M:$M,DATA!$C:$C,$B76,DATA!$N:$N,">="&DATE($I$2,D$4,1),DATA!$N:$N,"<="&DATE($I$2,D$4,D$5)) | E77: =SUMIFS(DATA!$M:$M,DATA!$C:$C,$B76,DATA!$N:$N,">="&DATE($I$2,E$4,1),DATA!$N:$N,"<="&DATE($I$2,E$4,E$5)) | F77: =SUMIFS(DATA!$M:$M,DATA!$C:$C,$B76,DATA!$N:$N,">="&DATE($I$2,F$4,1),DATA!$N:$N,"<="&DATE($I$2,F$4,F$5)) | G77: =SUMIFS(DATA!$M:$M,DATA!$C:$C,$B76,DATA!$N:$N,">="&DATE($I$2,G$4,1),DATA!$N:$N,"<="&DATE($I$2,G$4,G$5)) | H77: =SUMIFS(DATA!$M:$M,DATA!$C:$C,$B76,DATA!$N:$N,">="&DATE($I$2,H$4,1),DATA!$N:$N,"<="&DATE($I$2,H$4,H$5)) | I77: =SUMIFS(DATA!$M:$M,DATA!$C:$C,$B76,DATA!$N:$N,">="&DATE($I$2,I$4,1),DATA!$N:$N,"<="&DATE($I$2,I$4,I$5)) | J77: =SUMIFS(DATA!$M:$M,DATA!$C:$C,$B76,DATA!$N:$N,">="&DATE($I$2,J$4,1),DATA!$N:$N,"<="&DATE($I$2,J$4,J$5)) | K77: =SUMIFS(DATA!$M:$M,DATA!$C:$C,$B76,DATA!$N:$N,">="&DATE($I$2,K$4,1),DATA!$N:$N,"<="&DATE($I$2,K$4,K$5)) | ... O77: =SUMIFS(DATA!$M:$M,DATA!$C:$C,$B76,DATA!$N:$N,">="&DATE($I$2,O$4,1),DATA!$N:$N,"<="&DATE($I$2,O$4,O$5)) | P77: =SUM(D77:O77)
A78: 37 | B78: TAL VIETNAM | C78: Kế hoạch | D78: =SUMIFS(DATA!$I:$I,DATA!$C:$C,$B78,DATA!$J:$J,">="&DATE($I$2,D$4,1),DATA!$J:$J,"<="&DATE($I$2,D$4,D$5)) | E78: =SUMIFS(DATA!$I:$I,DATA!$C:$C,$B78,DATA!$J:$J,">="&DATE($I$2,E$4,1),DATA!$J:$J,"<="&DATE($I$2,E$4,E$5)) | F78: =SUMIFS(DATA!$I:$I,DATA!$C:$C,$B78,DATA!$J:$J,">="&DATE($I$2,F$4,1),DATA!$J:$J,"<="&DATE($I$2,F$4,F$5)) | G78: =SUMIFS(DATA!$I:$I,DATA!$C:$C,$B78,DATA!$J:$J,">="&DATE($I$2,G$4,1),DATA!$J:$J,"<="&DATE($I$2,G$4,G$5)) | H78: =SUMIFS(DATA!$I:$I,DATA!$C:$C,$B78,DATA!$J:$J,">="&DATE($I$2,H$4,1),DATA!$J:$J,"<="&DATE($I$2,H$4,H$5)) | I78: =SUMIFS(DATA!$I:$I,DATA!$C:$C,$B78,DATA!$J:$J,">="&DATE($I$2,I$4,1),DATA!$J:$J,"<="&DATE($I$2,I$4,I$5)) | J78: =SUMIFS(DATA!$I:$I,DATA!$C:$C,$B78,DATA!$J:$J,">="&DATE($I$2,J$4,1),DATA!$J:$J,"<="&DATE($I$2,J$4,J$5)) | K78: =SUMIFS(DATA!$I:$I,DATA!$C:$C,$B78,DATA!$J:$J,">="&DATE($I$2,K$4,1),DATA!$J:$J,"<="&DATE($I$2,K$4,K$5)) | ... O78: =SUMIFS(DATA!$I:$I,DATA!$C:$C,$B78,DATA!$J:$J,">="&DATE($I$2,O$4,1),DATA!$J:$J,"<="&DATE($I$2,O$4,O$5)) | P78: =SUM(D78:O78)
C79: Thực tế | D79: =SUMIFS(DATA!$M:$M,DATA!$C:$C,$B78,DATA!$N:$N,">="&DATE($I$2,D$4,1),DATA!$N:$N,"<="&DATE($I$2,D$4,D$5)) | E79: =SUMIFS(DATA!$M:$M,DATA!$C:$C,$B78,DATA!$N:$N,">="&DATE($I$2,E$4,1),DATA!$N:$N,"<="&DATE($I$2,E$4,E$5)) | F79: =SUMIFS(DATA!$M:$M,DATA!$C:$C,$B78,DATA!$N:$N,">="&DATE($I$2,F$4,1),DATA!$N:$N,"<="&DATE($I$2,F$4,F$5)) | G79: =SUMIFS(DATA!$M:$M,DATA!$C:$C,$B78,DATA!$N:$N,">="&DATE($I$2,G$4,1),DATA!$N:$N,"<="&DATE($I$2,G$4,G$5)) | H79: =SUMIFS(DATA!$M:$M,DATA!$C:$C,$B78,DATA!$N:$N,">="&DATE($I$2,H$4,1),DATA!$N:$N,"<="&DATE($I$2,H$4,H$5)) | I79: =SUMIFS(DATA!$M:$M,DATA!$C:$C,$B78,DATA!$N:$N,">="&DATE($I$2,I$4,1),DATA!$N:$N,"<="&DATE($I$2,I$4,I$5)) | J79: =SUMIFS(DATA!$M:$M,DATA!$C:$C,$B78,DATA!$N:$N,">="&DATE($I$2,J$4,1),DATA!$N:$N,"<="&DATE($I$2,J$4,J$5)) | K79: =SUMIFS(DATA!$M:$M,DATA!$C:$C,$B78,DATA!$N:$N,">="&DATE($I$2,K$4,1),DATA!$N:$N,"<="&DATE($I$2,K$4,K$5)) | ... O79: =SUMIFS(DATA!$M:$M,DATA!$C:$C,$B78,DATA!$N:$N,">="&DATE($I$2,O$4,1),DATA!$N:$N,"<="&DATE($I$2,O$4,O$5)) | P79: =SUM(D79:O79)
A80: 38 | B80: GELEXIMCO SOUTHERN STAR | C80: Kế hoạch | D80: =SUMIFS(DATA!$I:$I,DATA!$C:$C,$B80,DATA!$J:$J,">="&DATE($I$2,D$4,1),DATA!$J:$J,"<="&DATE($I$2,D$4,D$5)) | E80: =SUMIFS(DATA!$I:$I,DATA!$C:$C,$B80,DATA!$J:$J,">="&DATE($I$2,E$4,1),DATA!$J:$J,"<="&DATE($I$2,E$4,E$5)) | F80: =SUMIFS(DATA!$I:$I,DATA!$C:$C,$B80,DATA!$J:$J,">="&DATE($I$2,F$4,1),DATA!$J:$J,"<="&DATE($I$2,F$4,F$5)) | G80: =SUMIFS(DATA!$I:$I,DATA!$C:$C,$B80,DATA!$J:$J,">="&DATE($I$2,G$4,1),DATA!$J:$J,"<="&DATE($I$2,G$4,G$5)) | H80: =SUMIFS(DATA!$I:$I,DATA!$C:$C,$B80,DATA!$J:$J,">="&DATE($I$2,H$4,1),DATA!$J:$J,"<="&DATE($I$2,H$4,H$5)) | I80: =SUMIFS(DATA!$I:$I,DATA!$C:$C,$B80,DATA!$J:$J,">="&DATE($I$2,I$4,1),DATA!$J:$J,"<="&DATE($I$2,I$4,I$5)) | J80: =SUMIFS(DATA!$I:$I,DATA!$C:$C,$B80,DATA!$J:$J,">="&DATE($I$2,J$4,1),DATA!$J:$J,"<="&DATE($I$2,J$4,J$5)) | K80: =SUMIFS(DATA!$I:$I,DATA!$C:$C,$B80,DATA!$J:$J,">="&DATE($I$2,K$4,1),DATA!$J:$J,"<="&DATE($I$2,K$4,K$5)) | ... O80: =SUMIFS(DATA!$I:$I,DATA!$C:$C,$B80,DATA!$J:$J,">="&DATE($I$2,O$4,1),DATA!$J:$J,"<="&DATE($I$2,O$4,O$5)) | P80: =SUM(D80:O80)
C81: Thực tế | D81: =SUMIFS(DATA!$M:$M,DATA!$C:$C,$B80,DATA!$N:$N,">="&DATE($I$2,D$4,1),DATA!$N:$N,"<="&DATE($I$2,D$4,D$5)) | E81: =SUMIFS(DATA!$M:$M,DATA!$C:$C,$B80,DATA!$N:$N,">="&DATE($I$2,E$4,1),DATA!$N:$N,"<="&DATE($I$2,E$4,E$5)) | F81: =SUMIFS(DATA!$M:$M,DATA!$C:$C,$B80,DATA!$N:$N,">="&DATE($I$2,F$4,1),DATA!$N:$N,"<="&DATE($I$2,F$4,F$5)) | G81: =SUMIFS(DATA!$M:$M,DATA!$C:$C,$B80,DATA!$N:$N,">="&DATE($I$2,G$4,1),DATA!$N:$N,"<="&DATE($I$2,G$4,G$5)) | H81: =SUMIFS(DATA!$M:$M,DATA!$C:$C,$B80,DATA!$N:$N,">="&DATE($I$2,H$4,1),DATA!$N:$N,"<="&DATE($I$2,H$4,H$5)) | I81: =SUMIFS(DATA!$M:$M,DATA!$C:$C,$B80,DATA!$N:$N,">="&DATE($I$2,I$4,1),DATA!$N:$N,"<="&DATE($I$2,I$4,I$5)) | J81: =SUMIFS(DATA!$M:$M,DATA!$C:$C,$B80,DATA!$N:$N,">="&DATE($I$2,J$4,1),DATA!$N:$N,"<="&DATE($I$2,J$4,J$5)) | K81: =SUMIFS(DATA!$M:$M,DATA!$C:$C,$B80,DATA!$N:$N,">="&DATE($I$2,K$4,1),DATA!$N:$N,"<="&DATE($I$2,K$4,K$5)) | ... O81: =SUMIFS(DATA!$M:$M,DATA!$C:$C,$B80,DATA!$N:$N,">="&DATE($I$2,O$4,1),DATA!$N:$N,"<="&DATE($I$2,O$4,O$5)) | P81: =SUM(D81:O81)
A82: 39 | B82: CÔNG TY CỔ PHẦN ỨNG DỤNG CÔNG NGHỆ & CNC VIỆT NAM | C82: Kế hoạch | D82: =SUMIFS(DATA!$I:$I,DATA!$C:$C,$B82,DATA!$J:$J,">="&DATE($I$2,D$4,1),DATA!$J:$J,"<="&DATE($I$2,D$4,D$5)) | E82: =SUMIFS(DATA!$I:$I,DATA!$C:$C,$B82,DATA!$J:$J,">="&DATE($I$2,E$4,1),DATA!$J:$J,"<="&DATE($I$2,E$4,E$5)) | F82: =SUMIFS(DATA!$I:$I,DATA!$C:$C,$B82,DATA!$J:$J,">="&DATE($I$2,F$4,1),DATA!$J:$J,"<="&DATE($I$2,F$4,F$5)) | G82: =SUMIFS(DATA!$I:$I,DATA!$C:$C,$B82,DATA!$J:$J,">="&DATE($I$2,G$4,1),DATA!$J:$J,"<="&DATE($I$2,G$4,G$5)) | H82: =SUMIFS(DATA!$I:$I,DATA!$C:$C,$B82,DATA!$J:$J,">="&DATE($I$2,H$4,1),DATA!$J:$J,"<="&DATE($I$2,H$4,H$5)) | I82: =SUMIFS(DATA!$I:$I,DATA!$C:$C,$B82,DATA!$J:$J,">="&DATE($I$2,I$4,1),DATA!$J:$J,"<="&DATE($I$2,I$4,I$5)) | J82: =SUMIFS(DATA!$I:$I,DATA!$C:$C,$B82,DATA!$J:$J,">="&DATE($I$2,J$4,1),DATA!$J:$J,"<="&DATE($I$2,J$4,J$5)) | K82: =SUMIFS(DATA!$I:$I,DATA!$C:$C,$B82,DATA!$J:$J,">="&DATE($I$2,K$4,1),DATA!$J:$J,"<="&DATE($I$2,K$4,K$5)) | ... O82: =SUMIFS(DATA!$I:$I,DATA!$C:$C,$B82,DATA!$J:$J,">="&DATE($I$2,O$4,1),DATA!$J:$J,"<="&DATE($I$2,O$4,O$5)) | P82: =SUM(D82:O82)
C83: Thực tế | D83: =SUMIFS(DATA!$M:$M,DATA!$C:$C,$B82,DATA!$N:$N,">="&DATE($I$2,D$4,1),DATA!$N:$N,"<="&DATE($I$2,D$4,D$5)) | E83: =SUMIFS(DATA!$M:$M,DATA!$C:$C,$B82,DATA!$N:$N,">="&DATE($I$2,E$4,1),DATA!$N:$N,"<="&DATE($I$2,E$4,E$5)) | F83: =SUMIFS(DATA!$M:$M,DATA!$C:$C,$B82,DATA!$N:$N,">="&DATE($I$2,F$4,1),DATA!$N:$N,"<="&DATE($I$2,F$4,F$5)) | G83: =SUMIFS(DATA!$M:$M,DATA!$C:$C,$B82,DATA!$N:$N,">="&DATE($I$2,G$4,1),DATA!$N:$N,"<="&DATE($I$2,G$4,G$5)) | H83: =SUMIFS(DATA!$M:$M,DATA!$C:$C,$B82,DATA!$N:$N,">="&DATE($I$2,H$4,1),DATA!$N:$N,"<="&DATE($I$2,H$4,H$5)) | I83: =SUMIFS(DATA!$M:$M,DATA!$C:$C,$B82,DATA!$N:$N,">="&DATE($I$2,I$4,1),DATA!$N:$N,"<="&DATE($I$2,I$4,I$5)) | J83: =SUMIFS(DATA!$M:$M,DATA!$C:$C,$B82,DATA!$N:$N,">="&DATE($I$2,J$4,1),DATA!$N:$N,"<="&DATE($I$2,J$4,J$5)) | K83: =SUMIFS(DATA!$M:$M,DATA!$C:$C,$B82,DATA!$N:$N,">="&DATE($I$2,K$4,1),DATA!$N:$N,"<="&DATE($I$2,K$4,K$5)) | ... O83: =SUMIFS(DATA!$M:$M,DATA!$C:$C,$B82,DATA!$N:$N,">="&DATE($I$2,O$4,1),DATA!$N:$N,"<="&DATE($I$2,O$4,O$5)) | P83: =SUM(D83:O83)
A84: 40 | B84: AIR WATER SAFETY SERVICE INC. | C84: Kế hoạch | D84: =SUMIFS(DATA!$I:$I,DATA!$C:$C,$B84,DATA!$J:$J,">="&DATE($I$2,D$4,1),DATA!$J:$J,"<="&DATE($I$2,D$4,D$5)) | E84: =SUMIFS(DATA!$I:$I,DATA!$C:$C,$B84,DATA!$J:$J,">="&DATE($I$2,E$4,1),DATA!$J:$J,"<="&DATE($I$2,E$4,E$5)) | F84: =SUMIFS(DATA!$I:$I,DATA!$C:$C,$B84,DATA!$J:$J,">="&DATE($I$2,F$4,1),DATA!$J:$J,"<="&DATE($I$2,F$4,F$5)) | G84: =SUMIFS(DATA!$I:$I,DATA!$C:$C,$B84,DATA!$J:$J,">="&DATE($I$2,G$4,1),DATA!$J:$J,"<="&DATE($I$2,G$4,G$5)) | H84: =SUMIFS(DATA!$I:$I,DATA!$C:$C,$B84,DATA!$J:$J,">="&DATE($I$2,H$4,1),DATA!$J:$J,"<="&DATE($I$2,H$4,H$5)) | I84: =SUMIFS(DATA!$I:$I,DATA!$C:$C,$B84,DATA!$J:$J,">="&DATE($I$2,I$4,1),DATA!$J:$J,"<="&DATE($I$2,I$4,I$5)) | J84: =SUMIFS(DATA!$I:$I,DATA!$C:$C,$B84,DATA!$J:$J,">="&DATE($I$2,J$4,1),DATA!$J:$J,"<="&DATE($I$2,J$4,J$5)) | K84: =SUMIFS(DATA!$I:$I,DATA!$C:$C,$B84,DATA!$J:$J,">="&DATE($I$2,K$4,1),DATA!$J:$J,"<="&DATE($I$2,K$4,K$5)) | ... O84: =SUMIFS(DATA!$I:$I,DATA!$C:$C,$B84,DATA!$J:$J,">="&DATE($I$2,O$4,1),DATA!$J:$J,"<="&DATE($I$2,O$4,O$5)) | P84: =SUM(D84:O84)
C85: Thực tế | D85: =SUMIFS(DATA!$M:$M,DATA!$C:$C,$B84,DATA!$N:$N,">="&DATE($I$2,D$4,1),DATA!$N:$N,"<="&DATE($I$2,D$4,D$5)) | E85: =SUMIFS(DATA!$M:$M,DATA!$C:$C,$B84,DATA!$N:$N,">="&DATE($I$2,E$4,1),DATA!$N:$N,"<="&DATE($I$2,E$4,E$5)) | F85: =SUMIFS(DATA!$M:$M,DATA!$C:$C,$B84,DATA!$N:$N,">="&DATE($I$2,F$4,1),DATA!$N:$N,"<="&DATE($I$2,F$4,F$5)) | G85: =SUMIFS(DATA!$M:$M,DATA!$C:$C,$B84,DATA!$N:$N,">="&DATE($I$2,G$4,1),DATA!$N:$N,"<="&DATE($I$2,G$4,G$5)) | H85: =SUMIFS(DATA!$M:$M,DATA!$C:$C,$B84,DATA!$N:$N,">="&DATE($I$2,H$4,1),DATA!$N:$N,"<="&DATE($I$2,H$4,H$5)) | I85: =SUMIFS(DATA!$M:$M,DATA!$C:$C,$B84,DATA!$N:$N,">="&DATE($I$2,I$4,1),DATA!$N:$N,"<="&DATE($I$2,I$4,I$5)) | J85: =SUMIFS(DATA!$M:$M,DATA!$C:$C,$B84,DATA!$N:$N,">="&DATE($I$2,J$4,1),DATA!$N:$N,"<="&DATE($I$2,J$4,J$5)) | K85: =SUMIFS(DATA!$M:$M,DATA!$C:$C,$B84,DATA!$N:$N,">="&DATE($I$2,K$4,1),DATA!$N:$N,"<="&DATE($I$2,K$4,K$5)) | ... O85: =SUMIFS(DATA!$M:$M,DATA!$C:$C,$B84,DATA!$N:$N,">="&DATE($I$2,O$4,1),DATA!$N:$N,"<="&DATE($I$2,O$4,O$5)) | P85: =SUM(D85:O85)
A86: 41 | B86: SANTOMAS VIETNAM JSC | C86: Kế hoạch | D86: =SUMIFS(DATA!$I:$I,DATA!$C:$C,$B86,DATA!$J:$J,">="&DATE($I$2,D$4,1),DATA!$J:$J,"<="&DATE($I$2,D$4,D$5)) | E86: =SUMIFS(DATA!$I:$I,DATA!$C:$C,$B86,DATA!$J:$J,">="&DATE($I$2,E$4,1),DATA!$J:$J,"<="&DATE($I$2,E$4,E$5)) | F86: =SUMIFS(DATA!$I:$I,DATA!$C:$C,$B86,DATA!$J:$J,">="&DATE($I$2,F$4,1),DATA!$J:$J,"<="&DATE($I$2,F$4,F$5)) | G86: =SUMIFS(DATA!$I:$I,DATA!$C:$C,$B86,DATA!$J:$J,">="&DATE($I$2,G$4,1),DATA!$J:$J,"<="&DATE($I$2,G$4,G$5)) | H86: =SUMIFS(DATA!$I:$I,DATA!$C:$C,$B86,DATA!$J:$J,">="&DATE($I$2,H$4,1),DATA!$J:$J,"<="&DATE($I$2,H$4,H$5)) | I86: =SUMIFS(DATA!$I:$I,DATA!$C:$C,$B86,DATA!$J:$J,">="&DATE($I$2,I$4,1),DATA!$J:$J,"<="&DATE($I$2,I$4,I$5)) | J86: =SUMIFS(DATA!$I:$I,DATA!$C:$C,$B86,DATA!$J:$J,">="&DATE($I$2,J$4,1),DATA!$J:$J,"<="&DATE($I$2,J$4,J$5)) | K86: =SUMIFS(DATA!$I:$I,DATA!$C:$C,$B86,DATA!$J:$J,">="&DATE($I$2,K$4,1),DATA!$J:$J,"<="&DATE($I$2,K$4,K$5)) | ... O86: =SUMIFS(DATA!$I:$I,DATA!$C:$C,$B86,DATA!$J:$J,">="&DATE($I$2,O$4,1),DATA!$J:$J,"<="&DATE($I$2,O$4,O$5)) | P86: =SUM(D86:O86)
C87: Thực tế | D87: =SUMIFS(DATA!$M:$M,DATA!$C:$C,$B86,DATA!$N:$N,">="&DATE($I$2,D$4,1),DATA!$N:$N,"<="&DATE($I$2,D$4,D$5)) | E87: =SUMIFS(DATA!$M:$M,DATA!$C:$C,$B86,DATA!$N:$N,">="&DATE($I$2,E$4,1),DATA!$N:$N,"<="&DATE($I$2,E$4,E$5)) | F87: =SUMIFS(DATA!$M:$M,DATA!$C:$C,$B86,DATA!$N:$N,">="&DATE($I$2,F$4,1),DATA!$N:$N,"<="&DATE($I$2,F$4,F$5)) | G87: =SUMIFS(DATA!$M:$M,DATA!$C:$C,$B86,DATA!$N:$N,">="&DATE($I$2,G$4,1),DATA!$N:$N,"<="&DATE($I$2,G$4,G$5)) | H87: =SUMIFS(DATA!$M:$M,DATA!$C:$C,$B86,DATA!$N:$N,">="&DATE($I$2,H$4,1),DATA!$N:$N,"<="&DATE($I$2,H$4,H$5)) | I87: =SUMIFS(DATA!$M:$M,DATA!$C:$C,$B86,DATA!$N:$N,">="&DATE($I$2,I$4,1),DATA!$N:$N,"<="&DATE($I$2,I$4,I$5)) | J87: =SUMIFS(DATA!$M:$M,DATA!$C:$C,$B86,DATA!$N:$N,">="&DATE($I$2,J$4,1),DATA!$N:$N,"<="&DATE($I$2,J$4,J$5)) | K87: =SUMIFS(DATA!$M:$M,DATA!$C:$C,$B86,DATA!$N:$N,">="&DATE($I$2,K$4,1),DATA!$N:$N,"<="&DATE($I$2,K$4,K$5)) | ... O87: =SUMIFS(DATA!$M:$M,DATA!$C:$C,$B86,DATA!$N:$N,">="&DATE($I$2,O$4,1),DATA!$N:$N,"<="&DATE($I$2,O$4,O$5)) | P87: =SUM(D87:O87)
A88: 42 | B88: MACAU GAMING CLUB | C88: Kế hoạch | D88: =SUMIFS(DATA!$I:$I,DATA!$C:$C,$B88,DATA!$J:$J,">="&DATE($I$2,D$4,1),DATA!$J:$J,"<="&DATE($I$2,D$4,D$5)) | E88: =SUMIFS(DATA!$I:$I,DATA!$C:$C,$B88,DATA!$J:$J,">="&DATE($I$2,E$4,1),DATA!$J:$J,"<="&DATE($I$2,E$4,E$5)) | F88: =SUMIFS(DATA!$I:$I,DATA!$C:$C,$B88,DATA!$J:$J,">="&DATE($I$2,F$4,1),DATA!$J:$J,"<="&DATE($I$2,F$4,F$5)) | G88: =SUMIFS(DATA!$I:$I,DATA!$C:$C,$B88,DATA!$J:$J,">="&DATE($I$2,G$4,1),DATA!$J:$J,"<="&DATE($I$2,G$4,G$5)) | H88: =SUMIFS(DATA!$I:$I,DATA!$C:$C,$B88,DATA!$J:$J,">="&DATE($I$2,H$4,1),DATA!$J:$J,"<="&DATE($I$2,H$4,H$5)) | I88: =SUMIFS(DATA!$I:$I,DATA!$C:$C,$B88,DATA!$J:$J,">="&DATE($I$2,I$4,1),DATA!$J:$J,"<="&DATE($I$2,I$4,I$5)) | J88: =SUMIFS(DATA!$I:$I,DATA!$C:$C,$B88,DATA!$J:$J,">="&DATE($I$2,J$4,1),DATA!$J:$J,"<="&DATE($I$2,J$4,J$5)) | K88: =SUMIFS(DATA!$I:$I,DATA!$C:$C,$B88,DATA!$J:$J,">="&DATE($I$2,K$4,1),DATA!$J:$J,"<="&DATE($I$2,K$4,K$5)) | ... O88: =SUMIFS(DATA!$I:$I,DATA!$C:$C,$B88,DATA!$J:$J,">="&DATE($I$2,O$4,1),DATA!$J:$J,"<="&DATE($I$2,O$4,O$5)) | P88: =SUM(D88:O88)
C89: Thực tế | D89: =SUMIFS(DATA!$M:$M,DATA!$C:$C,$B88,DATA!$N:$N,">="&DATE($I$2,D$4,1),DATA!$N:$N,"<="&DATE($I$2,D$4,D$5)) | E89: =SUMIFS(DATA!$M:$M,DATA!$C:$C,$B88,DATA!$N:$N,">="&DATE($I$2,E$4,1),DATA!$N:$N,"<="&DATE($I$2,E$4,E$5)) | F89: =SUMIFS(DATA!$M:$M,DATA!$C:$C,$B88,DATA!$N:$N,">="&DATE($I$2,F$4,1),DATA!$N:$N,"<="&DATE($I$2,F$4,F$5)) | G89: =SUMIFS(DATA!$M:$M,DATA!$C:$C,$B88,DATA!$N:$N,">="&DATE($I$2,G$4,1),DATA!$N:$N,"<="&DATE($I$2,G$4,G$5)) | H89: =SUMIFS(DATA!$M:$M,DATA!$C:$C,$B88,DATA!$N:$N,">="&DATE($I$2,H$4,1),DATA!$N:$N,"<="&DATE($I$2,H$4,H$5)) | I89: =SUMIFS(DATA!$M:$M,DATA!$C:$C,$B88,DATA!$N:$N,">="&DATE($I$2,I$4,1),DATA!$N:$N,"<="&DATE($I$2,I$4,I$5)) | J89: =SUMIFS(DATA!$M:$M,DATA!$C:$C,$B88,DATA!$N:$N,">="&DATE($I$2,J$4,1),DATA!$N:$N,"<="&DATE($I$2,J$4,J$5)) | K89: =SUMIFS(DATA!$M:$M,DATA!$C:$C,$B88,DATA!$N:$N,">="&DATE($I$2,K$4,1),DATA!$N:$N,"<="&DATE($I$2,K$4,K$5)) | ... O89: =SUMIFS(DATA!$M:$M,DATA!$C:$C,$B88,DATA!$N:$N,">="&DATE($I$2,O$4,1),DATA!$N:$N,"<="&DATE($I$2,O$4,O$5)) | P89: =SUM(D89:O89)
A90: 43 | B90: TRUNG TÂM PHÁT THANH - TRUYỀN HÌNH QUÂN ĐỘI | C90: Kế hoạch | D90: =SUMIFS(DATA!$I:$I,DATA!$C:$C,$B90,DATA!$J:$J,">="&DATE($I$2,D$4,1),DATA!$J:$J,"<="&DATE($I$2,D$4,D$5)) | E90: =SUMIFS(DATA!$I:$I,DATA!$C:$C,$B90,DATA!$J:$J,">="&DATE($I$2,E$4,1),DATA!$J:$J,"<="&DATE($I$2,E$4,E$5)) | F90: =SUMIFS(DATA!$I:$I,DATA!$C:$C,$B90,DATA!$J:$J,">="&DATE($I$2,F$4,1),DATA!$J:$J,"<="&DATE($I$2,F$4,F$5)) | G90: =SUMIFS(DATA!$I:$I,DATA!$C:$C,$B90,DATA!$J:$J,">="&DATE($I$2,G$4,1),DATA!$J:$J,"<="&DATE($I$2,G$4,G$5)) | H90: =SUMIFS(DATA!$I:$I,DATA!$C:$C,$B90,DATA!$J:$J,">="&DATE($I$2,H$4,1),DATA!$J:$J,"<="&DATE($I$2,H$4,H$5)) | I90: =SUMIFS(DATA!$I:$I,DATA!$C:$C,$B90,DATA!$J:$J,">="&DATE($I$2,I$4,1),DATA!$J:$J,"<="&DATE($I$2,I$4,I$5)) | J90: =SUMIFS(DATA!$I:$I,DATA!$C:$C,$B90,DATA!$J:$J,">="&DATE($I$2,J$4,1),DATA!$J:$J,"<="&DATE($I$2,J$4,J$5)) | K90: =SUMIFS(DATA!$I:$I,DATA!$C:$C,$B90,DATA!$J:$J,">="&DATE($I$2,K$4,1),DATA!$J:$J,"<="&DATE($I$2,K$4,K$5)) | ... O90: =SUMIFS(DATA!$I:$I,DATA!$C:$C,$B90,DATA!$J:$J,">="&DATE($I$2,O$4,1),DATA!$J:$J,"<="&DATE($I$2,O$4,O$5)) | P90: =SUM(D90:O90)
C91: Thực tế | D91: =SUMIFS(DATA!$M:$M,DATA!$C:$C,$B90,DATA!$N:$N,">="&DATE($I$2,D$4,1),DATA!$N:$N,"<="&DATE($I$2,D$4,D$5)) | E91: =SUMIFS(DATA!$M:$M,DATA!$C:$C,$B90,DATA!$N:$N,">="&DATE($I$2,E$4,1),DATA!$N:$N,"<="&DATE($I$2,E$4,E$5)) | F91: =SUMIFS(DATA!$M:$M,DATA!$C:$C,$B90,DATA!$N:$N,">="&DATE($I$2,F$4,1),DATA!$N:$N,"<="&DATE($I$2,F$4,F$5)) | G91: =SUMIFS(DATA!$M:$M,DATA!$C:$C,$B90,DATA!$N:$N,">="&DATE($I$2,G$4,1),DATA!$N:$N,"<="&DATE($I$2,G$4,G$5)) | H91: =SUMIFS(DATA!$M:$M,DATA!$C:$C,$B90,DATA!$N:$N,">="&DATE($I$2,H$4,1),DATA!$N:$N,"<="&DATE($I$2,H$4,H$5)) | I91: =SUMIFS(DATA!$M:$M,DATA!$C:$C,$B90,DATA!$N:$N,">="&DATE($I$2,I$4,1),DATA!$N:$N,"<="&DATE($I$2,I$4,I$5)) | J91: =SUMIFS(DATA!$M:$M,DATA!$C:$C,$B90,DATA!$N:$N,">="&DATE($I$2,J$4,1),DATA!$N:$N,"<="&DATE($I$2,J$4,J$5)) | K91: =SUMIFS(DATA!$M:$M,DATA!$C:$C,$B90,DATA!$N:$N,">="&DATE($I$2,K$4,1),DATA!$N:$N,"<="&DATE($I$2,K$4,K$5)) | ... O91: =SUMIFS(DATA!$M:$M,DATA!$C:$C,$B90,DATA!$N:$N,">="&DATE($I$2,O$4,1),DATA!$N:$N,"<="&DATE($I$2,O$4,O$5)) | P91: =SUM(D91:O91)
A92: 44 | B92: THE GARDEN (BITEXCO) | C92: Kế hoạch | D92: =SUMIFS(DATA!$I:$I,DATA!$C:$C,$B92,DATA!$J:$J,">="&DATE($I$2,D$4,1),DATA!$J:$J,"<="&DATE($I$2,D$4,D$5)) | E92: =SUMIFS(DATA!$I:$I,DATA!$C:$C,$B92,DATA!$J:$J,">="&DATE($I$2,E$4,1),DATA!$J:$J,"<="&DATE($I$2,E$4,E$5)) | F92: =SUMIFS(DATA!$I:$I,DATA!$C:$C,$B92,DATA!$J:$J,">="&DATE($I$2,F$4,1),DATA!$J:$J,"<="&DATE($I$2,F$4,F$5)) | G92: =SUMIFS(DATA!$I:$I,DATA!$C:$C,$B92,DATA!$J:$J,">="&DATE($I$2,G$4,1),DATA!$J:$J,"<="&DATE($I$2,G$4,G$5)) | H92: =SUMIFS(DATA!$I:$I,DATA!$C:$C,$B92,DATA!$J:$J,">="&DATE($I$2,H$4,1),DATA!$J:$J,"<="&DATE($I$2,H$4,H$5)) | I92: =SUMIFS(DATA!$I:$I,DATA!$C:$C,$B92,DATA!$J:$J,">="&DATE($I$2,I$4,1),DATA!$J:$J,"<="&DATE($I$2,I$4,I$5)) | J92: =SUMIFS(DATA!$I:$I,DATA!$C:$C,$B92,DATA!$J:$J,">="&DATE($I$2,J$4,1),DATA!$J:$J,"<="&DATE($I$2,J$4,J$5)) | K92: =SUMIFS(DATA!$I:$I,DATA!$C:$C,$B92,DATA!$J:$J,">="&DATE($I$2,K$4,1),DATA!$J:$J,"<="&DATE($I$2,K$4,K$5)) | ... O92: =SUMIFS(DATA!$I:$I,DATA!$C:$C,$B92,DATA!$J:$J,">="&DATE($I$2,O$4,1),DATA!$J:$J,"<="&DATE($I$2,O$4,O$5)) | P92: =SUM(D92:O92)
C93: Thực tế | D93: =SUMIFS(DATA!$M:$M,DATA!$C:$C,$B92,DATA!$N:$N,">="&DATE($I$2,D$4,1),DATA!$N:$N,"<="&DATE($I$2,D$4,D$5)) | E93: =SUMIFS(DATA!$M:$M,DATA!$C:$C,$B92,DATA!$N:$N,">="&DATE($I$2,E$4,1),DATA!$N:$N,"<="&DATE($I$2,E$4,E$5)) | F93: =SUMIFS(DATA!$M:$M,DATA!$C:$C,$B92,DATA!$N:$N,">="&DATE($I$2,F$4,1),DATA!$N:$N,"<="&DATE($I$2,F$4,F$5)) | G93: =SUMIFS(DATA!$M:$M,DATA!$C:$C,$B92,DATA!$N:$N,">="&DATE($I$2,G$4,1),DATA!$N:$N,"<="&DATE($I$2,G$4,G$5)) | H93: =SUMIFS(DATA!$M:$M,DATA!$C:$C,$B92,DATA!$N:$N,">="&DATE($I$2,H$4,1),DATA!$N:$N,"<="&DATE($I$2,H$4,H$5)) | I93: =SUMIFS(DATA!$M:$M,DATA!$C:$C,$B92,DATA!$N:$N,">="&DATE($I$2,I$4,1),DATA!$N:$N,"<="&DATE($I$2,I$4,I$5)) | J93: =SUMIFS(DATA!$M:$M,DATA!$C:$C,$B92,DATA!$N:$N,">="&DATE($I$2,J$4,1),DATA!$N:$N,"<="&DATE($I$2,J$4,J$5)) | K93: =SUMIFS(DATA!$M:$M,DATA!$C:$C,$B92,DATA!$N:$N,">="&DATE($I$2,K$4,1),DATA!$N:$N,"<="&DATE($I$2,K$4,K$5)) | ... O93: =SUMIFS(DATA!$M:$M,DATA!$C:$C,$B92,DATA!$N:$N,">="&DATE($I$2,O$4,1),DATA!$N:$N,"<="&DATE($I$2,O$4,O$5)) | P93: =SUM(D93:O93)
A94: 45 | B94: US PEACE CORPS | C94: Kế hoạch | D94: =SUMIFS(DATA!$I:$I,DATA!$C:$C,$B94,DATA!$J:$J,">="&DATE($I$2,D$4,1),DATA!$J:$J,"<="&DATE($I$2,D$4,D$5)) | E94: =SUMIFS(DATA!$I:$I,DATA!$C:$C,$B94,DATA!$J:$J,">="&DATE($I$2,E$4,1),DATA!$J:$J,"<="&DATE($I$2,E$4,E$5)) | F94: =SUMIFS(DATA!$I:$I,DATA!$C:$C,$B94,DATA!$J:$J,">="&DATE($I$2,F$4,1),DATA!$J:$J,"<="&DATE($I$2,F$4,F$5)) | G94: =SUMIFS(DATA!$I:$I,DATA!$C:$C,$B94,DATA!$J:$J,">="&DATE($I$2,G$4,1),DATA!$J:$J,"<="&DATE($I$2,G$4,G$5)) | H94: =SUMIFS(DATA!$I:$I,DATA!$C:$C,$B94,DATA!$J:$J,">="&DATE($I$2,H$4,1),DATA!$J:$J,"<="&DATE($I$2,H$4,H$5)) | I94: =SUMIFS(DATA!$I:$I,DATA!$C:$C,$B94,DATA!$J:$J,">="&DATE($I$2,I$4,1),DATA!$J:$J,"<="&DATE($I$2,I$4,I$5)) | J94: =SUMIFS(DATA!$I:$I,DATA!$C:$C,$B94,DATA!$J:$J,">="&DATE($I$2,J$4,1),DATA!$J:$J,"<="&DATE($I$2,J$4,J$5)) | K94: =SUMIFS(DATA!$I:$I,DATA!$C:$C,$B94,DATA!$J:$J,">="&DATE($I$2,K$4,1),DATA!$J:$J,"<="&DATE($I$2,K$4,K$5)) | ... O94: =SUMIFS(DATA!$I:$I,DATA!$C:$C,$B94,DATA!$J:$J,">="&DATE($I$2,O$4,1),DATA!$J:$J,"<="&DATE($I$2,O$4,O$5)) | P94: =SUM(D94:O94)
C95: Thực tế | D95: =SUMIFS(DATA!$M:$M,DATA!$C:$C,$B94,DATA!$N:$N,">="&DATE($I$2,D$4,1),DATA!$N:$N,"<="&DATE($I$2,D$4,D$5)) | E95: =SUMIFS(DATA!$M:$M,DATA!$C:$C,$B94,DATA!$N:$N,">="&DATE($I$2,E$4,1),DATA!$N:$N,"<="&DATE($I$2,E$4,E$5)) | F95: =SUMIFS(DATA!$M:$M,DATA!$C:$C,$B94,DATA!$N:$N,">="&DATE($I$2,F$4,1),DATA!$N:$N,"<="&DATE($I$2,F$4,F$5)) | G95: =SUMIFS(DATA!$M:$M,DATA!$C:$C,$B94,DATA!$N:$N,">="&DATE($I$2,G$4,1),DATA!$N:$N,"<="&DATE($I$2,G$4,G$5)) | H95: =SUMIFS(DATA!$M:$M,DATA!$C:$C,$B94,DATA!$N:$N,">="&DATE($I$2,H$4,1),DATA!$N:$N,"<="&DATE($I$2,H$4,H$5)) | I95: =SUMIFS(DATA!$M:$M,DATA!$C:$C,$B94,DATA!$N:$N,">="&DATE($I$2,I$4,1),DATA!$N:$N,"<="&DATE($I$2,I$4,I$5)) | J95: =SUMIFS(DATA!$M:$M,DATA!$C:$C,$B94,DATA!$N:$N,">="&DATE($I$2,J$4,1),DATA!$N:$N,"<="&DATE($I$2,J$4,J$5)) | K95: =SUMIFS(DATA!$M:$M,DATA!$C:$C,$B94,DATA!$N:$N,">="&DATE($I$2,K$4,1),DATA!$N:$N,"<="&DATE($I$2,K$4,K$5)) | ... O95: =SUMIFS(DATA!$M:$M,DATA!$C:$C,$B94,DATA!$N:$N,">="&DATE($I$2,O$4,1),DATA!$N:$N,"<="&DATE($I$2,O$4,O$5)) | P95: =SUM(D95:O95)
A96: 46 | B96: CÔNG TY TNHH MỘT THÀNH VIÊN ĐẦU TƯ VÀ XÂY LẮP ACC | C96: Kế hoạch | D96: =SUMIFS(DATA!$I:$I,DATA!$C:$C,$B96,DATA!$J:$J,">="&DATE($I$2,D$4,1),DATA!$J:$J,"<="&DATE($I$2,D$4,D$5)) | E96: =SUMIFS(DATA!$I:$I,DATA!$C:$C,$B96,DATA!$J:$J,">="&DATE($I$2,E$4,1),DATA!$J:$J,"<="&DATE($I$2,E$4,E$5)) | F96: =SUMIFS(DATA!$I:$I,DATA!$C:$C,$B96,DATA!$J:$J,">="&DATE($I$2,F$4,1),DATA!$J:$J,"<="&DATE($I$2,F$4,F$5)) | G96: =SUMIFS(DATA!$I:$I,DATA!$C:$C,$B96,DATA!$J:$J,">="&DATE($I$2,G$4,1),DATA!$J:$J,"<="&DATE($I$2,G$4,G$5)) | H96: =SUMIFS(DATA!$I:$I,DATA!$C:$C,$B96,DATA!$J:$J,">="&DATE($I$2,H$4,1),DATA!$J:$J,"<="&DATE($I$2,H$4,H$5)) | I96: =SUMIFS(DATA!$I:$I,DATA!$C:$C,$B96,DATA!$J:$J,">="&DATE($I$2,I$4,1),DATA!$J:$J,"<="&DATE($I$2,I$4,I$5)) | J96: =SUMIFS(DATA!$I:$I,DATA!$C:$C,$B96,DATA!$J:$J,">="&DATE($I$2,J$4,1),DATA!$J:$J,"<="&DATE($I$2,J$4,J$5)) | K96: =SUMIFS(DATA!$I:$I,DATA!$C:$C,$B96,DATA!$J:$J,">="&DATE($I$2,K$4,1),DATA!$J:$J,"<="&DATE($I$2,K$4,K$5)) | ... O96: =SUMIFS(DATA!$I:$I,DATA!$C:$C,$B96,DATA!$J:$J,">="&DATE($I$2,O$4,1),DATA!$J:$J,"<="&DATE($I$2,O$4,O$5)) | P96: =SUM(D96:O96)
C97: Thực tế | D97: =SUMIFS(DATA!$M:$M,DATA!$C:$C,$B96,DATA!$N:$N,">="&DATE($I$2,D$4,1),DATA!$N:$N,"<="&DATE($I$2,D$4,D$5)) | E97: =SUMIFS(DATA!$M:$M,DATA!$C:$C,$B96,DATA!$N:$N,">="&DATE($I$2,E$4,1),DATA!$N:$N,"<="&DATE($I$2,E$4,E$5)) | F97: =SUMIFS(DATA!$M:$M,DATA!$C:$C,$B96,DATA!$N:$N,">="&DATE($I$2,F$4,1),DATA!$N:$N,"<="&DATE($I$2,F$4,F$5)) | G97: =SUMIFS(DATA!$M:$M,DATA!$C:$C,$B96,DATA!$N:$N,">="&DATE($I$2,G$4,1),DATA!$N:$N,"<="&DATE($I$2,G$4,G$5)) | H97: =SUMIFS(DATA!$M:$M,DATA!$C:$C,$B96,DATA!$N:$N,">="&DATE($I$2,H$4,1),DATA!$N:$N,"<="&DATE($I$2,H$4,H$5)) | I97: =SUMIFS(DATA!$M:$M,DATA!$C:$C,$B96,DATA!$N:$N,">="&DATE($I$2,I$4,1),DATA!$N:$N,"<="&DATE($I$2,I$4,I$5)) | J97: =SUMIFS(DATA!$M:$M,DATA!$C:$C,$B96,DATA!$N:$N,">="&DATE($I$2,J$4,1),DATA!$N:$N,"<="&DATE($I$2,J$4,J$5)) | K97: =SUMIFS(DATA!$M:$M,DATA!$C:$C,$B96,DATA!$N:$N,">="&DATE($I$2,K$4,1),DATA!$N:$N,"<="&DATE($I$2,K$4,K$5)) | ... O97: =SUMIFS(DATA!$M:$M,DATA!$C:$C,$B96,DATA!$N:$N,">="&DATE($I$2,O$4,1),DATA!$N:$N,"<="&DATE($I$2,O$4,O$5)) | P97: =SUM(D97:O97)
A98: 47 | B98: YAMAHA MOTOR VIETNAM(Inactive) | C98: Kế hoạch | D98: =SUMIFS(DATA!$I:$I,DATA!$C:$C,$B98,DATA!$J:$J,">="&DATE($I$2,D$4,1),DATA!$J:$J,"<="&DATE($I$2,D$4,D$5)) | E98: =SUMIFS(DATA!$I:$I,DATA!$C:$C,$B98,DATA!$J:$J,">="&DATE($I$2,E$4,1),DATA!$J:$J,"<="&DATE($I$2,E$4,E$5)) | F98: =SUMIFS(DATA!$I:$I,DATA!$C:$C,$B98,DATA!$J:$J,">="&DATE($I$2,F$4,1),DATA!$J:$J,"<="&DATE($I$2,F$4,F$5)) | G98: =SUMIFS(DATA!$I:$I,DATA!$C:$C,$B98,DATA!$J:$J,">="&DATE($I$2,G$4,1),DATA!$J:$J,"<="&DATE($I$2,G$4,G$5)) | H98: =SUMIFS(DATA!$I:$I,DATA!$C:$C,$B98,DATA!$J:$J,">="&DATE($I$2,H$4,1),DATA!$J:$J,"<="&DATE($I$2,H$4,H$5)) | I98: =SUMIFS(DATA!$I:$I,DATA!$C:$C,$B98,DATA!$J:$J,">="&DATE($I$2,I$4,1),DATA!$J:$J,"<="&DATE($I$2,I$4,I$5)) | J98: =SUMIFS(DATA!$I:$I,DATA!$C:$C,$B98,DATA!$J:$J,">="&DATE($I$2,J$4,1),DATA!$J:$J,"<="&DATE($I$2,J$4,J$5)) | K98: =SUMIFS(DATA!$I:$I,DATA!$C:$C,$B98,DATA!$J:$J,">="&DATE($I$2,K$4,1),DATA!$J:$J,"<="&DATE($I$2,K$4,K$5)) | ... O98: =SUMIFS(DATA!$I:$I,DATA!$C:$C,$B98,DATA!$J:$J,">="&DATE($I$2,O$4,1),DATA!$J:$J,"<="&DATE($I$2,O$4,O$5)) | P98: =SUM(D98:O98)
C99: Thực tế | D99: =SUMIFS(DATA!$M:$M,DATA!$C:$C,$B98,DATA!$N:$N,">="&DATE($I$2,D$4,1),DATA!$N:$N,"<="&DATE($I$2,D$4,D$5)) | E99: =SUMIFS(DATA!$M:$M,DATA!$C:$C,$B98,DATA!$N:$N,">="&DATE($I$2,E$4,1),DATA!$N:$N,"<="&DATE($I$2,E$4,E$5)) | F99: =SUMIFS(DATA!$M:$M,DATA!$C:$C,$B98,DATA!$N:$N,">="&DATE($I$2,F$4,1),DATA!$N:$N,"<="&DATE($I$2,F$4,F$5)) | G99: =SUMIFS(DATA!$M:$M,DATA!$C:$C,$B98,DATA!$N:$N,">="&DATE($I$2,G$4,1),DATA!$N:$N,"<="&DATE($I$2,G$4,G$5)) | H99: =SUMIFS(DATA!$M:$M,DATA!$C:$C,$B98,DATA!$N:$N,">="&DATE($I$2,H$4,1),DATA!$N:$N,"<="&DATE($I$2,H$4,H$5)) | I99: =SUMIFS(DATA!$M:$M,DATA!$C:$C,$B98,DATA!$N:$N,">="&DATE($I$2,I$4,1),DATA!$N:$N,"<="&DATE($I$2,I$4,I$5)) | J99: =SUMIFS(DATA!$M:$M,DATA!$C:$C,$B98,DATA!$N:$N,">="&DATE($I$2,J$4,1),DATA!$N:$N,"<="&DATE($I$2,J$4,J$5)) | K99: =SUMIFS(DATA!$M:$M,DATA!$C:$C,$B98,DATA!$N:$N,">="&DATE($I$2,K$4,1),DATA!$N:$N,"<="&DATE($I$2,K$4,K$5)) | ... O99: =SUMIFS(DATA!$M:$M,DATA!$C:$C,$B98,DATA!$N:$N,">="&DATE($I$2,O$4,1),DATA!$N:$N,"<="&DATE($I$2,O$4,O$5)) | P99: =SUM(D99:O99)
A100: 48 | B100: US EMBASSY HANOI(Inactive_01) | C100: Kế hoạch | D100: =SUMIFS(DATA!$I:$I,DATA!$C:$C,$B100,DATA!$J:$J,">="&DATE($I$2,D$4,1),DATA!$J:$J,"<="&DATE($I$2,D$4,D$5)) | E100: =SUMIFS(DATA!$I:$I,DATA!$C:$C,$B100,DATA!$J:$J,">="&DATE($I$2,E$4,1),DATA!$J:$J,"<="&DATE($I$2,E$4,E$5)) | F100: =SUMIFS(DATA!$I:$I,DATA!$C:$C,$B100,DATA!$J:$J,">="&DATE($I$2,F$4,1),DATA!$J:$J,"<="&DATE($I$2,F$4,F$5)) | G100: =SUMIFS(DATA!$I:$I,DATA!$C:$C,$B100,DATA!$J:$J,">="&DATE($I$2,G$4,1),DATA!$J:$J,"<="&DATE($I$2,G$4,G$5)) | H100: =SUMIFS(DATA!$I:$I,DATA!$C:$C,$B100,DATA!$J:$J,">="&DATE($I$2,H$4,1),DATA!$J:$J,"<="&DATE($I$2,H$4,H$5)) | I100: =SUMIFS(DATA!$I:$I,DATA!$C:$C,$B100,DATA!$J:$J,">="&DATE($I$2,I$4,1),DATA!$J:$J,"<="&DATE($I$2,I$4,I$5)) | J100: =SUMIFS(DATA!$I:$I,DATA!$C:$C,$B100,DATA!$J:$J,">="&DATE($I$2,J$4,1),DATA!$J:$J,"<="&DATE($I$2,J$4,J$5)) | K100: =SUMIFS(DATA!$I:$I,DATA!$C:$C,$B100,DATA!$J:$J,">="&DATE($I$2,K$4,1),DATA!$J:$J,"<="&DATE($I$2,K$4,K$5)) | ... O100: =SUMIFS(DATA!$I:$I,DATA!$C:$C,$B100,DATA!$J:$J,">="&DATE($I$2,O$4,1),DATA!$J:$J,"<="&DATE($I$2,O$4,O$5)) | P100: =SUM(D100:O100)
C101: Thực tế | D101: =SUMIFS(DATA!$M:$M,DATA!$C:$C,$B100,DATA!$N:$N,">="&DATE($I$2,D$4,1),DATA!$N:$N,"<="&DATE($I$2,D$4,D$5)) | E101: =SUMIFS(DATA!$M:$M,DATA!$C:$C,$B100,DATA!$N:$N,">="&DATE($I$2,E$4,1),DATA!$N:$N,"<="&DATE($I$2,E$4,E$5)) | F101: =SUMIFS(DATA!$M:$M,DATA!$C:$C,$B100,DATA!$N:$N,">="&DATE($I$2,F$4,1),DATA!$N:$N,"<="&DATE($I$2,F$4,F$5)) | G101: =SUMIFS(DATA!$M:$M,DATA!$C:$C,$B100,DATA!$N:$N,">="&DATE($I$2,G$4,1),DATA!$N:$N,"<="&DATE($I$2,G$4,G$5)) | H101: =SUMIFS(DATA!$M:$M,DATA!$C:$C,$B100,DATA!$N:$N,">="&DATE($I$2,H$4,1),DATA!$N:$N,"<="&DATE($I$2,H$4,H$5)) | I101: =SUMIFS(DATA!$M:$M,DATA!$C:$C,$B100,DATA!$N:$N,">="&DATE($I$2,I$4,1),DATA!$N:$N,"<="&DATE($I$2,I$4,I$5)) | J101: =SUMIFS(DATA!$M:$M,DATA!$C:$C,$B100,DATA!$N:$N,">="&DATE($I$2,J$4,1),DATA!$N:$N,"<="&DATE($I$2,J$4,J$5)) | K101: =SUMIFS(DATA!$M:$M,DATA!$C:$C,$B100,DATA!$N:$N,">="&DATE($I$2,K$4,1),DATA!$N:$N,"<="&DATE($I$2,K$4,K$5)) | ... O101: =SUMIFS(DATA!$M:$M,DATA!$C:$C,$B100,DATA!$N:$N,">="&DATE($I$2,O$4,1),DATA!$N:$N,"<="&DATE($I$2,O$4,O$5)) | P101: =SUM(D101:O101)
...

Sheet Annual
E2: BÁO CÁO DOANH THU NĂM
E3: ANNUAL TURN-OVER REPORT | I3: UPDATED ON | J3: =TODAY()
J4: VND
A5: No | B5: Tên Khách hàng Client Name | C5: =D5-1 | D5: =E5-1 | E5: =F5-1 | F5: =G5-1 | G5: =H5-1 | H5: =I5-1 | I5: =YEAR(TODAY()) | J5: Tổng Total | K5: %
A6: 1 | B6: VNPT IDC - NAM THANG LONG(Inactive) | C6: =SUMIFS(DATA!$M:$M,DATA!$C:$C,$B6,DATA!$N:$N,">="&DATE(C$5,1,1),DATA!$N:$N,"<="&DATE(C$5,12,31)) | D6: =SUMIFS(DATA!$M:$M,DATA!$C:$C,$B6,DATA!$N:$N,">="&DATE(D$5,1,1),DATA!$N:$N,"<="&DATE(D$5,12,31)) | E6: =SUMIFS(DATA!$M:$M,DATA!$C:$C,$B6,DATA!$N:$N,">="&DATE(E$5,1,1),DATA!$N:$N,"<="&DATE(E$5,12,31)) | F6: =SUMIFS(DATA!$M:$M,DATA!$C:$C,$B6,DATA!$N:$N,">="&DATE(F$5,1,1),DATA!$N:$N,"<="&DATE(F$5,12,31)) | G6: =SUMIFS(DATA!$M:$M,DATA!$C:$C,$B6,DATA!$N:$N,">="&DATE(G$5,1,1),DATA!$N:$N,"<="&DATE(G$5,12,31)) | H6: =SUMIFS(DATA!$M:$M,DATA!$C:$C,$B6,DATA!$N:$N,">="&DATE(H$5,1,1),DATA!$N:$N,"<="&DATE(H$5,12,31)) | I6: =SUMIFS(DATA!$M:$M,DATA!$C:$C,$B6,DATA!$N:$N,">="&DATE(I$5,1,1),DATA!$N:$N,"<="&DATE(I$5,12,31)) | J6: =SUM(C6:I6) | K6: =J6/$J$506
A7: 2 | B7: EMBASSY OF AUSTRALIA | C7: =SUMIFS(DATA!$M:$M,DATA!$C:$C,$B7,DATA!$N:$N,">="&DATE(C$5,1,1),DATA!$N:$N,"<="&DATE(C$5,12,31)) | D7: =SUMIFS(DATA!$M:$M,DATA!$C:$C,$B7,DATA!$N:$N,">="&DATE(D$5,1,1),DATA!$N:$N,"<="&DATE(D$5,12,31)) | E7: =SUMIFS(DATA!$M:$M,DATA!$C:$C,$B7,DATA!$N:$N,">="&DATE(E$5,1,1),DATA!$N:$N,"<="&DATE(E$5,12,31)) | F7: =SUMIFS(DATA!$M:$M,DATA!$C:$C,$B7,DATA!$N:$N,">="&DATE(F$5,1,1),DATA!$N:$N,"<="&DATE(F$5,12,31)) | G7: =SUMIFS(DATA!$M:$M,DATA!$C:$C,$B7,DATA!$N:$N,">="&DATE(G$5,1,1),DATA!$N:$N,"<="&DATE(G$5,12,31)) | H7: =SUMIFS(DATA!$M:$M,DATA!$C:$C,$B7,DATA!$N:$N,">="&DATE(H$5,1,1),DATA!$N:$N,"<="&DATE(H$5,12,31)) | I7: =SUMIFS(DATA!$M:$M,DATA!$C:$C,$B7,DATA!$N:$N,">="&DATE(I$5,1,1),DATA!$N:$N,"<="&DATE(I$5,12,31)) | J7: =SUM(C7:I7) | K7: =J7/$J$506
A8: 3 | B8: YAMAHA MOTOR VIETNAM | C8: =SUMIFS(DATA!$M:$M,DATA!$C:$C,$B8,DATA!$N:$N,">="&DATE(C$5,1,1),DATA!$N:$N,"<="&DATE(C$5,12,31)) | D8: =SUMIFS(DATA!$M:$M,DATA!$C:$C,$B8,DATA!$N:$N,">="&DATE(D$5,1,1),DATA!$N:$N,"<="&DATE(D$5,12,31)) | E8: =SUMIFS(DATA!$M:$M,DATA!$C:$C,$B8,DATA!$N:$N,">="&DATE(E$5,1,1),DATA!$N:$N,"<="&DATE(E$5,12,31)) | F8: =SUMIFS(DATA!$M:$M,DATA!$C:$C,$B8,DATA!$N:$N,">="&DATE(F$5,1,1),DATA!$N:$N,"<="&DATE(F$5,12,31)) | G8: =SUMIFS(DATA!$M:$M,DATA!$C:$C,$B8,DATA!$N:$N,">="&DATE(G$5,1,1),DATA!$N:$N,"<="&DATE(G$5,12,31)) | H8: =SUMIFS(DATA!$M:$M,DATA!$C:$C,$B8,DATA!$N:$N,">="&DATE(H$5,1,1),DATA!$N:$N,"<="&DATE(H$5,12,31)) | I8: =SUMIFS(DATA!$M:$M,DATA!$C:$C,$B8,DATA!$N:$N,">="&DATE(I$5,1,1),DATA!$N:$N,"<="&DATE(I$5,12,31)) | J8: =SUM(C8:I8) | K8: =J8/$J$506
A9: 4 | B9: CÔNG TY TNHH THÁP LÁNG HẠ | C9: =SUMIFS(DATA!$M:$M,DATA!$C:$C,$B9,DATA!$N:$N,">="&DATE(C$5,1,1),DATA!$N:$N,"<="&DATE(C$5,12,31)) | D9: =SUMIFS(DATA!$M:$M,DATA!$C:$C,$B9,DATA!$N:$N,">="&DATE(D$5,1,1),DATA!$N:$N,"<="&DATE(D$5,12,31)) | E9: =SUMIFS(DATA!$M:$M,DATA!$C:$C,$B9,DATA!$N:$N,">="&DATE(E$5,1,1),DATA!$N:$N,"<="&DATE(E$5,12,31)) | F9: =SUMIFS(DATA!$M:$M,DATA!$C:$C,$B9,DATA!$N:$N,">="&DATE(F$5,1,1),DATA!$N:$N,"<="&DATE(F$5,12,31)) | G9: =SUMIFS(DATA!$M:$M,DATA!$C:$C,$B9,DATA!$N:$N,">="&DATE(G$5,1,1),DATA!$N:$N,"<="&DATE(G$5,12,31)) | H9: =SUMIFS(DATA!$M:$M,DATA!$C:$C,$B9,DATA!$N:$N,">="&DATE(H$5,1,1),DATA!$N:$N,"<="&DATE(H$5,12,31)) | I9: =SUMIFS(DATA!$M:$M,DATA!$C:$C,$B9,DATA!$N:$N,">="&DATE(I$5,1,1),DATA!$N:$N,"<="&DATE(I$5,12,31)) | J9: =SUM(C9:I9) | K9: =J9/$J$506
A10: 5 | B10: TRUNG TÂM HẠ TẦNG IDC - CÔNG TY CÔNG NGHỆ THÔNG TIN VNPT (VNPT-IT) | C10: =SUMIFS(DATA!$M:$M,DATA!$C:$C,$B10,DATA!$N:$N,">="&DATE(C$5,1,1),DATA!$N:$N,"<="&DATE(C$5,12,31)) | D10: =SUMIFS(DATA!$M:$M,DATA!$C:$C,$B10,DATA!$N:$N,">="&DATE(D$5,1,1),DATA!$N:$N,"<="&DATE(D$5,12,31)) | E10: =SUMIFS(DATA!$M:$M,DATA!$C:$C,$B10,DATA!$N:$N,">="&DATE(E$5,1,1),DATA!$N:$N,"<="&DATE(E$5,12,31)) | F10: =SUMIFS(DATA!$M:$M,DATA!$C:$C,$B10,DATA!$N:$N,">="&DATE(F$5,1,1),DATA!$N:$N,"<="&DATE(F$5,12,31)) | G10: =SUMIFS(DATA!$M:$M,DATA!$C:$C,$B10,DATA!$N:$N,">="&DATE(G$5,1,1),DATA!$N:$N,"<="&DATE(G$5,12,31)) | H10: =SUMIFS(DATA!$M:$M,DATA!$C:$C,$B10,DATA!$N:$N,">="&DATE(H$5,1,1),DATA!$N:$N,"<="&DATE(H$5,12,31)) | I10: =SUMIFS(DATA!$M:$M,DATA!$C:$C,$B10,DATA!$N:$N,">="&DATE(I$5,1,1),DATA!$N:$N,"<="&DATE(I$5,12,31)) | J10: =SUM(C10:I10) | K10: =J10/$J$506
A11: 6 | B11: CRYSTAL MARTIN VIETNAM | C11: =SUMIFS(DATA!$M:$M,DATA!$C:$C,$B11,DATA!$N:$N,">="&DATE(C$5,1,1),DATA!$N:$N,"<="&DATE(C$5,12,31)) | D11: =SUMIFS(DATA!$M:$M,DATA!$C:$C,$B11,DATA!$N:$N,">="&DATE(D$5,1,1),DATA!$N:$N,"<="&DATE(D$5,12,31)) | E11: =SUMIFS(DATA!$M:$M,DATA!$C:$C,$B11,DATA!$N:$N,">="&DATE(E$5,1,1),DATA!$N:$N,"<="&DATE(E$5,12,31)) | F11: =SUMIFS(DATA!$M:$M,DATA!$C:$C,$B11,DATA!$N:$N,">="&DATE(F$5,1,1),DATA!$N:$N,"<="&DATE(F$5,12,31)) | G11: =SUMIFS(DATA!$M:$M,DATA!$C:$C,$B11,DATA!$N:$N,">="&DATE(G$5,1,1),DATA!$N:$N,"<="&DATE(G$5,12,31)) | H11: =SUMIFS(DATA!$M:$M,DATA!$C:$C,$B11,DATA!$N:$N,">="&DATE(H$5,1,1),DATA!$N:$N,"<="&DATE(H$5,12,31)) | I11: =SUMIFS(DATA!$M:$M,DATA!$C:$C,$B11,DATA!$N:$N,">="&DATE(I$5,1,1),DATA!$N:$N,"<="&DATE(I$5,12,31)) | J11: =SUM(C11:I11) | K11: =J11/$J$506
A12: 7 | B12: RMIT UNIVERSITY | C12: =SUMIFS(DATA!$M:$M,DATA!$C:$C,$B12,DATA!$N:$N,">="&DATE(C$5,1,1),DATA!$N:$N,"<="&DATE(C$5,12,31)) | D12: =SUMIFS(DATA!$M:$M,DATA!$C:$C,$B12,DATA!$N:$N,">="&DATE(D$5,1,1),DATA!$N:$N,"<="&DATE(D$5,12,31)) | E12: =SUMIFS(DATA!$M:$M,DATA!$C:$C,$B12,DATA!$N:$N,">="&DATE(E$5,1,1),DATA!$N:$N,"<="&DATE(E$5,12,31)) | F12: =SUMIFS(DATA!$M:$M,DATA!$C:$C,$B12,DATA!$N:$N,">="&DATE(F$5,1,1),DATA!$N:$N,"<="&DATE(F$5,12,31)) | G12: =SUMIFS(DATA!$M:$M,DATA!$C:$C,$B12,DATA!$N:$N,">="&DATE(G$5,1,1),DATA!$N:$N,"<="&DATE(G$5,12,31)) | H12: =SUMIFS(DATA!$M:$M,DATA!$C:$C,$B12,DATA!$N:$N,">="&DATE(H$5,1,1),DATA!$N:$N,"<="&DATE(H$5,12,31)) | I12: =SUMIFS(DATA!$M:$M,DATA!$C:$C,$B12,DATA!$N:$N,">="&DATE(I$5,1,1),DATA!$N:$N,"<="&DATE(I$5,12,31)) | J12: =SUM(C12:I12) | K12: =J12/$J$506
A13: 8 | B13: GOLDEN PALACE MỄ TRÌ | C13: =SUMIFS(DATA!$M:$M,DATA!$C:$C,$B13,DATA!$N:$N,">="&DATE(C$5,1,1),DATA!$N:$N,"<="&DATE(C$5,12,31)) | D13: =SUMIFS(DATA!$M:$M,DATA!$C:$C,$B13,DATA!$N:$N,">="&DATE(D$5,1,1),DATA!$N:$N,"<="&DATE(D$5,12,31)) | E13: =SUMIFS(DATA!$M:$M,DATA!$C:$C,$B13,DATA!$N:$N,">="&DATE(E$5,1,1),DATA!$N:$N,"<="&DATE(E$5,12,31)) | F13: =SUMIFS(DATA!$M:$M,DATA!$C:$C,$B13,DATA!$N:$N,">="&DATE(F$5,1,1),DATA!$N:$N,"<="&DATE(F$5,12,31)) | G13: =SUMIFS(DATA!$M:$M,DATA!$C:$C,$B13,DATA!$N:$N,">="&DATE(G$5,1,1),DATA!$N:$N,"<="&DATE(G$5,12,31)) | H13: =SUMIFS(DATA!$M:$M,DATA!$C:$C,$B13,DATA!$N:$N,">="&DATE(H$5,1,1),DATA!$N:$N,"<="&DATE(H$5,12,31)) | I13: =SUMIFS(DATA!$M:$M,DATA!$C:$C,$B13,DATA!$N:$N,">="&DATE(I$5,1,1),DATA!$N:$N,"<="&DATE(I$5,12,31)) | J13: =SUM(C13:I13) | K13: =J13/$J$506
A14: 9 | B14: U.S. PEACE CORPS | C14: =SUMIFS(DATA!$M:$M,DATA!$C:$C,$B14,DATA!$N:$N,">="&DATE(C$5,1,1),DATA!$N:$N,"<="&DATE(C$5,12,31)) | D14: =SUMIFS(DATA!$M:$M,DATA!$C:$C,$B14,DATA!$N:$N,">="&DATE(D$5,1,1),DATA!$N:$N,"<="&DATE(D$5,12,31)) | E14: =SUMIFS(DATA!$M:$M,DATA!$C:$C,$B14,DATA!$N:$N,">="&DATE(E$5,1,1),DATA!$N:$N,"<="&DATE(E$5,12,31)) | F14: =SUMIFS(DATA!$M:$M,DATA!$C:$C,$B14,DATA!$N:$N,">="&DATE(F$5,1,1),DATA!$N:$N,"<="&DATE(F$5,12,31)) | G14: =SUMIFS(DATA!$M:$M,DATA!$C:$C,$B14,DATA!$N:$N,">="&DATE(G$5,1,1),DATA!$N:$N,"<="&DATE(G$5,12,31)) | H14: =SUMIFS(DATA!$M:$M,DATA!$C:$C,$B14,DATA!$N:$N,">="&DATE(H$5,1,1),DATA!$N:$N,"<="&DATE(H$5,12,31)) | I14: =SUMIFS(DATA!$M:$M,DATA!$C:$C,$B14,DATA!$N:$N,">="&DATE(I$5,1,1),DATA!$N:$N,"<="&DATE(I$5,12,31)) | J14: =SUM(C14:I14) | K14: =J14/$J$506
A15: 10 | B15: DETECH TOWER II | C15: =SUMIFS(DATA!$M:$M,DATA!$C:$C,$B15,DATA!$N:$N,">="&DATE(C$5,1,1),DATA!$N:$N,"<="&DATE(C$5,12,31)) | D15: =SUMIFS(DATA!$M:$M,DATA!$C:$C,$B15,DATA!$N:$N,">="&DATE(D$5,1,1),DATA!$N:$N,"<="&DATE(D$5,12,31)) | E15: =SUMIFS(DATA!$M:$M,DATA!$C:$C,$B15,DATA!$N:$N,">="&DATE(E$5,1,1),DATA!$N:$N,"<="&DATE(E$5,12,31)) | F15: =SUMIFS(DATA!$M:$M,DATA!$C:$C,$B15,DATA!$N:$N,">="&DATE(F$5,1,1),DATA!$N:$N,"<="&DATE(F$5,12,31)) | G15: =SUMIFS(DATA!$M:$M,DATA!$C:$C,$B15,DATA!$N:$N,">="&DATE(G$5,1,1),DATA!$N:$N,"<="&DATE(G$5,12,31)) | H15: =SUMIFS(DATA!$M:$M,DATA!$C:$C,$B15,DATA!$N:$N,">="&DATE(H$5,1,1),DATA!$N:$N,"<="&DATE(H$5,12,31)) | I15: =SUMIFS(DATA!$M:$M,DATA!$C:$C,$B15,DATA!$N:$N,">="&DATE(I$5,1,1),DATA!$N:$N,"<="&DATE(I$5,12,31)) | J15: =SUM(C15:I15) | K15: =J15/$J$506
A16: 11 | B16: WIDIA SHINKI VIETNAM | C16: =SUMIFS(DATA!$M:$M,DATA!$C:$C,$B16,DATA!$N:$N,">="&DATE(C$5,1,1),DATA!$N:$N,"<="&DATE(C$5,12,31)) | D16: =SUMIFS(DATA!$M:$M,DATA!$C:$C,$B16,DATA!$N:$N,">="&DATE(D$5,1,1),DATA!$N:$N,"<="&DATE(D$5,12,31)) | E16: =SUMIFS(DATA!$M:$M,DATA!$C:$C,$B16,DATA!$N:$N,">="&DATE(E$5,1,1),DATA!$N:$N,"<="&DATE(E$5,12,31)) | F16: =SUMIFS(DATA!$M:$M,DATA!$C:$C,$B16,DATA!$N:$N,">="&DATE(F$5,1,1),DATA!$N:$N,"<="&DATE(F$5,12,31)) | G16: =SUMIFS(DATA!$M:$M,DATA!$C:$C,$B16,DATA!$N:$N,">="&DATE(G$5,1,1),DATA!$N:$N,"<="&DATE(G$5,12,31)) | H16: =SUMIFS(DATA!$M:$M,DATA!$C:$C,$B16,DATA!$N:$N,">="&DATE(H$5,1,1),DATA!$N:$N,"<="&DATE(H$5,12,31)) | I16: =SUMIFS(DATA!$M:$M,DATA!$C:$C,$B16,DATA!$N:$N,">="&DATE(I$5,1,1),DATA!$N:$N,"<="&DATE(I$5,12,31)) | J16: =SUM(C16:I16) | K16: =J16/$J$506
A17: 12 | B17: GENTHERM VIETNAM CO., LTD | C17: =SUMIFS(DATA!$M:$M,DATA!$C:$C,$B17,DATA!$N:$N,">="&DATE(C$5,1,1),DATA!$N:$N,"<="&DATE(C$5,12,31)) | D17: =SUMIFS(DATA!$M:$M,DATA!$C:$C,$B17,DATA!$N:$N,">="&DATE(D$5,1,1),DATA!$N:$N,"<="&DATE(D$5,12,31)) | E17: =SUMIFS(DATA!$M:$M,DATA!$C:$C,$B17,DATA!$N:$N,">="&DATE(E$5,1,1),DATA!$N:$N,"<="&DATE(E$5,12,31)) | F17: =SUMIFS(DATA!$M:$M,DATA!$C:$C,$B17,DATA!$N:$N,">="&DATE(F$5,1,1),DATA!$N:$N,"<="&DATE(F$5,12,31)) | G17: =SUMIFS(DATA!$M:$M,DATA!$C:$C,$B17,DATA!$N:$N,">="&DATE(G$5,1,1),DATA!$N:$N,"<="&DATE(G$5,12,31)) | H17: =SUMIFS(DATA!$M:$M,DATA!$C:$C,$B17,DATA!$N:$N,">="&DATE(H$5,1,1),DATA!$N:$N,"<="&DATE(H$5,12,31)) | I17: =SUMIFS(DATA!$M:$M,DATA!$C:$C,$B17,DATA!$N:$N,">="&DATE(I$5,1,1),DATA!$N:$N,"<="&DATE(I$5,12,31)) | J17: =SUM(C17:I17) | K17: =J17/$J$506
... A161: 156 | B161: CÔNG TY TNHH TƯ VẤN & XÂY LẮP PCCC NTK | C161: =SUMIFS(DATA!$M:$M,DATA!$C:$C,$B161,DATA!$N:$N,">="&DATE(C$5,1,1),DATA!$N:$N,"<="&DATE(C$5,12,31)) | D161: =SUMIFS(DATA!$M:$M,DATA!$C:$C,$B161,DATA!$N:$N,">="&DATE(D$5,1,1),DATA!$N:$N,"<="&DATE(D$5,12,31)) | E161: =SUMIFS(DATA!$M:$M,DATA!$C:$C,$B161,DATA!$N:$N,">="&DATE(E$5,1,1),DATA!$N:$N,"<="&DATE(E$5,12,31)) | F161: =SUMIFS(DATA!$M:$M,DATA!$C:$C,$B161,DATA!$N:$N,">="&DATE(F$5,1,1),DATA!$N:$N,"<="&DATE(F$5,12,31)) | G161: =SUMIFS(DATA!$M:$M,DATA!$C:$C,$B161,DATA!$N:$N,">="&DATE(G$5,1,1),DATA!$N:$N,"<="&DATE(G$5,12,31)) | H161: =SUMIFS(DATA!$M:$M,DATA!$C:$C,$B161,DATA!$N:$N,">="&DATE(H$5,1,1),DATA!$N:$N,"<="&DATE(H$5,12,31)) | I161: =SUMIFS(DATA!$M:$M,DATA!$C:$C,$B161,DATA!$N:$N,">="&DATE(I$5,1,1),DATA!$N:$N,"<="&DATE(I$5,12,31)) | J161: =SUM(C161:I161) | K161: =J161/$J$506
A162: 157 | C162: =SUMIFS(DATA!$M:$M,DATA!$C:$C,$B162,DATA!$N:$N,">="&DATE(C$5,1,1),DATA!$N:$N,"<="&DATE(C$5,12,31)) | D162: =SUMIFS(DATA!$M:$M,DATA!$C:$C,$B162,DATA!$N:$N,">="&DATE(D$5,1,1),DATA!$N:$N,"<="&DATE(D$5,12,31)) | E162: =SUMIFS(DATA!$M:$M,DATA!$C:$C,$B162,DATA!$N:$N,">="&DATE(E$5,1,1),DATA!$N:$N,"<="&DATE(E$5,12,31)) | F162: =SUMIFS(DATA!$M:$M,DATA!$C:$C,$B162,DATA!$N:$N,">="&DATE(F$5,1,1),DATA!$N:$N,"<="&DATE(F$5,12,31)) | G162: =SUMIFS(DATA!$M:$M,DATA!$C:$C,$B162,DATA!$N:$N,">="&DATE(G$5,1,1),DATA!$N:$N,"<="&DATE(G$5,12,31)) | H162: =SUMIFS(DATA!$M:$M,DATA!$C:$C,$B162,DATA!$N:$N,">="&DATE(H$5,1,1),DATA!$N:$N,"<="&DATE(H$5,12,31)) | I162: =SUMIFS(DATA!$M:$M,DATA!$C:$C,$B162,DATA!$N:$N,">="&DATE(I$5,1,1),DATA!$N:$N,"<="&DATE(I$5,12,31)) | J162: =SUM(C162:I162) | K162: =J162/$J$506
A163: 158 | C163: =SUMIFS(DATA!$M:$M,DATA!$C:$C,$B163,DATA!$N:$N,">="&DATE(C$5,1,1),DATA!$N:$N,"<="&DATE(C$5,12,31)) | D163: =SUMIFS(DATA!$M:$M,DATA!$C:$C,$B163,DATA!$N:$N,">="&DATE(D$5,1,1),DATA!$N:$N,"<="&DATE(D$5,12,31)) | E163: =SUMIFS(DATA!$M:$M,DATA!$C:$C,$B163,DATA!$N:$N,">="&DATE(E$5,1,1),DATA!$N:$N,"<="&DATE(E$5,12,31)) | F163: =SUMIFS(DATA!$M:$M,DATA!$C:$C,$B163,DATA!$N:$N,">="&DATE(F$5,1,1),DATA!$N:$N,"<="&DATE(F$5,12,31)) | G163: =SUMIFS(DATA!$M:$M,DATA!$C:$C,$B163,DATA!$N:$N,">="&DATE(G$5,1,1),DATA!$N:$N,"<="&DATE(G$5,12,31)) | H163: =SUMIFS(DATA!$M:$M,DATA!$C:$C,$B163,DATA!$N:$N,">="&DATE(H$5,1,1),DATA!$N:$N,"<="&DATE(H$5,12,31)) | I163: =SUMIFS(DATA!$M:$M,DATA!$C:$C,$B163,DATA!$N:$N,">="&DATE(I$5,1,1),DATA!$N:$N,"<="&DATE(I$5,12,31)) | J163: =SUM(C163:I163) | K163: =J163/$J$506
A164: 159 | C164: =SUMIFS(DATA!$M:$M,DATA!$C:$C,$B164,DATA!$N:$N,">="&DATE(C$5,1,1),DATA!$N:$N,"<="&DATE(C$5,12,31)) | D164: =SUMIFS(DATA!$M:$M,DATA!$C:$C,$B164,DATA!$N:$N,">="&DATE(D$5,1,1),DATA!$N:$N,"<="&DATE(D$5,12,31)) | E164: =SUMIFS(DATA!$M:$M,DATA!$C:$C,$B164,DATA!$N:$N,">="&DATE(E$5,1,1),DATA!$N:$N,"<="&DATE(E$5,12,31)) | F164: =SUMIFS(DATA!$M:$M,DATA!$C:$C,$B164,DATA!$N:$N,">="&DATE(F$5,1,1),DATA!$N:$N,"<="&DATE(F$5,12,31)) | G164: =SUMIFS(DATA!$M:$M,DATA!$C:$C,$B164,DATA!$N:$N,">="&DATE(G$5,1,1),DATA!$N:$N,"<="&DATE(G$5,12,31)) | H164: =SUMIFS(DATA!$M:$M,DATA!$C:$C,$B164,DATA!$N:$N,">="&DATE(H$5,1,1),DATA!$N:$N,"<="&DATE(H$5,12,31)) | I164: =SUMIFS(DATA!$M:$M,DATA!$C:$C,$B164,DATA!$N:$N,">="&DATE(I$5,1,1),DATA!$N:$N,"<="&DATE(I$5,12,31)) | J164: =SUM(C164:I164) | K164: =J164/$J$506
A165: 160 | C165: =SUMIFS(DATA!$M:$M,DATA!$C:$C,$B165,DATA!$N:$N,">="&DATE(C$5,1,1),DATA!$N:$N,"<="&DATE(C$5,12,31)) | D165: =SUMIFS(DATA!$M:$M,DATA!$C:$C,$B165,DATA!$N:$N,">="&DATE(D$5,1,1),DATA!$N:$N,"<="&DATE(D$5,12,31)) | E165: =SUMIFS(DATA!$M:$M,DATA!$C:$C,$B165,DATA!$N:$N,">="&DATE(E$5,1,1),DATA!$N:$N,"<="&DATE(E$5,12,31)) | F165: =SUMIFS(DATA!$M:$M,DATA!$C:$C,$B165,DATA!$N:$N,">="&DATE(F$5,1,1),DATA!$N:$N,"<="&DATE(F$5,12,31)) | G165: =SUMIFS(DATA!$M:$M,DATA!$C:$C,$B165,DATA!$N:$N,">="&DATE(G$5,1,1),DATA!$N:$N,"<="&DATE(G$5,12,31)) | H165: =SUMIFS(DATA!$M:$M,DATA!$C:$C,$B165,DATA!$N:$N,">="&DATE(H$5,1,1),DATA!$N:$N,"<="&DATE(H$5,12,31)) | I165: =SUMIFS(DATA!$M:$M,DATA!$C:$C,$B165,DATA!$N:$N,">="&DATE(I$5,1,1),DATA!$N:$N,"<="&DATE(I$5,12,31)) | J165: =SUM(C165:I165) | K165: =J165/$J$506
A166: 161 | C166: =SUMIFS(DATA!$M:$M,DATA!$C:$C,$B166,DATA!$N:$N,">="&DATE(C$5,1,1),DATA!$N:$N,"<="&DATE(C$5,12,31)) | D166: =SUMIFS(DATA!$M:$M,DATA!$C:$C,$B166,DATA!$N:$N,">="&DATE(D$5,1,1),DATA!$N:$N,"<="&DATE(D$5,12,31)) | E166: =SUMIFS(DATA!$M:$M,DATA!$C:$C,$B166,DATA!$N:$N,">="&DATE(E$5,1,1),DATA!$N:$N,"<="&DATE(E$5,12,31)) | F166: =SUMIFS(DATA!$M:$M,DATA!$C:$C,$B166,DATA!$N:$N,">="&DATE(F$5,1,1),DATA!$N:$N,"<="&DATE(F$5,12,31)) | G166: =SUMIFS(DATA!$M:$M,DATA!$C:$C,$B166,DATA!$N:$N,">="&DATE(G$5,1,1),DATA!$N:$N,"<="&DATE(G$5,12,31)) | H166: =SUMIFS(DATA!$M:$M,DATA!$C:$C,$B166,DATA!$N:$N,">="&DATE(H$5,1,1),DATA!$N:$N,"<="&DATE(H$5,12,31)) | I166: =SUMIFS(DATA!$M:$M,DATA!$C:$C,$B166,DATA!$N:$N,">="&DATE(I$5,1,1),DATA!$N:$N,"<="&DATE(I$5,12,31)) | J166: =SUM(C166:I166) | K166: =J166/$J$506
A167: 162 | C167: =SUMIFS(DATA!$M:$M,DATA!$C:$C,$B167,DATA!$N:$N,">="&DATE(C$5,1,1),DATA!$N:$N,"<="&DATE(C$5,12,31)) | D167: =SUMIFS(DATA!$M:$M,DATA!$C:$C,$B167,DATA!$N:$N,">="&DATE(D$5,1,1),DATA!$N:$N,"<="&DATE(D$5,12,31)) | E167: =SUMIFS(DATA!$M:$M,DATA!$C:$C,$B167,DATA!$N:$N,">="&DATE(E$5,1,1),DATA!$N:$N,"<="&DATE(E$5,12,31)) | F167: =SUMIFS(DATA!$M:$M,DATA!$C:$C,$B167,DATA!$N:$N,">="&DATE(F$5,1,1),DATA!$N:$N,"<="&DATE(F$5,12,31)) | G167: =SUMIFS(DATA!$M:$M,DATA!$C:$C,$B167,DATA!$N:$N,">="&DATE(G$5,1,1),DATA!$N:$N,"<="&DATE(G$5,12,31)) | H167: =SUMIFS(DATA!$M:$M,DATA!$C:$C,$B167,DATA!$N:$N,">="&DATE(H$5,1,1),DATA!$N:$N,"<="&DATE(H$5,12,31)) | I167: =SUMIFS(DATA!$M:$M,DATA!$C:$C,$B167,DATA!$N:$N,">="&DATE(I$5,1,1),DATA!$N:$N,"<="&DATE(I$5,12,31)) | J167: =SUM(C167:I167) | K167: =J167/$J$506
A168: 163 | C168: =SUMIFS(DATA!$M:$M,DATA!$C:$C,$B168,DATA!$N:$N,">="&DATE(C$5,1,1),DATA!$N:$N,"<="&DATE(C$5,12,31)) | D168: =SUMIFS(DATA!$M:$M,DATA!$C:$C,$B168,DATA!$N:$N,">="&DATE(D$5,1,1),DATA!$N:$N,"<="&DATE(D$5,12,31)) | E168: =SUMIFS(DATA!$M:$M,DATA!$C:$C,$B168,DATA!$N:$N,">="&DATE(E$5,1,1),DATA!$N:$N,"<="&DATE(E$5,12,31)) | F168: =SUMIFS(DATA!$M:$M,DATA!$C:$C,$B168,DATA!$N:$N,">="&DATE(F$5,1,1),DATA!$N:$N,"<="&DATE(F$5,12,31)) | G168: =SUMIFS(DATA!$M:$M,DATA!$C:$C,$B168,DATA!$N:$N,">="&DATE(G$5,1,1),DATA!$N:$N,"<="&DATE(G$5,12,31)) | H168: =SUMIFS(DATA!$M:$M,DATA!$C:$C,$B168,DATA!$N:$N,">="&DATE(H$5,1,1),DATA!$N:$N,"<="&DATE(H$5,12,31)) | I168: =SUMIFS(DATA!$M:$M,DATA!$C:$C,$B168,DATA!$N:$N,">="&DATE(I$5,1,1),DATA!$N:$N,"<="&DATE(I$5,12,31)) | J168: =SUM(C168:I168) | K168: =J168/$J$506
A169: 164 | C169: =SUMIFS(DATA!$M:$M,DATA!$C:$C,$B169,DATA!$N:$N,">="&DATE(C$5,1,1),DATA!$N:$N,"<="&DATE(C$5,12,31)) | D169: =SUMIFS(DATA!$M:$M,DATA!$C:$C,$B169,DATA!$N:$N,">="&DATE(D$5,1,1),DATA!$N:$N,"<="&DATE(D$5,12,31)) | E169: =SUMIFS(DATA!$M:$M,DATA!$C:$C,$B169,DATA!$N:$N,">="&DATE(E$5,1,1),DATA!$N:$N,"<="&DATE(E$5,12,31)) | F169: =SUMIFS(DATA!$M:$M,DATA!$C:$C,$B169,DATA!$N:$N,">="&DATE(F$5,1,1),DATA!$N:$N,"<="&DATE(F$5,12,31)) | G169: =SUMIFS(DATA!$M:$M,DATA!$C:$C,$B169,DATA!$N:$N,">="&DATE(G$5,1,1),DATA!$N:$N,"<="&DATE(G$5,12,31)) | H169: =SUMIFS(DATA!$M:$M,DATA!$C:$C,$B169,DATA!$N:$N,">="&DATE(H$5,1,1),DATA!$N:$N,"<="&DATE(H$5,12,31)) | I169: =SUMIFS(DATA!$M:$M,DATA!$C:$C,$B169,DATA!$N:$N,">="&DATE(I$5,1,1),DATA!$N:$N,"<="&DATE(I$5,12,31)) | J169: =SUM(C169:I169) | K169: =J169/$J$506
A170: 165 | C170: =SUMIFS(DATA!$M:$M,DATA!$C:$C,$B170,DATA!$N:$N,">="&DATE(C$5,1,1),DATA!$N:$N,"<="&DATE(C$5,12,31)) | D170: =SUMIFS(DATA!$M:$M,DATA!$C:$C,$B170,DATA!$N:$N,">="&DATE(D$5,1,1),DATA!$N:$N,"<="&DATE(D$5,12,31)) | E170: =SUMIFS(DATA!$M:$M,DATA!$C:$C,$B170,DATA!$N:$N,">="&DATE(E$5,1,1),DATA!$N:$N,"<="&DATE(E$5,12,31)) | F170: =SUMIFS(DATA!$M:$M,DATA!$C:$C,$B170,DATA!$N:$N,">="&DATE(F$5,1,1),DATA!$N:$N,"<="&DATE(F$5,12,31)) | G170: =SUMIFS(DATA!$M:$M,DATA!$C:$C,$B170,DATA!$N:$N,">="&DATE(G$5,1,1),DATA!$N:$N,"<="&DATE(G$5,12,31)) | H170: =SUMIFS(DATA!$M:$M,DATA!$C:$C,$B170,DATA!$N:$N,">="&DATE(H$5,1,1),DATA!$N:$N,"<="&DATE(H$5,12,31)) | I170: =SUMIFS(DATA!$M:$M,DATA!$C:$C,$B170,DATA!$N:$N,">="&DATE(I$5,1,1),DATA!$N:$N,"<="&DATE(I$5,12,31)) | J170: =SUM(C170:I170) | K170: =J170/$J$506
A171: 166 | C171: =SUMIFS(DATA!$M:$M,DATA!$C:$C,$B171,DATA!$N:$N,">="&DATE(C$5,1,1),DATA!$N:$N,"<="&DATE(C$5,12,31)) | D171: =SUMIFS(DATA!$M:$M,DATA!$C:$C,$B171,DATA!$N:$N,">="&DATE(D$5,1,1),DATA!$N:$N,"<="&DATE(D$5,12,31)) | E171: =SUMIFS(DATA!$M:$M,DATA!$C:$C,$B171,DATA!$N:$N,">="&DATE(E$5,1,1),DATA!$N:$N,"<="&DATE(E$5,12,31)) | F171: =SUMIFS(DATA!$M:$M,DATA!$C:$C,$B171,DATA!$N:$N,">="&DATE(F$5,1,1),DATA!$N:$N,"<="&DATE(F$5,12,31)) | G171: =SUMIFS(DATA!$M:$M,DATA!$C:$C,$B171,DATA!$N:$N,">="&DATE(G$5,1,1),DATA!$N:$N,"<="&DATE(G$5,12,31)) | H171: =SUMIFS(DATA!$M:$M,DATA!$C:$C,$B171,DATA!$N:$N,">="&DATE(H$5,1,1),DATA!$N:$N,"<="&DATE(H$5,12,31)) | I171: =SUMIFS(DATA!$M:$M,DATA!$C:$C,$B171,DATA!$N:$N,">="&DATE(I$5,1,1),DATA!$N:$N,"<="&DATE(I$5,12,31)) | J171: =SUM(C171:I171) | K171: =J171/$J$506
A172: 167 | C172: =SUMIFS(DATA!$M:$M,DATA!$C:$C,$B172,DATA!$N:$N,">="&DATE(C$5,1,1),DATA!$N:$N,"<="&DATE(C$5,12,31)) | D172: =SUMIFS(DATA!$M:$M,DATA!$C:$C,$B172,DATA!$N:$N,">="&DATE(D$5,1,1),DATA!$N:$N,"<="&DATE(D$5,12,31)) | E172: =SUMIFS(DATA!$M:$M,DATA!$C:$C,$B172,DATA!$N:$N,">="&DATE(E$5,1,1),DATA!$N:$N,"<="&DATE(E$5,12,31)) | F172: =SUMIFS(DATA!$M:$M,DATA!$C:$C,$B172,DATA!$N:$N,">="&DATE(F$5,1,1),DATA!$N:$N,"<="&DATE(F$5,12,31)) | G172: =SUMIFS(DATA!$M:$M,DATA!$C:$C,$B172,DATA!$N:$N,">="&DATE(G$5,1,1),DATA!$N:$N,"<="&DATE(G$5,12,31)) | H172: =SUMIFS(DATA!$M:$M,DATA!$C:$C,$B172,DATA!$N:$N,">="&DATE(H$5,1,1),DATA!$N:$N,"<="&DATE(H$5,12,31)) | I172: =SUMIFS(DATA!$M:$M,DATA!$C:$C,$B172,DATA!$N:$N,">="&DATE(I$5,1,1),DATA!$N:$N,"<="&DATE(I$5,12,31)) | J172: =SUM(C172:I172) | K172: =J172/$J$506
A173: 168 | C173: =SUMIFS(DATA!$M:$M,DATA!$C:$C,$B173,DATA!$N:$N,">="&DATE(C$5,1,1),DATA!$N:$N,"<="&DATE(C$5,12,31)) | D173: =SUMIFS(DATA!$M:$M,DATA!$C:$C,$B173,DATA!$N:$N,">="&DATE(D$5,1,1),DATA!$N:$N,"<="&DATE(D$5,12,31)) | E173: =SUMIFS(DATA!$M:$M,DATA!$C:$C,$B173,DATA!$N:$N,">="&DATE(E$5,1,1),DATA!$N:$N,"<="&DATE(E$5,12,31)) | F173: =SUMIFS(DATA!$M:$M,DATA!$C:$C,$B173,DATA!$N:$N,">="&DATE(F$5,1,1),DATA!$N:$N,"<="&DATE(F$5,12,31)) | G173: =SUMIFS(DATA!$M:$M,DATA!$C:$C,$B173,DATA!$N:$N,">="&DATE(G$5,1,1),DATA!$N:$N,"<="&DATE(G$5,12,31)) | H173: =SUMIFS(DATA!$M:$M,DATA!$C:$C,$B173,DATA!$N:$N,">="&DATE(H$5,1,1),DATA!$N:$N,"<="&DATE(H$5,12,31)) | I173: =SUMIFS(DATA!$M:$M,DATA!$C:$C,$B173,DATA!$N:$N,">="&DATE(I$5,1,1),DATA!$N:$N,"<="&DATE(I$5,12,31)) | J173: =SUM(C173:I173) | K173: =J173/$J$506
... A505: 500 | C505: =SUMIFS(DATA!$M:$M,DATA!$C:$C,$B505,DATA!$N:$N,">="&DATE(C$5,1,1),DATA!$N:$N,"<="&DATE(C$5,12,31)) | D505: =SUMIFS(DATA!$M:$M,DATA!$C:$C,$B505,DATA!$N:$N,">="&DATE(D$5,1,1),DATA!$N:$N,"<="&DATE(D$5,12,31)) | E505: =SUMIFS(DATA!$M:$M,DATA!$C:$C,$B505,DATA!$N:$N,">="&DATE(E$5,1,1),DATA!$N:$N,"<="&DATE(E$5,12,31)) | F505: =SUMIFS(DATA!$M:$M,DATA!$C:$C,$B505,DATA!$N:$N,">="&DATE(F$5,1,1),DATA!$N:$N,"<="&DATE(F$5,12,31)) | G505: =SUMIFS(DATA!$M:$M,DATA!$C:$C,$B505,DATA!$N:$N,">="&DATE(G$5,1,1),DATA!$N:$N,"<="&DATE(G$5,12,31)) | H505: =SUMIFS(DATA!$M:$M,DATA!$C:$C,$B505,DATA!$N:$N,">="&DATE(H$5,1,1),DATA!$N:$N,"<="&DATE(H$5,12,31)) | I505: =SUMIFS(DATA!$M:$M,DATA!$C:$C,$B505,DATA!$N:$N,">="&DATE(I$5,1,1),DATA!$N:$N,"<="&DATE(I$5,12,31)) | J505: =SUM(C505:I505) | K505: =J505/$J$506
B506: Tổng cộng Grand total: | C506: =SUM(C6:C505) | D506: =SUM(D6:D505) | E506: =SUM(E6:E505) | F506: =SUM(F6:F505) | G506: =SUM(G6:G505) | H506: =SUM(H6:H505) | I506: =SUM(I6:I505) | J506: =SUM(J6:J505)
B507: Number of clients | C507: =COUNTIF(C5:C505,">"&0) | D507: =COUNTIF(D5:D505,">"&0) | E507: =COUNTIF(E5:E505,">"&0) | F507: =COUNTIF(F5:F505,">"&0) | G507: =COUNTIF(G5:G505,">"&0) | H507: =COUNTIF(H5:H505,">"&0) | I507: =COUNTIF(I5:I505,">"&0) | J507: =COUNTIF(J5:J505,">"&0)
B508: Increase (%) | D508: =(D506-C506)/C506 | E508: =(E506-D506)/D506 | F508: =(F506-E506)/E506 | G508: =(G506-F506)/F506 | H508: =(H506-G506)/G506 | I508: =(I506-H506)/H506
C531: Số liệu năm 2020, 2021 & 2022 chưa được cập nhật/ chưa cập nhật đầy đủ
C532: Số liệu của các năm trên xem chi tiết tại file báo cáo Turn over report (cũ) lưu trữ tại server SPS.

Sheet Debt report
D1: BẢNG THEO DÕI NỢ PHẢI THU & NỢ QUÁ HẠN TRONG NĂM RECEIVABLE & OUSTANDING DEBT IN YEAR
G2: YEAR: | H2: 2025
A4: No. | B4: Month Item | C4: Nợ cũ các năm trước Old debt | D4: 1 | E4: 2 | F4: 3 | G4: 4 | H4: 5 | I4: 6 | J4: 7 | K4: 8 | L4: 9 | M4: 10 | N4: 11 | O4: 12 | P4: Total in year | Q4: Total (Cũ + hiện tại)
B5: Trung gian tính ngày cuối của tháng | D5: 31 | E5: =DAY(EOMONTH(DATE(H2,E4,1),0)) | F5: 31 | G5: 30 | H5: 31 | I5: 30 | J5: 31 | K5: 31 | L5: 30 | M5: 31 | N5: 30 | O5: 31
B6: Nợ phải thu/ Receivable | C6: =SUM(C8:C11) | D6: =SUM(D8:D11) | E6: =SUM(E8:E11) | F6: =SUM(F8:F11) | G6: =SUM(G8:G11) | H6: =SUM(H8:H11) | I6: =SUM(I8:I11) | J6: =SUM(J8:J11) | ... O6: =SUM(O8:O11) | P6: =SUM(D6:O6) | Q6: =SUM(Q8:Q10)
A7: A | B7: Nợ phải thu - Giá trị đã xuất hóa đơn/ Receivable | C7: =SUM(C8:C10) | D7: =SUM(D8:D10) | E7: =SUM(E8:E10) | F7: =SUM(F8:F10) | G7: =SUM(G8:G10) | H7: =SUM(H8:H10) | I7: =SUM(I8:I10) | J7: =SUM(J8:J10) | ... P7: =SUM(P8:P10) | Q7: =C7+P7
A8: 1 | B8: Waiting for payment in time | C8: =SUMIFS(DATA!$O:$O,DATA!$P:$P,'Debt report'!$B$8,DATA!$Q:$Q,"<="&DATE($H$2-1,12,31)) | D8: =SUMIFS(DATA!$O:$O,DATA!$P:$P,'Debt report'!$B$8,DATA!$Q:$Q,">="&DATE($H$2,D$4,1),DATA!$Q:$Q,"<="&DATE($H$2,D$4,D$5)) | E8: =SUMIFS(DATA!$O:$O,DATA!$P:$P,'Debt report'!$B$8,DATA!$Q:$Q,">="&DATE($H$2,E$4,1),DATA!$Q:$Q,"<="&DATE($H$2,E$4,E$5)) | F8: =SUMIFS(DATA!$O:$O,DATA!$P:$P,'Debt report'!$B$8,DATA!$Q:$Q,">="&DATE($H$2,F$4,1),DATA!$Q:$Q,"<="&DATE($H$2,F$4,F$5)) | G8: =SUMIFS(DATA!$O:$O,DATA!$P:$P,'Debt report'!$B$8,DATA!$Q:$Q,">="&DATE($H$2,G$4,1),DATA!$Q:$Q,"<="&DATE($H$2,G$4,G$5)) | H8: =SUMIFS(DATA!$O:$O,DATA!$P:$P,'Debt report'!$B$8,DATA!$Q:$Q,">="&DATE($H$2,H$4,1),DATA!$Q:$Q,"<="&DATE($H$2,H$4,H$5)) | I8: =SUMIFS(DATA!$O:$O,DATA!$P:$P,'Debt report'!$B$8,DATA!$Q:$Q,">="&DATE($H$2,I$4,1),DATA!$Q:$Q,"<="&DATE($H$2,I$4,I$5)) | J8: =SUMIFS(DATA!$O:$O,DATA!$P:$P,'Debt report'!$B$8,DATA!$Q:$Q,">="&DATE($H$2,J$4,1),DATA!$Q:$Q,"<="&DATE($H$2,J$4,J$5)) | K8: =SUMIFS(DATA!$O:$O,DATA!$P:$P,'Debt report'!$B$8,DATA!$Q:$Q,">="&DATE($H$2,K$4,1),DATA!$Q:$Q,"<="&DATE($H$2,K$4,K$5)) | ... O8: =SUMIFS(DATA!$O:$O,DATA!$P:$P,'Debt report'!$B$8,DATA!$Q:$Q,">="&DATE($H$2,O$4,1),DATA!$Q:$Q,"<="&DATE($H$2,O$4,O$5)) | P8: =SUM(D8:O8) | Q8: =C8+P8
A9: 2 | B9: Remaining | C9: =SUMIFS(DATA!$O:$O,DATA!$P:$P,'Debt report'!$B$9,DATA!$Q:$Q,"<="&DATE($H$2-1,12,31)) | D9: =SUMIFS(DATA!$O:$O,DATA!$P:$P,'Debt report'!$B$9,DATA!$Q:$Q,">="&DATE($H$2,D$4,1),DATA!$Q:$Q,"<="&DATE($H$2,D$4,D$5)) | E9: =SUMIFS(DATA!$O:$O,DATA!$P:$P,'Debt report'!$B$9,DATA!$Q:$Q,">="&DATE($H$2,E$4,1),DATA!$Q:$Q,"<="&DATE($H$2,E$4,E$5)) | F9: =SUMIFS(DATA!$O:$O,DATA!$P:$P,'Debt report'!$B$9,DATA!$Q:$Q,">="&DATE($H$2,F$4,1),DATA!$Q:$Q,"<="&DATE($H$2,F$4,F$5)) | G9: =SUMIFS(DATA!$O:$O,DATA!$P:$P,'Debt report'!$B$9,DATA!$Q:$Q,">="&DATE($H$2,G$4,1),DATA!$Q:$Q,"<="&DATE($H$2,G$4,G$5)) | H9: =SUMIFS(DATA!$O:$O,DATA!$P:$P,'Debt report'!$B$9,DATA!$Q:$Q,">="&DATE($H$2,H$4,1),DATA!$Q:$Q,"<="&DATE($H$2,H$4,H$5)) | I9: =SUMIFS(DATA!$O:$O,DATA!$P:$P,'Debt report'!$B$9,DATA!$Q:$Q,">="&DATE($H$2,I$4,1),DATA!$Q:$Q,"<="&DATE($H$2,I$4,I$5)) | J9: =SUMIFS(DATA!$O:$O,DATA!$P:$P,'Debt report'!$B$9,DATA!$Q:$Q,">="&DATE($H$2,J$4,1),DATA!$Q:$Q,"<="&DATE($H$2,J$4,J$5)) | K9: =SUMIFS(DATA!$O:$O,DATA!$P:$P,'Debt report'!$B$9,DATA!$Q:$Q,">="&DATE($H$2,K$4,1),DATA!$Q:$Q,"<="&DATE($H$2,K$4,K$5)) | ... O9: =SUMIFS(DATA!$O:$O,DATA!$P:$P,'Debt report'!$B$9,DATA!$Q:$Q,">="&DATE($H$2,O$4,1),DATA!$Q:$Q,"<="&DATE($H$2,O$4,O$5)) | P9: =SUM(D9:O9) | Q9: =C9+P9
A10: 3 | B10: Waiting for payment out time | C10: =SUMIFS(DATA!$O:$O,DATA!$P:$P,'Debt report'!$B$10,DATA!$Q:$Q,"<="&DATE($H$2-1,12,31)) | D10: =SUMIFS(DATA!$O:$O,DATA!$P:$P,'Debt report'!$B$10,DATA!$Q:$Q,">="&DATE($H$2,D$4,1),DATA!$Q:$Q,"<="&DATE($H$2,D$4,D$5)) | E10: =SUMIFS(DATA!$O:$O,DATA!$P:$P,'Debt report'!$B$10,DATA!$Q:$Q,">="&DATE($H$2,E$4,1),DATA!$Q:$Q,"<="&DATE($H$2,E$4,E$5)) | F10: =SUMIFS(DATA!$O:$O,DATA!$P:$P,'Debt report'!$B$10,DATA!$Q:$Q,">="&DATE($H$2,F$4,1),DATA!$Q:$Q,"<="&DATE($H$2,F$4,F$5)) | G10: =SUMIFS(DATA!$O:$O,DATA!$P:$P,'Debt report'!$B$10,DATA!$Q:$Q,">="&DATE($H$2,G$4,1),DATA!$Q:$Q,"<="&DATE($H$2,G$4,G$5)) | H10: =SUMIFS(DATA!$O:$O,DATA!$P:$P,'Debt report'!$B$10,DATA!$Q:$Q,">="&DATE($H$2,H$4,1),DATA!$Q:$Q,"<="&DATE($H$2,H$4,H$5)) | I10: =SUMIFS(DATA!$O:$O,DATA!$P:$P,'Debt report'!$B$10,DATA!$Q:$Q,">="&DATE($H$2,I$4,1),DATA!$Q:$Q,"<="&DATE($H$2,I$4,I$5)) | J10: =SUMIFS(DATA!$O:$O,DATA!$P:$P,'Debt report'!$B$10,DATA!$Q:$Q,">="&DATE($H$2,J$4,1),DATA!$Q:$Q,"<="&DATE($H$2,J$4,J$5)) | K10: =SUMIFS(DATA!$O:$O,DATA!$P:$P,'Debt report'!$B$10,DATA!$Q:$Q,">="&DATE($H$2,K$4,1),DATA!$Q:$Q,"<="&DATE($H$2,K$4,K$5)) | ... O10: =SUMIFS(DATA!$O:$O,DATA!$P:$P,'Debt report'!$B$10,DATA!$Q:$Q,">="&DATE($H$2,O$4,1),DATA!$Q:$Q,"<="&DATE($H$2,O$4,O$5)) | P10: =SUM(D10:O10) | Q10: =C10+P10
A11: B | B11: Pending payment | C11: =SUMIFS(DATA!$I:$I,DATA!$P:$P,'Debt report'!$B$11,DATA!$U:$U,">="&DATE($H$2,C$4,1),DATA!$U:$U,"<="&DATE($H$2,C$4,C$5)) | D11: =SUMIFS(DATA!$I:$I,DATA!$P:$P,'Debt report'!$B$11,DATA!$U:$U,">="&DATE($H$2,D$4,1),DATA!$U:$U,"<="&DATE($H$2,D$4,D$5)) | E11: =SUMIFS(DATA!$I:$I,DATA!$P:$P,'Debt report'!$B$11,DATA!$U:$U,">="&DATE($H$2,E$4,1),DATA!$U:$U,"<="&DATE($H$2,E$4,E$5)) | F11: =SUMIFS(DATA!$I:$I,DATA!$P:$P,'Debt report'!$B$11,DATA!$U:$U,">="&DATE($H$2,F$4,1),DATA!$U:$U,"<="&DATE($H$2,F$4,F$5)) | G11: =SUMIFS(DATA!$I:$I,DATA!$P:$P,'Debt report'!$B$11,DATA!$U:$U,">="&DATE($H$2,G$4,1),DATA!$U:$U,"<="&DATE($H$2,G$4,G$5)) | H11: =SUMIFS(DATA!$I:$I,DATA!$P:$P,'Debt report'!$B$11,DATA!$U:$U,">="&DATE($H$2,H$4,1),DATA!$U:$U,"<="&DATE($H$2,H$4,H$5)) | I11: =SUMIFS(DATA!$I:$I,DATA!$P:$P,'Debt report'!$B$11,DATA!$U:$U,">="&DATE($H$2,I$4,1),DATA!$U:$U,"<="&DATE($H$2,I$4,I$5)) | J11: =SUMIFS(DATA!$I:$I,DATA!$P:$P,'Debt report'!$B$11,DATA!$U:$U,">="&DATE($H$2,J$4,1),DATA!$U:$U,"<="&DATE($H$2,J$4,J$5)) | ... N11: =SUMIFS(DATA!$I:$I,DATA!$P:$P,'Debt report'!$B$11,DATA!$U:$U,">="&DATE($H$2,N$4,1),DATA!$U:$U,"<="&DATE($H$2,N$4,N$5)) | O11: =SUMIFS(DATA!$O:$O,DATA!$P:$P,'Debt report'!$B$11,DATA!$Q:$Q,">="&DATE($H$2,O$4,1),DATA!$Q:$Q,"<="&DATE($H$2,O$4,O$5)) | P11: =SUM(D11:O11) | Q11: =C11+P11

Sheet Note
A1: CÁC KHÁCH HÀNG YÊU CẦU NGÀY HÓA ĐƠN GTGT TRÙNG VỚI NGÀY KÝ NGHIỆM THU | F1: Lưu ý: Hợp đồng bảo hiểm của gói Cải tạo bể bơi ĐSQ ÚC hết hạn vào ngày 30/09/2022 => Ms Bích EOA JLL nhắc gửi bản Chứng nhận bảo hiểm mới vào ngày hết hạn của bản cũ
A3: STT | B3: TÊN KH | C3: GHI CHÚ
A4: 1 | B4: TOYOTA BOSHOKU HÀ NỘI | C4: Hóa đơn GTGT, Báo cáo nghiệm thu trùng ngày nhau
A5: 2 | B5: YAMAHA MOTOR VN | C5: Hóa đơn GTGT, Báo cáo nghiệm thu, Đề nghị thanh toán, Báo cáo DV,... trùng ngày nhau | F5: Lưu ý: Cách tra cứu thông tin hóa đơn => in gửi cùng HSTT cho Big C Mê Linh http://tracuuhoadon.gdt.gov.vn/ => Thông tin hóa đơn, biên lai => Hóa đơn => Tra cứu 1 hóa đơn => Kết quả tra cứu => gõ các thông tin (Mã số thuế cty SPS, mẫu số hóa đơn, ký hiệu hóa đơn,..)
A6: 3 | B6: MASCOT VIỆT NAM | C6: Hóa đơn GTGT, Báo cáo nghiệm thu trùng ngày nhau
A7: 4 | B7: LAURELTON DIAMONDS VIỆT NAM | C7: Hóa đơn GTGT, Báo cáo nghiệm thu trùng ngày nhau
A8: 5 | B8: MHI AEROSPACE VIỆT NAM | C8: Hóa đơn GTGT, Báo cáo nghiệm thu trùng ngày nhau
A9: 6 | B9: BBP VIỆT NAM | C9: Hóa đơn GTGT, Báo cáo nghiệm thu trùng ngày nhau
A10: 7 | B10: JEMMTEC | C10: Hóa đơn GTGT, Báo cáo nghiệm thu trùng ngày nhau
A11: 8 | B11: GDS | C11: Hóa đơn GTGT, Báo cáo nghiệm thu trùng ngày nhau
A12: THEO DÕI TÌNH TRẠNG TÀI LIỆU ĐÃ GỬI KHÁCH HÀNG
A13: STT | B13: TÊN KH | C13: MÃ SỐ DỰ ÁN | D13: HẠNG MỤC | E13: TÀI LIỆU | F13: PHÂN LOẠI | G13: NGÀY GỬI KH | H13: GHI CHÚ
A14: 1 | B14: VNPT IDC - NAM THANG LONG | C14: IDC-200611 | D14: SỬA CHỮA HỆ THỐNG UPS | E14: Hợp đồng | F14: N/A | G14: N/A | H14: Chưa soạn hợp đồng
A15: 2 | B15: DOLPHIN PLAZA | C15: DPP-200901 | D15: THAY THẾ BỘ ĐIỀU KHIỂN CHO MÁY PHÁT ĐIỆN SỐ 2 | E15: Hợp đồng | F15: Bản cứng | G15: 44078 | H15: Gửi CPN hợp đồng bản cứng SPS ký đóng dấu trước cho Mr Giang GĐ BQL Tòa nhà
A16: 3 | B16: EMBASSY OF AUSTRALIA/ JLL | C16: EOA-210128 | D16: CẢI TẠO QUẦY BAR | E16: Hợp đồng | F16: N/A | G16: N/A | H16: HĐ theo mẫu KH => KH chưa gửi file mềm hợp đồng để check
A17: 4 | B17: MHI AEROSPACE VIETNAM | C17: N/A | D17: HỢP ĐỒNG NGUYÊN TẮC 2021 | E17: Hợp đồng | F17: Bản cứng | G17: 44473 | H17: => Ngày 4/10/2021 đã gửi bản cứng hợp đồng SPS ký đóng dấu trước cho Ms.Ngọc MHI
A18: 5 | B18: BBP VIỆT NAM | C18: BBP_210929_R3 | D18: LẮP ĐẶT SENSOR VÀ THIẾT BỊ PHỤC VỤ ĐO KIỂM | E18: Hợp đồng | F18: Bản mềm | G18: 44489 | H18: Ngày 20/10/2021 Nghĩa đã gửi file mềm hợp đồngnguyên tắc - Rev lần cuối qua mail cho Ms Ngọc BBP check
A19: 6 | B19: PHC Complex | C19: N/A | D19: BẢO TRÌ BƠM NƯỚC SẠCH | E19: Hợp đồng | F19: Bản cứng | G19: 44886 | H19: => Ngày 21/11/2022 đã gửi 3 bản cứng hợp đồng SPS ký đóng dấu trước cho Mr.Âu Xuân Dũng
A20: 7 | B20: Golden Palace | C20: N/A | D20: CUNG CẤP & THAY THẾ CÔNG TƠ ĐIỆN | E20: Hợp đồng | F20: Bản cứng | G20: 44886 | H20: => Ngày 21/11/2022 đã gửi Phúc cầm 3 bản cứng hợp đồng + Đề nghị tạm ứng 50% giá trị HĐ (SPS ký đóng dấu trước) cho Hoàng Anh
A21: 8 | B21: CT36A Định Công | C21: N/A | D21: BẢO TRÌ MÁY PHÁT ĐIỆN | E21: Hợp đồng | F21: Bản cứng | G21: 44890 | H21: => Ngày 25/11/2022 đã gửi CPN 3 bản cứng hợp đồng + Đề nghị tạm ứng 50% giá trị HĐ (SPS ký đóng dấu trước) cho Mr Tiến Trưởng BQL
A22: 9 | B22: YEVN | C22: N/A | D22: LẮP ĐẶT BỔ SUNG THIẾT BỊ PCCC | E22: Hợp đồng | F22: Bản cứng | G22: 44902 | H22: => Ngày 7/12/2022 đã gửi CPN 3 bản cứng hợp đồng ((SPS ký đóng dấu trước) cho Ms Hải Dương - P. Mua hàng
