Workbook

Sheet DATA
E1: PROJECT COMPLETED REPORT FOLLOW UP
B2: 1. Pending report (báo cáo chưa hoàn thiện) (P): Công việc chưa thực hiện được (do KH chưa sắp lịch, bộ phận chưa/quên sắp lịch)...hoặc thực hiện chưa xong/ Works haven't been done
A3: NOTE: | B3: 2. Missing report (báo cáo thiếu) (M): Công việc đã thực hiện (chưa nộp báo cáo về VP/ KH chưa ký/ mất báo cáo…)/ Works done but Report havent been submitted to Office
B4: 3. Cancel report: CV không thực hiện do KH hủy ko yêu cầu/ Works cancel because client not require
B5: 4. Các dự án đã thực hiện xong, không có báo cáo do KH không gửi trả lại: đóng dự án và ghi nhận mức "Không hài lòng" khi đủ 3 yếu tố: - KH đã thanh toán xong - Dự án hết thời hạn bảo hành/ hết hiệu lực hợp đồng - BOD đã xem xét
A6: Tên khách hàng | B6: Địa điểm thực hiện dịch vụ | C6: Mã số dự án | D6: Mã số dự án | E6: Tên dự án | F6: Phân loại | G6: Tính or miễn phí | H6: Kế hoạch Planed | J6: Thực tế Actual | L6: Tình trạng chung | M6: Ý kiến của KH (nếu có) | N6: P.trách dự án | O6: Hành động khắc phục | P6: Mức hài lòng | Q6: Ghi chú | R6: PIC - Leader | S6: Tháng đóng dự án | T6: Mức hài lòng không được đo đếm đối với các mã gộp
A7: Customer name | B7: Service Location | C7: Project number | D7: Project number | E7: Project name | F7: Classify | G7: Charge / Free services | H7: Ngày bắt đầu Start date | I7: Ngày kết thúc Finish date | J7: Ngày hoàn thành / ngày kí báo cáo Date signed report | K7: Ngày nhận báo cáo / Received report date | L7: General Status | M7: Customer's comment (if any | N7: P.I.C | O7: Follow up action | P7: Satisfaction feedback | Q7: Remarks

Sheet General
G1: CHỈ SỐ HÀI LÒNG CỦA KHÁCH HÀNG | N1: Prepared by: | O1: Hang.ntt
G2: Customer Satisfaction Report | N2: Checked by: | O2: Phuc.vx
A3: SPS SERVICES.,JSC | F3: YEAR: | G3: 2023 | N3: Updated to: | O3: =TODAY() -> 46004
B4: Công thức trung gian lọc ra ngày cuối tháng | D4: 31 | E4: =DAY(EOMONTH(DATE(G3,E5,1),0)) -> 28 | F4: 31 | G4: 30 | H4: 31 | I4: 30 | J4: 31 | K4: 31 | L4: 30 | M4: 31 | N4: 30 | O4: 31
B5: THÁNG / MONTH | C5: Phân loại | D5: 1 | E5: 2 | F5: 3 | G5: 4 | H5: 5 | I5: 6 | J5: 7 | K5: 8 | L5: 9 | M5: 10 | N5: 11 | O5: 12 | P5: TOTAL | Q5: %
A6: REPORT | B6: SỐ BÁO CÁO THEO KẾ HOẠCH NUMBER OF REPORTS AS SCHEDULED | D6: =COUNTIFS(DATA!$I:$I,">="&DATE($G$3,D$5,1),DATA!$I:$I,"<="&DATE($G$3,D$5,D$4)) -> 0 | E6: =COUNTIFS(DATA!$I:$I,">="&DATE($G$3,E$5,1),DATA!$I:$I,"<="&DATE($G$3,E$5,E$4)) -> 0 | F6: =COUNTIFS(DATA!$I:$I,">="&DATE($G$3,F$5,1),DATA!$I:$I,"<="&DATE($G$3,F$5,F$4)) -> 0 | G6: =COUNTIFS(DATA!$I:$I,">="&DATE($G$3,G$5,1),DATA!$I:$I,"<="&DATE($G$3,G$5,G$4)) -> 0 | H6: =COUNTIFS(DATA!$I:$I,">="&DATE($G$3,H$5,1),DATA!$I:$I,"<="&DATE($G$3,H$5,H$4)) -> 0 | I6: =COUNTIFS(DATA!$I:$I,">="&DATE($G$3,I$5,1),DATA!$I:$I,"<="&DATE($G$3,I$5,I$4)) -> 0 | J6: =COUNTIFS(DATA!$I:$I,">="&DATE($G$3,J$5,1),DATA!$I:$I,"<="&DATE($G$3,J$5,J$4)) -> 0 | K6: =COUNTIFS(DATA!$I:$I,">="&DATE($G$3,K$5,1),DATA!$I:$I,"<="&DATE($G$3,K$5,K$4)) -> 0 | ... O6: =COUNTIFS(DATA!$I:$I,">="&DATE($G$3,O$5,1),DATA!$I:$I,"<="&DATE($G$3,O$5,O$4)) -> 0 | P6: =SUM(D6:O6) -> 0 | Q6: 1
B7: SỐ BÁO CÁO ĐÃ NHẬN VỀ RECEIVED REPORTS | D7: =COUNTIFS(DATA!$K:$K,">0",DATA!$I:$I,">="&DATE($G$3,D$5,1),DATA!$I:$I,"<="&DATE($G$3,D$5,D$4)) -> 0 | E7: =COUNTIFS(DATA!$K:$K,">0",DATA!$I:$I,">="&DATE($G$3,E$5,1),DATA!$I:$I,"<="&DATE($G$3,E$5,E$4)) -> 0 | F7: =COUNTIFS(DATA!$K:$K,">0",DATA!$I:$I,">="&DATE($G$3,F$5,1),DATA!$I:$I,"<="&DATE($G$3,F$5,F$4)) -> 0 | G7: =COUNTIFS(DATA!$K:$K,">0",DATA!$I:$I,">="&DATE($G$3,G$5,1),DATA!$I:$I,"<="&DATE($G$3,G$5,G$4)) -> 0 | H7: =COUNTIFS(DATA!$K:$K,">0",DATA!$I:$I,">="&DATE($G$3,H$5,1),DATA!$I:$I,"<="&DATE($G$3,H$5,H$4)) -> 0 | I7: =COUNTIFS(DATA!$K:$K,">0",DATA!$I:$I,">="&DATE($G$3,I$5,1),DATA!$I:$I,"<="&DATE($G$3,I$5,I$4)) -> 0 | J7: =COUNTIFS(DATA!$K:$K,">0",DATA!$I:$I,">="&DATE($G$3,J$5,1),DATA!$I:$I,"<="&DATE($G$3,J$5,J$4)) -> 0 | K7: =COUNTIFS(DATA!$K:$K,">0",DATA!$I:$I,">="&DATE($G$3,K$5,1),DATA!$I:$I,"<="&DATE($G$3,K$5,K$4)) -> 0 | ... O7: =COUNTIFS(DATA!$K:$K,">0",DATA!$I:$I,">="&DATE($G$3,O$5,1),DATA!$I:$I,"<="&DATE($G$3,O$5,O$4)) -> 0 | P7: =SUM(D7:O7) -> 0 | Q7: =P7/P6 -> #DIV/0!
B8: SỐ HẠNG MỤC CHƯA HOÀN THÀNH PENDING ITEMS | D8: =IF(TODAY()>DATE($G$3,D5,D4),D6-D7,0) -> 0 | E8: =IF(TODAY()>DATE($G$3,E5,E4),E6-E7,0) -> 0 | F8: =IF(TODAY()>DATE($G$3,F5,F4),F6-F7,0) -> 0 | G8: =IF(TODAY()>DATE($G$3,G5,G4),G6-G7,0) -> 0 | H8: =IF(TODAY()>DATE($G$3,H5,H4),H6-H7,0) -> 0 | I8: =IF(TODAY()>DATE($G$3,I5,I4),I6-I7,0) -> 0 | J8: =IF(TODAY()>DATE($G$3,J5,J4),J6-J7,0) -> 0 | K8: =IF(TODAY()>DATE($G$3,K5,K4),K6-K7,0) -> 0 | ... O8: =IF(TODAY()>DATE($G$3,O5,O4),O6-O7,0) -> 0 | P8: =SUM(D8:O8) -> 0 | Q8: =P8/P7 -> #DIV/0!
A9: CLIENT FEED BACK | B9: SỐ BÁO CÁO CÓ PHẢN HỒI KHÁCH HÀNG NUMBER OF REPORTS WITH CUSTOMER'S FEED BACK | D9: =SUM(D10:D13) -> 0 | E9: =SUM(E10:E13) -> 0 | F9: =SUM(F10:F13) -> 0 | G9: =SUM(G10:G13) -> 0 | H9: =SUM(H10:H13) -> 0 | I9: =SUM(I10:I13) -> 0 | J9: =SUM(J10:J13) -> 0 | K9: =SUM(K10:K13) -> 0 | ... O9: =SUM(O10:O13) -> 0 | P9: =SUM(D9:O9) -> 0 | Q9: =P9/P7 -> #DIV/0!
B10: RẤT HÀI LÒNG EXCEEDED SATISFY | C10: E | D10: =COUNTIFS(DATA!$P:$P,"=E",DATA!$K:$K,">="&DATE($G$3,D$5,1),DATA!$K:$K,"<="&DATE($G$3,D$5,D$4)) -> 0 | E10: =COUNTIFS(DATA!$P:$P,"=E",DATA!$K:$K,">="&DATE($G$3,E$5,1),DATA!$K:$K,"<="&DATE($G$3,E$5,E$4)) -> 0 | F10: =COUNTIFS(DATA!$P:$P,"=E",DATA!$K:$K,">="&DATE($G$3,F$5,1),DATA!$K:$K,"<="&DATE($G$3,F$5,F$4)) -> 0 | G10: =COUNTIFS(DATA!$P:$P,"=E",DATA!$K:$K,">="&DATE($G$3,G$5,1),DATA!$K:$K,"<="&DATE($G$3,G$5,G$4)) -> 0 | H10: =COUNTIFS(DATA!$P:$P,"=E",DATA!$K:$K,">="&DATE($G$3,H$5,1),DATA!$K:$K,"<="&DATE($G$3,H$5,H$4)) -> 0 | I10: =COUNTIFS(DATA!$P:$P,"=E",DATA!$K:$K,">="&DATE($G$3,I$5,1),DATA!$K:$K,"<="&DATE($G$3,I$5,I$4)) -> 0 | J10: =COUNTIFS(DATA!$P:$P,"=E",DATA!$K:$K,">="&DATE($G$3,J$5,1),DATA!$K:$K,"<="&DATE($G$3,J$5,J$4)) -> 0 | K10: =COUNTIFS(DATA!$P:$P,"=E",DATA!$K:$K,">="&DATE($G$3,K$5,1),DATA!$K:$K,"<="&DATE($G$3,K$5,K$4)) -> 0 | ... O10: =COUNTIFS(DATA!$P:$P,"=E",DATA!$K:$K,">="&DATE($G$3,O$5,1),DATA!$K:$K,"<="&DATE($G$3,O$5,O$4)) -> 0 | P10: =SUM(D10:O10) -> 0 | Q10: =P10/$P$9 -> #DIV/0!
B11: HÀI LÒNG SATISFIED | C11: S | D11: =COUNTIFS(DATA!$P:$P,"=S",DATA!$K:$K,">="&DATE($G$3,D$5,1),DATA!$K:$K,"<="&DATE($G$3,D$5,D$4)) -> 0 | E11: =COUNTIFS(DATA!$P:$P,"=S",DATA!$K:$K,">="&DATE($G$3,E$5,1),DATA!$K:$K,"<="&DATE($G$3,E$5,E$4)) -> 0 | F11: =COUNTIFS(DATA!$P:$P,"=S",DATA!$K:$K,">="&DATE($G$3,F$5,1),DATA!$K:$K,"<="&DATE($G$3,F$5,F$4)) -> 0 | G11: =COUNTIFS(DATA!$P:$P,"=S",DATA!$K:$K,">="&DATE($G$3,G$5,1),DATA!$K:$K,"<="&DATE($G$3,G$5,G$4)) -> 0 | H11: =COUNTIFS(DATA!$P:$P,"=S",DATA!$K:$K,">="&DATE($G$3,H$5,1),DATA!$K:$K,"<="&DATE($G$3,H$5,H$4)) -> 0 | I11: =COUNTIFS(DATA!$P:$P,"=S",DATA!$K:$K,">="&DATE($G$3,I$5,1),DATA!$K:$K,"<="&DATE($G$3,I$5,I$4)) -> 0 | J11: =COUNTIFS(DATA!$P:$P,"=S",DATA!$K:$K,">="&DATE($G$3,J$5,1),DATA!$K:$K,"<="&DATE($G$3,J$5,J$4)) -> 0 | K11: =COUNTIFS(DATA!$P:$P,"=S",DATA!$K:$K,">="&DATE($G$3,K$5,1),DATA!$K:$K,"<="&DATE($G$3,K$5,K$4)) -> 0 | ... O11: =COUNTIFS(DATA!$P:$P,"=S",DATA!$K:$K,">="&DATE($G$3,O$5,1),DATA!$K:$K,"<="&DATE($G$3,O$5,O$4)) -> 0 | P11: =SUM(D11:O11) -> 0 | Q11: =P11/$P$9 -> #DIV/0!
B12: CHẤP NHẬN ACCEPTABLE | C12: A | D12: =COUNTIFS(DATA!$P:$P,"=A",DATA!$K:$K,">="&DATE($G$3,D$5,1),DATA!$K:$K,"<="&DATE($G$3,D$5,D$4)) -> 0 | E12: =COUNTIFS(DATA!$P:$P,"=A",DATA!$K:$K,">="&DATE($G$3,E$5,1),DATA!$K:$K,"<="&DATE($G$3,E$5,E$4)) -> 0 | F12: =COUNTIFS(DATA!$P:$P,"=A",DATA!$K:$K,">="&DATE($G$3,F$5,1),DATA!$K:$K,"<="&DATE($G$3,F$5,F$4)) -> 0 | G12: =COUNTIFS(DATA!$P:$P,"=A",DATA!$K:$K,">="&DATE($G$3,G$5,1),DATA!$K:$K,"<="&DATE($G$3,G$5,G$4)) -> 0 | H12: =COUNTIFS(DATA!$P:$P,"=A",DATA!$K:$K,">="&DATE($G$3,H$5,1),DATA!$K:$K,"<="&DATE($G$3,H$5,H$4)) -> 0 | I12: =COUNTIFS(DATA!$P:$P,"=A",DATA!$K:$K,">="&DATE($G$3,I$5,1),DATA!$K:$K,"<="&DATE($G$3,I$5,I$4)) -> 0 | J12: =COUNTIFS(DATA!$P:$P,"=A",DATA!$K:$K,">="&DATE($G$3,J$5,1),DATA!$K:$K,"<="&DATE($G$3,J$5,J$4)) -> 0 | K12: =COUNTIFS(DATA!$P:$P,"=A",DATA!$K:$K,">="&DATE($G$3,K$5,1),DATA!$K:$K,"<="&DATE($G$3,K$5,K$4)) -> 0 | ... O12: =COUNTIFS(DATA!$P:$P,"=A",DATA!$K:$K,">="&DATE($G$3,O$5,1),DATA!$K:$K,"<="&DATE($G$3,O$5,O$4)) -> 0 | P12: =SUM(D12:O12) -> 0 | Q12: =P12/$P$9 -> #DIV/0!
B13: KHÔNG HÀI LÒNG DISSATISFIED | C13: D | D13: =COUNTIFS(DATA!$P:$P,"=D",DATA!$K:$K,">="&DATE($G$3,D$5,1),DATA!$K:$K,"<="&DATE($G$3,D$5,D$4)) -> 0 | E13: =COUNTIFS(DATA!$P:$P,"=D",DATA!$K:$K,">="&DATE($G$3,E$5,1),DATA!$K:$K,"<="&DATE($G$3,E$5,E$4)) -> 0 | F13: =COUNTIFS(DATA!$P:$P,"=D",DATA!$K:$K,">="&DATE($G$3,F$5,1),DATA!$K:$K,"<="&DATE($G$3,F$5,F$4)) -> 0 | G13: =COUNTIFS(DATA!$P:$P,"=D",DATA!$K:$K,">="&DATE($G$3,G$5,1),DATA!$K:$K,"<="&DATE($G$3,G$5,G$4)) -> 0 | H13: =COUNTIFS(DATA!$P:$P,"=D",DATA!$K:$K,">="&DATE($G$3,H$5,1),DATA!$K:$K,"<="&DATE($G$3,H$5,H$4)) -> 0 | I13: =COUNTIFS(DATA!$P:$P,"=D",DATA!$K:$K,">="&DATE($G$3,I$5,1),DATA!$K:$K,"<="&DATE($G$3,I$5,I$4)) -> 0 | J13: =COUNTIFS(DATA!$P:$P,"=D",DATA!$K:$K,">="&DATE($G$3,J$5,1),DATA!$K:$K,"<="&DATE($G$3,J$5,J$4)) -> 0 | K13: =COUNTIFS(DATA!$P:$P,"=D",DATA!$K:$K,">="&DATE($G$3,K$5,1),DATA!$K:$K,"<="&DATE($G$3,K$5,K$4)) -> 0 | ... O13: =COUNTIFS(DATA!$P:$P,"=D",DATA!$K:$K,">="&DATE($G$3,O$5,1),DATA!$K:$K,"<="&DATE($G$3,O$5,O$4)) -> 0 | P13: =SUM(D13:O13) -> 0 | Q13: =P13/$P$9 -> #DIV/0!
A14: PERCENTAGE | B14: MỤC TIÊU MỨC ĐỘ HÀI LÒNG TARGET OF SATISFIED LEVEL | D14: 0.95 | E14: =$D$14 -> 0.95 | F14: =$D$14 -> 0.95 | G14: =$D$14 -> 0.95 | H14: =$D$14 -> 0.95 | I14: =$D$14 -> 0.95 | J14: =$D$14 -> 0.95 | K14: =$D$14 -> 0.95 | L14: =$D$14 -> 0.95 | ... P14: =$D$14 -> 0.95
B15: % MỨC ĐỘ HÀI LÒNG PERCENTAGE OF SATISFIED LEVEL | D15: =IF(D9>0,(D11+D10)/D9,"") | E15: =IF(E9>0,(E11+E10)/E9,"") | F15: =IF(F9>0,(F11+F10)/F9,"") | G15: =IF(G9>0,(G11+G10)/G9,"") | H15: =IF(H9>0,(H11+H10)/H9,"") | I15: =IF(I9>0,(I11+I10)/I9,"") | J15: =IF(J9>0,(J11+J10)/J9,"") | K15: =IF(K9>0,(K11+K10)/K9,"") | ... P15: =IF(P9>0,(P11+P10)/P9,"")
P16: =P15

Sheet Yearly Staff Satisfaction
F1: CHỈ SỐ HÀI LÒNG CỦA KHÁCH HÀNG ĐỐI VỚI NHÂN VIÊN | M1: Prepared by: | N1: Hang.ntt
F2: ASSESSMENT OF CUSTOMER SATISFACTION FOR EACH EMPLOYEES | M2: Checked by: | N2: Phuc.vx
A3: SPS SERVICES.,JSC | E3: YEAR: | F3: 2025 | M3: Updated to: | N3: =TODAY() -> 46004
B5: Công thức trung gian lọc ra ngày cuối tháng | C5: 31 | D5: =DAY(EOMONTH(DATE(F3,D6,1),0)) -> 28 | E5: 31 | F5: 30 | G5: 31 | H5: 30 | I5: 31 | J5: 31 | K5: 30 | L5: 31 | M5: 30 | N5: 31
A6: STT No. | B6: Tên nhân viên Full name | C6: 1 | D6: 2 | E6: 3 | F6: 4 | G6: 5 | H6: 6 | I6: 7 | J6: 8 | K6: 9 | L6: 10 | M6: 11 | N6: 12 | O6: TOTAL | Q6: Ký kiệu trung gian cho công thức tự động
A7: STT No. | B7: Tên nhân viên Full name | C7: JAN | D7: FEB | E7: MAR | F7: APR | G7: MAY | H7: JUN | I7: JUL | J7: AUG | K7: SEP | L7: OCT | M7: NOV | N7: DEC | O7: TOTAL | Q7: Ký kiệu trung gian cho công thức tự động
A8: 13 | B8: =VLOOKUP(Q8, StaffList!B:C,2,FALSE) -> Nguyễn Văn Đức | C8: =(COUNTIFS(DATA!$P:$P,"=E",DATA!$K:$K,">="&DATE($F$3,C$6,1),DATA!$K:$K,"<="&DATE($F$3,C$6,C$5),DATA!$N:$N,$Q8)*10)+COUNTIFS(DATA!$P:$P,"=S",DATA!$K:$K,">="&DATE($F$3,C$6,1),DATA!$K:$K,"<="&DATE($F$3,C$6,C$5),DATA!$N:$N,$Q8) -> 0 | D8: =(COUNTIFS(DATA!$P:$P,"=E",DATA!$K:$K,">="&DATE($F$3,D$6,1),DATA!$K:$K,"<="&DATE($F$3,D$6,D$5),DATA!$N:$N,$Q8)*10)+COUNTIFS(DATA!$P:$P,"=S",DATA!$K:$K,">="&DATE($F$3,D$6,1),DATA!$K:$K,"<="&DATE($F$3,D$6,D$5),DATA!$N:$N,$Q8) -> 0 | E8: =(COUNTIFS(DATA!$P:$P,"=E",DATA!$K:$K,">="&DATE($F$3,E$6,1),DATA!$K:$K,"<="&DATE($F$3,E$6,E$5),DATA!$N:$N,$Q8)*10)+COUNTIFS(DATA!$P:$P,"=S",DATA!$K:$K,">="&DATE($F$3,E$6,1),DATA!$K:$K,"<="&DATE($F$3,E$6,E$5),DATA!$N:$N,$Q8) -> 0 | F8: =(COUNTIFS(DATA!$P:$P,"=E",DATA!$K:$K,">="&DATE($F$3,F$6,1),DATA!$K:$K,"<="&DATE($F$3,F$6,F$5),DATA!$N:$N,$Q8)*10)+COUNTIFS(DATA!$P:$P,"=S",DATA!$K:$K,">="&DATE($F$3,F$6,1),DATA!$K:$K,"<="&DATE($F$3,F$6,F$5),DATA!$N:$N,$Q8) -> 0 | G8: =(COUNTIFS(DATA!$P:$P,"=E",DATA!$K:$K,">="&DATE($F$3,G$6,1),DATA!$K:$K,"<="&DATE($F$3,G$6,G$5),DATA!$N:$N,$Q8)*10)+COUNTIFS(DATA!$P:$P,"=S",DATA!$K:$K,">="&DATE($F$3,G$6,1),DATA!$K:$K,"<="&DATE($F$3,G$6,G$5),DATA!$N:$N,$Q8) -> 0 | H8: =(COUNTIFS(DATA!$P:$P,"=E",DATA!$K:$K,">="&DATE($F$3,H$6,1),DATA!$K:$K,"<="&DATE($F$3,H$6,H$5),DATA!$N:$N,$Q8)*10)+COUNTIFS(DATA!$P:$P,"=S",DATA!$K:$K,">="&DATE($F$3,H$6,1),DATA!$K:$K,"<="&DATE($F$3,H$6,H$5),DATA!$N:$N,$Q8) -> 0 | I8: =(COUNTIFS(DATA!$P:$P,"=E",DATA!$K:$K,">="&DATE($F$3,I$6,1),DATA!$K:$K,"<="&DATE($F$3,I$6,I$5),DATA!$N:$N,$Q8)*10)+COUNTIFS(DATA!$P:$P,"=S",DATA!$K:$K,">="&DATE($F$3,I$6,1),DATA!$K:$K,"<="&DATE($F$3,I$6,I$5),DATA!$N:$N,$Q8) -> 0 | J8: =(COUNTIFS(DATA!$P:$P,"=E",DATA!$K:$K,">="&DATE($F$3,J$6,1),DATA!$K:$K,"<="&DATE($F$3,J$6,J$5),DATA!$N:$N,$Q8)*10)+COUNTIFS(DATA!$P:$P,"=S",DATA!$K:$K,">="&DATE($F$3,J$6,1),DATA!$K:$K,"<="&DATE($F$3,J$6,J$5),DATA!$N:$N,$Q8) -> 0 | ... N8: =(COUNTIFS(DATA!$P:$P,"=E",DATA!$K:$K,">="&DATE($F$3,N$6,1),DATA!$K:$K,"<="&DATE($F$3,N$6,N$5),DATA!$N:$N,$Q8)*10)+COUNTIFS(DATA!$P:$P,"=S",DATA!$K:$K,">="&DATE($F$3,N$6,1),DATA!$K:$K,"<="&DATE($F$3,N$6,N$5),DATA!$N:$N,$Q8) -> 0 | O8: =SUM(C8:N8) -> 0 | Q8: ="*"&StaffList!B17&"*" -> *Duc.nv*
A9: 11 | B9: =VLOOKUP(Q9, StaffList!B:C,2,FALSE) -> Đỗ Văn Cường | C9: =(COUNTIFS(DATA!$P:$P,"=E",DATA!$K:$K,">="&DATE($F$3,C$6,1),DATA!$K:$K,"<="&DATE($F$3,C$6,C$5),DATA!$N:$N,$Q9)*10)+COUNTIFS(DATA!$P:$P,"=S",DATA!$K:$K,">="&DATE($F$3,C$6,1),DATA!$K:$K,"<="&DATE($F$3,C$6,C$5),DATA!$N:$N,$Q9) -> 0 | D9: =(COUNTIFS(DATA!$P:$P,"=E",DATA!$K:$K,">="&DATE($F$3,D$6,1),DATA!$K:$K,"<="&DATE($F$3,D$6,D$5),DATA!$N:$N,$Q9)*10)+COUNTIFS(DATA!$P:$P,"=S",DATA!$K:$K,">="&DATE($F$3,D$6,1),DATA!$K:$K,"<="&DATE($F$3,D$6,D$5),DATA!$N:$N,$Q9) -> 0 | E9: =(COUNTIFS(DATA!$P:$P,"=E",DATA!$K:$K,">="&DATE($F$3,E$6,1),DATA!$K:$K,"<="&DATE($F$3,E$6,E$5),DATA!$N:$N,$Q9)*10)+COUNTIFS(DATA!$P:$P,"=S",DATA!$K:$K,">="&DATE($F$3,E$6,1),DATA!$K:$K,"<="&DATE($F$3,E$6,E$5),DATA!$N:$N,$Q9) -> 0 | F9: =(COUNTIFS(DATA!$P:$P,"=E",DATA!$K:$K,">="&DATE($F$3,F$6,1),DATA!$K:$K,"<="&DATE($F$3,F$6,F$5),DATA!$N:$N,$Q9)*10)+COUNTIFS(DATA!$P:$P,"=S",DATA!$K:$K,">="&DATE($F$3,F$6,1),DATA!$K:$K,"<="&DATE($F$3,F$6,F$5),DATA!$N:$N,$Q9) -> 0 | G9: =(COUNTIFS(DATA!$P:$P,"=E",DATA!$K:$K,">="&DATE($F$3,G$6,1),DATA!$K:$K,"<="&DATE($F$3,G$6,G$5),DATA!$N:$N,$Q9)*10)+COUNTIFS(DATA!$P:$P,"=S",DATA!$K:$K,">="&DATE($F$3,G$6,1),DATA!$K:$K,"<="&DATE($F$3,G$6,G$5),DATA!$N:$N,$Q9) -> 0 | H9: =(COUNTIFS(DATA!$P:$P,"=E",DATA!$K:$K,">="&DATE($F$3,H$6,1),DATA!$K:$K,"<="&DATE($F$3,H$6,H$5),DATA!$N:$N,$Q9)*10)+COUNTIFS(DATA!$P:$P,"=S",DATA!$K:$K,">="&DATE($F$3,H$6,1),DATA!$K:$K,"<="&DATE($F$3,H$6,H$5),DATA!$N:$N,$Q9) -> 0 | I9: =(COUNTIFS(DATA!$P:$P,"=E",DATA!$K:$K,">="&DATE($F$3,I$6,1),DATA!$K:$K,"<="&DATE($F$3,I$6,I$5),DATA!$N:$N,$Q9)*10)+COUNTIFS(DATA!$P:$P,"=S",DATA!$K:$K,">="&DATE($F$3,I$6,1),DATA!$K:$K,"<="&DATE($F$3,I$6,I$5),DATA!$N:$N,$Q9) -> 0 | J9: =(COUNTIFS(DATA!$P:$P,"=E",DATA!$K:$K,">="&DATE($F$3,J$6,1),DATA!$K:$K,"<="&DATE($F$3,J$6,J$5),DATA!$N:$N,$Q9)*10)+COUNTIFS(DATA!$P:$P,"=S",DATA!$K:$K,">="&DATE($F$3,J$6,1),DATA!$K:$K,"<="&DATE($F$3,J$6,J$5),DATA!$N:$N,$Q9) -> 0 | ... N9: =(COUNTIFS(DATA!$P:$P,"=E",DATA!$K:$K,">="&DATE($F$3,N$6,1),DATA!$K:$K,"<="&DATE($F$3,N$6,N$5),DATA!$N:$N,$Q9)*10)+COUNTIFS(DATA!$P:$P,"=S",DATA!$K:$K,">="&DATE($F$3,N$6,1),DATA!$K:$K,"<="&DATE($F$3,N$6,N$5),DATA!$N:$N,$Q9) -> 0 | O9: =SUM(C9:N9) -> 0 | Q9: ="*"&StaffList!B15&"*" -> *Cuong.dv*
A10: 27 | B10: =VLOOKUP(Q10, StaffList!B:C,2,FALSE) -> Mai Văn Tuấn | C10: =(COUNTIFS(DATA!$P:$P,"=E",DATA!$K:$K,">="&DATE($F$3,C$6,1),DATA!$K:$K,"<="&DATE($F$3,C$6,C$5),DATA!$N:$N,$Q10)*10)+COUNTIFS(DATA!$P:$P,"=S",DATA!$K:$K,">="&DATE($F$3,C$6,1),DATA!$K:$K,"<="&DATE($F$3,C$6,C$5),DATA!$N:$N,$Q10) -> 0 | D10: =(COUNTIFS(DATA!$P:$P,"=E",DATA!$K:$K,">="&DATE($F$3,D$6,1),DATA!$K:$K,"<="&DATE($F$3,D$6,D$5),DATA!$N:$N,$Q10)*10)+COUNTIFS(DATA!$P:$P,"=S",DATA!$K:$K,">="&DATE($F$3,D$6,1),DATA!$K:$K,"<="&DATE($F$3,D$6,D$5),DATA!$N:$N,$Q10) -> 0 | E10: =(COUNTIFS(DATA!$P:$P,"=E",DATA!$K:$K,">="&DATE($F$3,E$6,1),DATA!$K:$K,"<="&DATE($F$3,E$6,E$5),DATA!$N:$N,$Q10)*10)+COUNTIFS(DATA!$P:$P,"=S",DATA!$K:$K,">="&DATE($F$3,E$6,1),DATA!$K:$K,"<="&DATE($F$3,E$6,E$5),DATA!$N:$N,$Q10) -> 0 | F10: =(COUNTIFS(DATA!$P:$P,"=E",DATA!$K:$K,">="&DATE($F$3,F$6,1),DATA!$K:$K,"<="&DATE($F$3,F$6,F$5),DATA!$N:$N,$Q10)*10)+COUNTIFS(DATA!$P:$P,"=S",DATA!$K:$K,">="&DATE($F$3,F$6,1),DATA!$K:$K,"<="&DATE($F$3,F$6,F$5),DATA!$N:$N,$Q10) -> 0 | G10: =(COUNTIFS(DATA!$P:$P,"=E",DATA!$K:$K,">="&DATE($F$3,G$6,1),DATA!$K:$K,"<="&DATE($F$3,G$6,G$5),DATA!$N:$N,$Q10)*10)+COUNTIFS(DATA!$P:$P,"=S",DATA!$K:$K,">="&DATE($F$3,G$6,1),DATA!$K:$K,"<="&DATE($F$3,G$6,G$5),DATA!$N:$N,$Q10) -> 0 | H10: =(COUNTIFS(DATA!$P:$P,"=E",DATA!$K:$K,">="&DATE($F$3,H$6,1),DATA!$K:$K,"<="&DATE($F$3,H$6,H$5),DATA!$N:$N,$Q10)*10)+COUNTIFS(DATA!$P:$P,"=S",DATA!$K:$K,">="&DATE($F$3,H$6,1),DATA!$K:$K,"<="&DATE($F$3,H$6,H$5),DATA!$N:$N,$Q10) -> 0 | I10: =(COUNTIFS(DATA!$P:$P,"=E",DATA!$K:$K,">="&DATE($F$3,I$6,1),DATA!$K:$K,"<="&DATE($F$3,I$6,I$5),DATA!$N:$N,$Q10)*10)+COUNTIFS(DATA!$P:$P,"=S",DATA!$K:$K,">="&DATE($F$3,I$6,1),DATA!$K:$K,"<="&DATE($F$3,I$6,I$5),DATA!$N:$N,$Q10) -> 0 | J10: =(COUNTIFS(DATA!$P:$P,"=E",DATA!$K:$K,">="&DATE($F$3,J$6,1),DATA!$K:$K,"<="&DATE($F$3,J$6,J$5),DATA!$N:$N,$Q10)*10)+COUNTIFS(DATA!$P:$P,"=S",DATA!$K:$K,">="&DATE($F$3,J$6,1),DATA!$K:$K,"<="&DATE($F$3,J$6,J$5),DATA!$N:$N,$Q10) -> 0 | ... N10: =(COUNTIFS(DATA!$P:$P,"=E",DATA!$K:$K,">="&DATE($F$3,N$6,1),DATA!$K:$K,"<="&DATE($F$3,N$6,N$5),DATA!$N:$N,$Q10)*10)+COUNTIFS(DATA!$P:$P,"=S",DATA!$K:$K,">="&DATE($F$3,N$6,1),DATA!$K:$K,"<="&DATE($F$3,N$6,N$5),DATA!$N:$N,$Q10) -> 0 | O10: =SUM(C10:N10) -> 0 | Q10: ="*"&StaffList!B31&"*" -> *Tuan.mv*
A11: 5 | B11: =VLOOKUP(Q11, StaffList!B:C,2,FALSE) -> Hồ Sỹ Hiệp | C11: =(COUNTIFS(DATA!$P:$P,"=E",DATA!$K:$K,">="&DATE($F$3,C$6,1),DATA!$K:$K,"<="&DATE($F$3,C$6,C$5),DATA!$N:$N,$Q11)*10)+COUNTIFS(DATA!$P:$P,"=S",DATA!$K:$K,">="&DATE($F$3,C$6,1),DATA!$K:$K,"<="&DATE($F$3,C$6,C$5),DATA!$N:$N,$Q11) -> 0 | D11: =(COUNTIFS(DATA!$P:$P,"=E",DATA!$K:$K,">="&DATE($F$3,D$6,1),DATA!$K:$K,"<="&DATE($F$3,D$6,D$5),DATA!$N:$N,$Q11)*10)+COUNTIFS(DATA!$P:$P,"=S",DATA!$K:$K,">="&DATE($F$3,D$6,1),DATA!$K:$K,"<="&DATE($F$3,D$6,D$5),DATA!$N:$N,$Q11) -> 0 | E11: =(COUNTIFS(DATA!$P:$P,"=E",DATA!$K:$K,">="&DATE($F$3,E$6,1),DATA!$K:$K,"<="&DATE($F$3,E$6,E$5),DATA!$N:$N,$Q11)*10)+COUNTIFS(DATA!$P:$P,"=S",DATA!$K:$K,">="&DATE($F$3,E$6,1),DATA!$K:$K,"<="&DATE($F$3,E$6,E$5),DATA!$N:$N,$Q11) -> 0 | F11: =(COUNTIFS(DATA!$P:$P,"=E",DATA!$K:$K,">="&DATE($F$3,F$6,1),DATA!$K:$K,"<="&DATE($F$3,F$6,F$5),DATA!$N:$N,$Q11)*10)+COUNTIFS(DATA!$P:$P,"=S",DATA!$K:$K,">="&DATE($F$3,F$6,1),DATA!$K:$K,"<="&DATE($F$3,F$6,F$5),DATA!$N:$N,$Q11) -> 0 | G11: =(COUNTIFS(DATA!$P:$P,"=E",DATA!$K:$K,">="&DATE($F$3,G$6,1),DATA!$K:$K,"<="&DATE($F$3,G$6,G$5),DATA!$N:$N,$Q11)*10)+COUNTIFS(DATA!$P:$P,"=S",DATA!$K:$K,">="&DATE($F$3,G$6,1),DATA!$K:$K,"<="&DATE($F$3,G$6,G$5),DATA!$N:$N,$Q11) -> 0 | H11: =(COUNTIFS(DATA!$P:$P,"=E",DATA!$K:$K,">="&DATE($F$3,H$6,1),DATA!$K:$K,"<="&DATE($F$3,H$6,H$5),DATA!$N:$N,$Q11)*10)+COUNTIFS(DATA!$P:$P,"=S",DATA!$K:$K,">="&DATE($F$3,H$6,1),DATA!$K:$K,"<="&DATE($F$3,H$6,H$5),DATA!$N:$N,$Q11) -> 0 | I11: =(COUNTIFS(DATA!$P:$P,"=E",DATA!$K:$K,">="&DATE($F$3,I$6,1),DATA!$K:$K,"<="&DATE($F$3,I$6,I$5),DATA!$N:$N,$Q11)*10)+COUNTIFS(DATA!$P:$P,"=S",DATA!$K:$K,">="&DATE($F$3,I$6,1),DATA!$K:$K,"<="&DATE($F$3,I$6,I$5),DATA!$N:$N,$Q11) -> 0 | J11: =(COUNTIFS(DATA!$P:$P,"=E",DATA!$K:$K,">="&DATE($F$3,J$6,1),DATA!$K:$K,"<="&DATE($F$3,J$6,J$5),DATA!$N:$N,$Q11)*10)+COUNTIFS(DATA!$P:$P,"=S",DATA!$K:$K,">="&DATE($F$3,J$6,1),DATA!$K:$K,"<="&DATE($F$3,J$6,J$5),DATA!$N:$N,$Q11) -> 0 | ... N11: =(COUNTIFS(DATA!$P:$P,"=E",DATA!$K:$K,">="&DATE($F$3,N$6,1),DATA!$K:$K,"<="&DATE($F$3,N$6,N$5),DATA!$N:$N,$Q11)*10)+COUNTIFS(DATA!$P:$P,"=S",DATA!$K:$K,">="&DATE($F$3,N$6,1),DATA!$K:$K,"<="&DATE($F$3,N$6,N$5),DATA!$N:$N,$Q11) -> 0 | O11: =SUM(C11:N11) -> 0 | Q11: ="*"&StaffList!B9&"*" -> *Hiep.hs*
A12: 14 | B12: =VLOOKUP(Q12, StaffList!B:C,2,FALSE) -> Vũ Xuân Trường | C12: =(COUNTIFS(DATA!$P:$P,"=E",DATA!$K:$K,">="&DATE($F$3,C$6,1),DATA!$K:$K,"<="&DATE($F$3,C$6,C$5),DATA!$N:$N,$Q12)*10)+COUNTIFS(DATA!$P:$P,"=S",DATA!$K:$K,">="&DATE($F$3,C$6,1),DATA!$K:$K,"<="&DATE($F$3,C$6,C$5),DATA!$N:$N,$Q12) -> 0 | D12: =(COUNTIFS(DATA!$P:$P,"=E",DATA!$K:$K,">="&DATE($F$3,D$6,1),DATA!$K:$K,"<="&DATE($F$3,D$6,D$5),DATA!$N:$N,$Q12)*10)+COUNTIFS(DATA!$P:$P,"=S",DATA!$K:$K,">="&DATE($F$3,D$6,1),DATA!$K:$K,"<="&DATE($F$3,D$6,D$5),DATA!$N:$N,$Q12) -> 0 | E12: =(COUNTIFS(DATA!$P:$P,"=E",DATA!$K:$K,">="&DATE($F$3,E$6,1),DATA!$K:$K,"<="&DATE($F$3,E$6,E$5),DATA!$N:$N,$Q12)*10)+COUNTIFS(DATA!$P:$P,"=S",DATA!$K:$K,">="&DATE($F$3,E$6,1),DATA!$K:$K,"<="&DATE($F$3,E$6,E$5),DATA!$N:$N,$Q12) -> 0 | F12: =(COUNTIFS(DATA!$P:$P,"=E",DATA!$K:$K,">="&DATE($F$3,F$6,1),DATA!$K:$K,"<="&DATE($F$3,F$6,F$5),DATA!$N:$N,$Q12)*10)+COUNTIFS(DATA!$P:$P,"=S",DATA!$K:$K,">="&DATE($F$3,F$6,1),DATA!$K:$K,"<="&DATE($F$3,F$6,F$5),DATA!$N:$N,$Q12) -> 0 | G12: =(COUNTIFS(DATA!$P:$P,"=E",DATA!$K:$K,">="&DATE($F$3,G$6,1),DATA!$K:$K,"<="&DATE($F$3,G$6,G$5),DATA!$N:$N,$Q12)*10)+COUNTIFS(DATA!$P:$P,"=S",DATA!$K:$K,">="&DATE($F$3,G$6,1),DATA!$K:$K,"<="&DATE($F$3,G$6,G$5),DATA!$N:$N,$Q12) -> 0 | H12: =(COUNTIFS(DATA!$P:$P,"=E",DATA!$K:$K,">="&DATE($F$3,H$6,1),DATA!$K:$K,"<="&DATE($F$3,H$6,H$5),DATA!$N:$N,$Q12)*10)+COUNTIFS(DATA!$P:$P,"=S",DATA!$K:$K,">="&DATE($F$3,H$6,1),DATA!$K:$K,"<="&DATE($F$3,H$6,H$5),DATA!$N:$N,$Q12) -> 0 | I12: =(COUNTIFS(DATA!$P:$P,"=E",DATA!$K:$K,">="&DATE($F$3,I$6,1),DATA!$K:$K,"<="&DATE($F$3,I$6,I$5),DATA!$N:$N,$Q12)*10)+COUNTIFS(DATA!$P:$P,"=S",DATA!$K:$K,">="&DATE($F$3,I$6,1),DATA!$K:$K,"<="&DATE($F$3,I$6,I$5),DATA!$N:$N,$Q12) -> 0 | J12: =(COUNTIFS(DATA!$P:$P,"=E",DATA!$K:$K,">="&DATE($F$3,J$6,1),DATA!$K:$K,"<="&DATE($F$3,J$6,J$5),DATA!$N:$N,$Q12)*10)+COUNTIFS(DATA!$P:$P,"=S",DATA!$K:$K,">="&DATE($F$3,J$6,1),DATA!$K:$K,"<="&DATE($F$3,J$6,J$5),DATA!$N:$N,$Q12) -> 0 | ... N12: =(COUNTIFS(DATA!$P:$P,"=E",DATA!$K:$K,">="&DATE($F$3,N$6,1),DATA!$K:$K,"<="&DATE($F$3,N$6,N$5),DATA!$N:$N,$Q12)*10)+COUNTIFS(DATA!$P:$P,"=S",DATA!$K:$K,">="&DATE($F$3,N$6,1),DATA!$K:$K,"<="&DATE($F$3,N$6,N$5),DATA!$N:$N,$Q12) -> 0 | O12: =SUM(C12:N12) -> 0 | Q12: ="*"&StaffList!B18&"*" -> *Truong.vx*
A13: 16 | B13: =VLOOKUP(Q13, StaffList!B:C,2,FALSE) -> Lê Minh Đức | C13: =(COUNTIFS(DATA!$P:$P,"=E",DATA!$K:$K,">="&DATE($F$3,C$6,1),DATA!$K:$K,"<="&DATE($F$3,C$6,C$5),DATA!$N:$N,$Q13)*10)+COUNTIFS(DATA!$P:$P,"=S",DATA!$K:$K,">="&DATE($F$3,C$6,1),DATA!$K:$K,"<="&DATE($F$3,C$6,C$5),DATA!$N:$N,$Q13) -> 0 | D13: =(COUNTIFS(DATA!$P:$P,"=E",DATA!$K:$K,">="&DATE($F$3,D$6,1),DATA!$K:$K,"<="&DATE($F$3,D$6,D$5),DATA!$N:$N,$Q13)*10)+COUNTIFS(DATA!$P:$P,"=S",DATA!$K:$K,">="&DATE($F$3,D$6,1),DATA!$K:$K,"<="&DATE($F$3,D$6,D$5),DATA!$N:$N,$Q13) -> 0 | E13: =(COUNTIFS(DATA!$P:$P,"=E",DATA!$K:$K,">="&DATE($F$3,E$6,1),DATA!$K:$K,"<="&DATE($F$3,E$6,E$5),DATA!$N:$N,$Q13)*10)+COUNTIFS(DATA!$P:$P,"=S",DATA!$K:$K,">="&DATE($F$3,E$6,1),DATA!$K:$K,"<="&DATE($F$3,E$6,E$5),DATA!$N:$N,$Q13) -> 0 | F13: =(COUNTIFS(DATA!$P:$P,"=E",DATA!$K:$K,">="&DATE($F$3,F$6,1),DATA!$K:$K,"<="&DATE($F$3,F$6,F$5),DATA!$N:$N,$Q13)*10)+COUNTIFS(DATA!$P:$P,"=S",DATA!$K:$K,">="&DATE($F$3,F$6,1),DATA!$K:$K,"<="&DATE($F$3,F$6,F$5),DATA!$N:$N,$Q13) -> 0 | G13: =(COUNTIFS(DATA!$P:$P,"=E",DATA!$K:$K,">="&DATE($F$3,G$6,1),DATA!$K:$K,"<="&DATE($F$3,G$6,G$5),DATA!$N:$N,$Q13)*10)+COUNTIFS(DATA!$P:$P,"=S",DATA!$K:$K,">="&DATE($F$3,G$6,1),DATA!$K:$K,"<="&DATE($F$3,G$6,G$5),DATA!$N:$N,$Q13) -> 0 | H13: =(COUNTIFS(DATA!$P:$P,"=E",DATA!$K:$K,">="&DATE($F$3,H$6,1),DATA!$K:$K,"<="&DATE($F$3,H$6,H$5),DATA!$N:$N,$Q13)*10)+COUNTIFS(DATA!$P:$P,"=S",DATA!$K:$K,">="&DATE($F$3,H$6,1),DATA!$K:$K,"<="&DATE($F$3,H$6,H$5),DATA!$N:$N,$Q13) -> 0 | I13: =(COUNTIFS(DATA!$P:$P,"=E",DATA!$K:$K,">="&DATE($F$3,I$6,1),DATA!$K:$K,"<="&DATE($F$3,I$6,I$5),DATA!$N:$N,$Q13)*10)+COUNTIFS(DATA!$P:$P,"=S",DATA!$K:$K,">="&DATE($F$3,I$6,1),DATA!$K:$K,"<="&DATE($F$3,I$6,I$5),DATA!$N:$N,$Q13) -> 0 | J13: =(COUNTIFS(DATA!$P:$P,"=E",DATA!$K:$K,">="&DATE($F$3,J$6,1),DATA!$K:$K,"<="&DATE($F$3,J$6,J$5),DATA!$N:$N,$Q13)*10)+COUNTIFS(DATA!$P:$P,"=S",DATA!$K:$K,">="&DATE($F$3,J$6,1),DATA!$K:$K,"<="&DATE($F$3,J$6,J$5),DATA!$N:$N,$Q13) -> 0 | ... N13: =(COUNTIFS(DATA!$P:$P,"=E",DATA!$K:$K,">="&DATE($F$3,N$6,1),DATA!$K:$K,"<="&DATE($F$3,N$6,N$5),DATA!$N:$N,$Q13)*10)+COUNTIFS(DATA!$P:$P,"=S",DATA!$K:$K,">="&DATE($F$3,N$6,1),DATA!$K:$K,"<="&DATE($F$3,N$6,N$5),DATA!$N:$N,$Q13) -> 0 | O13: =SUM(C13:N13) -> 0 | Q13: ="*"&StaffList!B20&"*" -> *Duc.lm*
A14: 7 | B14: =VLOOKUP(Q14, StaffList!B:C,2,FALSE) -> Mông Văn Thương | C14: =(COUNTIFS(DATA!$P:$P,"=E",DATA!$K:$K,">="&DATE($F$3,C$6,1),DATA!$K:$K,"<="&DATE($F$3,C$6,C$5),DATA!$N:$N,$Q14)*10)+COUNTIFS(DATA!$P:$P,"=S",DATA!$K:$K,">="&DATE($F$3,C$6,1),DATA!$K:$K,"<="&DATE($F$3,C$6,C$5),DATA!$N:$N,$Q14) -> 0 | D14: =(COUNTIFS(DATA!$P:$P,"=E",DATA!$K:$K,">="&DATE($F$3,D$6,1),DATA!$K:$K,"<="&DATE($F$3,D$6,D$5),DATA!$N:$N,$Q14)*10)+COUNTIFS(DATA!$P:$P,"=S",DATA!$K:$K,">="&DATE($F$3,D$6,1),DATA!$K:$K,"<="&DATE($F$3,D$6,D$5),DATA!$N:$N,$Q14) -> 0 | E14: =(COUNTIFS(DATA!$P:$P,"=E",DATA!$K:$K,">="&DATE($F$3,E$6,1),DATA!$K:$K,"<="&DATE($F$3,E$6,E$5),DATA!$N:$N,$Q14)*10)+COUNTIFS(DATA!$P:$P,"=S",DATA!$K:$K,">="&DATE($F$3,E$6,1),DATA!$K:$K,"<="&DATE($F$3,E$6,E$5),DATA!$N:$N,$Q14) -> 0 | F14: =(COUNTIFS(DATA!$P:$P,"=E",DATA!$K:$K,">="&DATE($F$3,F$6,1),DATA!$K:$K,"<="&DATE($F$3,F$6,F$5),DATA!$N:$N,$Q14)*10)+COUNTIFS(DATA!$P:$P,"=S",DATA!$K:$K,">="&DATE($F$3,F$6,1),DATA!$K:$K,"<="&DATE($F$3,F$6,F$5),DATA!$N:$N,$Q14) -> 0 | G14: =(COUNTIFS(DATA!$P:$P,"=E",DATA!$K:$K,">="&DATE($F$3,G$6,1),DATA!$K:$K,"<="&DATE($F$3,G$6,G$5),DATA!$N:$N,$Q14)*10)+COUNTIFS(DATA!$P:$P,"=S",DATA!$K:$K,">="&DATE($F$3,G$6,1),DATA!$K:$K,"<="&DATE($F$3,G$6,G$5),DATA!$N:$N,$Q14) -> 0 | H14: =(COUNTIFS(DATA!$P:$P,"=E",DATA!$K:$K,">="&DATE($F$3,H$6,1),DATA!$K:$K,"<="&DATE($F$3,H$6,H$5),DATA!$N:$N,$Q14)*10)+COUNTIFS(DATA!$P:$P,"=S",DATA!$K:$K,">="&DATE($F$3,H$6,1),DATA!$K:$K,"<="&DATE($F$3,H$6,H$5),DATA!$N:$N,$Q14) -> 0 | I14: =(COUNTIFS(DATA!$P:$P,"=E",DATA!$K:$K,">="&DATE($F$3,I$6,1),DATA!$K:$K,"<="&DATE($F$3,I$6,I$5),DATA!$N:$N,$Q14)*10)+COUNTIFS(DATA!$P:$P,"=S",DATA!$K:$K,">="&DATE($F$3,I$6,1),DATA!$K:$K,"<="&DATE($F$3,I$6,I$5),DATA!$N:$N,$Q14) -> 0 | J14: =(COUNTIFS(DATA!$P:$P,"=E",DATA!$K:$K,">="&DATE($F$3,J$6,1),DATA!$K:$K,"<="&DATE($F$3,J$6,J$5),DATA!$N:$N,$Q14)*10)+COUNTIFS(DATA!$P:$P,"=S",DATA!$K:$K,">="&DATE($F$3,J$6,1),DATA!$K:$K,"<="&DATE($F$3,J$6,J$5),DATA!$N:$N,$Q14) -> 0 | ... N14: =(COUNTIFS(DATA!$P:$P,"=E",DATA!$K:$K,">="&DATE($F$3,N$6,1),DATA!$K:$K,"<="&DATE($F$3,N$6,N$5),DATA!$N:$N,$Q14)*10)+COUNTIFS(DATA!$P:$P,"=S",DATA!$K:$K,">="&DATE($F$3,N$6,1),DATA!$K:$K,"<="&DATE($F$3,N$6,N$5),DATA!$N:$N,$Q14) -> 0 | O14: =SUM(C14:N14) -> 0 | Q14: ="*"&StaffList!B11&"*" -> *Thuong.mv*
A15: 8 | B15: =VLOOKUP(Q15, StaffList!B:C,2,FALSE) -> Chu Tiến Dũng | C15: =(COUNTIFS(DATA!$P:$P,"=E",DATA!$K:$K,">="&DATE($F$3,C$6,1),DATA!$K:$K,"<="&DATE($F$3,C$6,C$5),DATA!$N:$N,$Q15)*10)+COUNTIFS(DATA!$P:$P,"=S",DATA!$K:$K,">="&DATE($F$3,C$6,1),DATA!$K:$K,"<="&DATE($F$3,C$6,C$5),DATA!$N:$N,$Q15) -> 0 | D15: =(COUNTIFS(DATA!$P:$P,"=E",DATA!$K:$K,">="&DATE($F$3,D$6,1),DATA!$K:$K,"<="&DATE($F$3,D$6,D$5),DATA!$N:$N,$Q15)*10)+COUNTIFS(DATA!$P:$P,"=S",DATA!$K:$K,">="&DATE($F$3,D$6,1),DATA!$K:$K,"<="&DATE($F$3,D$6,D$5),DATA!$N:$N,$Q15) -> 0 | E15: =(COUNTIFS(DATA!$P:$P,"=E",DATA!$K:$K,">="&DATE($F$3,E$6,1),DATA!$K:$K,"<="&DATE($F$3,E$6,E$5),DATA!$N:$N,$Q15)*10)+COUNTIFS(DATA!$P:$P,"=S",DATA!$K:$K,">="&DATE($F$3,E$6,1),DATA!$K:$K,"<="&DATE($F$3,E$6,E$5),DATA!$N:$N,$Q15) -> 0 | F15: =(COUNTIFS(DATA!$P:$P,"=E",DATA!$K:$K,">="&DATE($F$3,F$6,1),DATA!$K:$K,"<="&DATE($F$3,F$6,F$5),DATA!$N:$N,$Q15)*10)+COUNTIFS(DATA!$P:$P,"=S",DATA!$K:$K,">="&DATE($F$3,F$6,1),DATA!$K:$K,"<="&DATE($F$3,F$6,F$5),DATA!$N:$N,$Q15) -> 0 | G15: =(COUNTIFS(DATA!$P:$P,"=E",DATA!$K:$K,">="&DATE($F$3,G$6,1),DATA!$K:$K,"<="&DATE($F$3,G$6,G$5),DATA!$N:$N,$Q15)*10)+COUNTIFS(DATA!$P:$P,"=S",DATA!$K:$K,">="&DATE($F$3,G$6,1),DATA!$K:$K,"<="&DATE($F$3,G$6,G$5),DATA!$N:$N,$Q15) -> 0 | H15: =(COUNTIFS(DATA!$P:$P,"=E",DATA!$K:$K,">="&DATE($F$3,H$6,1),DATA!$K:$K,"<="&DATE($F$3,H$6,H$5),DATA!$N:$N,$Q15)*10)+COUNTIFS(DATA!$P:$P,"=S",DATA!$K:$K,">="&DATE($F$3,H$6,1),DATA!$K:$K,"<="&DATE($F$3,H$6,H$5),DATA!$N:$N,$Q15) -> 0 | I15: =(COUNTIFS(DATA!$P:$P,"=E",DATA!$K:$K,">="&DATE($F$3,I$6,1),DATA!$K:$K,"<="&DATE($F$3,I$6,I$5),DATA!$N:$N,$Q15)*10)+COUNTIFS(DATA!$P:$P,"=S",DATA!$K:$K,">="&DATE($F$3,I$6,1),DATA!$K:$K,"<="&DATE($F$3,I$6,I$5),DATA!$N:$N,$Q15) -> 0 | J15: =(COUNTIFS(DATA!$P:$P,"=E",DATA!$K:$K,">="&DATE($F$3,J$6,1),DATA!$K:$K,"<="&DATE($F$3,J$6,J$5),DATA!$N:$N,$Q15)*10)+COUNTIFS(DATA!$P:$P,"=S",DATA!$K:$K,">="&DATE($F$3,J$6,1),DATA!$K:$K,"<="&DATE($F$3,J$6,J$5),DATA!$N:$N,$Q15) -> 0 | ... N15: =(COUNTIFS(DATA!$P:$P,"=E",DATA!$K:$K,">="&DATE($F$3,N$6,1),DATA!$K:$K,"<="&DATE($F$3,N$6,N$5),DATA!$N:$N,$Q15)*10)+COUNTIFS(DATA!$P:$P,"=S",DATA!$K:$K,">="&DATE($F$3,N$6,1),DATA!$K:$K,"<="&DATE($F$3,N$6,N$5),DATA!$N:$N,$Q15) -> 0 | O15: =SUM(C15:N15) -> 0 | Q15: ="*"&StaffList!B12&"*" -> *Dung.ct*
A16: 17 | B16: =VLOOKUP(Q16, StaffList!B:C,2,FALSE) -> Phan Xuân Lương | C16: =(COUNTIFS(DATA!$P:$P,"=E",DATA!$K:$K,">="&DATE($F$3,C$6,1),DATA!$K:$K,"<="&DATE($F$3,C$6,C$5),DATA!$N:$N,$Q16)*10)+COUNTIFS(DATA!$P:$P,"=S",DATA!$K:$K,">="&DATE($F$3,C$6,1),DATA!$K:$K,"<="&DATE($F$3,C$6,C$5),DATA!$N:$N,$Q16) -> 0 | D16: =(COUNTIFS(DATA!$P:$P,"=E",DATA!$K:$K,">="&DATE($F$3,D$6,1),DATA!$K:$K,"<="&DATE($F$3,D$6,D$5),DATA!$N:$N,$Q16)*10)+COUNTIFS(DATA!$P:$P,"=S",DATA!$K:$K,">="&DATE($F$3,D$6,1),DATA!$K:$K,"<="&DATE($F$3,D$6,D$5),DATA!$N:$N,$Q16) -> 0 | E16: =(COUNTIFS(DATA!$P:$P,"=E",DATA!$K:$K,">="&DATE($F$3,E$6,1),DATA!$K:$K,"<="&DATE($F$3,E$6,E$5),DATA!$N:$N,$Q16)*10)+COUNTIFS(DATA!$P:$P,"=S",DATA!$K:$K,">="&DATE($F$3,E$6,1),DATA!$K:$K,"<="&DATE($F$3,E$6,E$5),DATA!$N:$N,$Q16) -> 0 | F16: =(COUNTIFS(DATA!$P:$P,"=E",DATA!$K:$K,">="&DATE($F$3,F$6,1),DATA!$K:$K,"<="&DATE($F$3,F$6,F$5),DATA!$N:$N,$Q16)*10)+COUNTIFS(DATA!$P:$P,"=S",DATA!$K:$K,">="&DATE($F$3,F$6,1),DATA!$K:$K,"<="&DATE($F$3,F$6,F$5),DATA!$N:$N,$Q16) -> 0 | G16: =(COUNTIFS(DATA!$P:$P,"=E",DATA!$K:$K,">="&DATE($F$3,G$6,1),DATA!$K:$K,"<="&DATE($F$3,G$6,G$5),DATA!$N:$N,$Q16)*10)+COUNTIFS(DATA!$P:$P,"=S",DATA!$K:$K,">="&DATE($F$3,G$6,1),DATA!$K:$K,"<="&DATE($F$3,G$6,G$5),DATA!$N:$N,$Q16) -> 0 | H16: =(COUNTIFS(DATA!$P:$P,"=E",DATA!$K:$K,">="&DATE($F$3,H$6,1),DATA!$K:$K,"<="&DATE($F$3,H$6,H$5),DATA!$N:$N,$Q16)*10)+COUNTIFS(DATA!$P:$P,"=S",DATA!$K:$K,">="&DATE($F$3,H$6,1),DATA!$K:$K,"<="&DATE($F$3,H$6,H$5),DATA!$N:$N,$Q16) -> 0 | I16: =(COUNTIFS(DATA!$P:$P,"=E",DATA!$K:$K,">="&DATE($F$3,I$6,1),DATA!$K:$K,"<="&DATE($F$3,I$6,I$5),DATA!$N:$N,$Q16)*10)+COUNTIFS(DATA!$P:$P,"=S",DATA!$K:$K,">="&DATE($F$3,I$6,1),DATA!$K:$K,"<="&DATE($F$3,I$6,I$5),DATA!$N:$N,$Q16) -> 0 | J16: =(COUNTIFS(DATA!$P:$P,"=E",DATA!$K:$K,">="&DATE($F$3,J$6,1),DATA!$K:$K,"<="&DATE($F$3,J$6,J$5),DATA!$N:$N,$Q16)*10)+COUNTIFS(DATA!$P:$P,"=S",DATA!$K:$K,">="&DATE($F$3,J$6,1),DATA!$K:$K,"<="&DATE($F$3,J$6,J$5),DATA!$N:$N,$Q16) -> 0 | ... N16: =(COUNTIFS(DATA!$P:$P,"=E",DATA!$K:$K,">="&DATE($F$3,N$6,1),DATA!$K:$K,"<="&DATE($F$3,N$6,N$5),DATA!$N:$N,$Q16)*10)+COUNTIFS(DATA!$P:$P,"=S",DATA!$K:$K,">="&DATE($F$3,N$6,1),DATA!$K:$K,"<="&DATE($F$3,N$6,N$5),DATA!$N:$N,$Q16) -> 0 | O16: =SUM(C16:N16) -> 0 | Q16: ="*"&StaffList!B21&"*" -> *Luong.px*
A17: 10 | B17: =VLOOKUP(Q17, StaffList!B:C,2,FALSE) -> Hoàng Việt Thao | C17: =(COUNTIFS(DATA!$P:$P,"=E",DATA!$K:$K,">="&DATE($F$3,C$6,1),DATA!$K:$K,"<="&DATE($F$3,C$6,C$5),DATA!$N:$N,$Q17)*10)+COUNTIFS(DATA!$P:$P,"=S",DATA!$K:$K,">="&DATE($F$3,C$6,1),DATA!$K:$K,"<="&DATE($F$3,C$6,C$5),DATA!$N:$N,$Q17) -> 0 | D17: =(COUNTIFS(DATA!$P:$P,"=E",DATA!$K:$K,">="&DATE($F$3,D$6,1),DATA!$K:$K,"<="&DATE($F$3,D$6,D$5),DATA!$N:$N,$Q17)*10)+COUNTIFS(DATA!$P:$P,"=S",DATA!$K:$K,">="&DATE($F$3,D$6,1),DATA!$K:$K,"<="&DATE($F$3,D$6,D$5),DATA!$N:$N,$Q17) -> 0 | E17: =(COUNTIFS(DATA!$P:$P,"=E",DATA!$K:$K,">="&DATE($F$3,E$6,1),DATA!$K:$K,"<="&DATE($F$3,E$6,E$5),DATA!$N:$N,$Q17)*10)+COUNTIFS(DATA!$P:$P,"=S",DATA!$K:$K,">="&DATE($F$3,E$6,1),DATA!$K:$K,"<="&DATE($F$3,E$6,E$5),DATA!$N:$N,$Q17) -> 0 | F17: =(COUNTIFS(DATA!$P:$P,"=E",DATA!$K:$K,">="&DATE($F$3,F$6,1),DATA!$K:$K,"<="&DATE($F$3,F$6,F$5),DATA!$N:$N,$Q17)*10)+COUNTIFS(DATA!$P:$P,"=S",DATA!$K:$K,">="&DATE($F$3,F$6,1),DATA!$K:$K,"<="&DATE($F$3,F$6,F$5),DATA!$N:$N,$Q17) -> 0 | G17: =(COUNTIFS(DATA!$P:$P,"=E",DATA!$K:$K,">="&DATE($F$3,G$6,1),DATA!$K:$K,"<="&DATE($F$3,G$6,G$5),DATA!$N:$N,$Q17)*10)+COUNTIFS(DATA!$P:$P,"=S",DATA!$K:$K,">="&DATE($F$3,G$6,1),DATA!$K:$K,"<="&DATE($F$3,G$6,G$5),DATA!$N:$N,$Q17) -> 0 | H17: =(COUNTIFS(DATA!$P:$P,"=E",DATA!$K:$K,">="&DATE($F$3,H$6,1),DATA!$K:$K,"<="&DATE($F$3,H$6,H$5),DATA!$N:$N,$Q17)*10)+COUNTIFS(DATA!$P:$P,"=S",DATA!$K:$K,">="&DATE($F$3,H$6,1),DATA!$K:$K,"<="&DATE($F$3,H$6,H$5),DATA!$N:$N,$Q17) -> 0 | I17: =(COUNTIFS(DATA!$P:$P,"=E",DATA!$K:$K,">="&DATE($F$3,I$6,1),DATA!$K:$K,"<="&DATE($F$3,I$6,I$5),DATA!$N:$N,$Q17)*10)+COUNTIFS(DATA!$P:$P,"=S",DATA!$K:$K,">="&DATE($F$3,I$6,1),DATA!$K:$K,"<="&DATE($F$3,I$6,I$5),DATA!$N:$N,$Q17) -> 0 | J17: =(COUNTIFS(DATA!$P:$P,"=E",DATA!$K:$K,">="&DATE($F$3,J$6,1),DATA!$K:$K,"<="&DATE($F$3,J$6,J$5),DATA!$N:$N,$Q17)*10)+COUNTIFS(DATA!$P:$P,"=S",DATA!$K:$K,">="&DATE($F$3,J$6,1),DATA!$K:$K,"<="&DATE($F$3,J$6,J$5),DATA!$N:$N,$Q17) -> 0 | ... N17: =(COUNTIFS(DATA!$P:$P,"=E",DATA!$K:$K,">="&DATE($F$3,N$6,1),DATA!$K:$K,"<="&DATE($F$3,N$6,N$5),DATA!$N:$N,$Q17)*10)+COUNTIFS(DATA!$P:$P,"=S",DATA!$K:$K,">="&DATE($F$3,N$6,1),DATA!$K:$K,"<="&DATE($F$3,N$6,N$5),DATA!$N:$N,$Q17) -> 0 | O17: =SUM(C17:N17) -> 0 | Q17: ="*"&StaffList!B14&"*" -> *Thao.hv*
A18: 6 | B18: =VLOOKUP(Q18, StaffList!B:C,2,FALSE) -> Chu Trọng Thao | C18: =(COUNTIFS(DATA!$P:$P,"=E",DATA!$K:$K,">="&DATE($F$3,C$6,1),DATA!$K:$K,"<="&DATE($F$3,C$6,C$5),DATA!$N:$N,$Q18)*10)+COUNTIFS(DATA!$P:$P,"=S",DATA!$K:$K,">="&DATE($F$3,C$6,1),DATA!$K:$K,"<="&DATE($F$3,C$6,C$5),DATA!$N:$N,$Q18) -> 0 | D18: =(COUNTIFS(DATA!$P:$P,"=E",DATA!$K:$K,">="&DATE($F$3,D$6,1),DATA!$K:$K,"<="&DATE($F$3,D$6,D$5),DATA!$N:$N,$Q18)*10)+COUNTIFS(DATA!$P:$P,"=S",DATA!$K:$K,">="&DATE($F$3,D$6,1),DATA!$K:$K,"<="&DATE($F$3,D$6,D$5),DATA!$N:$N,$Q18) -> 0 | E18: =(COUNTIFS(DATA!$P:$P,"=E",DATA!$K:$K,">="&DATE($F$3,E$6,1),DATA!$K:$K,"<="&DATE($F$3,E$6,E$5),DATA!$N:$N,$Q18)*10)+COUNTIFS(DATA!$P:$P,"=S",DATA!$K:$K,">="&DATE($F$3,E$6,1),DATA!$K:$K,"<="&DATE($F$3,E$6,E$5),DATA!$N:$N,$Q18) -> 0 | F18: =(COUNTIFS(DATA!$P:$P,"=E",DATA!$K:$K,">="&DATE($F$3,F$6,1),DATA!$K:$K,"<="&DATE($F$3,F$6,F$5),DATA!$N:$N,$Q18)*10)+COUNTIFS(DATA!$P:$P,"=S",DATA!$K:$K,">="&DATE($F$3,F$6,1),DATA!$K:$K,"<="&DATE($F$3,F$6,F$5),DATA!$N:$N,$Q18) -> 0 | G18: =(COUNTIFS(DATA!$P:$P,"=E",DATA!$K:$K,">="&DATE($F$3,G$6,1),DATA!$K:$K,"<="&DATE($F$3,G$6,G$5),DATA!$N:$N,$Q18)*10)+COUNTIFS(DATA!$P:$P,"=S",DATA!$K:$K,">="&DATE($F$3,G$6,1),DATA!$K:$K,"<="&DATE($F$3,G$6,G$5),DATA!$N:$N,$Q18) -> 0 | H18: =(COUNTIFS(DATA!$P:$P,"=E",DATA!$K:$K,">="&DATE($F$3,H$6,1),DATA!$K:$K,"<="&DATE($F$3,H$6,H$5),DATA!$N:$N,$Q18)*10)+COUNTIFS(DATA!$P:$P,"=S",DATA!$K:$K,">="&DATE($F$3,H$6,1),DATA!$K:$K,"<="&DATE($F$3,H$6,H$5),DATA!$N:$N,$Q18) -> 0 | I18: =(COUNTIFS(DATA!$P:$P,"=E",DATA!$K:$K,">="&DATE($F$3,I$6,1),DATA!$K:$K,"<="&DATE($F$3,I$6,I$5),DATA!$N:$N,$Q18)*10)+COUNTIFS(DATA!$P:$P,"=S",DATA!$K:$K,">="&DATE($F$3,I$6,1),DATA!$K:$K,"<="&DATE($F$3,I$6,I$5),DATA!$N:$N,$Q18) -> 0 | J18: =(COUNTIFS(DATA!$P:$P,"=E",DATA!$K:$K,">="&DATE($F$3,J$6,1),DATA!$K:$K,"<="&DATE($F$3,J$6,J$5),DATA!$N:$N,$Q18)*10)+COUNTIFS(DATA!$P:$P,"=S",DATA!$K:$K,">="&DATE($F$3,J$6,1),DATA!$K:$K,"<="&DATE($F$3,J$6,J$5),DATA!$N:$N,$Q18) -> 0 | ... N18: =(COUNTIFS(DATA!$P:$P,"=E",DATA!$K:$K,">="&DATE($F$3,N$6,1),DATA!$K:$K,"<="&DATE($F$3,N$6,N$5),DATA!$N:$N,$Q18)*10)+COUNTIFS(DATA!$P:$P,"=S",DATA!$K:$K,">="&DATE($F$3,N$6,1),DATA!$K:$K,"<="&DATE($F$3,N$6,N$5),DATA!$N:$N,$Q18) -> 0 | O18: =SUM(C18:N18) -> 0 | Q18: ="*"&StaffList!B10&"*" -> *Thao.ct*
A19: 24 | B19: =VLOOKUP(Q19, StaffList!B:C,2,FALSE) -> Khúc Thành Đạt | C19: =(COUNTIFS(DATA!$P:$P,"=E",DATA!$K:$K,">="&DATE($F$3,C$6,1),DATA!$K:$K,"<="&DATE($F$3,C$6,C$5),DATA!$N:$N,$Q19)*10)+COUNTIFS(DATA!$P:$P,"=S",DATA!$K:$K,">="&DATE($F$3,C$6,1),DATA!$K:$K,"<="&DATE($F$3,C$6,C$5),DATA!$N:$N,$Q19) -> 0 | D19: =(COUNTIFS(DATA!$P:$P,"=E",DATA!$K:$K,">="&DATE($F$3,D$6,1),DATA!$K:$K,"<="&DATE($F$3,D$6,D$5),DATA!$N:$N,$Q19)*10)+COUNTIFS(DATA!$P:$P,"=S",DATA!$K:$K,">="&DATE($F$3,D$6,1),DATA!$K:$K,"<="&DATE($F$3,D$6,D$5),DATA!$N:$N,$Q19) -> 0 | E19: =(COUNTIFS(DATA!$P:$P,"=E",DATA!$K:$K,">="&DATE($F$3,E$6,1),DATA!$K:$K,"<="&DATE($F$3,E$6,E$5),DATA!$N:$N,$Q19)*10)+COUNTIFS(DATA!$P:$P,"=S",DATA!$K:$K,">="&DATE($F$3,E$6,1),DATA!$K:$K,"<="&DATE($F$3,E$6,E$5),DATA!$N:$N,$Q19) -> 0 | F19: =(COUNTIFS(DATA!$P:$P,"=E",DATA!$K:$K,">="&DATE($F$3,F$6,1),DATA!$K:$K,"<="&DATE($F$3,F$6,F$5),DATA!$N:$N,$Q19)*10)+COUNTIFS(DATA!$P:$P,"=S",DATA!$K:$K,">="&DATE($F$3,F$6,1),DATA!$K:$K,"<="&DATE($F$3,F$6,F$5),DATA!$N:$N,$Q19) -> 0 | G19: =(COUNTIFS(DATA!$P:$P,"=E",DATA!$K:$K,">="&DATE($F$3,G$6,1),DATA!$K:$K,"<="&DATE($F$3,G$6,G$5),DATA!$N:$N,$Q19)*10)+COUNTIFS(DATA!$P:$P,"=S",DATA!$K:$K,">="&DATE($F$3,G$6,1),DATA!$K:$K,"<="&DATE($F$3,G$6,G$5),DATA!$N:$N,$Q19) -> 0 | H19: =(COUNTIFS(DATA!$P:$P,"=E",DATA!$K:$K,">="&DATE($F$3,H$6,1),DATA!$K:$K,"<="&DATE($F$3,H$6,H$5),DATA!$N:$N,$Q19)*10)+COUNTIFS(DATA!$P:$P,"=S",DATA!$K:$K,">="&DATE($F$3,H$6,1),DATA!$K:$K,"<="&DATE($F$3,H$6,H$5),DATA!$N:$N,$Q19) -> 0 | I19: =(COUNTIFS(DATA!$P:$P,"=E",DATA!$K:$K,">="&DATE($F$3,I$6,1),DATA!$K:$K,"<="&DATE($F$3,I$6,I$5),DATA!$N:$N,$Q19)*10)+COUNTIFS(DATA!$P:$P,"=S",DATA!$K:$K,">="&DATE($F$3,I$6,1),DATA!$K:$K,"<="&DATE($F$3,I$6,I$5),DATA!$N:$N,$Q19) -> 0 | J19: =(COUNTIFS(DATA!$P:$P,"=E",DATA!$K:$K,">="&DATE($F$3,J$6,1),DATA!$K:$K,"<="&DATE($F$3,J$6,J$5),DATA!$N:$N,$Q19)*10)+COUNTIFS(DATA!$P:$P,"=S",DATA!$K:$K,">="&DATE($F$3,J$6,1),DATA!$K:$K,"<="&DATE($F$3,J$6,J$5),DATA!$N:$N,$Q19) -> 0 | ... N19: =(COUNTIFS(DATA!$P:$P,"=E",DATA!$K:$K,">="&DATE($F$3,N$6,1),DATA!$K:$K,"<="&DATE($F$3,N$6,N$5),DATA!$N:$N,$Q19)*10)+COUNTIFS(DATA!$P:$P,"=S",DATA!$K:$K,">="&DATE($F$3,N$6,1),DATA!$K:$K,"<="&DATE($F$3,N$6,N$5),DATA!$N:$N,$Q19) -> 0 | O19: =SUM(C19:N19) -> 0 | Q19: ="*"&StaffList!B28&"*" -> *Dat.kt*
A20: 19 | B20: =VLOOKUP(Q20, StaffList!B:C,2,FALSE) -> Đỗ Văn Long | C20: =(COUNTIFS(DATA!$P:$P,"=E",DATA!$K:$K,">="&DATE($F$3,C$6,1),DATA!$K:$K,"<="&DATE($F$3,C$6,C$5),DATA!$N:$N,$Q20)*10)+COUNTIFS(DATA!$P:$P,"=S",DATA!$K:$K,">="&DATE($F$3,C$6,1),DATA!$K:$K,"<="&DATE($F$3,C$6,C$5),DATA!$N:$N,$Q20) -> 0 | D20: =(COUNTIFS(DATA!$P:$P,"=E",DATA!$K:$K,">="&DATE($F$3,D$6,1),DATA!$K:$K,"<="&DATE($F$3,D$6,D$5),DATA!$N:$N,$Q20)*10)+COUNTIFS(DATA!$P:$P,"=S",DATA!$K:$K,">="&DATE($F$3,D$6,1),DATA!$K:$K,"<="&DATE($F$3,D$6,D$5),DATA!$N:$N,$Q20) -> 0 | E20: =(COUNTIFS(DATA!$P:$P,"=E",DATA!$K:$K,">="&DATE($F$3,E$6,1),DATA!$K:$K,"<="&DATE($F$3,E$6,E$5),DATA!$N:$N,$Q20)*10)+COUNTIFS(DATA!$P:$P,"=S",DATA!$K:$K,">="&DATE($F$3,E$6,1),DATA!$K:$K,"<="&DATE($F$3,E$6,E$5),DATA!$N:$N,$Q20) -> 0 | F20: =(COUNTIFS(DATA!$P:$P,"=E",DATA!$K:$K,">="&DATE($F$3,F$6,1),DATA!$K:$K,"<="&DATE($F$3,F$6,F$5),DATA!$N:$N,$Q20)*10)+COUNTIFS(DATA!$P:$P,"=S",DATA!$K:$K,">="&DATE($F$3,F$6,1),DATA!$K:$K,"<="&DATE($F$3,F$6,F$5),DATA!$N:$N,$Q20) -> 0 | G20: =(COUNTIFS(DATA!$P:$P,"=E",DATA!$K:$K,">="&DATE($F$3,G$6,1),DATA!$K:$K,"<="&DATE($F$3,G$6,G$5),DATA!$N:$N,$Q20)*10)+COUNTIFS(DATA!$P:$P,"=S",DATA!$K:$K,">="&DATE($F$3,G$6,1),DATA!$K:$K,"<="&DATE($F$3,G$6,G$5),DATA!$N:$N,$Q20) -> 0 | H20: =(COUNTIFS(DATA!$P:$P,"=E",DATA!$K:$K,">="&DATE($F$3,H$6,1),DATA!$K:$K,"<="&DATE($F$3,H$6,H$5),DATA!$N:$N,$Q20)*10)+COUNTIFS(DATA!$P:$P,"=S",DATA!$K:$K,">="&DATE($F$3,H$6,1),DATA!$K:$K,"<="&DATE($F$3,H$6,H$5),DATA!$N:$N,$Q20) -> 0 | I20: =(COUNTIFS(DATA!$P:$P,"=E",DATA!$K:$K,">="&DATE($F$3,I$6,1),DATA!$K:$K,"<="&DATE($F$3,I$6,I$5),DATA!$N:$N,$Q20)*10)+COUNTIFS(DATA!$P:$P,"=S",DATA!$K:$K,">="&DATE($F$3,I$6,1),DATA!$K:$K,"<="&DATE($F$3,I$6,I$5),DATA!$N:$N,$Q20) -> 0 | J20: =(COUNTIFS(DATA!$P:$P,"=E",DATA!$K:$K,">="&DATE($F$3,J$6,1),DATA!$K:$K,"<="&DATE($F$3,J$6,J$5),DATA!$N:$N,$Q20)*10)+COUNTIFS(DATA!$P:$P,"=S",DATA!$K:$K,">="&DATE($F$3,J$6,1),DATA!$K:$K,"<="&DATE($F$3,J$6,J$5),DATA!$N:$N,$Q20) -> 0 | ... N20: =(COUNTIFS(DATA!$P:$P,"=E",DATA!$K:$K,">="&DATE($F$3,N$6,1),DATA!$K:$K,"<="&DATE($F$3,N$6,N$5),DATA!$N:$N,$Q20)*10)+COUNTIFS(DATA!$P:$P,"=S",DATA!$K:$K,">="&DATE($F$3,N$6,1),DATA!$K:$K,"<="&DATE($F$3,N$6,N$5),DATA!$N:$N,$Q20) -> 0 | O20: =SUM(C20:N20) -> 0 | Q20: ="*"&StaffList!B23&"*" -> *Long.dv*
A21: 2 | B21: =VLOOKUP(Q21, StaffList!B:C,2,FALSE) -> Hà Đình Diên | C21: =(COUNTIFS(DATA!$P:$P,"=E",DATA!$K:$K,">="&DATE($F$3,C$6,1),DATA!$K:$K,"<="&DATE($F$3,C$6,C$5),DATA!$N:$N,$Q21)*10)+COUNTIFS(DATA!$P:$P,"=S",DATA!$K:$K,">="&DATE($F$3,C$6,1),DATA!$K:$K,"<="&DATE($F$3,C$6,C$5),DATA!$N:$N,$Q21) -> 0 | D21: =(COUNTIFS(DATA!$P:$P,"=E",DATA!$K:$K,">="&DATE($F$3,D$6,1),DATA!$K:$K,"<="&DATE($F$3,D$6,D$5),DATA!$N:$N,$Q21)*10)+COUNTIFS(DATA!$P:$P,"=S",DATA!$K:$K,">="&DATE($F$3,D$6,1),DATA!$K:$K,"<="&DATE($F$3,D$6,D$5),DATA!$N:$N,$Q21) -> 0 | E21: =(COUNTIFS(DATA!$P:$P,"=E",DATA!$K:$K,">="&DATE($F$3,E$6,1),DATA!$K:$K,"<="&DATE($F$3,E$6,E$5),DATA!$N:$N,$Q21)*10)+COUNTIFS(DATA!$P:$P,"=S",DATA!$K:$K,">="&DATE($F$3,E$6,1),DATA!$K:$K,"<="&DATE($F$3,E$6,E$5),DATA!$N:$N,$Q21) -> 0 | F21: =(COUNTIFS(DATA!$P:$P,"=E",DATA!$K:$K,">="&DATE($F$3,F$6,1),DATA!$K:$K,"<="&DATE($F$3,F$6,F$5),DATA!$N:$N,$Q21)*10)+COUNTIFS(DATA!$P:$P,"=S",DATA!$K:$K,">="&DATE($F$3,F$6,1),DATA!$K:$K,"<="&DATE($F$3,F$6,F$5),DATA!$N:$N,$Q21) -> 0 | G21: =(COUNTIFS(DATA!$P:$P,"=E",DATA!$K:$K,">="&DATE($F$3,G$6,1),DATA!$K:$K,"<="&DATE($F$3,G$6,G$5),DATA!$N:$N,$Q21)*10)+COUNTIFS(DATA!$P:$P,"=S",DATA!$K:$K,">="&DATE($F$3,G$6,1),DATA!$K:$K,"<="&DATE($F$3,G$6,G$5),DATA!$N:$N,$Q21) -> 0 | H21: =(COUNTIFS(DATA!$P:$P,"=E",DATA!$K:$K,">="&DATE($F$3,H$6,1),DATA!$K:$K,"<="&DATE($F$3,H$6,H$5),DATA!$N:$N,$Q21)*10)+COUNTIFS(DATA!$P:$P,"=S",DATA!$K:$K,">="&DATE($F$3,H$6,1),DATA!$K:$K,"<="&DATE($F$3,H$6,H$5),DATA!$N:$N,$Q21) -> 0 | I21: =(COUNTIFS(DATA!$P:$P,"=E",DATA!$K:$K,">="&DATE($F$3,I$6,1),DATA!$K:$K,"<="&DATE($F$3,I$6,I$5),DATA!$N:$N,$Q21)*10)+COUNTIFS(DATA!$P:$P,"=S",DATA!$K:$K,">="&DATE($F$3,I$6,1),DATA!$K:$K,"<="&DATE($F$3,I$6,I$5),DATA!$N:$N,$Q21) -> 0 | J21: =(COUNTIFS(DATA!$P:$P,"=E",DATA!$K:$K,">="&DATE($F$3,J$6,1),DATA!$K:$K,"<="&DATE($F$3,J$6,J$5),DATA!$N:$N,$Q21)*10)+COUNTIFS(DATA!$P:$P,"=S",DATA!$K:$K,">="&DATE($F$3,J$6,1),DATA!$K:$K,"<="&DATE($F$3,J$6,J$5),DATA!$N:$N,$Q21) -> 0 | ... N21: =(COUNTIFS(DATA!$P:$P,"=E",DATA!$K:$K,">="&DATE($F$3,N$6,1),DATA!$K:$K,"<="&DATE($F$3,N$6,N$5),DATA!$N:$N,$Q21)*10)+COUNTIFS(DATA!$P:$P,"=S",DATA!$K:$K,">="&DATE($F$3,N$6,1),DATA!$K:$K,"<="&DATE($F$3,N$6,N$5),DATA!$N:$N,$Q21) -> 0 | O21: =SUM(C21:N21) -> 0 | Q21: ="*"&StaffList!B6&"*" -> *Dien.hd*
A22: 12 | B22: =VLOOKUP(Q22, StaffList!B:C,2,FALSE) -> Mai Văn Hoàng | C22: =(COUNTIFS(DATA!$P:$P,"=E",DATA!$K:$K,">="&DATE($F$3,C$6,1),DATA!$K:$K,"<="&DATE($F$3,C$6,C$5),DATA!$N:$N,$Q22)*10)+COUNTIFS(DATA!$P:$P,"=S",DATA!$K:$K,">="&DATE($F$3,C$6,1),DATA!$K:$K,"<="&DATE($F$3,C$6,C$5),DATA!$N:$N,$Q22) -> 0 | D22: =(COUNTIFS(DATA!$P:$P,"=E",DATA!$K:$K,">="&DATE($F$3,D$6,1),DATA!$K:$K,"<="&DATE($F$3,D$6,D$5),DATA!$N:$N,$Q22)*10)+COUNTIFS(DATA!$P:$P,"=S",DATA!$K:$K,">="&DATE($F$3,D$6,1),DATA!$K:$K,"<="&DATE($F$3,D$6,D$5),DATA!$N:$N,$Q22) -> 0 | E22: =(COUNTIFS(DATA!$P:$P,"=E",DATA!$K:$K,">="&DATE($F$3,E$6,1),DATA!$K:$K,"<="&DATE($F$3,E$6,E$5),DATA!$N:$N,$Q22)*10)+COUNTIFS(DATA!$P:$P,"=S",DATA!$K:$K,">="&DATE($F$3,E$6,1),DATA!$K:$K,"<="&DATE($F$3,E$6,E$5),DATA!$N:$N,$Q22) -> 0 | F22: =(COUNTIFS(DATA!$P:$P,"=E",DATA!$K:$K,">="&DATE($F$3,F$6,1),DATA!$K:$K,"<="&DATE($F$3,F$6,F$5),DATA!$N:$N,$Q22)*10)+COUNTIFS(DATA!$P:$P,"=S",DATA!$K:$K,">="&DATE($F$3,F$6,1),DATA!$K:$K,"<="&DATE($F$3,F$6,F$5),DATA!$N:$N,$Q22) -> 0 | G22: =(COUNTIFS(DATA!$P:$P,"=E",DATA!$K:$K,">="&DATE($F$3,G$6,1),DATA!$K:$K,"<="&DATE($F$3,G$6,G$5),DATA!$N:$N,$Q22)*10)+COUNTIFS(DATA!$P:$P,"=S",DATA!$K:$K,">="&DATE($F$3,G$6,1),DATA!$K:$K,"<="&DATE($F$3,G$6,G$5),DATA!$N:$N,$Q22) -> 0 | H22: =(COUNTIFS(DATA!$P:$P,"=E",DATA!$K:$K,">="&DATE($F$3,H$6,1),DATA!$K:$K,"<="&DATE($F$3,H$6,H$5),DATA!$N:$N,$Q22)*10)+COUNTIFS(DATA!$P:$P,"=S",DATA!$K:$K,">="&DATE($F$3,H$6,1),DATA!$K:$K,"<="&DATE($F$3,H$6,H$5),DATA!$N:$N,$Q22) -> 0 | I22: =(COUNTIFS(DATA!$P:$P,"=E",DATA!$K:$K,">="&DATE($F$3,I$6,1),DATA!$K:$K,"<="&DATE($F$3,I$6,I$5),DATA!$N:$N,$Q22)*10)+COUNTIFS(DATA!$P:$P,"=S",DATA!$K:$K,">="&DATE($F$3,I$6,1),DATA!$K:$K,"<="&DATE($F$3,I$6,I$5),DATA!$N:$N,$Q22) -> 0 | J22: =(COUNTIFS(DATA!$P:$P,"=E",DATA!$K:$K,">="&DATE($F$3,J$6,1),DATA!$K:$K,"<="&DATE($F$3,J$6,J$5),DATA!$N:$N,$Q22)*10)+COUNTIFS(DATA!$P:$P,"=S",DATA!$K:$K,">="&DATE($F$3,J$6,1),DATA!$K:$K,"<="&DATE($F$3,J$6,J$5),DATA!$N:$N,$Q22) -> 0 | ... N22: =(COUNTIFS(DATA!$P:$P,"=E",DATA!$K:$K,">="&DATE($F$3,N$6,1),DATA!$K:$K,"<="&DATE($F$3,N$6,N$5),DATA!$N:$N,$Q22)*10)+COUNTIFS(DATA!$P:$P,"=S",DATA!$K:$K,">="&DATE($F$3,N$6,1),DATA!$K:$K,"<="&DATE($F$3,N$6,N$5),DATA!$N:$N,$Q22) -> 0 | O22: =SUM(C22:N22) -> 0 | Q22: ="*"&StaffList!B16&"*" -> *Hoang.mv*
A23: 4 | B23: =VLOOKUP(Q23, StaffList!B:C,2,FALSE) -> Vũ Hoàng | C23: =(COUNTIFS(DATA!$P:$P,"=E",DATA!$K:$K,">="&DATE($F$3,C$6,1),DATA!$K:$K,"<="&DATE($F$3,C$6,C$5),DATA!$N:$N,$Q23)*10)+COUNTIFS(DATA!$P:$P,"=S",DATA!$K:$K,">="&DATE($F$3,C$6,1),DATA!$K:$K,"<="&DATE($F$3,C$6,C$5),DATA!$N:$N,$Q23) -> 0 | D23: =(COUNTIFS(DATA!$P:$P,"=E",DATA!$K:$K,">="&DATE($F$3,D$6,1),DATA!$K:$K,"<="&DATE($F$3,D$6,D$5),DATA!$N:$N,$Q23)*10)+COUNTIFS(DATA!$P:$P,"=S",DATA!$K:$K,">="&DATE($F$3,D$6,1),DATA!$K:$K,"<="&DATE($F$3,D$6,D$5),DATA!$N:$N,$Q23) -> 0 | E23: =(COUNTIFS(DATA!$P:$P,"=E",DATA!$K:$K,">="&DATE($F$3,E$6,1),DATA!$K:$K,"<="&DATE($F$3,E$6,E$5),DATA!$N:$N,$Q23)*10)+COUNTIFS(DATA!$P:$P,"=S",DATA!$K:$K,">="&DATE($F$3,E$6,1),DATA!$K:$K,"<="&DATE($F$3,E$6,E$5),DATA!$N:$N,$Q23) -> 0 | F23: =(COUNTIFS(DATA!$P:$P,"=E",DATA!$K:$K,">="&DATE($F$3,F$6,1),DATA!$K:$K,"<="&DATE($F$3,F$6,F$5),DATA!$N:$N,$Q23)*10)+COUNTIFS(DATA!$P:$P,"=S",DATA!$K:$K,">="&DATE($F$3,F$6,1),DATA!$K:$K,"<="&DATE($F$3,F$6,F$5),DATA!$N:$N,$Q23) -> 0 | G23: =(COUNTIFS(DATA!$P:$P,"=E",DATA!$K:$K,">="&DATE($F$3,G$6,1),DATA!$K:$K,"<="&DATE($F$3,G$6,G$5),DATA!$N:$N,$Q23)*10)+COUNTIFS(DATA!$P:$P,"=S",DATA!$K:$K,">="&DATE($F$3,G$6,1),DATA!$K:$K,"<="&DATE($F$3,G$6,G$5),DATA!$N:$N,$Q23) -> 0 | H23: =(COUNTIFS(DATA!$P:$P,"=E",DATA!$K:$K,">="&DATE($F$3,H$6,1),DATA!$K:$K,"<="&DATE($F$3,H$6,H$5),DATA!$N:$N,$Q23)*10)+COUNTIFS(DATA!$P:$P,"=S",DATA!$K:$K,">="&DATE($F$3,H$6,1),DATA!$K:$K,"<="&DATE($F$3,H$6,H$5),DATA!$N:$N,$Q23) -> 0 | I23: =(COUNTIFS(DATA!$P:$P,"=E",DATA!$K:$K,">="&DATE($F$3,I$6,1),DATA!$K:$K,"<="&DATE($F$3,I$6,I$5),DATA!$N:$N,$Q23)*10)+COUNTIFS(DATA!$P:$P,"=S",DATA!$K:$K,">="&DATE($F$3,I$6,1),DATA!$K:$K,"<="&DATE($F$3,I$6,I$5),DATA!$N:$N,$Q23) -> 0 | J23: =(COUNTIFS(DATA!$P:$P,"=E",DATA!$K:$K,">="&DATE($F$3,J$6,1),DATA!$K:$K,"<="&DATE($F$3,J$6,J$5),DATA!$N:$N,$Q23)*10)+COUNTIFS(DATA!$P:$P,"=S",DATA!$K:$K,">="&DATE($F$3,J$6,1),DATA!$K:$K,"<="&DATE($F$3,J$6,J$5),DATA!$N:$N,$Q23) -> 0 | ... N23: =(COUNTIFS(DATA!$P:$P,"=E",DATA!$K:$K,">="&DATE($F$3,N$6,1),DATA!$K:$K,"<="&DATE($F$3,N$6,N$5),DATA!$N:$N,$Q23)*10)+COUNTIFS(DATA!$P:$P,"=S",DATA!$K:$K,">="&DATE($F$3,N$6,1),DATA!$K:$K,"<="&DATE($F$3,N$6,N$5),DATA!$N:$N,$Q23) -> 0 | O23: =SUM(C23:N23) -> 0 | Q23: ="*"&StaffList!B8&"*" -> *Hoang.v*
A24: 3 | B24: =VLOOKUP(Q24, StaffList!B:C,2,FALSE) -> Nguyễn Mạnh Hùng | C24: =(COUNTIFS(DATA!$P:$P,"=E",DATA!$K:$K,">="&DATE($F$3,C$6,1),DATA!$K:$K,"<="&DATE($F$3,C$6,C$5),DATA!$N:$N,$Q24)*10)+COUNTIFS(DATA!$P:$P,"=S",DATA!$K:$K,">="&DATE($F$3,C$6,1),DATA!$K:$K,"<="&DATE($F$3,C$6,C$5),DATA!$N:$N,$Q24) -> 0 | D24: =(COUNTIFS(DATA!$P:$P,"=E",DATA!$K:$K,">="&DATE($F$3,D$6,1),DATA!$K:$K,"<="&DATE($F$3,D$6,D$5),DATA!$N:$N,$Q24)*10)+COUNTIFS(DATA!$P:$P,"=S",DATA!$K:$K,">="&DATE($F$3,D$6,1),DATA!$K:$K,"<="&DATE($F$3,D$6,D$5),DATA!$N:$N,$Q24) -> 0 | E24: =(COUNTIFS(DATA!$P:$P,"=E",DATA!$K:$K,">="&DATE($F$3,E$6,1),DATA!$K:$K,"<="&DATE($F$3,E$6,E$5),DATA!$N:$N,$Q24)*10)+COUNTIFS(DATA!$P:$P,"=S",DATA!$K:$K,">="&DATE($F$3,E$6,1),DATA!$K:$K,"<="&DATE($F$3,E$6,E$5),DATA!$N:$N,$Q24) -> 0 | F24: =(COUNTIFS(DATA!$P:$P,"=E",DATA!$K:$K,">="&DATE($F$3,F$6,1),DATA!$K:$K,"<="&DATE($F$3,F$6,F$5),DATA!$N:$N,$Q24)*10)+COUNTIFS(DATA!$P:$P,"=S",DATA!$K:$K,">="&DATE($F$3,F$6,1),DATA!$K:$K,"<="&DATE($F$3,F$6,F$5),DATA!$N:$N,$Q24) -> 0 | G24: =(COUNTIFS(DATA!$P:$P,"=E",DATA!$K:$K,">="&DATE($F$3,G$6,1),DATA!$K:$K,"<="&DATE($F$3,G$6,G$5),DATA!$N:$N,$Q24)*10)+COUNTIFS(DATA!$P:$P,"=S",DATA!$K:$K,">="&DATE($F$3,G$6,1),DATA!$K:$K,"<="&DATE($F$3,G$6,G$5),DATA!$N:$N,$Q24) -> 0 | H24: =(COUNTIFS(DATA!$P:$P,"=E",DATA!$K:$K,">="&DATE($F$3,H$6,1),DATA!$K:$K,"<="&DATE($F$3,H$6,H$5),DATA!$N:$N,$Q24)*10)+COUNTIFS(DATA!$P:$P,"=S",DATA!$K:$K,">="&DATE($F$3,H$6,1),DATA!$K:$K,"<="&DATE($F$3,H$6,H$5),DATA!$N:$N,$Q24) -> 0 | I24: =(COUNTIFS(DATA!$P:$P,"=E",DATA!$K:$K,">="&DATE($F$3,I$6,1),DATA!$K:$K,"<="&DATE($F$3,I$6,I$5),DATA!$N:$N,$Q24)*10)+COUNTIFS(DATA!$P:$P,"=S",DATA!$K:$K,">="&DATE($F$3,I$6,1),DATA!$K:$K,"<="&DATE($F$3,I$6,I$5),DATA!$N:$N,$Q24) -> 0 | J24: =(COUNTIFS(DATA!$P:$P,"=E",DATA!$K:$K,">="&DATE($F$3,J$6,1),DATA!$K:$K,"<="&DATE($F$3,J$6,J$5),DATA!$N:$N,$Q24)*10)+COUNTIFS(DATA!$P:$P,"=S",DATA!$K:$K,">="&DATE($F$3,J$6,1),DATA!$K:$K,"<="&DATE($F$3,J$6,J$5),DATA!$N:$N,$Q24) -> 0 | ... N24: =(COUNTIFS(DATA!$P:$P,"=E",DATA!$K:$K,">="&DATE($F$3,N$6,1),DATA!$K:$K,"<="&DATE($F$3,N$6,N$5),DATA!$N:$N,$Q24)*10)+COUNTIFS(DATA!$P:$P,"=S",DATA!$K:$K,">="&DATE($F$3,N$6,1),DATA!$K:$K,"<="&DATE($F$3,N$6,N$5),DATA!$N:$N,$Q24) -> 0 | O24: =SUM(C24:N24) -> 0 | Q24: ="*"&StaffList!B7&"*" -> *Hung.nm*
A25: 21 | B25: =VLOOKUP(Q25, StaffList!B:C,2,FALSE) -> Bùi Văn Long | C25: =(COUNTIFS(DATA!$P:$P,"=E",DATA!$K:$K,">="&DATE($F$3,C$6,1),DATA!$K:$K,"<="&DATE($F$3,C$6,C$5),DATA!$N:$N,$Q25)*10)+COUNTIFS(DATA!$P:$P,"=S",DATA!$K:$K,">="&DATE($F$3,C$6,1),DATA!$K:$K,"<="&DATE($F$3,C$6,C$5),DATA!$N:$N,$Q25) -> 0 | D25: =(COUNTIFS(DATA!$P:$P,"=E",DATA!$K:$K,">="&DATE($F$3,D$6,1),DATA!$K:$K,"<="&DATE($F$3,D$6,D$5),DATA!$N:$N,$Q25)*10)+COUNTIFS(DATA!$P:$P,"=S",DATA!$K:$K,">="&DATE($F$3,D$6,1),DATA!$K:$K,"<="&DATE($F$3,D$6,D$5),DATA!$N:$N,$Q25) -> 0 | E25: =(COUNTIFS(DATA!$P:$P,"=E",DATA!$K:$K,">="&DATE($F$3,E$6,1),DATA!$K:$K,"<="&DATE($F$3,E$6,E$5),DATA!$N:$N,$Q25)*10)+COUNTIFS(DATA!$P:$P,"=S",DATA!$K:$K,">="&DATE($F$3,E$6,1),DATA!$K:$K,"<="&DATE($F$3,E$6,E$5),DATA!$N:$N,$Q25) -> 0 | F25: =(COUNTIFS(DATA!$P:$P,"=E",DATA!$K:$K,">="&DATE($F$3,F$6,1),DATA!$K:$K,"<="&DATE($F$3,F$6,F$5),DATA!$N:$N,$Q25)*10)+COUNTIFS(DATA!$P:$P,"=S",DATA!$K:$K,">="&DATE($F$3,F$6,1),DATA!$K:$K,"<="&DATE($F$3,F$6,F$5),DATA!$N:$N,$Q25) -> 0 | G25: =(COUNTIFS(DATA!$P:$P,"=E",DATA!$K:$K,">="&DATE($F$3,G$6,1),DATA!$K:$K,"<="&DATE($F$3,G$6,G$5),DATA!$N:$N,$Q25)*10)+COUNTIFS(DATA!$P:$P,"=S",DATA!$K:$K,">="&DATE($F$3,G$6,1),DATA!$K:$K,"<="&DATE($F$3,G$6,G$5),DATA!$N:$N,$Q25) -> 0 | H25: =(COUNTIFS(DATA!$P:$P,"=E",DATA!$K:$K,">="&DATE($F$3,H$6,1),DATA!$K:$K,"<="&DATE($F$3,H$6,H$5),DATA!$N:$N,$Q25)*10)+COUNTIFS(DATA!$P:$P,"=S",DATA!$K:$K,">="&DATE($F$3,H$6,1),DATA!$K:$K,"<="&DATE($F$3,H$6,H$5),DATA!$N:$N,$Q25) -> 0 | I25: =(COUNTIFS(DATA!$P:$P,"=E",DATA!$K:$K,">="&DATE($F$3,I$6,1),DATA!$K:$K,"<="&DATE($F$3,I$6,I$5),DATA!$N:$N,$Q25)*10)+COUNTIFS(DATA!$P:$P,"=S",DATA!$K:$K,">="&DATE($F$3,I$6,1),DATA!$K:$K,"<="&DATE($F$3,I$6,I$5),DATA!$N:$N,$Q25) -> 0 | J25: =(COUNTIFS(DATA!$P:$P,"=E",DATA!$K:$K,">="&DATE($F$3,J$6,1),DATA!$K:$K,"<="&DATE($F$3,J$6,J$5),DATA!$N:$N,$Q25)*10)+COUNTIFS(DATA!$P:$P,"=S",DATA!$K:$K,">="&DATE($F$3,J$6,1),DATA!$K:$K,"<="&DATE($F$3,J$6,J$5),DATA!$N:$N,$Q25) -> 0 | ... N25: =(COUNTIFS(DATA!$P:$P,"=E",DATA!$K:$K,">="&DATE($F$3,N$6,1),DATA!$K:$K,"<="&DATE($F$3,N$6,N$5),DATA!$N:$N,$Q25)*10)+COUNTIFS(DATA!$P:$P,"=S",DATA!$K:$K,">="&DATE($F$3,N$6,1),DATA!$K:$K,"<="&DATE($F$3,N$6,N$5),DATA!$N:$N,$Q25) -> 0 | O25: =SUM(C25:N25) -> 0 | Q25: ="*"&StaffList!B25&"*" -> *Long.bv*
A26: 22 | B26: =VLOOKUP(Q26, StaffList!B:C,2,FALSE) -> Đoàn Mạnh Thức | C26: =(COUNTIFS(DATA!$P:$P,"=E",DATA!$K:$K,">="&DATE($F$3,C$6,1),DATA!$K:$K,"<="&DATE($F$3,C$6,C$5),DATA!$N:$N,$Q26)*10)+COUNTIFS(DATA!$P:$P,"=S",DATA!$K:$K,">="&DATE($F$3,C$6,1),DATA!$K:$K,"<="&DATE($F$3,C$6,C$5),DATA!$N:$N,$Q26) -> 0 | D26: =(COUNTIFS(DATA!$P:$P,"=E",DATA!$K:$K,">="&DATE($F$3,D$6,1),DATA!$K:$K,"<="&DATE($F$3,D$6,D$5),DATA!$N:$N,$Q26)*10)+COUNTIFS(DATA!$P:$P,"=S",DATA!$K:$K,">="&DATE($F$3,D$6,1),DATA!$K:$K,"<="&DATE($F$3,D$6,D$5),DATA!$N:$N,$Q26) -> 0 | E26: =(COUNTIFS(DATA!$P:$P,"=E",DATA!$K:$K,">="&DATE($F$3,E$6,1),DATA!$K:$K,"<="&DATE($F$3,E$6,E$5),DATA!$N:$N,$Q26)*10)+COUNTIFS(DATA!$P:$P,"=S",DATA!$K:$K,">="&DATE($F$3,E$6,1),DATA!$K:$K,"<="&DATE($F$3,E$6,E$5),DATA!$N:$N,$Q26) -> 0 | F26: =(COUNTIFS(DATA!$P:$P,"=E",DATA!$K:$K,">="&DATE($F$3,F$6,1),DATA!$K:$K,"<="&DATE($F$3,F$6,F$5),DATA!$N:$N,$Q26)*10)+COUNTIFS(DATA!$P:$P,"=S",DATA!$K:$K,">="&DATE($F$3,F$6,1),DATA!$K:$K,"<="&DATE($F$3,F$6,F$5),DATA!$N:$N,$Q26) -> 0 | G26: =(COUNTIFS(DATA!$P:$P,"=E",DATA!$K:$K,">="&DATE($F$3,G$6,1),DATA!$K:$K,"<="&DATE($F$3,G$6,G$5),DATA!$N:$N,$Q26)*10)+COUNTIFS(DATA!$P:$P,"=S",DATA!$K:$K,">="&DATE($F$3,G$6,1),DATA!$K:$K,"<="&DATE($F$3,G$6,G$5),DATA!$N:$N,$Q26) -> 0 | H26: =(COUNTIFS(DATA!$P:$P,"=E",DATA!$K:$K,">="&DATE($F$3,H$6,1),DATA!$K:$K,"<="&DATE($F$3,H$6,H$5),DATA!$N:$N,$Q26)*10)+COUNTIFS(DATA!$P:$P,"=S",DATA!$K:$K,">="&DATE($F$3,H$6,1),DATA!$K:$K,"<="&DATE($F$3,H$6,H$5),DATA!$N:$N,$Q26) -> 0 | I26: =(COUNTIFS(DATA!$P:$P,"=E",DATA!$K:$K,">="&DATE($F$3,I$6,1),DATA!$K:$K,"<="&DATE($F$3,I$6,I$5),DATA!$N:$N,$Q26)*10)+COUNTIFS(DATA!$P:$P,"=S",DATA!$K:$K,">="&DATE($F$3,I$6,1),DATA!$K:$K,"<="&DATE($F$3,I$6,I$5),DATA!$N:$N,$Q26) -> 0 | J26: =(COUNTIFS(DATA!$P:$P,"=E",DATA!$K:$K,">="&DATE($F$3,J$6,1),DATA!$K:$K,"<="&DATE($F$3,J$6,J$5),DATA!$N:$N,$Q26)*10)+COUNTIFS(DATA!$P:$P,"=S",DATA!$K:$K,">="&DATE($F$3,J$6,1),DATA!$K:$K,"<="&DATE($F$3,J$6,J$5),DATA!$N:$N,$Q26) -> 0 | ... N26: =(COUNTIFS(DATA!$P:$P,"=E",DATA!$K:$K,">="&DATE($F$3,N$6,1),DATA!$K:$K,"<="&DATE($F$3,N$6,N$5),DATA!$N:$N,$Q26)*10)+COUNTIFS(DATA!$P:$P,"=S",DATA!$K:$K,">="&DATE($F$3,N$6,1),DATA!$K:$K,"<="&DATE($F$3,N$6,N$5),DATA!$N:$N,$Q26) -> 0 | O26: =SUM(C26:N26) -> 0 | Q26: ="*"&StaffList!B26&"*" -> *Thuc.dm*
A27: 23 | B27: =VLOOKUP(Q27, StaffList!B:C,2,FALSE) -> Đoàn Minh Đạo | C27: =(COUNTIFS(DATA!$P:$P,"=E",DATA!$K:$K,">="&DATE($F$3,C$6,1),DATA!$K:$K,"<="&DATE($F$3,C$6,C$5),DATA!$N:$N,$Q27)*10)+COUNTIFS(DATA!$P:$P,"=S",DATA!$K:$K,">="&DATE($F$3,C$6,1),DATA!$K:$K,"<="&DATE($F$3,C$6,C$5),DATA!$N:$N,$Q27) -> 0 | D27: =(COUNTIFS(DATA!$P:$P,"=E",DATA!$K:$K,">="&DATE($F$3,D$6,1),DATA!$K:$K,"<="&DATE($F$3,D$6,D$5),DATA!$N:$N,$Q27)*10)+COUNTIFS(DATA!$P:$P,"=S",DATA!$K:$K,">="&DATE($F$3,D$6,1),DATA!$K:$K,"<="&DATE($F$3,D$6,D$5),DATA!$N:$N,$Q27) -> 0 | E27: =(COUNTIFS(DATA!$P:$P,"=E",DATA!$K:$K,">="&DATE($F$3,E$6,1),DATA!$K:$K,"<="&DATE($F$3,E$6,E$5),DATA!$N:$N,$Q27)*10)+COUNTIFS(DATA!$P:$P,"=S",DATA!$K:$K,">="&DATE($F$3,E$6,1),DATA!$K:$K,"<="&DATE($F$3,E$6,E$5),DATA!$N:$N,$Q27) -> 0 | F27: =(COUNTIFS(DATA!$P:$P,"=E",DATA!$K:$K,">="&DATE($F$3,F$6,1),DATA!$K:$K,"<="&DATE($F$3,F$6,F$5),DATA!$N:$N,$Q27)*10)+COUNTIFS(DATA!$P:$P,"=S",DATA!$K:$K,">="&DATE($F$3,F$6,1),DATA!$K:$K,"<="&DATE($F$3,F$6,F$5),DATA!$N:$N,$Q27) -> 0 | G27: =(COUNTIFS(DATA!$P:$P,"=E",DATA!$K:$K,">="&DATE($F$3,G$6,1),DATA!$K:$K,"<="&DATE($F$3,G$6,G$5),DATA!$N:$N,$Q27)*10)+COUNTIFS(DATA!$P:$P,"=S",DATA!$K:$K,">="&DATE($F$3,G$6,1),DATA!$K:$K,"<="&DATE($F$3,G$6,G$5),DATA!$N:$N,$Q27) -> 0 | H27: =(COUNTIFS(DATA!$P:$P,"=E",DATA!$K:$K,">="&DATE($F$3,H$6,1),DATA!$K:$K,"<="&DATE($F$3,H$6,H$5),DATA!$N:$N,$Q27)*10)+COUNTIFS(DATA!$P:$P,"=S",DATA!$K:$K,">="&DATE($F$3,H$6,1),DATA!$K:$K,"<="&DATE($F$3,H$6,H$5),DATA!$N:$N,$Q27) -> 0 | I27: =(COUNTIFS(DATA!$P:$P,"=E",DATA!$K:$K,">="&DATE($F$3,I$6,1),DATA!$K:$K,"<="&DATE($F$3,I$6,I$5),DATA!$N:$N,$Q27)*10)+COUNTIFS(DATA!$P:$P,"=S",DATA!$K:$K,">="&DATE($F$3,I$6,1),DATA!$K:$K,"<="&DATE($F$3,I$6,I$5),DATA!$N:$N,$Q27) -> 0 | J27: =(COUNTIFS(DATA!$P:$P,"=E",DATA!$K:$K,">="&DATE($F$3,J$6,1),DATA!$K:$K,"<="&DATE($F$3,J$6,J$5),DATA!$N:$N,$Q27)*10)+COUNTIFS(DATA!$P:$P,"=S",DATA!$K:$K,">="&DATE($F$3,J$6,1),DATA!$K:$K,"<="&DATE($F$3,J$6,J$5),DATA!$N:$N,$Q27) -> 0 | ... N27: =(COUNTIFS(DATA!$P:$P,"=E",DATA!$K:$K,">="&DATE($F$3,N$6,1),DATA!$K:$K,"<="&DATE($F$3,N$6,N$5),DATA!$N:$N,$Q27)*10)+COUNTIFS(DATA!$P:$P,"=S",DATA!$K:$K,">="&DATE($F$3,N$6,1),DATA!$K:$K,"<="&DATE($F$3,N$6,N$5),DATA!$N:$N,$Q27) -> 0 | O27: =SUM(C27:N27) -> 0 | Q27: ="*"&StaffList!B27&"*" -> *Dao.dm*
A28: 1 | B28: =VLOOKUP(Q28, StaffList!B:C,2,FALSE) -> Lê Hùng Mạnh | C28: =(COUNTIFS(DATA!$P:$P,"=E",DATA!$K:$K,">="&DATE($F$3,C$6,1),DATA!$K:$K,"<="&DATE($F$3,C$6,C$5),DATA!$N:$N,$Q28)*10)+COUNTIFS(DATA!$P:$P,"=S",DATA!$K:$K,">="&DATE($F$3,C$6,1),DATA!$K:$K,"<="&DATE($F$3,C$6,C$5),DATA!$N:$N,$Q28) -> 0 | D28: =(COUNTIFS(DATA!$P:$P,"=E",DATA!$K:$K,">="&DATE($F$3,D$6,1),DATA!$K:$K,"<="&DATE($F$3,D$6,D$5),DATA!$N:$N,$Q28)*10)+COUNTIFS(DATA!$P:$P,"=S",DATA!$K:$K,">="&DATE($F$3,D$6,1),DATA!$K:$K,"<="&DATE($F$3,D$6,D$5),DATA!$N:$N,$Q28) -> 0 | E28: =(COUNTIFS(DATA!$P:$P,"=E",DATA!$K:$K,">="&DATE($F$3,E$6,1),DATA!$K:$K,"<="&DATE($F$3,E$6,E$5),DATA!$N:$N,$Q28)*10)+COUNTIFS(DATA!$P:$P,"=S",DATA!$K:$K,">="&DATE($F$3,E$6,1),DATA!$K:$K,"<="&DATE($F$3,E$6,E$5),DATA!$N:$N,$Q28) -> 0 | F28: =(COUNTIFS(DATA!$P:$P,"=E",DATA!$K:$K,">="&DATE($F$3,F$6,1),DATA!$K:$K,"<="&DATE($F$3,F$6,F$5),DATA!$N:$N,$Q28)*10)+COUNTIFS(DATA!$P:$P,"=S",DATA!$K:$K,">="&DATE($F$3,F$6,1),DATA!$K:$K,"<="&DATE($F$3,F$6,F$5),DATA!$N:$N,$Q28) -> 0 | G28: =(COUNTIFS(DATA!$P:$P,"=E",DATA!$K:$K,">="&DATE($F$3,G$6,1),DATA!$K:$K,"<="&DATE($F$3,G$6,G$5),DATA!$N:$N,$Q28)*10)+COUNTIFS(DATA!$P:$P,"=S",DATA!$K:$K,">="&DATE($F$3,G$6,1),DATA!$K:$K,"<="&DATE($F$3,G$6,G$5),DATA!$N:$N,$Q28) -> 0 | H28: =(COUNTIFS(DATA!$P:$P,"=E",DATA!$K:$K,">="&DATE($F$3,H$6,1),DATA!$K:$K,"<="&DATE($F$3,H$6,H$5),DATA!$N:$N,$Q28)*10)+COUNTIFS(DATA!$P:$P,"=S",DATA!$K:$K,">="&DATE($F$3,H$6,1),DATA!$K:$K,"<="&DATE($F$3,H$6,H$5),DATA!$N:$N,$Q28) -> 0 | I28: =(COUNTIFS(DATA!$P:$P,"=E",DATA!$K:$K,">="&DATE($F$3,I$6,1),DATA!$K:$K,"<="&DATE($F$3,I$6,I$5),DATA!$N:$N,$Q28)*10)+COUNTIFS(DATA!$P:$P,"=S",DATA!$K:$K,">="&DATE($F$3,I$6,1),DATA!$K:$K,"<="&DATE($F$3,I$6,I$5),DATA!$N:$N,$Q28) -> 0 | J28: =(COUNTIFS(DATA!$P:$P,"=E",DATA!$K:$K,">="&DATE($F$3,J$6,1),DATA!$K:$K,"<="&DATE($F$3,J$6,J$5),DATA!$N:$N,$Q28)*10)+COUNTIFS(DATA!$P:$P,"=S",DATA!$K:$K,">="&DATE($F$3,J$6,1),DATA!$K:$K,"<="&DATE($F$3,J$6,J$5),DATA!$N:$N,$Q28) -> 0 | ... N28: =(COUNTIFS(DATA!$P:$P,"=E",DATA!$K:$K,">="&DATE($F$3,N$6,1),DATA!$K:$K,"<="&DATE($F$3,N$6,N$5),DATA!$N:$N,$Q28)*10)+COUNTIFS(DATA!$P:$P,"=S",DATA!$K:$K,">="&DATE($F$3,N$6,1),DATA!$K:$K,"<="&DATE($F$3,N$6,N$5),DATA!$N:$N,$Q28) -> 0 | O28: =SUM(C28:N28) -> 0 | Q28: ="*"&StaffList!B5&"*" -> *Manh.lh*
A29: 18 | B29: =VLOOKUP(Q29, StaffList!B:C,2,FALSE) -> Nguyễn Thế Chân | C29: =(COUNTIFS(DATA!$P:$P,"=E",DATA!$K:$K,">="&DATE($F$3,C$6,1),DATA!$K:$K,"<="&DATE($F$3,C$6,C$5),DATA!$N:$N,$Q29)*10)+COUNTIFS(DATA!$P:$P,"=S",DATA!$K:$K,">="&DATE($F$3,C$6,1),DATA!$K:$K,"<="&DATE($F$3,C$6,C$5),DATA!$N:$N,$Q29) -> 0 | D29: =(COUNTIFS(DATA!$P:$P,"=E",DATA!$K:$K,">="&DATE($F$3,D$6,1),DATA!$K:$K,"<="&DATE($F$3,D$6,D$5),DATA!$N:$N,$Q29)*10)+COUNTIFS(DATA!$P:$P,"=S",DATA!$K:$K,">="&DATE($F$3,D$6,1),DATA!$K:$K,"<="&DATE($F$3,D$6,D$5),DATA!$N:$N,$Q29) -> 0 | E29: =(COUNTIFS(DATA!$P:$P,"=E",DATA!$K:$K,">="&DATE($F$3,E$6,1),DATA!$K:$K,"<="&DATE($F$3,E$6,E$5),DATA!$N:$N,$Q29)*10)+COUNTIFS(DATA!$P:$P,"=S",DATA!$K:$K,">="&DATE($F$3,E$6,1),DATA!$K:$K,"<="&DATE($F$3,E$6,E$5),DATA!$N:$N,$Q29) -> 0 | F29: =(COUNTIFS(DATA!$P:$P,"=E",DATA!$K:$K,">="&DATE($F$3,F$6,1),DATA!$K:$K,"<="&DATE($F$3,F$6,F$5),DATA!$N:$N,$Q29)*10)+COUNTIFS(DATA!$P:$P,"=S",DATA!$K:$K,">="&DATE($F$3,F$6,1),DATA!$K:$K,"<="&DATE($F$3,F$6,F$5),DATA!$N:$N,$Q29) -> 0 | G29: =(COUNTIFS(DATA!$P:$P,"=E",DATA!$K:$K,">="&DATE($F$3,G$6,1),DATA!$K:$K,"<="&DATE($F$3,G$6,G$5),DATA!$N:$N,$Q29)*10)+COUNTIFS(DATA!$P:$P,"=S",DATA!$K:$K,">="&DATE($F$3,G$6,1),DATA!$K:$K,"<="&DATE($F$3,G$6,G$5),DATA!$N:$N,$Q29) -> 0 | H29: =(COUNTIFS(DATA!$P:$P,"=E",DATA!$K:$K,">="&DATE($F$3,H$6,1),DATA!$K:$K,"<="&DATE($F$3,H$6,H$5),DATA!$N:$N,$Q29)*10)+COUNTIFS(DATA!$P:$P,"=S",DATA!$K:$K,">="&DATE($F$3,H$6,1),DATA!$K:$K,"<="&DATE($F$3,H$6,H$5),DATA!$N:$N,$Q29) -> 0 | I29: =(COUNTIFS(DATA!$P:$P,"=E",DATA!$K:$K,">="&DATE($F$3,I$6,1),DATA!$K:$K,"<="&DATE($F$3,I$6,I$5),DATA!$N:$N,$Q29)*10)+COUNTIFS(DATA!$P:$P,"=S",DATA!$K:$K,">="&DATE($F$3,I$6,1),DATA!$K:$K,"<="&DATE($F$3,I$6,I$5),DATA!$N:$N,$Q29) -> 0 | J29: =(COUNTIFS(DATA!$P:$P,"=E",DATA!$K:$K,">="&DATE($F$3,J$6,1),DATA!$K:$K,"<="&DATE($F$3,J$6,J$5),DATA!$N:$N,$Q29)*10)+COUNTIFS(DATA!$P:$P,"=S",DATA!$K:$K,">="&DATE($F$3,J$6,1),DATA!$K:$K,"<="&DATE($F$3,J$6,J$5),DATA!$N:$N,$Q29) -> 0 | ... N29: =(COUNTIFS(DATA!$P:$P,"=E",DATA!$K:$K,">="&DATE($F$3,N$6,1),DATA!$K:$K,"<="&DATE($F$3,N$6,N$5),DATA!$N:$N,$Q29)*10)+COUNTIFS(DATA!$P:$P,"=S",DATA!$K:$K,">="&DATE($F$3,N$6,1),DATA!$K:$K,"<="&DATE($F$3,N$6,N$5),DATA!$N:$N,$Q29) -> 0 | O29: =SUM(C29:N29) -> 0 | Q29: ="*"&StaffList!B22&"*" -> *Chan.nt*
A30: 28 | B30: =VLOOKUP(Q30, StaffList!B:C,2,FALSE) -> Lê Hồng Tuấn | C30: =(COUNTIFS(DATA!$P:$P,"=E",DATA!$K:$K,">="&DATE($F$3,C$6,1),DATA!$K:$K,"<="&DATE($F$3,C$6,C$5),DATA!$N:$N,$Q30)*10)+COUNTIFS(DATA!$P:$P,"=S",DATA!$K:$K,">="&DATE($F$3,C$6,1),DATA!$K:$K,"<="&DATE($F$3,C$6,C$5),DATA!$N:$N,$Q30) -> 0 | D30: =(COUNTIFS(DATA!$P:$P,"=E",DATA!$K:$K,">="&DATE($F$3,D$6,1),DATA!$K:$K,"<="&DATE($F$3,D$6,D$5),DATA!$N:$N,$Q30)*10)+COUNTIFS(DATA!$P:$P,"=S",DATA!$K:$K,">="&DATE($F$3,D$6,1),DATA!$K:$K,"<="&DATE($F$3,D$6,D$5),DATA!$N:$N,$Q30) -> 0 | E30: =(COUNTIFS(DATA!$P:$P,"=E",DATA!$K:$K,">="&DATE($F$3,E$6,1),DATA!$K:$K,"<="&DATE($F$3,E$6,E$5),DATA!$N:$N,$Q30)*10)+COUNTIFS(DATA!$P:$P,"=S",DATA!$K:$K,">="&DATE($F$3,E$6,1),DATA!$K:$K,"<="&DATE($F$3,E$6,E$5),DATA!$N:$N,$Q30) -> 0 | F30: =(COUNTIFS(DATA!$P:$P,"=E",DATA!$K:$K,">="&DATE($F$3,F$6,1),DATA!$K:$K,"<="&DATE($F$3,F$6,F$5),DATA!$N:$N,$Q30)*10)+COUNTIFS(DATA!$P:$P,"=S",DATA!$K:$K,">="&DATE($F$3,F$6,1),DATA!$K:$K,"<="&DATE($F$3,F$6,F$5),DATA!$N:$N,$Q30) -> 0 | G30: =(COUNTIFS(DATA!$P:$P,"=E",DATA!$K:$K,">="&DATE($F$3,G$6,1),DATA!$K:$K,"<="&DATE($F$3,G$6,G$5),DATA!$N:$N,$Q30)*10)+COUNTIFS(DATA!$P:$P,"=S",DATA!$K:$K,">="&DATE($F$3,G$6,1),DATA!$K:$K,"<="&DATE($F$3,G$6,G$5),DATA!$N:$N,$Q30) -> 0 | H30: =(COUNTIFS(DATA!$P:$P,"=E",DATA!$K:$K,">="&DATE($F$3,H$6,1),DATA!$K:$K,"<="&DATE($F$3,H$6,H$5),DATA!$N:$N,$Q30)*10)+COUNTIFS(DATA!$P:$P,"=S",DATA!$K:$K,">="&DATE($F$3,H$6,1),DATA!$K:$K,"<="&DATE($F$3,H$6,H$5),DATA!$N:$N,$Q30) -> 0 | I30: =(COUNTIFS(DATA!$P:$P,"=E",DATA!$K:$K,">="&DATE($F$3,I$6,1),DATA!$K:$K,"<="&DATE($F$3,I$6,I$5),DATA!$N:$N,$Q30)*10)+COUNTIFS(DATA!$P:$P,"=S",DATA!$K:$K,">="&DATE($F$3,I$6,1),DATA!$K:$K,"<="&DATE($F$3,I$6,I$5),DATA!$N:$N,$Q30) -> 0 | J30: =(COUNTIFS(DATA!$P:$P,"=E",DATA!$K:$K,">="&DATE($F$3,J$6,1),DATA!$K:$K,"<="&DATE($F$3,J$6,J$5),DATA!$N:$N,$Q30)*10)+COUNTIFS(DATA!$P:$P,"=S",DATA!$K:$K,">="&DATE($F$3,J$6,1),DATA!$K:$K,"<="&DATE($F$3,J$6,J$5),DATA!$N:$N,$Q30) -> 0 | ... N30: =(COUNTIFS(DATA!$P:$P,"=E",DATA!$K:$K,">="&DATE($F$3,N$6,1),DATA!$K:$K,"<="&DATE($F$3,N$6,N$5),DATA!$N:$N,$Q30)*10)+COUNTIFS(DATA!$P:$P,"=S",DATA!$K:$K,">="&DATE($F$3,N$6,1),DATA!$K:$K,"<="&DATE($F$3,N$6,N$5),DATA!$N:$N,$Q30) -> 0 | O30: =SUM(C30:N30) -> 0 | Q30: ="*"&StaffList!B32&"*" -> *Tuan.lh*
A31: 9 | B31: =VLOOKUP(Q31, StaffList!B:C,2,FALSE) -> Vũ Xuân Phúc | C31: =(COUNTIFS(DATA!$P:$P,"=E",DATA!$K:$K,">="&DATE($F$3,C$6,1),DATA!$K:$K,"<="&DATE($F$3,C$6,C$5),DATA!$N:$N,$Q31)*10)+COUNTIFS(DATA!$P:$P,"=S",DATA!$K:$K,">="&DATE($F$3,C$6,1),DATA!$K:$K,"<="&DATE($F$3,C$6,C$5),DATA!$N:$N,$Q31) -> 0 | D31: =(COUNTIFS(DATA!$P:$P,"=E",DATA!$K:$K,">="&DATE($F$3,D$6,1),DATA!$K:$K,"<="&DATE($F$3,D$6,D$5),DATA!$N:$N,$Q31)*10)+COUNTIFS(DATA!$P:$P,"=S",DATA!$K:$K,">="&DATE($F$3,D$6,1),DATA!$K:$K,"<="&DATE($F$3,D$6,D$5),DATA!$N:$N,$Q31) -> 0 | E31: =(COUNTIFS(DATA!$P:$P,"=E",DATA!$K:$K,">="&DATE($F$3,E$6,1),DATA!$K:$K,"<="&DATE($F$3,E$6,E$5),DATA!$N:$N,$Q31)*10)+COUNTIFS(DATA!$P:$P,"=S",DATA!$K:$K,">="&DATE($F$3,E$6,1),DATA!$K:$K,"<="&DATE($F$3,E$6,E$5),DATA!$N:$N,$Q31) -> 0 | F31: =(COUNTIFS(DATA!$P:$P,"=E",DATA!$K:$K,">="&DATE($F$3,F$6,1),DATA!$K:$K,"<="&DATE($F$3,F$6,F$5),DATA!$N:$N,$Q31)*10)+COUNTIFS(DATA!$P:$P,"=S",DATA!$K:$K,">="&DATE($F$3,F$6,1),DATA!$K:$K,"<="&DATE($F$3,F$6,F$5),DATA!$N:$N,$Q31) -> 0 | G31: =(COUNTIFS(DATA!$P:$P,"=E",DATA!$K:$K,">="&DATE($F$3,G$6,1),DATA!$K:$K,"<="&DATE($F$3,G$6,G$5),DATA!$N:$N,$Q31)*10)+COUNTIFS(DATA!$P:$P,"=S",DATA!$K:$K,">="&DATE($F$3,G$6,1),DATA!$K:$K,"<="&DATE($F$3,G$6,G$5),DATA!$N:$N,$Q31) -> 0 | H31: =(COUNTIFS(DATA!$P:$P,"=E",DATA!$K:$K,">="&DATE($F$3,H$6,1),DATA!$K:$K,"<="&DATE($F$3,H$6,H$5),DATA!$N:$N,$Q31)*10)+COUNTIFS(DATA!$P:$P,"=S",DATA!$K:$K,">="&DATE($F$3,H$6,1),DATA!$K:$K,"<="&DATE($F$3,H$6,H$5),DATA!$N:$N,$Q31) -> 0 | I31: =(COUNTIFS(DATA!$P:$P,"=E",DATA!$K:$K,">="&DATE($F$3,I$6,1),DATA!$K:$K,"<="&DATE($F$3,I$6,I$5),DATA!$N:$N,$Q31)*10)+COUNTIFS(DATA!$P:$P,"=S",DATA!$K:$K,">="&DATE($F$3,I$6,1),DATA!$K:$K,"<="&DATE($F$3,I$6,I$5),DATA!$N:$N,$Q31) -> 0 | J31: =(COUNTIFS(DATA!$P:$P,"=E",DATA!$K:$K,">="&DATE($F$3,J$6,1),DATA!$K:$K,"<="&DATE($F$3,J$6,J$5),DATA!$N:$N,$Q31)*10)+COUNTIFS(DATA!$P:$P,"=S",DATA!$K:$K,">="&DATE($F$3,J$6,1),DATA!$K:$K,"<="&DATE($F$3,J$6,J$5),DATA!$N:$N,$Q31) -> 0 | ... N31: =(COUNTIFS(DATA!$P:$P,"=E",DATA!$K:$K,">="&DATE($F$3,N$6,1),DATA!$K:$K,"<="&DATE($F$3,N$6,N$5),DATA!$N:$N,$Q31)*10)+COUNTIFS(DATA!$P:$P,"=S",DATA!$K:$K,">="&DATE($F$3,N$6,1),DATA!$K:$K,"<="&DATE($F$3,N$6,N$5),DATA!$N:$N,$Q31) -> 0 | O31: =SUM(C31:N31) -> 0 | Q31: ="*"&StaffList!B13&"*" -> *Phuc.vx*
A32: 25 | B32: =VLOOKUP(Q32, StaffList!B:C,2,FALSE) -> Bùi Văn Sỹ | C32: =(COUNTIFS(DATA!$P:$P,"=E",DATA!$K:$K,">="&DATE($F$3,C$6,1),DATA!$K:$K,"<="&DATE($F$3,C$6,C$5),DATA!$N:$N,$Q32)*10)+COUNTIFS(DATA!$P:$P,"=S",DATA!$K:$K,">="&DATE($F$3,C$6,1),DATA!$K:$K,"<="&DATE($F$3,C$6,C$5),DATA!$N:$N,$Q32) -> 0 | D32: =(COUNTIFS(DATA!$P:$P,"=E",DATA!$K:$K,">="&DATE($F$3,D$6,1),DATA!$K:$K,"<="&DATE($F$3,D$6,D$5),DATA!$N:$N,$Q32)*10)+COUNTIFS(DATA!$P:$P,"=S",DATA!$K:$K,">="&DATE($F$3,D$6,1),DATA!$K:$K,"<="&DATE($F$3,D$6,D$5),DATA!$N:$N,$Q32) -> 0 | E32: =(COUNTIFS(DATA!$P:$P,"=E",DATA!$K:$K,">="&DATE($F$3,E$6,1),DATA!$K:$K,"<="&DATE($F$3,E$6,E$5),DATA!$N:$N,$Q32)*10)+COUNTIFS(DATA!$P:$P,"=S",DATA!$K:$K,">="&DATE($F$3,E$6,1),DATA!$K:$K,"<="&DATE($F$3,E$6,E$5),DATA!$N:$N,$Q32) -> 0 | F32: =(COUNTIFS(DATA!$P:$P,"=E",DATA!$K:$K,">="&DATE($F$3,F$6,1),DATA!$K:$K,"<="&DATE($F$3,F$6,F$5),DATA!$N:$N,$Q32)*10)+COUNTIFS(DATA!$P:$P,"=S",DATA!$K:$K,">="&DATE($F$3,F$6,1),DATA!$K:$K,"<="&DATE($F$3,F$6,F$5),DATA!$N:$N,$Q32) -> 0 | G32: =(COUNTIFS(DATA!$P:$P,"=E",DATA!$K:$K,">="&DATE($F$3,G$6,1),DATA!$K:$K,"<="&DATE($F$3,G$6,G$5),DATA!$N:$N,$Q32)*10)+COUNTIFS(DATA!$P:$P,"=S",DATA!$K:$K,">="&DATE($F$3,G$6,1),DATA!$K:$K,"<="&DATE($F$3,G$6,G$5),DATA!$N:$N,$Q32) -> 0 | H32: =(COUNTIFS(DATA!$P:$P,"=E",DATA!$K:$K,">="&DATE($F$3,H$6,1),DATA!$K:$K,"<="&DATE($F$3,H$6,H$5),DATA!$N:$N,$Q32)*10)+COUNTIFS(DATA!$P:$P,"=S",DATA!$K:$K,">="&DATE($F$3,H$6,1),DATA!$K:$K,"<="&DATE($F$3,H$6,H$5),DATA!$N:$N,$Q32) -> 0 | I32: =(COUNTIFS(DATA!$P:$P,"=E",DATA!$K:$K,">="&DATE($F$3,I$6,1),DATA!$K:$K,"<="&DATE($F$3,I$6,I$5),DATA!$N:$N,$Q32)*10)+COUNTIFS(DATA!$P:$P,"=S",DATA!$K:$K,">="&DATE($F$3,I$6,1),DATA!$K:$K,"<="&DATE($F$3,I$6,I$5),DATA!$N:$N,$Q32) -> 0 | J32: =(COUNTIFS(DATA!$P:$P,"=E",DATA!$K:$K,">="&DATE($F$3,J$6,1),DATA!$K:$K,"<="&DATE($F$3,J$6,J$5),DATA!$N:$N,$Q32)*10)+COUNTIFS(DATA!$P:$P,"=S",DATA!$K:$K,">="&DATE($F$3,J$6,1),DATA!$K:$K,"<="&DATE($F$3,J$6,J$5),DATA!$N:$N,$Q32) -> 0 | ... N32: =(COUNTIFS(DATA!$P:$P,"=E",DATA!$K:$K,">="&DATE($F$3,N$6,1),DATA!$K:$K,"<="&DATE($F$3,N$6,N$5),DATA!$N:$N,$Q32)*10)+COUNTIFS(DATA!$P:$P,"=S",DATA!$K:$K,">="&DATE($F$3,N$6,1),DATA!$K:$K,"<="&DATE($F$3,N$6,N$5),DATA!$N:$N,$Q32) -> 0 | O32: =SUM(C32:N32) -> 0 | Q32: ="*"&StaffList!B29&"*" -> *Sy.bv*
A33: 29 | B33: =VLOOKUP(Q33, StaffList!B:C,2,FALSE) -> Nguyễn Công Hoàng | C33: =(COUNTIFS(DATA!$P:$P,"=E",DATA!$K:$K,">="&DATE($F$3,C$6,1),DATA!$K:$K,"<="&DATE($F$3,C$6,C$5),DATA!$N:$N,$Q33)*10)+COUNTIFS(DATA!$P:$P,"=S",DATA!$K:$K,">="&DATE($F$3,C$6,1),DATA!$K:$K,"<="&DATE($F$3,C$6,C$5),DATA!$N:$N,$Q33) -> 0 | D33: =(COUNTIFS(DATA!$P:$P,"=E",DATA!$K:$K,">="&DATE($F$3,D$6,1),DATA!$K:$K,"<="&DATE($F$3,D$6,D$5),DATA!$N:$N,$Q33)*10)+COUNTIFS(DATA!$P:$P,"=S",DATA!$K:$K,">="&DATE($F$3,D$6,1),DATA!$K:$K,"<="&DATE($F$3,D$6,D$5),DATA!$N:$N,$Q33) -> 0 | E33: =(COUNTIFS(DATA!$P:$P,"=E",DATA!$K:$K,">="&DATE($F$3,E$6,1),DATA!$K:$K,"<="&DATE($F$3,E$6,E$5),DATA!$N:$N,$Q33)*10)+COUNTIFS(DATA!$P:$P,"=S",DATA!$K:$K,">="&DATE($F$3,E$6,1),DATA!$K:$K,"<="&DATE($F$3,E$6,E$5),DATA!$N:$N,$Q33) -> 0 | F33: =(COUNTIFS(DATA!$P:$P,"=E",DATA!$K:$K,">="&DATE($F$3,F$6,1),DATA!$K:$K,"<="&DATE($F$3,F$6,F$5),DATA!$N:$N,$Q33)*10)+COUNTIFS(DATA!$P:$P,"=S",DATA!$K:$K,">="&DATE($F$3,F$6,1),DATA!$K:$K,"<="&DATE($F$3,F$6,F$5),DATA!$N:$N,$Q33) -> 0 | G33: =(COUNTIFS(DATA!$P:$P,"=E",DATA!$K:$K,">="&DATE($F$3,G$6,1),DATA!$K:$K,"<="&DATE($F$3,G$6,G$5),DATA!$N:$N,$Q33)*10)+COUNTIFS(DATA!$P:$P,"=S",DATA!$K:$K,">="&DATE($F$3,G$6,1),DATA!$K:$K,"<="&DATE($F$3,G$6,G$5),DATA!$N:$N,$Q33) -> 0 | H33: =(COUNTIFS(DATA!$P:$P,"=E",DATA!$K:$K,">="&DATE($F$3,H$6,1),DATA!$K:$K,"<="&DATE($F$3,H$6,H$5),DATA!$N:$N,$Q33)*10)+COUNTIFS(DATA!$P:$P,"=S",DATA!$K:$K,">="&DATE($F$3,H$6,1),DATA!$K:$K,"<="&DATE($F$3,H$6,H$5),DATA!$N:$N,$Q33) -> 0 | I33: =(COUNTIFS(DATA!$P:$P,"=E",DATA!$K:$K,">="&DATE($F$3,I$6,1),DATA!$K:$K,"<="&DATE($F$3,I$6,I$5),DATA!$N:$N,$Q33)*10)+COUNTIFS(DATA!$P:$P,"=S",DATA!$K:$K,">="&DATE($F$3,I$6,1),DATA!$K:$K,"<="&DATE($F$3,I$6,I$5),DATA!$N:$N,$Q33) -> 0 | J33: =(COUNTIFS(DATA!$P:$P,"=E",DATA!$K:$K,">="&DATE($F$3,J$6,1),DATA!$K:$K,"<="&DATE($F$3,J$6,J$5),DATA!$N:$N,$Q33)*10)+COUNTIFS(DATA!$P:$P,"=S",DATA!$K:$K,">="&DATE($F$3,J$6,1),DATA!$K:$K,"<="&DATE($F$3,J$6,J$5),DATA!$N:$N,$Q33) -> 0 | ... N33: =(COUNTIFS(DATA!$P:$P,"=E",DATA!$K:$K,">="&DATE($F$3,N$6,1),DATA!$K:$K,"<="&DATE($F$3,N$6,N$5),DATA!$N:$N,$Q33)*10)+COUNTIFS(DATA!$P:$P,"=S",DATA!$K:$K,">="&DATE($F$3,N$6,1),DATA!$K:$K,"<="&DATE($F$3,N$6,N$5),DATA!$N:$N,$Q33) -> 0 | O33: =SUM(C33:N33) -> 0 | Q33: ="*"&StaffList!B33&"*" -> *Hoang.nc*
A34: 26 | B34: =VLOOKUP(Q34, StaffList!B:C,2,FALSE) -> Nguyễn Tiến Đạt | C34: =(COUNTIFS(DATA!$P:$P,"=E",DATA!$K:$K,">="&DATE($F$3,C$6,1),DATA!$K:$K,"<="&DATE($F$3,C$6,C$5),DATA!$N:$N,$Q34)*10)+COUNTIFS(DATA!$P:$P,"=S",DATA!$K:$K,">="&DATE($F$3,C$6,1),DATA!$K:$K,"<="&DATE($F$3,C$6,C$5),DATA!$N:$N,$Q34) -> 0 | D34: =(COUNTIFS(DATA!$P:$P,"=E",DATA!$K:$K,">="&DATE($F$3,D$6,1),DATA!$K:$K,"<="&DATE($F$3,D$6,D$5),DATA!$N:$N,$Q34)*10)+COUNTIFS(DATA!$P:$P,"=S",DATA!$K:$K,">="&DATE($F$3,D$6,1),DATA!$K:$K,"<="&DATE($F$3,D$6,D$5),DATA!$N:$N,$Q34) -> 0 | E34: =(COUNTIFS(DATA!$P:$P,"=E",DATA!$K:$K,">="&DATE($F$3,E$6,1),DATA!$K:$K,"<="&DATE($F$3,E$6,E$5),DATA!$N:$N,$Q34)*10)+COUNTIFS(DATA!$P:$P,"=S",DATA!$K:$K,">="&DATE($F$3,E$6,1),DATA!$K:$K,"<="&DATE($F$3,E$6,E$5),DATA!$N:$N,$Q34) -> 0 | F34: =(COUNTIFS(DATA!$P:$P,"=E",DATA!$K:$K,">="&DATE($F$3,F$6,1),DATA!$K:$K,"<="&DATE($F$3,F$6,F$5),DATA!$N:$N,$Q34)*10)+COUNTIFS(DATA!$P:$P,"=S",DATA!$K:$K,">="&DATE($F$3,F$6,1),DATA!$K:$K,"<="&DATE($F$3,F$6,F$5),DATA!$N:$N,$Q34) -> 0 | G34: =(COUNTIFS(DATA!$P:$P,"=E",DATA!$K:$K,">="&DATE($F$3,G$6,1),DATA!$K:$K,"<="&DATE($F$3,G$6,G$5),DATA!$N:$N,$Q34)*10)+COUNTIFS(DATA!$P:$P,"=S",DATA!$K:$K,">="&DATE($F$3,G$6,1),DATA!$K:$K,"<="&DATE($F$3,G$6,G$5),DATA!$N:$N,$Q34) -> 0 | H34: =(COUNTIFS(DATA!$P:$P,"=E",DATA!$K:$K,">="&DATE($F$3,H$6,1),DATA!$K:$K,"<="&DATE($F$3,H$6,H$5),DATA!$N:$N,$Q34)*10)+COUNTIFS(DATA!$P:$P,"=S",DATA!$K:$K,">="&DATE($F$3,H$6,1),DATA!$K:$K,"<="&DATE($F$3,H$6,H$5),DATA!$N:$N,$Q34) -> 0 | I34: =(COUNTIFS(DATA!$P:$P,"=E",DATA!$K:$K,">="&DATE($F$3,I$6,1),DATA!$K:$K,"<="&DATE($F$3,I$6,I$5),DATA!$N:$N,$Q34)*10)+COUNTIFS(DATA!$P:$P,"=S",DATA!$K:$K,">="&DATE($F$3,I$6,1),DATA!$K:$K,"<="&DATE($F$3,I$6,I$5),DATA!$N:$N,$Q34) -> 0 | J34: =(COUNTIFS(DATA!$P:$P,"=E",DATA!$K:$K,">="&DATE($F$3,J$6,1),DATA!$K:$K,"<="&DATE($F$3,J$6,J$5),DATA!$N:$N,$Q34)*10)+COUNTIFS(DATA!$P:$P,"=S",DATA!$K:$K,">="&DATE($F$3,J$6,1),DATA!$K:$K,"<="&DATE($F$3,J$6,J$5),DATA!$N:$N,$Q34) -> 0 | ... N34: =(COUNTIFS(DATA!$P:$P,"=E",DATA!$K:$K,">="&DATE($F$3,N$6,1),DATA!$K:$K,"<="&DATE($F$3,N$6,N$5),DATA!$N:$N,$Q34)*10)+COUNTIFS(DATA!$P:$P,"=S",DATA!$K:$K,">="&DATE($F$3,N$6,1),DATA!$K:$K,"<="&DATE($F$3,N$6,N$5),DATA!$N:$N,$Q34) -> 0 | O34: =SUM(C34:N34) -> 0 | Q34: ="*"&StaffList!B30&"*" -> *Dat.nt*
A35: 15 | B35: =VLOOKUP(Q35, StaffList!B:C,2,FALSE) -> Bùi Ngọc Linh | C35: =(COUNTIFS(DATA!$P:$P,"=E",DATA!$K:$K,">="&DATE($F$3,C$6,1),DATA!$K:$K,"<="&DATE($F$3,C$6,C$5),DATA!$N:$N,$Q35)*10)+COUNTIFS(DATA!$P:$P,"=S",DATA!$K:$K,">="&DATE($F$3,C$6,1),DATA!$K:$K,"<="&DATE($F$3,C$6,C$5),DATA!$N:$N,$Q35) -> 0 | D35: =(COUNTIFS(DATA!$P:$P,"=E",DATA!$K:$K,">="&DATE($F$3,D$6,1),DATA!$K:$K,"<="&DATE($F$3,D$6,D$5),DATA!$N:$N,$Q35)*10)+COUNTIFS(DATA!$P:$P,"=S",DATA!$K:$K,">="&DATE($F$3,D$6,1),DATA!$K:$K,"<="&DATE($F$3,D$6,D$5),DATA!$N:$N,$Q35) -> 0 | E35: =(COUNTIFS(DATA!$P:$P,"=E",DATA!$K:$K,">="&DATE($F$3,E$6,1),DATA!$K:$K,"<="&DATE($F$3,E$6,E$5),DATA!$N:$N,$Q35)*10)+COUNTIFS(DATA!$P:$P,"=S",DATA!$K:$K,">="&DATE($F$3,E$6,1),DATA!$K:$K,"<="&DATE($F$3,E$6,E$5),DATA!$N:$N,$Q35) -> 0 | F35: =(COUNTIFS(DATA!$P:$P,"=E",DATA!$K:$K,">="&DATE($F$3,F$6,1),DATA!$K:$K,"<="&DATE($F$3,F$6,F$5),DATA!$N:$N,$Q35)*10)+COUNTIFS(DATA!$P:$P,"=S",DATA!$K:$K,">="&DATE($F$3,F$6,1),DATA!$K:$K,"<="&DATE($F$3,F$6,F$5),DATA!$N:$N,$Q35) -> 0 | G35: =(COUNTIFS(DATA!$P:$P,"=E",DATA!$K:$K,">="&DATE($F$3,G$6,1),DATA!$K:$K,"<="&DATE($F$3,G$6,G$5),DATA!$N:$N,$Q35)*10)+COUNTIFS(DATA!$P:$P,"=S",DATA!$K:$K,">="&DATE($F$3,G$6,1),DATA!$K:$K,"<="&DATE($F$3,G$6,G$5),DATA!$N:$N,$Q35) -> 0 | H35: =(COUNTIFS(DATA!$P:$P,"=E",DATA!$K:$K,">="&DATE($F$3,H$6,1),DATA!$K:$K,"<="&DATE($F$3,H$6,H$5),DATA!$N:$N,$Q35)*10)+COUNTIFS(DATA!$P:$P,"=S",DATA!$K:$K,">="&DATE($F$3,H$6,1),DATA!$K:$K,"<="&DATE($F$3,H$6,H$5),DATA!$N:$N,$Q35) -> 0 | I35: =(COUNTIFS(DATA!$P:$P,"=E",DATA!$K:$K,">="&DATE($F$3,I$6,1),DATA!$K:$K,"<="&DATE($F$3,I$6,I$5),DATA!$N:$N,$Q35)*10)+COUNTIFS(DATA!$P:$P,"=S",DATA!$K:$K,">="&DATE($F$3,I$6,1),DATA!$K:$K,"<="&DATE($F$3,I$6,I$5),DATA!$N:$N,$Q35) -> 0 | J35: =(COUNTIFS(DATA!$P:$P,"=E",DATA!$K:$K,">="&DATE($F$3,J$6,1),DATA!$K:$K,"<="&DATE($F$3,J$6,J$5),DATA!$N:$N,$Q35)*10)+COUNTIFS(DATA!$P:$P,"=S",DATA!$K:$K,">="&DATE($F$3,J$6,1),DATA!$K:$K,"<="&DATE($F$3,J$6,J$5),DATA!$N:$N,$Q35) -> 0 | ... N35: =(COUNTIFS(DATA!$P:$P,"=E",DATA!$K:$K,">="&DATE($F$3,N$6,1),DATA!$K:$K,"<="&DATE($F$3,N$6,N$5),DATA!$N:$N,$Q35)*10)+COUNTIFS(DATA!$P:$P,"=S",DATA!$K:$K,">="&DATE($F$3,N$6,1),DATA!$K:$K,"<="&DATE($F$3,N$6,N$5),DATA!$N:$N,$Q35) -> 0 | O35: =SUM(C35:N35) -> 0 | Q35: ="*"&StaffList!B19&"*" -> *Linh.bn*
A36: 20 | B36: =VLOOKUP(Q36, StaffList!B:C,2,FALSE) -> Nguyễn Như Khương | C36: =(COUNTIFS(DATA!$P:$P,"=E",DATA!$K:$K,">="&DATE($F$3,C$6,1),DATA!$K:$K,"<="&DATE($F$3,C$6,C$5),DATA!$N:$N,$Q36)*10)+COUNTIFS(DATA!$P:$P,"=S",DATA!$K:$K,">="&DATE($F$3,C$6,1),DATA!$K:$K,"<="&DATE($F$3,C$6,C$5),DATA!$N:$N,$Q36) -> 0 | D36: =(COUNTIFS(DATA!$P:$P,"=E",DATA!$K:$K,">="&DATE($F$3,D$6,1),DATA!$K:$K,"<="&DATE($F$3,D$6,D$5),DATA!$N:$N,$Q36)*10)+COUNTIFS(DATA!$P:$P,"=S",DATA!$K:$K,">="&DATE($F$3,D$6,1),DATA!$K:$K,"<="&DATE($F$3,D$6,D$5),DATA!$N:$N,$Q36) -> 0 | E36: =(COUNTIFS(DATA!$P:$P,"=E",DATA!$K:$K,">="&DATE($F$3,E$6,1),DATA!$K:$K,"<="&DATE($F$3,E$6,E$5),DATA!$N:$N,$Q36)*10)+COUNTIFS(DATA!$P:$P,"=S",DATA!$K:$K,">="&DATE($F$3,E$6,1),DATA!$K:$K,"<="&DATE($F$3,E$6,E$5),DATA!$N:$N,$Q36) -> 0 | F36: =(COUNTIFS(DATA!$P:$P,"=E",DATA!$K:$K,">="&DATE($F$3,F$6,1),DATA!$K:$K,"<="&DATE($F$3,F$6,F$5),DATA!$N:$N,$Q36)*10)+COUNTIFS(DATA!$P:$P,"=S",DATA!$K:$K,">="&DATE($F$3,F$6,1),DATA!$K:$K,"<="&DATE($F$3,F$6,F$5),DATA!$N:$N,$Q36) -> 0 | G36: =(COUNTIFS(DATA!$P:$P,"=E",DATA!$K:$K,">="&DATE($F$3,G$6,1),DATA!$K:$K,"<="&DATE($F$3,G$6,G$5),DATA!$N:$N,$Q36)*10)+COUNTIFS(DATA!$P:$P,"=S",DATA!$K:$K,">="&DATE($F$3,G$6,1),DATA!$K:$K,"<="&DATE($F$3,G$6,G$5),DATA!$N:$N,$Q36) -> 0 | H36: =(COUNTIFS(DATA!$P:$P,"=E",DATA!$K:$K,">="&DATE($F$3,H$6,1),DATA!$K:$K,"<="&DATE($F$3,H$6,H$5),DATA!$N:$N,$Q36)*10)+COUNTIFS(DATA!$P:$P,"=S",DATA!$K:$K,">="&DATE($F$3,H$6,1),DATA!$K:$K,"<="&DATE($F$3,H$6,H$5),DATA!$N:$N,$Q36) -> 0 | I36: =(COUNTIFS(DATA!$P:$P,"=E",DATA!$K:$K,">="&DATE($F$3,I$6,1),DATA!$K:$K,"<="&DATE($F$3,I$6,I$5),DATA!$N:$N,$Q36)*10)+COUNTIFS(DATA!$P:$P,"=S",DATA!$K:$K,">="&DATE($F$3,I$6,1),DATA!$K:$K,"<="&DATE($F$3,I$6,I$5),DATA!$N:$N,$Q36) -> 0 | J36: =(COUNTIFS(DATA!$P:$P,"=E",DATA!$K:$K,">="&DATE($F$3,J$6,1),DATA!$K:$K,"<="&DATE($F$3,J$6,J$5),DATA!$N:$N,$Q36)*10)+COUNTIFS(DATA!$P:$P,"=S",DATA!$K:$K,">="&DATE($F$3,J$6,1),DATA!$K:$K,"<="&DATE($F$3,J$6,J$5),DATA!$N:$N,$Q36) -> 0 | ... N36: =(COUNTIFS(DATA!$P:$P,"=E",DATA!$K:$K,">="&DATE($F$3,N$6,1),DATA!$K:$K,"<="&DATE($F$3,N$6,N$5),DATA!$N:$N,$Q36)*10)+COUNTIFS(DATA!$P:$P,"=S",DATA!$K:$K,">="&DATE($F$3,N$6,1),DATA!$K:$K,"<="&DATE($F$3,N$6,N$5),DATA!$N:$N,$Q36) -> 0 | O36: =SUM(C36:N36) -> 0 | Q36: ="*"&StaffList!B24&"*" -> *Khuong.nn*
B37: TOTAL | C37: =SUM(C8:C36) -> 0 | D37: =SUM(D8:D36) -> 0 | E37: =SUM(E8:E36) -> 0 | F37: =SUM(F8:F36) -> 0 | G37: =SUM(G8:G36) -> 0 | H37: =SUM(H8:H36) -> 0 | I37: =SUM(I8:I36) -> 0 | J37: =SUM(J8:J36) -> 0 | ... N37: =SUM(N8:N36) -> 0

Sheet Monthly Staff Satisfaction
C1: CHỈ SỐ HÀI LÒNG CỦA KHÁCH HÀNG ĐỐI VỚI NHÂN VIÊN
A2: SPS SERVICES.,JSC | C2: ASSESSMENT OF CUSTOMER SATISFACTION FOR EACH EMPLOYEES
B3: Từ ngày / From date: | C3: 45597 | D3: Tới / To: | E3: =EOMONTH(C3,0) -> 45626 | I3: Reported by: Hang.ntt
A4: Ghi chú: Số báo cáo một dịch vụ bằng tổng số người thực tế đi làm dịch vụ đó. Báo cáo không bao gồm thực tập sinh hoặc thầu phụ
A6: TT | B6: Tên nhân viên | C6: Tổng số báo cáo có phản hồi | D6: Rất hài lòng | E6: Hài lòng | F6: Chấp nhận | G6: Không hài lòng | H6: Tỉ lệ hài lòng | I6: Điểm để so sánh | K6: Ký kiệu trung gian cho công thức tự động
A7: No | B7: Full Name | C7: Total report wt feedback | D7: Exceeded satisfy (E) | E7: Satisfied (S) | F7: Acceptable (A) | G7: Dissatisfied (D) | H7: Satisfaction rate (%) | I7: Rating (Ex10+Sx1) | K7: Name for calculator
A8: 27 | B8: =VLOOKUP(K8, StaffList!B:C,2,FALSE) -> Mai Văn Tuấn | C8: =SUM(D8:G8) -> 0 | D8: =COUNTIFS(DATA!$P:$P,"=E", DATA!$N:$N,$K:$K,DATA!$K:$K,">="&$C$3,DATA!$K:$K,"<="&$E$3) -> 0 | E8: =COUNTIFS(DATA!$P:$P,"=S", DATA!$N:$N,$K:$K,DATA!$K:$K,">="&$C$3,DATA!$K:$K,"<="&$E$3) -> 0 | F8: =COUNTIFS(DATA!$P:$P,"=A", DATA!$N:$N,$K:$K,DATA!$K:$K,">="&$C$3,DATA!$K:$K,"<="&$E$3) -> 0 | G8: =COUNTIFS(DATA!$P:$P,"=D", DATA!$N:$N,$K:$K,DATA!$K:$K,">="&$C$3,DATA!$K:$K,"<="&$E$3) -> 0 | H8: =IF(SUM(D8:G8)=0,"-",SUM(D8:E8)/SUM(D8:G8)) -> - | I8: =D8*10+E8 -> 0 | K8: ="*"&StaffList!B31&"*" -> *Tuan.mv*
A9: 13 | B9: =VLOOKUP(K9, StaffList!B:C,2,FALSE) -> Nguyễn Văn Đức | C9: =SUM(D9:G9) -> 0 | D9: =COUNTIFS(DATA!$P:$P,"=E", DATA!$N:$N,$K:$K,DATA!$K:$K,">="&$C$3,DATA!$K:$K,"<="&$E$3) -> 0 | E9: =COUNTIFS(DATA!$P:$P,"=S", DATA!$N:$N,$K:$K,DATA!$K:$K,">="&$C$3,DATA!$K:$K,"<="&$E$3) -> 0 | F9: =COUNTIFS(DATA!$P:$P,"=A", DATA!$N:$N,$K:$K,DATA!$K:$K,">="&$C$3,DATA!$K:$K,"<="&$E$3) -> 0 | G9: =COUNTIFS(DATA!$P:$P,"=D", DATA!$N:$N,$K:$K,DATA!$K:$K,">="&$C$3,DATA!$K:$K,"<="&$E$3) -> 0 | H9: =IF(SUM(D9:G9)=0,"-",SUM(D9:E9)/SUM(D9:G9)) -> - | I9: =D9*10+E9 -> 0 | K9: ="*"&StaffList!B17&"*" -> *Duc.nv*
A10: 28 | B10: =VLOOKUP(K10, StaffList!B:C,2,FALSE) -> Lê Hồng Tuấn | C10: =SUM(D10:G10) -> 0 | D10: =COUNTIFS(DATA!$P:$P,"=E", DATA!$N:$N,$K:$K,DATA!$K:$K,">="&$C$3,DATA!$K:$K,"<="&$E$3) -> 0 | E10: =COUNTIFS(DATA!$P:$P,"=S", DATA!$N:$N,$K:$K,DATA!$K:$K,">="&$C$3,DATA!$K:$K,"<="&$E$3) -> 0 | F10: =COUNTIFS(DATA!$P:$P,"=A", DATA!$N:$N,$K:$K,DATA!$K:$K,">="&$C$3,DATA!$K:$K,"<="&$E$3) -> 0 | G10: =COUNTIFS(DATA!$P:$P,"=D", DATA!$N:$N,$K:$K,DATA!$K:$K,">="&$C$3,DATA!$K:$K,"<="&$E$3) -> 0 | H10: =IF(SUM(D10:G10)=0,"-",SUM(D10:E10)/SUM(D10:G10)) -> - | I10: =D10*10+E10 -> 0 | K10: ="*"&StaffList!B32&"*" -> *Tuan.lh*
A11: 10 | B11: =VLOOKUP(K11, StaffList!B:C,2,FALSE) -> Hoàng Việt Thao | C11: =SUM(D11:G11) -> 0 | D11: =COUNTIFS(DATA!$P:$P,"=E", DATA!$N:$N,$K:$K,DATA!$K:$K,">="&$C$3,DATA!$K:$K,"<="&$E$3) -> 0 | E11: =COUNTIFS(DATA!$P:$P,"=S", DATA!$N:$N,$K:$K,DATA!$K:$K,">="&$C$3,DATA!$K:$K,"<="&$E$3) -> 0 | F11: =COUNTIFS(DATA!$P:$P,"=A", DATA!$N:$N,$K:$K,DATA!$K:$K,">="&$C$3,DATA!$K:$K,"<="&$E$3) -> 0 | G11: =COUNTIFS(DATA!$P:$P,"=D", DATA!$N:$N,$K:$K,DATA!$K:$K,">="&$C$3,DATA!$K:$K,"<="&$E$3) -> 0 | H11: =IF(SUM(D11:G11)=0,"-",SUM(D11:E11)/SUM(D11:G11)) -> - | I11: =D11*10+E11 -> 0 | K11: ="*"&StaffList!B14&"*" -> *Thao.hv*
A12: 29 | B12: =VLOOKUP(K12, StaffList!B:C,2,FALSE) -> Nguyễn Công Hoàng | C12: =SUM(D12:G12) -> 0 | D12: =COUNTIFS(DATA!$P:$P,"=E", DATA!$N:$N,$K:$K,DATA!$K:$K,">="&$C$3,DATA!$K:$K,"<="&$E$3) -> 0 | E12: =COUNTIFS(DATA!$P:$P,"=S", DATA!$N:$N,$K:$K,DATA!$K:$K,">="&$C$3,DATA!$K:$K,"<="&$E$3) -> 0 | F12: =COUNTIFS(DATA!$P:$P,"=A", DATA!$N:$N,$K:$K,DATA!$K:$K,">="&$C$3,DATA!$K:$K,"<="&$E$3) -> 0 | G12: =COUNTIFS(DATA!$P:$P,"=D", DATA!$N:$N,$K:$K,DATA!$K:$K,">="&$C$3,DATA!$K:$K,"<="&$E$3) -> 0 | H12: =IF(SUM(D12:G12)=0,"-",SUM(D12:E12)/SUM(D12:G12)) -> - | I12: =D12*10+E12 -> 0 | K12: ="*"&StaffList!B33&"*" -> *Hoang.nc*
A13: 8 | B13: =VLOOKUP(K13, StaffList!B:C,2,FALSE) -> Chu Tiến Dũng | C13: =SUM(D13:G13) -> 0 | D13: =COUNTIFS(DATA!$P:$P,"=E", DATA!$N:$N,$K:$K,DATA!$K:$K,">="&$C$3,DATA!$K:$K,"<="&$E$3) -> 0 | E13: =COUNTIFS(DATA!$P:$P,"=S", DATA!$N:$N,$K:$K,DATA!$K:$K,">="&$C$3,DATA!$K:$K,"<="&$E$3) -> 0 | F13: =COUNTIFS(DATA!$P:$P,"=A", DATA!$N:$N,$K:$K,DATA!$K:$K,">="&$C$3,DATA!$K:$K,"<="&$E$3) -> 0 | G13: =COUNTIFS(DATA!$P:$P,"=D", DATA!$N:$N,$K:$K,DATA!$K:$K,">="&$C$3,DATA!$K:$K,"<="&$E$3) -> 0 | H13: =IF(SUM(D13:G13)=0,"-",SUM(D13:E13)/SUM(D13:G13)) -> - | I13: =D13*10+E13 -> 0 | K13: ="*"&StaffList!B12&"*" -> *Dung.ct*
A14: 22 | B14: =VLOOKUP(K14, StaffList!B:C,2,FALSE) -> Đoàn Mạnh Thức | C14: =SUM(D14:G14) -> 0 | D14: =COUNTIFS(DATA!$P:$P,"=E", DATA!$N:$N,$K:$K,DATA!$K:$K,">="&$C$3,DATA!$K:$K,"<="&$E$3) -> 0 | E14: =COUNTIFS(DATA!$P:$P,"=S", DATA!$N:$N,$K:$K,DATA!$K:$K,">="&$C$3,DATA!$K:$K,"<="&$E$3) -> 0 | F14: =COUNTIFS(DATA!$P:$P,"=A", DATA!$N:$N,$K:$K,DATA!$K:$K,">="&$C$3,DATA!$K:$K,"<="&$E$3) -> 0 | G14: =COUNTIFS(DATA!$P:$P,"=D", DATA!$N:$N,$K:$K,DATA!$K:$K,">="&$C$3,DATA!$K:$K,"<="&$E$3) -> 0 | H14: =IF(SUM(D14:G14)=0,"-",SUM(D14:E14)/SUM(D14:G14)) -> - | I14: =D14*10+E14 -> 0 | K14: ="*"&StaffList!B26&"*" -> *Thuc.dm*
A15: 1 | B15: =VLOOKUP(K15, StaffList!B:C,2,FALSE) -> Lê Hùng Mạnh | C15: =SUM(D15:G15) -> 0 | D15: =COUNTIFS(DATA!$P:$P,"=E", DATA!$N:$N,$K:$K,DATA!$K:$K,">="&$C$3,DATA!$K:$K,"<="&$E$3) -> 0 | E15: =COUNTIFS(DATA!$P:$P,"=S", DATA!$N:$N,$K:$K,DATA!$K:$K,">="&$C$3,DATA!$K:$K,"<="&$E$3) -> 0 | F15: =COUNTIFS(DATA!$P:$P,"=A", DATA!$N:$N,$K:$K,DATA!$K:$K,">="&$C$3,DATA!$K:$K,"<="&$E$3) -> 0 | G15: =COUNTIFS(DATA!$P:$P,"=D", DATA!$N:$N,$K:$K,DATA!$K:$K,">="&$C$3,DATA!$K:$K,"<="&$E$3) -> 0 | H15: =IF(SUM(D15:G15)=0,"-",SUM(D15:E15)/SUM(D15:G15)) -> - | I15: =D15*10+E15 -> 0 | K15: ="*"&StaffList!B5&"*" -> *Manh.lh*
A16: 16 | B16: =VLOOKUP(K16, StaffList!B:C,2,FALSE) -> Lê Minh Đức | C16: =SUM(D16:G16) -> 0 | D16: =COUNTIFS(DATA!$P:$P,"=E", DATA!$N:$N,$K:$K,DATA!$K:$K,">="&$C$3,DATA!$K:$K,"<="&$E$3) -> 0 | E16: =COUNTIFS(DATA!$P:$P,"=S", DATA!$N:$N,$K:$K,DATA!$K:$K,">="&$C$3,DATA!$K:$K,"<="&$E$3) -> 0 | F16: =COUNTIFS(DATA!$P:$P,"=A", DATA!$N:$N,$K:$K,DATA!$K:$K,">="&$C$3,DATA!$K:$K,"<="&$E$3) -> 0 | G16: =COUNTIFS(DATA!$P:$P,"=D", DATA!$N:$N,$K:$K,DATA!$K:$K,">="&$C$3,DATA!$K:$K,"<="&$E$3) -> 0 | H16: =IF(SUM(D16:G16)=0,"-",SUM(D16:E16)/SUM(D16:G16)) -> - | I16: =D16*10+E16 -> 0 | K16: ="*"&StaffList!B20&"*" -> *Duc.lm*
A17: 6 | B17: =VLOOKUP(K17, StaffList!B:C,2,FALSE) -> Chu Trọng Thao | C17: =SUM(D17:G17) -> 0 | D17: =COUNTIFS(DATA!$P:$P,"=E", DATA!$N:$N,$K:$K,DATA!$K:$K,">="&$C$3,DATA!$K:$K,"<="&$E$3) -> 0 | E17: =COUNTIFS(DATA!$P:$P,"=S", DATA!$N:$N,$K:$K,DATA!$K:$K,">="&$C$3,DATA!$K:$K,"<="&$E$3) -> 0 | F17: =COUNTIFS(DATA!$P:$P,"=A", DATA!$N:$N,$K:$K,DATA!$K:$K,">="&$C$3,DATA!$K:$K,"<="&$E$3) -> 0 | G17: =COUNTIFS(DATA!$P:$P,"=D", DATA!$N:$N,$K:$K,DATA!$K:$K,">="&$C$3,DATA!$K:$K,"<="&$E$3) -> 0 | H17: =IF(SUM(D17:G17)=0,"-",SUM(D17:E17)/SUM(D17:G17)) -> - | I17: =D17*10+E17 -> 0 | K17: ="*"&StaffList!B10&"*" -> *Thao.ct*
A18: 3 | B18: =VLOOKUP(K18, StaffList!B:C,2,FALSE) -> Nguyễn Mạnh Hùng | C18: =SUM(D18:G18) -> 0 | D18: =COUNTIFS(DATA!$P:$P,"=E", DATA!$N:$N,$K:$K,DATA!$K:$K,">="&$C$3,DATA!$K:$K,"<="&$E$3) -> 0 | E18: =COUNTIFS(DATA!$P:$P,"=S", DATA!$N:$N,$K:$K,DATA!$K:$K,">="&$C$3,DATA!$K:$K,"<="&$E$3) -> 0 | F18: =COUNTIFS(DATA!$P:$P,"=A", DATA!$N:$N,$K:$K,DATA!$K:$K,">="&$C$3,DATA!$K:$K,"<="&$E$3) -> 0 | G18: =COUNTIFS(DATA!$P:$P,"=D", DATA!$N:$N,$K:$K,DATA!$K:$K,">="&$C$3,DATA!$K:$K,"<="&$E$3) -> 0 | H18: =IF(SUM(D18:G18)=0,"-",SUM(D18:E18)/SUM(D18:G18)) -> - | I18: =D18*10+E18 -> 0 | K18: ="*"&StaffList!B7&"*" -> *Hung.nm*
A19: 14 | B19: =VLOOKUP(K19, StaffList!B:C,2,FALSE) -> Vũ Xuân Trường | C19: =SUM(D19:G19) -> 0 | D19: =COUNTIFS(DATA!$P:$P,"=E", DATA!$N:$N,$K:$K,DATA!$K:$K,">="&$C$3,DATA!$K:$K,"<="&$E$3) -> 0 | E19: =COUNTIFS(DATA!$P:$P,"=S", DATA!$N:$N,$K:$K,DATA!$K:$K,">="&$C$3,DATA!$K:$K,"<="&$E$3) -> 0 | F19: =COUNTIFS(DATA!$P:$P,"=A", DATA!$N:$N,$K:$K,DATA!$K:$K,">="&$C$3,DATA!$K:$K,"<="&$E$3) -> 0 | G19: =COUNTIFS(DATA!$P:$P,"=D", DATA!$N:$N,$K:$K,DATA!$K:$K,">="&$C$3,DATA!$K:$K,"<="&$E$3) -> 0 | H19: =IF(SUM(D19:G19)=0,"-",SUM(D19:E19)/SUM(D19:G19)) -> - | I19: =D19*10+E19 -> 0 | K19: ="*"&StaffList!B18&"*" -> *Truong.vx*
A20: 5 | B20: =VLOOKUP(K20, StaffList!B:C,2,FALSE) -> Hồ Sỹ Hiệp | C20: =SUM(D20:G20) -> 0 | D20: =COUNTIFS(DATA!$P:$P,"=E", DATA!$N:$N,$K:$K,DATA!$K:$K,">="&$C$3,DATA!$K:$K,"<="&$E$3) -> 0 | E20: =COUNTIFS(DATA!$P:$P,"=S", DATA!$N:$N,$K:$K,DATA!$K:$K,">="&$C$3,DATA!$K:$K,"<="&$E$3) -> 0 | F20: =COUNTIFS(DATA!$P:$P,"=A", DATA!$N:$N,$K:$K,DATA!$K:$K,">="&$C$3,DATA!$K:$K,"<="&$E$3) -> 0 | G20: =COUNTIFS(DATA!$P:$P,"=D", DATA!$N:$N,$K:$K,DATA!$K:$K,">="&$C$3,DATA!$K:$K,"<="&$E$3) -> 0 | H20: =IF(SUM(D20:G20)=0,"-",SUM(D20:E20)/SUM(D20:G20)) -> - | I20: =D20*10+E20 -> 0 | K20: ="*"&StaffList!B9&"*" -> *Hiep.hs*
A21: 21 | B21: =VLOOKUP(K21, StaffList!B:C,2,FALSE) -> Bùi Văn Long | C21: =SUM(D21:G21) -> 0 | D21: =COUNTIFS(DATA!$P:$P,"=E", DATA!$N:$N,$K:$K,DATA!$K:$K,">="&$C$3,DATA!$K:$K,"<="&$E$3) -> 0 | E21: =COUNTIFS(DATA!$P:$P,"=S", DATA!$N:$N,$K:$K,DATA!$K:$K,">="&$C$3,DATA!$K:$K,"<="&$E$3) -> 0 | F21: =COUNTIFS(DATA!$P:$P,"=A", DATA!$N:$N,$K:$K,DATA!$K:$K,">="&$C$3,DATA!$K:$K,"<="&$E$3) -> 0 | G21: =COUNTIFS(DATA!$P:$P,"=D", DATA!$N:$N,$K:$K,DATA!$K:$K,">="&$C$3,DATA!$K:$K,"<="&$E$3) -> 0 | H21: =IF(SUM(D21:G21)=0,"-",SUM(D21:E21)/SUM(D21:G21)) -> - | I21: =D21*10+E21 -> 0 | K21: ="*"&StaffList!B25&"*" -> *Long.bv*
A22: 7 | B22: =VLOOKUP(K22, StaffList!B:C,2,FALSE) -> Mông Văn Thương | C22: =SUM(D22:G22) -> 0 | D22: =COUNTIFS(DATA!$P:$P,"=E", DATA!$N:$N,$K:$K,DATA!$K:$K,">="&$C$3,DATA!$K:$K,"<="&$E$3) -> 0 | E22: =COUNTIFS(DATA!$P:$P,"=S", DATA!$N:$N,$K:$K,DATA!$K:$K,">="&$C$3,DATA!$K:$K,"<="&$E$3) -> 0 | F22: =COUNTIFS(DATA!$P:$P,"=A", DATA!$N:$N,$K:$K,DATA!$K:$K,">="&$C$3,DATA!$K:$K,"<="&$E$3) -> 0 | G22: =COUNTIFS(DATA!$P:$P,"=D", DATA!$N:$N,$K:$K,DATA!$K:$K,">="&$C$3,DATA!$K:$K,"<="&$E$3) -> 0 | H22: =IF(SUM(D22:G22)=0,"-",SUM(D22:E22)/SUM(D22:G22)) -> - | I22: =D22*10+E22 -> 0 | K22: ="*"&StaffList!B11&"*" -> *Thuong.mv*
A23: 23 | B23: =VLOOKUP(K23, StaffList!B:C,2,FALSE) -> Đoàn Minh Đạo | C23: =SUM(D23:G23) -> 0 | D23: =COUNTIFS(DATA!$P:$P,"=E", DATA!$N:$N,$K:$K,DATA!$K:$K,">="&$C$3,DATA!$K:$K,"<="&$E$3) -> 0 | E23: =COUNTIFS(DATA!$P:$P,"=S", DATA!$N:$N,$K:$K,DATA!$K:$K,">="&$C$3,DATA!$K:$K,"<="&$E$3) -> 0 | F23: =COUNTIFS(DATA!$P:$P,"=A", DATA!$N:$N,$K:$K,DATA!$K:$K,">="&$C$3,DATA!$K:$K,"<="&$E$3) -> 0 | G23: =COUNTIFS(DATA!$P:$P,"=D", DATA!$N:$N,$K:$K,DATA!$K:$K,">="&$C$3,DATA!$K:$K,"<="&$E$3) -> 0 | H23: =IF(SUM(D23:G23)=0,"-",SUM(D23:E23)/SUM(D23:G23)) -> - | I23: =D23*10+E23 -> 0 | K23: ="*"&StaffList!B27&"*" -> *Dao.dm*
A24: 11 | B24: =VLOOKUP(K24, StaffList!B:C,2,FALSE) -> Đỗ Văn Cường | C24: =SUM(D24:G24) -> 0 | D24: =COUNTIFS(DATA!$P:$P,"=E", DATA!$N:$N,$K:$K,DATA!$K:$K,">="&$C$3,DATA!$K:$K,"<="&$E$3) -> 0 | E24: =COUNTIFS(DATA!$P:$P,"=S", DATA!$N:$N,$K:$K,DATA!$K:$K,">="&$C$3,DATA!$K:$K,"<="&$E$3) -> 0 | F24: =COUNTIFS(DATA!$P:$P,"=A", DATA!$N:$N,$K:$K,DATA!$K:$K,">="&$C$3,DATA!$K:$K,"<="&$E$3) -> 0 | G24: =COUNTIFS(DATA!$P:$P,"=D", DATA!$N:$N,$K:$K,DATA!$K:$K,">="&$C$3,DATA!$K:$K,"<="&$E$3) -> 0 | H24: =IF(SUM(D24:G24)=0,"-",SUM(D24:E24)/SUM(D24:G24)) -> - | I24: =D24*10+E24 -> 0 | K24: ="*"&StaffList!B15&"*" -> *Cuong.dv*
A25: 17 | B25: =VLOOKUP(K25, StaffList!B:C,2,FALSE) -> Phan Xuân Lương | C25: =SUM(D25:G25) -> 0 | D25: =COUNTIFS(DATA!$P:$P,"=E", DATA!$N:$N,$K:$K,DATA!$K:$K,">="&$C$3,DATA!$K:$K,"<="&$E$3) -> 0 | E25: =COUNTIFS(DATA!$P:$P,"=S", DATA!$N:$N,$K:$K,DATA!$K:$K,">="&$C$3,DATA!$K:$K,"<="&$E$3) -> 0 | F25: =COUNTIFS(DATA!$P:$P,"=A", DATA!$N:$N,$K:$K,DATA!$K:$K,">="&$C$3,DATA!$K:$K,"<="&$E$3) -> 0 | G25: =COUNTIFS(DATA!$P:$P,"=D", DATA!$N:$N,$K:$K,DATA!$K:$K,">="&$C$3,DATA!$K:$K,"<="&$E$3) -> 0 | H25: =IF(SUM(D25:G25)=0,"-",SUM(D25:E25)/SUM(D25:G25)) -> - | I25: =D25*10+E25 -> 0 | K25: ="*"&StaffList!B21&"*" -> *Luong.px*
A26: 2 | B26: =VLOOKUP(K26, StaffList!B:C,2,FALSE) -> Hà Đình Diên | C26: =SUM(D26:G26) -> 0 | D26: =COUNTIFS(DATA!$P:$P,"=E", DATA!$N:$N,$K:$K,DATA!$K:$K,">="&$C$3,DATA!$K:$K,"<="&$E$3) -> 0 | E26: =COUNTIFS(DATA!$P:$P,"=S", DATA!$N:$N,$K:$K,DATA!$K:$K,">="&$C$3,DATA!$K:$K,"<="&$E$3) -> 0 | F26: =COUNTIFS(DATA!$P:$P,"=A", DATA!$N:$N,$K:$K,DATA!$K:$K,">="&$C$3,DATA!$K:$K,"<="&$E$3) -> 0 | G26: =COUNTIFS(DATA!$P:$P,"=D", DATA!$N:$N,$K:$K,DATA!$K:$K,">="&$C$3,DATA!$K:$K,"<="&$E$3) -> 0 | H26: =IF(SUM(D26:G26)=0,"-",SUM(D26:E26)/SUM(D26:G26)) -> - | I26: =D26*10+E26 -> 0 | K26: ="*"&StaffList!B6&"*" -> *Dien.hd*
A27: 12 | B27: =VLOOKUP(K27, StaffList!B:C,2,FALSE) -> Mai Văn Hoàng | C27: =SUM(D27:G27) -> 0 | D27: =COUNTIFS(DATA!$P:$P,"=E", DATA!$N:$N,$K:$K,DATA!$K:$K,">="&$C$3,DATA!$K:$K,"<="&$E$3) -> 0 | E27: =COUNTIFS(DATA!$P:$P,"=S", DATA!$N:$N,$K:$K,DATA!$K:$K,">="&$C$3,DATA!$K:$K,"<="&$E$3) -> 0 | F27: =COUNTIFS(DATA!$P:$P,"=A", DATA!$N:$N,$K:$K,DATA!$K:$K,">="&$C$3,DATA!$K:$K,"<="&$E$3) -> 0 | G27: =COUNTIFS(DATA!$P:$P,"=D", DATA!$N:$N,$K:$K,DATA!$K:$K,">="&$C$3,DATA!$K:$K,"<="&$E$3) -> 0 | H27: =IF(SUM(D27:G27)=0,"-",SUM(D27:E27)/SUM(D27:G27)) -> - | I27: =D27*10+E27 -> 0 | K27: ="*"&StaffList!B16&"*" -> *Hoang.mv*
A28: 4 | B28: =VLOOKUP(K28, StaffList!B:C,2,FALSE) -> Vũ Hoàng | C28: =SUM(D28:G28) -> 0 | D28: =COUNTIFS(DATA!$P:$P,"=E", DATA!$N:$N,$K:$K,DATA!$K:$K,">="&$C$3,DATA!$K:$K,"<="&$E$3) -> 0 | E28: =COUNTIFS(DATA!$P:$P,"=S", DATA!$N:$N,$K:$K,DATA!$K:$K,">="&$C$3,DATA!$K:$K,"<="&$E$3) -> 0 | F28: =COUNTIFS(DATA!$P:$P,"=A", DATA!$N:$N,$K:$K,DATA!$K:$K,">="&$C$3,DATA!$K:$K,"<="&$E$3) -> 0 | G28: =COUNTIFS(DATA!$P:$P,"=D", DATA!$N:$N,$K:$K,DATA!$K:$K,">="&$C$3,DATA!$K:$K,"<="&$E$3) -> 0 | H28: =IF(SUM(D28:G28)=0,"-",SUM(D28:E28)/SUM(D28:G28)) -> - | I28: =D28*10+E28 -> 0 | K28: ="*"&StaffList!B8&"*" -> *Hoang.v*
A29: 9 | B29: =VLOOKUP(K29, StaffList!B:C,2,FALSE) -> Vũ Xuân Phúc | C29: =SUM(D29:G29) -> 0 | D29: =COUNTIFS(DATA!$P:$P,"=E", DATA!$N:$N,$K:$K,DATA!$K:$K,">="&$C$3,DATA!$K:$K,"<="&$E$3) -> 0 | E29: =COUNTIFS(DATA!$P:$P,"=S", DATA!$N:$N,$K:$K,DATA!$K:$K,">="&$C$3,DATA!$K:$K,"<="&$E$3) -> 0 | F29: =COUNTIFS(DATA!$P:$P,"=A", DATA!$N:$N,$K:$K,DATA!$K:$K,">="&$C$3,DATA!$K:$K,"<="&$E$3) -> 0 | G29: =COUNTIFS(DATA!$P:$P,"=D", DATA!$N:$N,$K:$K,DATA!$K:$K,">="&$C$3,DATA!$K:$K,"<="&$E$3) -> 0 | H29: =IF(SUM(D29:G29)=0,"-",SUM(D29:E29)/SUM(D29:G29)) -> - | I29: =D29*10+E29 -> 0 | K29: ="*"&StaffList!B13&"*" -> *Phuc.vx*
A30: 18 | B30: =VLOOKUP(K30, StaffList!B:C,2,FALSE) -> Nguyễn Thế Chân | C30: =SUM(D30:G30) -> 0 | D30: =COUNTIFS(DATA!$P:$P,"=E", DATA!$N:$N,$K:$K,DATA!$K:$K,">="&$C$3,DATA!$K:$K,"<="&$E$3) -> 0 | E30: =COUNTIFS(DATA!$P:$P,"=S", DATA!$N:$N,$K:$K,DATA!$K:$K,">="&$C$3,DATA!$K:$K,"<="&$E$3) -> 0 | F30: =COUNTIFS(DATA!$P:$P,"=A", DATA!$N:$N,$K:$K,DATA!$K:$K,">="&$C$3,DATA!$K:$K,"<="&$E$3) -> 0 | G30: =COUNTIFS(DATA!$P:$P,"=D", DATA!$N:$N,$K:$K,DATA!$K:$K,">="&$C$3,DATA!$K:$K,"<="&$E$3) -> 0 | H30: =IF(SUM(D30:G30)=0,"-",SUM(D30:E30)/SUM(D30:G30)) -> - | I30: =D30*10+E30 -> 0 | K30: ="*"&StaffList!B22&"*" -> *Chan.nt*
A31: 19 | B31: =VLOOKUP(K31, StaffList!B:C,2,FALSE) -> Đỗ Văn Long | C31: =SUM(D31:G31) -> 0 | D31: =COUNTIFS(DATA!$P:$P,"=E", DATA!$N:$N,$K:$K,DATA!$K:$K,">="&$C$3,DATA!$K:$K,"<="&$E$3) -> 0 | E31: =COUNTIFS(DATA!$P:$P,"=S", DATA!$N:$N,$K:$K,DATA!$K:$K,">="&$C$3,DATA!$K:$K,"<="&$E$3) -> 0 | F31: =COUNTIFS(DATA!$P:$P,"=A", DATA!$N:$N,$K:$K,DATA!$K:$K,">="&$C$3,DATA!$K:$K,"<="&$E$3) -> 0 | G31: =COUNTIFS(DATA!$P:$P,"=D", DATA!$N:$N,$K:$K,DATA!$K:$K,">="&$C$3,DATA!$K:$K,"<="&$E$3) -> 0 | H31: =IF(SUM(D31:G31)=0,"-",SUM(D31:E31)/SUM(D31:G31)) -> - | I31: =D31*10+E31 -> 0 | K31: ="*"&StaffList!B23&"*" -> *Long.dv*
A32: 15 | B32: =VLOOKUP(K32, StaffList!B:C,2,FALSE) -> Bùi Ngọc Linh | C32: =SUM(D32:G32) -> 0 | D32: =COUNTIFS(DATA!$P:$P,"=E", DATA!$N:$N,$K:$K,DATA!$K:$K,">="&$C$3,DATA!$K:$K,"<="&$E$3) -> 0 | E32: =COUNTIFS(DATA!$P:$P,"=S", DATA!$N:$N,$K:$K,DATA!$K:$K,">="&$C$3,DATA!$K:$K,"<="&$E$3) -> 0 | F32: =COUNTIFS(DATA!$P:$P,"=A", DATA!$N:$N,$K:$K,DATA!$K:$K,">="&$C$3,DATA!$K:$K,"<="&$E$3) -> 0 | G32: =COUNTIFS(DATA!$P:$P,"=D", DATA!$N:$N,$K:$K,DATA!$K:$K,">="&$C$3,DATA!$K:$K,"<="&$E$3) -> 0 | H32: =IF(SUM(D32:G32)=0,"-",SUM(D32:E32)/SUM(D32:G32)) -> - | I32: =D32*10+E32 -> 0 | K32: ="*"&StaffList!B19&"*" -> *Linh.bn*
A33: 20 | B33: =VLOOKUP(K33, StaffList!B:C,2,FALSE) -> Nguyễn Như Khương | C33: =SUM(D33:G33) -> 0 | D33: =COUNTIFS(DATA!$P:$P,"=E", DATA!$N:$N,$K:$K,DATA!$K:$K,">="&$C$3,DATA!$K:$K,"<="&$E$3) -> 0 | E33: =COUNTIFS(DATA!$P:$P,"=S", DATA!$N:$N,$K:$K,DATA!$K:$K,">="&$C$3,DATA!$K:$K,"<="&$E$3) -> 0 | F33: =COUNTIFS(DATA!$P:$P,"=A", DATA!$N:$N,$K:$K,DATA!$K:$K,">="&$C$3,DATA!$K:$K,"<="&$E$3) -> 0 | G33: =COUNTIFS(DATA!$P:$P,"=D", DATA!$N:$N,$K:$K,DATA!$K:$K,">="&$C$3,DATA!$K:$K,"<="&$E$3) -> 0 | H33: =IF(SUM(D33:G33)=0,"-",SUM(D33:E33)/SUM(D33:G33)) -> - | I33: =D33*10+E33 -> 0 | K33: ="*"&StaffList!B24&"*" -> *Khuong.nn*
A34: 24 | B34: =VLOOKUP(K34, StaffList!B:C,2,FALSE) -> Khúc Thành Đạt | C34: =SUM(D34:G34) -> 0 | D34: =COUNTIFS(DATA!$P:$P,"=E", DATA!$N:$N,$K:$K,DATA!$K:$K,">="&$C$3,DATA!$K:$K,"<="&$E$3) -> 0 | E34: =COUNTIFS(DATA!$P:$P,"=S", DATA!$N:$N,$K:$K,DATA!$K:$K,">="&$C$3,DATA!$K:$K,"<="&$E$3) -> 0 | F34: =COUNTIFS(DATA!$P:$P,"=A", DATA!$N:$N,$K:$K,DATA!$K:$K,">="&$C$3,DATA!$K:$K,"<="&$E$3) -> 0 | G34: =COUNTIFS(DATA!$P:$P,"=D", DATA!$N:$N,$K:$K,DATA!$K:$K,">="&$C$3,DATA!$K:$K,"<="&$E$3) -> 0 | H34: =IF(SUM(D34:G34)=0,"-",SUM(D34:E34)/SUM(D34:G34)) -> - | I34: =D34*10+E34 -> 0 | K34: ="*"&StaffList!B28&"*" -> *Dat.kt*
A35: 25 | B35: =VLOOKUP(K35, StaffList!B:C,2,FALSE) -> Bùi Văn Sỹ | C35: =SUM(D35:G35) -> 0 | D35: =COUNTIFS(DATA!$P:$P,"=E", DATA!$N:$N,$K:$K,DATA!$K:$K,">="&$C$3,DATA!$K:$K,"<="&$E$3) -> 0 | E35: =COUNTIFS(DATA!$P:$P,"=S", DATA!$N:$N,$K:$K,DATA!$K:$K,">="&$C$3,DATA!$K:$K,"<="&$E$3) -> 0 | F35: =COUNTIFS(DATA!$P:$P,"=A", DATA!$N:$N,$K:$K,DATA!$K:$K,">="&$C$3,DATA!$K:$K,"<="&$E$3) -> 0 | G35: =COUNTIFS(DATA!$P:$P,"=D", DATA!$N:$N,$K:$K,DATA!$K:$K,">="&$C$3,DATA!$K:$K,"<="&$E$3) -> 0 | H35: =IF(SUM(D35:G35)=0,"-",SUM(D35:E35)/SUM(D35:G35)) -> - | I35: =D35*10+E35 -> 0 | K35: ="*"&StaffList!B29&"*" -> *Sy.bv*
A36: 26 | B36: =VLOOKUP(K36, StaffList!B:C,2,FALSE) -> Nguyễn Tiến Đạt | C36: =SUM(D36:G36) -> 0 | D36: =COUNTIFS(DATA!$P:$P,"=E", DATA!$N:$N,$K:$K,DATA!$K:$K,">="&$C$3,DATA!$K:$K,"<="&$E$3) -> 0 | E36: =COUNTIFS(DATA!$P:$P,"=S", DATA!$N:$N,$K:$K,DATA!$K:$K,">="&$C$3,DATA!$K:$K,"<="&$E$3) -> 0 | F36: =COUNTIFS(DATA!$P:$P,"=A", DATA!$N:$N,$K:$K,DATA!$K:$K,">="&$C$3,DATA!$K:$K,"<="&$E$3) -> 0 | G36: =COUNTIFS(DATA!$P:$P,"=D", DATA!$N:$N,$K:$K,DATA!$K:$K,">="&$C$3,DATA!$K:$K,"<="&$E$3) -> 0 | H36: =IF(SUM(D36:G36)=0,"-",SUM(D36:E36)/SUM(D36:G36)) -> - | I36: =D36*10+E36 -> 0 | K36: ="*"&StaffList!B30&"*" -> *Dat.nt*
B37: TOTAL | C37: =SUM(C8:C36) -> 0 | D37: =SUM(D8:D36) -> 0 | E37: =SUM(E8:E36) -> 0 | F37: =SUM(F8:F36) -> 0 | G37: =SUM(G8:G36) -> 0 | H37: =IF(SUM(D37:G37)=0,"-",SUM(D37:E37)/SUM(D37:G37)) -> -

Sheet Prject Staffs Satisfaction
B1: CHỈ SỐ HÀI LÒNG CỦA KHÁCH HÀNG ĐỐI VỚI NHÂN VIÊN TỪNG DỰ ÁN/ ASSESSMENT OF CUSTOMER SATISFACTION FOR EACH EMPLOYEES
A2: SPS SERVICES JSC | C2: Khách hàng/ Customer name: | E2: FRENCH EMBASSY
B3: Từ ngày / From date: | C3: 43862 | D3: Tới / To: | E3: 43890 | H3: Reported by: Ninh.tv
A4: Ghi chú: Số báo cáo một dịch vụ bằng tổng số người thực tế đi làm dịch vụ đó. Báo cáo không bao gồm thực tập sinh hoặc thầu phụ
A6: TT | B6: Tên nhân viên | C6: Tổng số báo cáo có phản hồi | D6: Rất hài lòng | E6: Hài lòng | F6: Chấp nhận | G6: Không hài lòng | H6: Điểm để so sánh | J6: Ký kiệu trung gian cho công thức tự động
A7: No | B7: Full Name | C7: Total report wt feedback | D7: Exceeded satisfy (A) | E7: Satisfied (B) | F7: Acceptable (C) | G7: Dissatisfied (D) | H7: Rating (Ax10+Bx1) | J7: Name for calculator
A8: 1 | B8: =VLOOKUP(J8, StaffList!B:C,2,FALSE) -> Hà Đình Diên | C8: =SUM(D8:G8) -> #REF! | D8: =SUMIFS(DATA!P:P,DATA!$A:$A,$E$2,DATA!$N:$N,$J:$J,DATA!$K:$K,">="&$C$3,DATA!$K:$K,"<"&$E$3) -> 0 | E8: =SUMIFS(DATA!#REF!,DATA!$A:$A,$E$2,DATA!$N:$N,$J:$J,DATA!$K:$K,">="&$C$3,DATA!$K:$K,"<"&$E$3) -> #REF! | F8: =SUMIFS(DATA!#REF!,DATA!$A:$A,$E$2,DATA!$N:$N,$J:$J,DATA!$K:$K,">="&$C$3,DATA!$K:$K,"<"&$E$3) -> #REF! | G8: =SUMIFS(DATA!#REF!,DATA!$A:$A,$E$2,DATA!$N:$N,$J:$J,DATA!$K:$K,">="&$C$3,DATA!$K:$K,"<"&$E$3) -> #REF! | H8: =D8*10+E8 -> #REF! | J8: ="*"&StaffList!B6&"*" -> *Dien.hd*
A9: 2 | B9: =VLOOKUP(J9, StaffList!B:C,2,FALSE) -> Mông Văn Thương | C9: =SUM(D9:G9) -> #REF! | D9: =SUMIFS(DATA!P:P,DATA!$A:$A,$E$2,DATA!$N:$N,$J:$J,DATA!$K:$K,">="&$C$3,DATA!$K:$K,"<"&$E$3) -> 0 | E9: =SUMIFS(DATA!#REF!,DATA!$A:$A,$E$2,DATA!$N:$N,$J:$J,DATA!$K:$K,">="&$C$3,DATA!$K:$K,"<"&$E$3) -> #REF! | F9: =SUMIFS(DATA!#REF!,DATA!$A:$A,$E$2,DATA!$N:$N,$J:$J,DATA!$K:$K,">="&$C$3,DATA!$K:$K,"<"&$E$3) -> #REF! | G9: =SUMIFS(DATA!#REF!,DATA!$A:$A,$E$2,DATA!$N:$N,$J:$J,DATA!$K:$K,">="&$C$3,DATA!$K:$K,"<"&$E$3) -> #REF! | H9: =D9*10+E9 -> #REF! | J9: ="*"&StaffList!B11&"*" -> *Thuong.mv*
A10: 3 | B10: =VLOOKUP(J10, StaffList!B:C,2,FALSE) -> Vũ Hoàng | C10: =SUM(D10:G10) -> #REF! | D10: =SUMIFS(DATA!P:P,DATA!$A:$A,$E$2,DATA!$N:$N,$J:$J,DATA!$K:$K,">="&$C$3,DATA!$K:$K,"<"&$E$3) -> 0 | E10: =SUMIFS(DATA!#REF!,DATA!$A:$A,$E$2,DATA!$N:$N,$J:$J,DATA!$K:$K,">="&$C$3,DATA!$K:$K,"<"&$E$3) -> #REF! | F10: =SUMIFS(DATA!#REF!,DATA!$A:$A,$E$2,DATA!$N:$N,$J:$J,DATA!$K:$K,">="&$C$3,DATA!$K:$K,"<"&$E$3) -> #REF! | G10: =SUMIFS(DATA!#REF!,DATA!$A:$A,$E$2,DATA!$N:$N,$J:$J,DATA!$K:$K,">="&$C$3,DATA!$K:$K,"<"&$E$3) -> #REF! | H10: =D10*10+E10 -> #REF! | J10: ="*"&StaffList!B8&"*" -> *Hoang.v*
A11: 4 | B11: =VLOOKUP(J11, StaffList!B:C,2,FALSE) -> Hồ Sỹ Hiệp | C11: =SUM(D11:G11) -> #REF! | D11: =SUMIFS(DATA!P:P,DATA!$A:$A,$E$2,DATA!$N:$N,$J:$J,DATA!$K:$K,">="&$C$3,DATA!$K:$K,"<"&$E$3) -> 0 | E11: =SUMIFS(DATA!#REF!,DATA!$A:$A,$E$2,DATA!$N:$N,$J:$J,DATA!$K:$K,">="&$C$3,DATA!$K:$K,"<"&$E$3) -> #REF! | F11: =SUMIFS(DATA!#REF!,DATA!$A:$A,$E$2,DATA!$N:$N,$J:$J,DATA!$K:$K,">="&$C$3,DATA!$K:$K,"<"&$E$3) -> #REF! | G11: =SUMIFS(DATA!#REF!,DATA!$A:$A,$E$2,DATA!$N:$N,$J:$J,DATA!$K:$K,">="&$C$3,DATA!$K:$K,"<"&$E$3) -> #REF! | H11: =D11*10+E11 -> #REF! | J11: ="*"&StaffList!B9&"*" -> *Hiep.hs*
A12: 5 | B12: =VLOOKUP(J12, StaffList!B:C,2,FALSE) -> #REF! | C12: =SUM(D12:G12) -> #REF! | D12: =SUMIFS(DATA!P:P,DATA!$A:$A,$E$2,DATA!$N:$N,$J:$J,DATA!$K:$K,">="&$C$3,DATA!$K:$K,"<"&$E$3) -> 0 | E12: =SUMIFS(DATA!#REF!,DATA!$A:$A,$E$2,DATA!$N:$N,$J:$J,DATA!$K:$K,">="&$C$3,DATA!$K:$K,"<"&$E$3) -> #REF! | F12: =SUMIFS(DATA!#REF!,DATA!$A:$A,$E$2,DATA!$N:$N,$J:$J,DATA!$K:$K,">="&$C$3,DATA!$K:$K,"<"&$E$3) -> #REF! | G12: =SUMIFS(DATA!#REF!,DATA!$A:$A,$E$2,DATA!$N:$N,$J:$J,DATA!$K:$K,">="&$C$3,DATA!$K:$K,"<"&$E$3) -> #REF! | H12: =D12*10+E12 -> #REF! | J12: ="*"&StaffList!#REF!&"*" -> #REF!
A13: 6 | B13: =VLOOKUP(J13, StaffList!B:C,2,FALSE) -> Chu Trọng Thao | C13: =SUM(D13:G13) -> #REF! | D13: =SUMIFS(DATA!P:P,DATA!$A:$A,$E$2,DATA!$N:$N,$J:$J,DATA!$K:$K,">="&$C$3,DATA!$K:$K,"<"&$E$3) -> 0 | E13: =SUMIFS(DATA!#REF!,DATA!$A:$A,$E$2,DATA!$N:$N,$J:$J,DATA!$K:$K,">="&$C$3,DATA!$K:$K,"<"&$E$3) -> #REF! | F13: =SUMIFS(DATA!#REF!,DATA!$A:$A,$E$2,DATA!$N:$N,$J:$J,DATA!$K:$K,">="&$C$3,DATA!$K:$K,"<"&$E$3) -> #REF! | G13: =SUMIFS(DATA!#REF!,DATA!$A:$A,$E$2,DATA!$N:$N,$J:$J,DATA!$K:$K,">="&$C$3,DATA!$K:$K,"<"&$E$3) -> #REF! | H13: =D13*10+E13 -> #REF! | J13: ="*"&StaffList!B10&"*" -> *Thao.ct*
A14: 7 | B14: =VLOOKUP(J14, StaffList!B:C,2,FALSE) -> #REF! | C14: =SUM(D14:G14) -> #REF! | D14: =SUMIFS(DATA!P:P,DATA!$A:$A,$E$2,DATA!$N:$N,$J:$J,DATA!$K:$K,">="&$C$3,DATA!$K:$K,"<"&$E$3) -> 0 | E14: =SUMIFS(DATA!#REF!,DATA!$A:$A,$E$2,DATA!$N:$N,$J:$J,DATA!$K:$K,">="&$C$3,DATA!$K:$K,"<"&$E$3) -> #REF! | F14: =SUMIFS(DATA!#REF!,DATA!$A:$A,$E$2,DATA!$N:$N,$J:$J,DATA!$K:$K,">="&$C$3,DATA!$K:$K,"<"&$E$3) -> #REF! | G14: =SUMIFS(DATA!#REF!,DATA!$A:$A,$E$2,DATA!$N:$N,$J:$J,DATA!$K:$K,">="&$C$3,DATA!$K:$K,"<"&$E$3) -> #REF! | H14: =D14*10+E14 -> #REF! | J14: ="*"&StaffList!#REF!&"*" -> #REF!
A15: 8 | B15: =VLOOKUP(J15, StaffList!B:C,2,FALSE) -> #REF! | C15: =SUM(D15:G15) -> #REF! | D15: =SUMIFS(DATA!P:P,DATA!$A:$A,$E$2,DATA!$N:$N,$J:$J,DATA!$K:$K,">="&$C$3,DATA!$K:$K,"<"&$E$3) -> 0 | E15: =SUMIFS(DATA!#REF!,DATA!$A:$A,$E$2,DATA!$N:$N,$J:$J,DATA!$K:$K,">="&$C$3,DATA!$K:$K,"<"&$E$3) -> #REF! | F15: =SUMIFS(DATA!#REF!,DATA!$A:$A,$E$2,DATA!$N:$N,$J:$J,DATA!$K:$K,">="&$C$3,DATA!$K:$K,"<"&$E$3) -> #REF! | G15: =SUMIFS(DATA!#REF!,DATA!$A:$A,$E$2,DATA!$N:$N,$J:$J,DATA!$K:$K,">="&$C$3,DATA!$K:$K,"<"&$E$3) -> #REF! | H15: =D15*10+E15 -> #REF! | J15: ="*"&StaffList!#REF!&"*" -> #REF!
A16: 9 | B16: =VLOOKUP(J16, StaffList!B:C,2,FALSE) -> #REF! | C16: =SUM(D16:G16) -> #REF! | D16: =SUMIFS(DATA!P:P,DATA!$A:$A,$E$2,DATA!$N:$N,$J:$J,DATA!$K:$K,">="&$C$3,DATA!$K:$K,"<"&$E$3) -> 0 | E16: =SUMIFS(DATA!#REF!,DATA!$A:$A,$E$2,DATA!$N:$N,$J:$J,DATA!$K:$K,">="&$C$3,DATA!$K:$K,"<"&$E$3) -> #REF! | F16: =SUMIFS(DATA!#REF!,DATA!$A:$A,$E$2,DATA!$N:$N,$J:$J,DATA!$K:$K,">="&$C$3,DATA!$K:$K,"<"&$E$3) -> #REF! | G16: =SUMIFS(DATA!#REF!,DATA!$A:$A,$E$2,DATA!$N:$N,$J:$J,DATA!$K:$K,">="&$C$3,DATA!$K:$K,"<"&$E$3) -> #REF! | H16: =D16*10+E16 -> #REF! | J16: ="*"&StaffList!#REF!&"*" -> #REF!
A17: 10 | B17: =VLOOKUP(J17, StaffList!B:C,2,FALSE) -> Lê Hùng Mạnh | C17: =SUM(D17:G17) -> #REF! | D17: =SUMIFS(DATA!P:P,DATA!$A:$A,$E$2,DATA!$N:$N,$J:$J,DATA!$K:$K,">="&$C$3,DATA!$K:$K,"<"&$E$3) -> 0 | E17: =SUMIFS(DATA!#REF!,DATA!$A:$A,$E$2,DATA!$N:$N,$J:$J,DATA!$K:$K,">="&$C$3,DATA!$K:$K,"<"&$E$3) -> #REF! | F17: =SUMIFS(DATA!#REF!,DATA!$A:$A,$E$2,DATA!$N:$N,$J:$J,DATA!$K:$K,">="&$C$3,DATA!$K:$K,"<"&$E$3) -> #REF! | G17: =SUMIFS(DATA!#REF!,DATA!$A:$A,$E$2,DATA!$N:$N,$J:$J,DATA!$K:$K,">="&$C$3,DATA!$K:$K,"<"&$E$3) -> #REF! | H17: =D17*10+E17 -> #REF! | J17: ="*"&StaffList!B5&"*" -> *Manh.lh*
A18: 11 | B18: =VLOOKUP(J18, StaffList!B:C,2,FALSE) -> #REF! | C18: =SUM(D18:G18) -> #REF! | D18: =SUMIFS(DATA!P:P,DATA!$A:$A,$E$2,DATA!$N:$N,$J:$J,DATA!$K:$K,">="&$C$3,DATA!$K:$K,"<"&$E$3) -> 0 | E18: =SUMIFS(DATA!#REF!,DATA!$A:$A,$E$2,DATA!$N:$N,$J:$J,DATA!$K:$K,">="&$C$3,DATA!$K:$K,"<"&$E$3) -> #REF! | F18: =SUMIFS(DATA!#REF!,DATA!$A:$A,$E$2,DATA!$N:$N,$J:$J,DATA!$K:$K,">="&$C$3,DATA!$K:$K,"<"&$E$3) -> #REF! | G18: =SUMIFS(DATA!#REF!,DATA!$A:$A,$E$2,DATA!$N:$N,$J:$J,DATA!$K:$K,">="&$C$3,DATA!$K:$K,"<"&$E$3) -> #REF! | H18: =D18*10+E18 -> #REF! | J18: ="*"&StaffList!#REF!&"*" -> #REF!
A19: 12 | B19: =VLOOKUP(J19, StaffList!B:C,2,FALSE) -> #REF! | C19: =SUM(D19:G19) -> #REF! | D19: =SUMIFS(DATA!P:P,DATA!$A:$A,$E$2,DATA!$N:$N,$J:$J,DATA!$K:$K,">="&$C$3,DATA!$K:$K,"<"&$E$3) -> 0 | E19: =SUMIFS(DATA!#REF!,DATA!$A:$A,$E$2,DATA!$N:$N,$J:$J,DATA!$K:$K,">="&$C$3,DATA!$K:$K,"<"&$E$3) -> #REF! | F19: =SUMIFS(DATA!#REF!,DATA!$A:$A,$E$2,DATA!$N:$N,$J:$J,DATA!$K:$K,">="&$C$3,DATA!$K:$K,"<"&$E$3) -> #REF! | G19: =SUMIFS(DATA!#REF!,DATA!$A:$A,$E$2,DATA!$N:$N,$J:$J,DATA!$K:$K,">="&$C$3,DATA!$K:$K,"<"&$E$3) -> #REF! | H19: =D19*10+E19 -> #REF! | J19: ="*"&StaffList!#REF!&"*" -> #REF!
A20: 13 | B20: =VLOOKUP(J20, StaffList!B:C,2,FALSE) -> Nguyễn Mạnh Hùng | C20: =SUM(D20:G20) -> #REF! | D20: =SUMIFS(DATA!P:P,DATA!$A:$A,$E$2,DATA!$N:$N,$J:$J,DATA!$K:$K,">="&$C$3,DATA!$K:$K,"<"&$E$3) -> 0 | E20: =SUMIFS(DATA!#REF!,DATA!$A:$A,$E$2,DATA!$N:$N,$J:$J,DATA!$K:$K,">="&$C$3,DATA!$K:$K,"<"&$E$3) -> #REF! | F20: =SUMIFS(DATA!#REF!,DATA!$A:$A,$E$2,DATA!$N:$N,$J:$J,DATA!$K:$K,">="&$C$3,DATA!$K:$K,"<"&$E$3) -> #REF! | G20: =SUMIFS(DATA!#REF!,DATA!$A:$A,$E$2,DATA!$N:$N,$J:$J,DATA!$K:$K,">="&$C$3,DATA!$K:$K,"<"&$E$3) -> #REF! | H20: =D20*10+E20 -> #REF! | J20: ="*"&StaffList!B7&"*" -> *Hung.nm*
A21: 14 | B21: =VLOOKUP(J21, StaffList!B:C,2,FALSE) -> #REF! | C21: =SUM(D21:G21) -> #REF! | D21: =SUMIFS(DATA!P:P,DATA!$A:$A,$E$2,DATA!$N:$N,$J:$J,DATA!$K:$K,">="&$C$3,DATA!$K:$K,"<"&$E$3) -> 0 | E21: =SUMIFS(DATA!#REF!,DATA!$A:$A,$E$2,DATA!$N:$N,$J:$J,DATA!$K:$K,">="&$C$3,DATA!$K:$K,"<"&$E$3) -> #REF! | F21: =SUMIFS(DATA!#REF!,DATA!$A:$A,$E$2,DATA!$N:$N,$J:$J,DATA!$K:$K,">="&$C$3,DATA!$K:$K,"<"&$E$3) -> #REF! | G21: =SUMIFS(DATA!#REF!,DATA!$A:$A,$E$2,DATA!$N:$N,$J:$J,DATA!$K:$K,">="&$C$3,DATA!$K:$K,"<"&$E$3) -> #REF! | H21: =D21*10+E21 -> #REF! | J21: ="*"&StaffList!#REF!&"*" -> #REF!
A22: 15 | B22: =VLOOKUP(J22, StaffList!B:C,2,FALSE) -> #REF! | C22: =SUM(D22:G22) -> #REF! | D22: =SUMIFS(DATA!P:P,DATA!$A:$A,$E$2,DATA!$N:$N,$J:$J,DATA!$K:$K,">="&$C$3,DATA!$K:$K,"<"&$E$3) -> 0 | E22: =SUMIFS(DATA!#REF!,DATA!$A:$A,$E$2,DATA!$N:$N,$J:$J,DATA!$K:$K,">="&$C$3,DATA!$K:$K,"<"&$E$3) -> #REF! | F22: =SUMIFS(DATA!#REF!,DATA!$A:$A,$E$2,DATA!$N:$N,$J:$J,DATA!$K:$K,">="&$C$3,DATA!$K:$K,"<"&$E$3) -> #REF! | G22: =SUMIFS(DATA!#REF!,DATA!$A:$A,$E$2,DATA!$N:$N,$J:$J,DATA!$K:$K,">="&$C$3,DATA!$K:$K,"<"&$E$3) -> #REF! | H22: =D22*10+E22 -> #REF! | J22: ="*"&StaffList!#REF!&"*" -> #REF!
A23: 16 | B23: =VLOOKUP(J23, StaffList!B:C,2,FALSE) -> #REF! | C23: =SUM(D23:G23) -> #REF! | D23: =SUMIFS(DATA!P:P,DATA!$A:$A,$E$2,DATA!$N:$N,$J:$J,DATA!$K:$K,">="&$C$3,DATA!$K:$K,"<"&$E$3) -> 0 | E23: =SUMIFS(DATA!#REF!,DATA!$A:$A,$E$2,DATA!$N:$N,$J:$J,DATA!$K:$K,">="&$C$3,DATA!$K:$K,"<"&$E$3) -> #REF! | F23: =SUMIFS(DATA!#REF!,DATA!$A:$A,$E$2,DATA!$N:$N,$J:$J,DATA!$K:$K,">="&$C$3,DATA!$K:$K,"<"&$E$3) -> #REF! | G23: =SUMIFS(DATA!#REF!,DATA!$A:$A,$E$2,DATA!$N:$N,$J:$J,DATA!$K:$K,">="&$C$3,DATA!$K:$K,"<"&$E$3) -> #REF! | H23: =D23*10+E23 -> #REF! | J23: ="*"&StaffList!#REF!&"*" -> #REF!
A24: 17 | B24: =VLOOKUP(J24, StaffList!B:C,2,FALSE) -> #REF! | C24: =SUM(D24:G24) -> #REF! | D24: =SUMIFS(DATA!P:P,DATA!$A:$A,$E$2,DATA!$N:$N,$J:$J,DATA!$K:$K,">="&$C$3,DATA!$K:$K,"<"&$E$3) -> 0 | E24: =SUMIFS(DATA!#REF!,DATA!$A:$A,$E$2,DATA!$N:$N,$J:$J,DATA!$K:$K,">="&$C$3,DATA!$K:$K,"<"&$E$3) -> #REF! | F24: =SUMIFS(DATA!#REF!,DATA!$A:$A,$E$2,DATA!$N:$N,$J:$J,DATA!$K:$K,">="&$C$3,DATA!$K:$K,"<"&$E$3) -> #REF! | G24: =SUMIFS(DATA!#REF!,DATA!$A:$A,$E$2,DATA!$N:$N,$J:$J,DATA!$K:$K,">="&$C$3,DATA!$K:$K,"<"&$E$3) -> #REF! | H24: =D24*10+E24 -> #REF! | J24: ="*"&StaffList!#REF!&"*" -> #REF!
A25: 18 | B25: Chu Tiến Dũng | C25: =SUM(D25:G25) -> #REF! | D25: =SUMIFS(DATA!P:P,DATA!$A:$A,$E$2,DATA!$N:$N,$J:$J,DATA!$K:$K,">="&$C$3,DATA!$K:$K,"<"&$E$3) -> 0 | E25: =SUMIFS(DATA!#REF!,DATA!$A:$A,$E$2,DATA!$N:$N,$J:$J,DATA!$K:$K,">="&$C$3,DATA!$K:$K,"<"&$E$3) -> #REF! | F25: =SUMIFS(DATA!#REF!,DATA!$A:$A,$E$2,DATA!$N:$N,$J:$J,DATA!$K:$K,">="&$C$3,DATA!$K:$K,"<"&$E$3) -> #REF! | G25: =SUMIFS(DATA!#REF!,DATA!$A:$A,$E$2,DATA!$N:$N,$J:$J,DATA!$K:$K,">="&$C$3,DATA!$K:$K,"<"&$E$3) -> #REF! | H25: =D25*10+E25 -> #REF! | J25: ="*"&StaffList!B12&"*" -> *Dung.ct*
A26: 19 | B26: Lê Đức Anh | C26: =SUM(D26:G26) -> #REF! | D26: =SUMIFS(DATA!P:P,DATA!$A:$A,$E$2,DATA!$N:$N,$J:$J,DATA!$K:$K,">="&$C$3,DATA!$K:$K,"<"&$E$3) -> 0 | E26: =SUMIFS(DATA!#REF!,DATA!$A:$A,$E$2,DATA!$N:$N,$J:$J,DATA!$K:$K,">="&$C$3,DATA!$K:$K,"<"&$E$3) -> #REF! | F26: =SUMIFS(DATA!#REF!,DATA!$A:$A,$E$2,DATA!$N:$N,$J:$J,DATA!$K:$K,">="&$C$3,DATA!$K:$K,"<"&$E$3) -> #REF! | G26: =SUMIFS(DATA!#REF!,DATA!$A:$A,$E$2,DATA!$N:$N,$J:$J,DATA!$K:$K,">="&$C$3,DATA!$K:$K,"<"&$E$3) -> #REF! | H26: =D26*10+E26 -> #REF! | J26: ="*"&StaffList!#REF!&"*" -> #REF!
A27: 20 | B27: Nguyễn Ngọc Lộc | C27: =SUM(D27:G27) -> #REF! | D27: =SUMIFS(DATA!P:P,DATA!$A:$A,$E$2,DATA!$N:$N,$J:$J,DATA!$K:$K,">="&$C$3,DATA!$K:$K,"<"&$E$3) -> 0 | E27: =SUMIFS(DATA!#REF!,DATA!$A:$A,$E$2,DATA!$N:$N,$J:$J,DATA!$K:$K,">="&$C$3,DATA!$K:$K,"<"&$E$3) -> #REF! | F27: =SUMIFS(DATA!#REF!,DATA!$A:$A,$E$2,DATA!$N:$N,$J:$J,DATA!$K:$K,">="&$C$3,DATA!$K:$K,"<"&$E$3) -> #REF! | G27: =SUMIFS(DATA!#REF!,DATA!$A:$A,$E$2,DATA!$N:$N,$J:$J,DATA!$K:$K,">="&$C$3,DATA!$K:$K,"<"&$E$3) -> #REF! | H27: =D27*10+E27 -> #REF! | J27: ="*"&StaffList!#REF!&"*" -> #REF!
A28: 21 | B28: Vũ Đình Khang | C28: =SUM(D28:G28) -> #REF! | D28: =SUMIFS(DATA!P:P,DATA!$A:$A,$E$2,DATA!$N:$N,$J:$J,DATA!$K:$K,">="&$C$3,DATA!$K:$K,"<"&$E$3) -> 0 | E28: =SUMIFS(DATA!#REF!,DATA!$A:$A,$E$2,DATA!$N:$N,$J:$J,DATA!$K:$K,">="&$C$3,DATA!$K:$K,"<"&$E$3) -> #REF! | F28: =SUMIFS(DATA!#REF!,DATA!$A:$A,$E$2,DATA!$N:$N,$J:$J,DATA!$K:$K,">="&$C$3,DATA!$K:$K,"<"&$E$3) -> #REF! | G28: =SUMIFS(DATA!#REF!,DATA!$A:$A,$E$2,DATA!$N:$N,$J:$J,DATA!$K:$K,">="&$C$3,DATA!$K:$K,"<"&$E$3) -> #REF! | H28: =D28*10+E28 -> #REF! | J28: ="*"&StaffList!#REF!&"*" -> #REF!
B29: TOTAL | C29: =SUM(C8:C28) -> #REF! | D29: =SUM(D8:D28) -> 0 | E29: =SUM(E8:E28) -> #REF! | F29: =SUM(F8:F28) -> #REF! | G29: =SUM(G8:G28) -> #REF!
J30: ="*"&StaffList!#REF!&"*" -> #REF!

Sheet General (Project Satisfaction)
G1: CHỈ SỐ HÀI LÒNG CỦA TỪNG KHÁCH HÀNG | N1: Prepared by: | O1: Hang.ntt
G2: Customer Satisfaction Report | N2: Checked by: | O2: Phong.hv
A3: SPS SERVICES., JSC | F3: Khách hàng/ Customer name: | G3: FRENCH EMBASSY | N3: Updated to: | O3: =TODAY() -> 46004
F4: YEAR: | G4: 2024
B5: Công thức trung gian lọc ra ngày cuối tháng | D5: 31 | E5: =DAY(EOMONTH(DATE(G4,E6,1),0)) -> 29 | F5: 31 | G5: 30 | H5: 31 | I5: 30 | J5: 31 | K5: 31 | L5: 30 | M5: 31 | N5: 30 | O5: 31
B6: THÁNG / MONTH | C6: Phân loại | D6: 1 | E6: 2 | F6: 3 | G6: 4 | H6: 5 | I6: 6 | J6: 7 | K6: 8 | L6: 9 | M6: 10 | N6: 11 | O6: 12 | P6: TOTAL | Q6: %
A7: REPORT | B7: SỐ BÁO CÁO THEO KẾ HOẠCH NUMBER OF REPORTS AS SCHEDULED | D7: =COUNTIFS(DATA!$A:$A,$G$3,DATA!$I:$I,">="&DATE($G$4,D$6,1),DATA!$A:$A,$G$3,DATA!$I:$I,"<="&DATE($G$4,D$6,D$5)) -> 0 | E7: =COUNTIFS(DATA!$A:$A,$G$3,DATA!$I:$I,">="&DATE($G$4,E$6,1),DATA!$A:$A,$G$3,DATA!$I:$I,"<="&DATE($G$4,E$6,E$5)) -> 0 | F7: =COUNTIFS(DATA!$A:$A,$G$3,DATA!$I:$I,">="&DATE($G$4,F$6,1),DATA!$A:$A,$G$3,DATA!$I:$I,"<="&DATE($G$4,F$6,F$5)) -> 0 | G7: =COUNTIFS(DATA!$A:$A,$G$3,DATA!$I:$I,">="&DATE($G$4,G$6,1),DATA!$A:$A,$G$3,DATA!$I:$I,"<="&DATE($G$4,G$6,G$5)) -> 0 | H7: =COUNTIFS(DATA!$A:$A,$G$3,DATA!$I:$I,">="&DATE($G$4,H$6,1),DATA!$A:$A,$G$3,DATA!$I:$I,"<="&DATE($G$4,H$6,H$5)) -> 0 | I7: =COUNTIFS(DATA!$A:$A,$G$3,DATA!$I:$I,">="&DATE($G$4,I$6,1),DATA!$A:$A,$G$3,DATA!$I:$I,"<="&DATE($G$4,I$6,I$5)) -> 0 | J7: =COUNTIFS(DATA!$A:$A,$G$3,DATA!$I:$I,">="&DATE($G$4,J$6,1),DATA!$A:$A,$G$3,DATA!$I:$I,"<="&DATE($G$4,J$6,J$5)) -> 0 | K7: =COUNTIFS(DATA!$A:$A,$G$3,DATA!$I:$I,">="&DATE($G$4,K$6,1),DATA!$A:$A,$G$3,DATA!$I:$I,"<="&DATE($G$4,K$6,K$5)) -> 0 | ... M7: =COUNTIFS(DATA!$A:$A,$G$3,DATA!$I:$I,">="&DATE($G$4,M$6,1),DATA!$A:$A,$G$3,DATA!$I:$I,"<="&DATE($G$4,M$6,M$5)) -> 0 | P7: =SUM(D7:O7) -> 0 | Q7: 1
B8: SỐ BÁO CÁO ĐÃ NHẬN VỀ RECEIVED REPORTS | D8: =COUNTIFS(DATA!$A:$A,$G$3,DATA!$K:$K,">0",DATA!$I:$I,">="&DATE($G$4,D$6,1),DATA!$A:$A,$G$3,DATA!$I:$I,"<="&DATE($G$4,D$6,D$5)) -> 0 | E8: =COUNTIFS(DATA!$A:$A,$G$3,DATA!$K:$K,">0",DATA!$I:$I,">="&DATE($G$4,E$6,1),DATA!$A:$A,$G$3,DATA!$I:$I,"<="&DATE($G$4,E$6,E$5)) -> 0 | F8: =COUNTIFS(DATA!$A:$A,$G$3,DATA!$K:$K,">0",DATA!$I:$I,">="&DATE($G$4,F$6,1),DATA!$A:$A,$G$3,DATA!$I:$I,"<="&DATE($G$4,F$6,F$5)) -> 0 | G8: =COUNTIFS(DATA!$A:$A,$G$3,DATA!$K:$K,">0",DATA!$I:$I,">="&DATE($G$4,G$6,1),DATA!$A:$A,$G$3,DATA!$I:$I,"<="&DATE($G$4,G$6,G$5)) -> 0 | H8: =COUNTIFS(DATA!$A:$A,$G$3,DATA!$K:$K,">0",DATA!$I:$I,">="&DATE($G$4,H$6,1),DATA!$A:$A,$G$3,DATA!$I:$I,"<="&DATE($G$4,H$6,H$5)) -> 0 | I8: =COUNTIFS(DATA!$A:$A,$G$3,DATA!$K:$K,">0",DATA!$I:$I,">="&DATE($G$4,I$6,1),DATA!$A:$A,$G$3,DATA!$I:$I,"<="&DATE($G$4,I$6,I$5)) -> 0 | J8: =COUNTIFS(DATA!$A:$A,$G$3,DATA!$K:$K,">0",DATA!$I:$I,">="&DATE($G$4,J$6,1),DATA!$A:$A,$G$3,DATA!$I:$I,"<="&DATE($G$4,J$6,J$5)) -> 0 | K8: =COUNTIFS(DATA!$A:$A,$G$3,DATA!$K:$K,">0",DATA!$I:$I,">="&DATE($G$4,K$6,1),DATA!$A:$A,$G$3,DATA!$I:$I,"<="&DATE($G$4,K$6,K$5)) -> 0 | ... M8: =COUNTIFS(DATA!$A:$A,$G$3,DATA!$K:$K,">0",DATA!$I:$I,">="&DATE($G$4,M$6,1),DATA!$A:$A,$G$3,DATA!$I:$I,"<="&DATE($G$4,M$6,M$5)) -> 0 | P8: =SUM(D8:O8) -> 0 | Q8: =P8/P7 -> #DIV/0!
B9: SỐ HẠNG MỤC CHƯA HOÀN THÀNH PENDING ITEMS | D9: =IF(TODAY()>DATE($G$4,D6,D5),D7-D8,0) -> 0 | E9: =IF(TODAY()>DATE($G$4,E6,E5),E7-E8,0) -> 0 | F9: =IF(TODAY()>DATE($G$4,F6,F5),F7-F8,0) -> 0 | G9: =IF(TODAY()>DATE($G$4,G6,G5),G7-G8,0) -> 0 | H9: =IF(TODAY()>DATE($G$4,H6,H5),H7-H8,0) -> 0 | I9: =IF(TODAY()>DATE($G$4,I6,I5),I7-I8,0) -> 0 | J9: =IF(TODAY()>DATE($G$4,J6,J5),J7-J8,0) -> 0 | K9: =IF(TODAY()>DATE($G$4,K6,K5),K7-K8,0) -> 0 | ... M9: =IF(TODAY()>DATE($G$4,M6,M5),M7-M8,0) -> 0 | P9: =SUM(D9:O9) -> 0 | Q9: =P9/P8 -> #DIV/0!
A10: CLIENT FEED BACK | B10: SỐ BÁO CÁO CÓ PHẢN HỒI KHÁCH HÀNG NUMBER OF REPORTS WITH CUSTOMER'S FEED BACK | D10: =SUM(D11:D14) -> 0 | E10: =SUM(E11:E14) -> 0 | F10: =SUM(F11:F14) -> 0 | G10: =SUM(G11:G14) -> 0 | H10: =SUM(H11:H14) -> 0 | I10: =SUM(I11:I14) -> 0 | J10: =SUM(J11:J14) -> 0 | K10: =SUM(K11:K14) -> 0 | ... M10: =SUM(M11:M14) -> 0 | P10: =SUM(D10:O10) -> 0 | Q10: =P10/P8 -> #DIV/0!
B11: RẤT HÀI LÒNG EXCEEDED SATISFY | C11: E | D11: =COUNTIFS(DATA!$A:$A,$G$3,DATA!$P:$P,"=E",DATA!$K:$K,">="&DATE($G$4,D$6,1),DATA!$K:$K,"<="&DATE($G$4,D$6,D$5)) -> 0 | E11: =COUNTIFS(DATA!$A:$A,$G$3,DATA!$P:$P,"=E",DATA!$K:$K,">="&DATE($G$4,E$6,1),DATA!$K:$K,"<="&DATE($G$4,E$6,E$5)) -> 0 | F11: =COUNTIFS(DATA!$A:$A,$G$3,DATA!$P:$P,"=E",DATA!$K:$K,">="&DATE($G$4,F$6,1),DATA!$K:$K,"<="&DATE($G$4,F$6,F$5)) -> 0 | G11: =COUNTIFS(DATA!$A:$A,$G$3,DATA!$P:$P,"=E",DATA!$K:$K,">="&DATE($G$4,G$6,1),DATA!$K:$K,"<="&DATE($G$4,G$6,G$5)) -> 0 | H11: =COUNTIFS(DATA!$A:$A,$G$3,DATA!$P:$P,"=E",DATA!$K:$K,">="&DATE($G$4,H$6,1),DATA!$K:$K,"<="&DATE($G$4,H$6,H$5)) -> 0 | I11: =COUNTIFS(DATA!$A:$A,$G$3,DATA!$P:$P,"=E",DATA!$K:$K,">="&DATE($G$4,I$6,1),DATA!$K:$K,"<="&DATE($G$4,I$6,I$5)) -> 0 | J11: =COUNTIFS(DATA!$A:$A,$G$3,DATA!$P:$P,"=E",DATA!$K:$K,">="&DATE($G$4,J$6,1),DATA!$K:$K,"<="&DATE($G$4,J$6,J$5)) -> 0 | K11: =COUNTIFS(DATA!$A:$A,$G$3,DATA!$P:$P,"=E",DATA!$K:$K,">="&DATE($G$4,K$6,1),DATA!$K:$K,"<="&DATE($G$4,K$6,K$5)) -> 0 | ... M11: =COUNTIFS(DATA!$A:$A,$G$3,DATA!$P:$P,"=E",DATA!$K:$K,">="&DATE($G$4,M$6,1),DATA!$K:$K,"<="&DATE($G$4,M$6,M$5)) -> 0 | P11: =SUM(D11:O11) -> 0 | Q11: =P11/$P$10 -> #DIV/0!
B12: HÀI LÒNG SATISFIED | C12: S | D12: =COUNTIFS(DATA!$A:$A,$G$3,DATA!$P:$P,"=S",DATA!$K:$K,">="&DATE($G$4,D$6,1),DATA!$K:$K,"<="&DATE($G$4,D$6,D$5)) -> 0 | E12: =COUNTIFS(DATA!$A:$A,$G$3,DATA!$P:$P,"=S",DATA!$K:$K,">="&DATE($G$4,E$6,1),DATA!$K:$K,"<="&DATE($G$4,E$6,E$5)) -> 0 | F12: =COUNTIFS(DATA!$A:$A,$G$3,DATA!$P:$P,"=S",DATA!$K:$K,">="&DATE($G$4,F$6,1),DATA!$K:$K,"<="&DATE($G$4,F$6,F$5)) -> 0 | G12: =COUNTIFS(DATA!$A:$A,$G$3,DATA!$P:$P,"=S",DATA!$K:$K,">="&DATE($G$4,G$6,1),DATA!$K:$K,"<="&DATE($G$4,G$6,G$5)) -> 0 | H12: =COUNTIFS(DATA!$A:$A,$G$3,DATA!$P:$P,"=S",DATA!$K:$K,">="&DATE($G$4,H$6,1),DATA!$K:$K,"<="&DATE($G$4,H$6,H$5)) -> 0 | I12: =COUNTIFS(DATA!$A:$A,$G$3,DATA!$P:$P,"=S",DATA!$K:$K,">="&DATE($G$4,I$6,1),DATA!$K:$K,"<="&DATE($G$4,I$6,I$5)) -> 0 | J12: =COUNTIFS(DATA!$A:$A,$G$3,DATA!$P:$P,"=S",DATA!$K:$K,">="&DATE($G$4,J$6,1),DATA!$K:$K,"<="&DATE($G$4,J$6,J$5)) -> 0 | K12: =COUNTIFS(DATA!$A:$A,$G$3,DATA!$P:$P,"=S",DATA!$K:$K,">="&DATE($G$4,K$6,1),DATA!$K:$K,"<="&DATE($G$4,K$6,K$5)) -> 0 | ... M12: =COUNTIFS(DATA!$A:$A,$G$3,DATA!$P:$P,"=S",DATA!$K:$K,">="&DATE($G$4,M$6,1),DATA!$K:$K,"<="&DATE($G$4,M$6,M$5)) -> 0 | P12: =SUM(D12:O12) -> 0 | Q12: =P12/$P$10 -> #DIV/0!
B13: CHẤP NHẬN ACCEPTABLE | C13: A | D13: =COUNTIFS(DATA!$A:$A,$G$3,DATA!$P:$P,"=A",DATA!$K:$K,">="&DATE($G$4,D$6,1),DATA!$K:$K,"<="&DATE($G$4,D$6,D$5)) -> 0 | E13: =COUNTIFS(DATA!$A:$A,$G$3,DATA!$P:$P,"=A",DATA!$K:$K,">="&DATE($G$4,E$6,1),DATA!$K:$K,"<="&DATE($G$4,E$6,E$5)) -> 0 | F13: =COUNTIFS(DATA!$A:$A,$G$3,DATA!$P:$P,"=A",DATA!$K:$K,">="&DATE($G$4,F$6,1),DATA!$K:$K,"<="&DATE($G$4,F$6,F$5)) -> 0 | G13: =COUNTIFS(DATA!$A:$A,$G$3,DATA!$P:$P,"=A",DATA!$K:$K,">="&DATE($G$4,G$6,1),DATA!$K:$K,"<="&DATE($G$4,G$6,G$5)) -> 0 | H13: =COUNTIFS(DATA!$A:$A,$G$3,DATA!$P:$P,"=A",DATA!$K:$K,">="&DATE($G$4,H$6,1),DATA!$K:$K,"<="&DATE($G$4,H$6,H$5)) -> 0 | I13: =COUNTIFS(DATA!$A:$A,$G$3,DATA!$P:$P,"=A",DATA!$K:$K,">="&DATE($G$4,I$6,1),DATA!$K:$K,"<="&DATE($G$4,I$6,I$5)) -> 0 | J13: =COUNTIFS(DATA!$A:$A,$G$3,DATA!$P:$P,"=A",DATA!$K:$K,">="&DATE($G$4,J$6,1),DATA!$K:$K,"<="&DATE($G$4,J$6,J$5)) -> 0 | K13: =COUNTIFS(DATA!$A:$A,$G$3,DATA!$P:$P,"=A",DATA!$K:$K,">="&DATE($G$4,K$6,1),DATA!$K:$K,"<="&DATE($G$4,K$6,K$5)) -> 0 | ... M13: =COUNTIFS(DATA!$A:$A,$G$3,DATA!$P:$P,"=A",DATA!$K:$K,">="&DATE($G$4,M$6,1),DATA!$K:$K,"<="&DATE($G$4,M$6,M$5)) -> 0 | P13: =SUM(D13:O13) -> 0 | Q13: =P13/$P$10 -> #DIV/0!
B14: KHÔNG HÀI LÒNG DISSATISFIED | C14: D | D14: =COUNTIFS(DATA!$A:$A,$G$3,DATA!$P:$P,"=D",DATA!$K:$K,">="&DATE($G$4,D$6,1),DATA!$K:$K,"<="&DATE($G$4,D$6,D$5)) -> 0 | E14: =COUNTIFS(DATA!$A:$A,$G$3,DATA!$P:$P,"=D",DATA!$K:$K,">="&DATE($G$4,E$6,1),DATA!$K:$K,"<="&DATE($G$4,E$6,E$5)) -> 0 | F14: =COUNTIFS(DATA!$A:$A,$G$3,DATA!$P:$P,"=D",DATA!$K:$K,">="&DATE($G$4,F$6,1),DATA!$K:$K,"<="&DATE($G$4,F$6,F$5)) -> 0 | G14: =COUNTIFS(DATA!$A:$A,$G$3,DATA!$P:$P,"=D",DATA!$K:$K,">="&DATE($G$4,G$6,1),DATA!$K:$K,"<="&DATE($G$4,G$6,G$5)) -> 0 | H14: =COUNTIFS(DATA!$A:$A,$G$3,DATA!$P:$P,"=D",DATA!$K:$K,">="&DATE($G$4,H$6,1),DATA!$K:$K,"<="&DATE($G$4,H$6,H$5)) -> 0 | I14: =COUNTIFS(DATA!$A:$A,$G$3,DATA!$P:$P,"=D",DATA!$K:$K,">="&DATE($G$4,I$6,1),DATA!$K:$K,"<="&DATE($G$4,I$6,I$5)) -> 0 | J14: =COUNTIFS(DATA!$A:$A,$G$3,DATA!$P:$P,"=D",DATA!$K:$K,">="&DATE($G$4,J$6,1),DATA!$K:$K,"<="&DATE($G$4,J$6,J$5)) -> 0 | K14: =COUNTIFS(DATA!$A:$A,$G$3,DATA!$P:$P,"=D",DATA!$K:$K,">="&DATE($G$4,K$6,1),DATA!$K:$K,"<="&DATE($G$4,K$6,K$5)) -> 0 | ... M14: =COUNTIFS(DATA!$A:$A,$G$3,DATA!$P:$P,"=D",DATA!$K:$K,">="&DATE($G$4,M$6,1),DATA!$K:$K,"<="&DATE($G$4,M$6,M$5)) -> 0 | P14: =SUM(D14:O14) -> 0 | Q14: =P14/$P$10 -> #DIV/0!
A15: PERCENTAGE | B15: MỤC TIÊU MỨC ĐỘ HÀI LÒNG TARGET OF SATISFIED LEVEL | D15: 0.95 | E15: =D15 -> 0.95 | F15: =E15 -> 0.95 | G15: =F15 -> 0.95 | H15: =G15 -> 0.95 | I15: =H15 -> 0.95 | J15: =I15 -> 0.95 | K15: =J15 -> 0.95 | L15: =K15 -> 0.95 | ... P15: =O15 -> 0.95 | Q15: =P15/P16 -> #VALUE!
B16: % MỨC ĐỘ HÀI LÒNG PERCENTAGE OF SATISFIED LEVEL | D16: =IF(D10>0,(D12+D11)/D10,"") | E16: =IF(E10>0,(E12+E11)/E10,"") | F16: =IF(F10>0,(F12+F11)/F10,"") | G16: =IF(G10>0,(G12+G11)/G10,"") | H16: =IF(H10>0,(H12+H11)/H10,"") | I16: =IF(I10>0,(I12+I11)/I10,"") | J16: =IF(J10>0,(J12+J11)/J10,"") | K16: =IF(K10>0,(K12+K11)/K10,"") | ... P16: =IF(P10>0,(P12+P11)/P10,"")
P17: =P16

Sheet Trouble shooting
C1: CHỈ SỐ HÀI LÒNG CỦA KHÁCH HÀNG ĐỐI VỚI NHÂN VIÊN XỬ LÝ SỰ CỐ
A2: SPS SERVICES.,JSC | C2: ASSESSMENT OF CUSTOMER SATISFACTION FOR EACH EMPLOYEES
B3: Từ ngày / From date: | C3: 45261 | D3: Tới / To: | E3: =EOMONTH(C3,0) -> 45291 | I3: Reported by: Hang.ntt
A4: Ghi chú: Số báo cáo một dịch vụ bằng tổng số người thực tế đi làm dịch vụ đó. Báo cáo không bao gồm thực tập sinh hoặc thầu phụ
A6: TT | B6: Tên nhân viên | C6: Tổng số báo cáo xử lý sự cố có phản hồi của từng NV | D6: Rất hài lòng | E6: Hài lòng | F6: Chấp nhận | G6: Không hài lòng | H6: Tỉ lệ hài lòng | I6: Điểm để so sánh | K6: Ký kiệu trung gian cho công thức tự động
A7: No | B7: Full Name | C7: Total report wt feedback | D7: Exceeded satisfy (E) | E7: Satisfied (S) | F7: Acceptable (A) | G7: Dissatisfied (D) | H7: Satisfaction rate (%) | I7: Rating (Ex10+Sx1) | K7: Name for calculator
A8: 1 | B8: =VLOOKUP(K8, StaffList!B:C,2,FALSE) -> Lê Hùng Mạnh | C8: =COUNTIFS(DATA!$F:$F,"=Trouble shooting", DATA!$N:$N,$K:$K,DATA!$K:$K,">="&$C$3,DATA!$K:$K,"<="&$E$3) -> 0 | D8: =COUNTIFS(DATA!$P:$P,"=E", DATA!$F:$F,"=Trouble shooting",DATA!$N:$N,$K:$K,DATA!$K:$K,">="&$C$3,DATA!$K:$K,"<="&$E$3) -> 0 | E8: =COUNTIFS(DATA!$P:$P,"=S", DATA!$F:$F,"=Trouble shooting",DATA!$N:$N,$K:$K,DATA!$K:$K,">="&$C$3,DATA!$K:$K,"<="&$E$3) -> 0 | F8: =COUNTIFS(DATA!$P:$P,"=A", DATA!$F:$F,"=Trouble shooting",DATA!$N:$N,$K:$K,DATA!$K:$K,">="&$C$3,DATA!$K:$K,"<="&$E$3) -> 0 | G8: =COUNTIFS(DATA!$P:$P,"=D", DATA!$F:$F,"=Trouble shooting",DATA!$N:$N,$K:$K,DATA!$K:$K,">="&$C$3,DATA!$K:$K,"<="&$E$3) -> 0 | H8: =IF(SUM(D8:G8)=0,"-",SUM(D8:E8)/SUM(D8:G8)) -> - | I8: =D8*10+E8 -> 0 | K8: ="*"&StaffList!B5&"*" -> *Manh.lh*
A9: 2 | B9: =VLOOKUP(K9, StaffList!B:C,2,FALSE) -> Hà Đình Diên | C9: =COUNTIFS(DATA!$F:$F,"=Trouble shooting", DATA!$N:$N,$K:$K,DATA!$K:$K,">="&$C$3,DATA!$K:$K,"<="&$E$3) -> 0 | D9: =COUNTIFS(DATA!$P:$P,"=E", DATA!$F:$F,"=Trouble shooting",DATA!$N:$N,$K:$K,DATA!$K:$K,">="&$C$3,DATA!$K:$K,"<="&$E$3) -> 0 | E9: =COUNTIFS(DATA!$P:$P,"=S", DATA!$F:$F,"=Trouble shooting",DATA!$N:$N,$K:$K,DATA!$K:$K,">="&$C$3,DATA!$K:$K,"<="&$E$3) -> 0 | F9: =COUNTIFS(DATA!$P:$P,"=A", DATA!$F:$F,"=Trouble shooting",DATA!$N:$N,$K:$K,DATA!$K:$K,">="&$C$3,DATA!$K:$K,"<="&$E$3) -> 0 | G9: =COUNTIFS(DATA!$P:$P,"=D", DATA!$F:$F,"=Trouble shooting",DATA!$N:$N,$K:$K,DATA!$K:$K,">="&$C$3,DATA!$K:$K,"<="&$E$3) -> 0 | H9: =IF(SUM(D9:G9)=0,"-",SUM(D9:E9)/SUM(D9:G9)) -> - | I9: =D9*10+E9 -> 0 | K9: ="*"&StaffList!B6&"*" -> *Dien.hd*
A10: 3 | B10: =VLOOKUP(K10, StaffList!B:C,2,FALSE) -> Nguyễn Mạnh Hùng | C10: =COUNTIFS(DATA!$F:$F,"=Trouble shooting", DATA!$N:$N,$K:$K,DATA!$K:$K,">="&$C$3,DATA!$K:$K,"<="&$E$3) -> 0 | D10: =COUNTIFS(DATA!$P:$P,"=E", DATA!$F:$F,"=Trouble shooting",DATA!$N:$N,$K:$K,DATA!$K:$K,">="&$C$3,DATA!$K:$K,"<="&$E$3) -> 0 | E10: =COUNTIFS(DATA!$P:$P,"=S", DATA!$F:$F,"=Trouble shooting",DATA!$N:$N,$K:$K,DATA!$K:$K,">="&$C$3,DATA!$K:$K,"<="&$E$3) -> 0 | F10: =COUNTIFS(DATA!$P:$P,"=A", DATA!$F:$F,"=Trouble shooting",DATA!$N:$N,$K:$K,DATA!$K:$K,">="&$C$3,DATA!$K:$K,"<="&$E$3) -> 0 | G10: =COUNTIFS(DATA!$P:$P,"=D", DATA!$F:$F,"=Trouble shooting",DATA!$N:$N,$K:$K,DATA!$K:$K,">="&$C$3,DATA!$K:$K,"<="&$E$3) -> 0 | H10: =IF(SUM(D10:G10)=0,"-",SUM(D10:E10)/SUM(D10:G10)) -> - | I10: =D10*10+E10 -> 0 | K10: ="*"&StaffList!B7&"*" -> *Hung.nm*
A11: 4 | B11: =VLOOKUP(K11, StaffList!B:C,2,FALSE) -> Vũ Hoàng | C11: =COUNTIFS(DATA!$F:$F,"=Trouble shooting", DATA!$N:$N,$K:$K,DATA!$K:$K,">="&$C$3,DATA!$K:$K,"<="&$E$3) -> 0 | D11: =COUNTIFS(DATA!$P:$P,"=E", DATA!$F:$F,"=Trouble shooting",DATA!$N:$N,$K:$K,DATA!$K:$K,">="&$C$3,DATA!$K:$K,"<="&$E$3) -> 0 | E11: =COUNTIFS(DATA!$P:$P,"=S", DATA!$F:$F,"=Trouble shooting",DATA!$N:$N,$K:$K,DATA!$K:$K,">="&$C$3,DATA!$K:$K,"<="&$E$3) -> 0 | F11: =COUNTIFS(DATA!$P:$P,"=A", DATA!$F:$F,"=Trouble shooting",DATA!$N:$N,$K:$K,DATA!$K:$K,">="&$C$3,DATA!$K:$K,"<="&$E$3) -> 0 | G11: =COUNTIFS(DATA!$P:$P,"=D", DATA!$F:$F,"=Trouble shooting",DATA!$N:$N,$K:$K,DATA!$K:$K,">="&$C$3,DATA!$K:$K,"<="&$E$3) -> 0 | H11: =IF(SUM(D11:G11)=0,"-",SUM(D11:E11)/SUM(D11:G11)) -> - | I11: =D11*10+E11 -> 0 | K11: ="*"&StaffList!B8&"*" -> *Hoang.v*
A12: 5 | B12: =VLOOKUP(K12, StaffList!B:C,2,FALSE) -> Hồ Sỹ Hiệp | C12: =COUNTIFS(DATA!$F:$F,"=Trouble shooting", DATA!$N:$N,$K:$K,DATA!$K:$K,">="&$C$3,DATA!$K:$K,"<="&$E$3) -> 0 | D12: =COUNTIFS(DATA!$P:$P,"=E", DATA!$F:$F,"=Trouble shooting",DATA!$N:$N,$K:$K,DATA!$K:$K,">="&$C$3,DATA!$K:$K,"<="&$E$3) -> 0 | E12: =COUNTIFS(DATA!$P:$P,"=S", DATA!$F:$F,"=Trouble shooting",DATA!$N:$N,$K:$K,DATA!$K:$K,">="&$C$3,DATA!$K:$K,"<="&$E$3) -> 0 | F12: =COUNTIFS(DATA!$P:$P,"=A", DATA!$F:$F,"=Trouble shooting",DATA!$N:$N,$K:$K,DATA!$K:$K,">="&$C$3,DATA!$K:$K,"<="&$E$3) -> 0 | G12: =COUNTIFS(DATA!$P:$P,"=D", DATA!$F:$F,"=Trouble shooting",DATA!$N:$N,$K:$K,DATA!$K:$K,">="&$C$3,DATA!$K:$K,"<="&$E$3) -> 0 | H12: =IF(SUM(D12:G12)=0,"-",SUM(D12:E12)/SUM(D12:G12)) -> - | I12: =D12*10+E12 -> 0 | K12: ="*"&StaffList!B9&"*" -> *Hiep.hs*
A13: 6 | B13: =VLOOKUP(K13, StaffList!B:C,2,FALSE) -> Chu Trọng Thao | C13: =COUNTIFS(DATA!$F:$F,"=Trouble shooting", DATA!$N:$N,$K:$K,DATA!$K:$K,">="&$C$3,DATA!$K:$K,"<="&$E$3) -> 0 | D13: =COUNTIFS(DATA!$P:$P,"=E", DATA!$F:$F,"=Trouble shooting",DATA!$N:$N,$K:$K,DATA!$K:$K,">="&$C$3,DATA!$K:$K,"<="&$E$3) -> 0 | E13: =COUNTIFS(DATA!$P:$P,"=S", DATA!$F:$F,"=Trouble shooting",DATA!$N:$N,$K:$K,DATA!$K:$K,">="&$C$3,DATA!$K:$K,"<="&$E$3) -> 0 | F13: =COUNTIFS(DATA!$P:$P,"=A", DATA!$F:$F,"=Trouble shooting",DATA!$N:$N,$K:$K,DATA!$K:$K,">="&$C$3,DATA!$K:$K,"<="&$E$3) -> 0 | G13: =COUNTIFS(DATA!$P:$P,"=D", DATA!$F:$F,"=Trouble shooting",DATA!$N:$N,$K:$K,DATA!$K:$K,">="&$C$3,DATA!$K:$K,"<="&$E$3) -> 0 | H13: =IF(SUM(D13:G13)=0,"-",SUM(D13:E13)/SUM(D13:G13)) -> - | I13: =D13*10+E13 -> 0 | K13: ="*"&StaffList!B10&"*" -> *Thao.ct*
A14: 7 | B14: =VLOOKUP(K14, StaffList!B:C,2,FALSE) -> Mông Văn Thương | C14: =COUNTIFS(DATA!$F:$F,"=Trouble shooting", DATA!$N:$N,$K:$K,DATA!$K:$K,">="&$C$3,DATA!$K:$K,"<="&$E$3) -> 0 | D14: =COUNTIFS(DATA!$P:$P,"=E", DATA!$F:$F,"=Trouble shooting",DATA!$N:$N,$K:$K,DATA!$K:$K,">="&$C$3,DATA!$K:$K,"<="&$E$3) -> 0 | E14: =COUNTIFS(DATA!$P:$P,"=S", DATA!$F:$F,"=Trouble shooting",DATA!$N:$N,$K:$K,DATA!$K:$K,">="&$C$3,DATA!$K:$K,"<="&$E$3) -> 0 | F14: =COUNTIFS(DATA!$P:$P,"=A", DATA!$F:$F,"=Trouble shooting",DATA!$N:$N,$K:$K,DATA!$K:$K,">="&$C$3,DATA!$K:$K,"<="&$E$3) -> 0 | G14: =COUNTIFS(DATA!$P:$P,"=D", DATA!$F:$F,"=Trouble shooting",DATA!$N:$N,$K:$K,DATA!$K:$K,">="&$C$3,DATA!$K:$K,"<="&$E$3) -> 0 | H14: =IF(SUM(D14:G14)=0,"-",SUM(D14:E14)/SUM(D14:G14)) -> - | I14: =D14*10+E14 -> 0 | K14: ="*"&StaffList!B11&"*" -> *Thuong.mv*
A15: 8 | B15: =VLOOKUP(K15, StaffList!B:C,2,FALSE) -> Chu Tiến Dũng | C15: =COUNTIFS(DATA!$F:$F,"=Trouble shooting", DATA!$N:$N,$K:$K,DATA!$K:$K,">="&$C$3,DATA!$K:$K,"<="&$E$3) -> 0 | D15: =COUNTIFS(DATA!$P:$P,"=E", DATA!$F:$F,"=Trouble shooting",DATA!$N:$N,$K:$K,DATA!$K:$K,">="&$C$3,DATA!$K:$K,"<="&$E$3) -> 0 | E15: =COUNTIFS(DATA!$P:$P,"=S", DATA!$F:$F,"=Trouble shooting",DATA!$N:$N,$K:$K,DATA!$K:$K,">="&$C$3,DATA!$K:$K,"<="&$E$3) -> 0 | F15: =COUNTIFS(DATA!$P:$P,"=A", DATA!$F:$F,"=Trouble shooting",DATA!$N:$N,$K:$K,DATA!$K:$K,">="&$C$3,DATA!$K:$K,"<="&$E$3) -> 0 | G15: =COUNTIFS(DATA!$P:$P,"=D", DATA!$F:$F,"=Trouble shooting",DATA!$N:$N,$K:$K,DATA!$K:$K,">="&$C$3,DATA!$K:$K,"<="&$E$3) -> 0 | H15: =IF(SUM(D15:G15)=0,"-",SUM(D15:E15)/SUM(D15:G15)) -> - | I15: =D15*10+E15 -> 0 | K15: ="*"&StaffList!B12&"*" -> *Dung.ct*
A16: 9 | B16: =VLOOKUP(K16, StaffList!B:C,2,FALSE) -> Vũ Xuân Phúc | C16: =COUNTIFS(DATA!$F:$F,"=Trouble shooting", DATA!$N:$N,$K:$K,DATA!$K:$K,">="&$C$3,DATA!$K:$K,"<="&$E$3) -> 0 | D16: =COUNTIFS(DATA!$P:$P,"=E", DATA!$F:$F,"=Trouble shooting",DATA!$N:$N,$K:$K,DATA!$K:$K,">="&$C$3,DATA!$K:$K,"<="&$E$3) -> 0 | E16: =COUNTIFS(DATA!$P:$P,"=S", DATA!$F:$F,"=Trouble shooting",DATA!$N:$N,$K:$K,DATA!$K:$K,">="&$C$3,DATA!$K:$K,"<="&$E$3) -> 0 | F16: =COUNTIFS(DATA!$P:$P,"=A", DATA!$F:$F,"=Trouble shooting",DATA!$N:$N,$K:$K,DATA!$K:$K,">="&$C$3,DATA!$K:$K,"<="&$E$3) -> 0 | G16: =COUNTIFS(DATA!$P:$P,"=D", DATA!$F:$F,"=Trouble shooting",DATA!$N:$N,$K:$K,DATA!$K:$K,">="&$C$3,DATA!$K:$K,"<="&$E$3) -> 0 | H16: =IF(SUM(D16:G16)=0,"-",SUM(D16:E16)/SUM(D16:G16)) -> - | I16: =D16*10+E16 -> 0 | K16: ="*"&StaffList!B13&"*" -> *Phuc.vx*
A17: 10 | B17: =VLOOKUP(K17, StaffList!B:C,2,FALSE) -> Hoàng Việt Thao | C17: =COUNTIFS(DATA!$F:$F,"=Trouble shooting", DATA!$N:$N,$K:$K,DATA!$K:$K,">="&$C$3,DATA!$K:$K,"<="&$E$3) -> 0 | D17: =COUNTIFS(DATA!$P:$P,"=E", DATA!$F:$F,"=Trouble shooting",DATA!$N:$N,$K:$K,DATA!$K:$K,">="&$C$3,DATA!$K:$K,"<="&$E$3) -> 0 | E17: =COUNTIFS(DATA!$P:$P,"=S", DATA!$F:$F,"=Trouble shooting",DATA!$N:$N,$K:$K,DATA!$K:$K,">="&$C$3,DATA!$K:$K,"<="&$E$3) -> 0 | F17: =COUNTIFS(DATA!$P:$P,"=A", DATA!$F:$F,"=Trouble shooting",DATA!$N:$N,$K:$K,DATA!$K:$K,">="&$C$3,DATA!$K:$K,"<="&$E$3) -> 0 | G17: =COUNTIFS(DATA!$P:$P,"=D", DATA!$F:$F,"=Trouble shooting",DATA!$N:$N,$K:$K,DATA!$K:$K,">="&$C$3,DATA!$K:$K,"<="&$E$3) -> 0 | H17: =IF(SUM(D17:G17)=0,"-",SUM(D17:E17)/SUM(D17:G17)) -> - | I17: =D17*10+E17 -> 0 | K17: ="*"&StaffList!B14&"*" -> *Thao.hv*
A18: 11 | B18: =VLOOKUP(K18, StaffList!B:C,2,FALSE) -> Đỗ Văn Cường | C18: =COUNTIFS(DATA!$F:$F,"=Trouble shooting", DATA!$N:$N,$K:$K,DATA!$K:$K,">="&$C$3,DATA!$K:$K,"<="&$E$3) -> 0 | D18: =COUNTIFS(DATA!$P:$P,"=E", DATA!$F:$F,"=Trouble shooting",DATA!$N:$N,$K:$K,DATA!$K:$K,">="&$C$3,DATA!$K:$K,"<="&$E$3) -> 0 | E18: =COUNTIFS(DATA!$P:$P,"=S", DATA!$F:$F,"=Trouble shooting",DATA!$N:$N,$K:$K,DATA!$K:$K,">="&$C$3,DATA!$K:$K,"<="&$E$3) -> 0 | F18: =COUNTIFS(DATA!$P:$P,"=A", DATA!$F:$F,"=Trouble shooting",DATA!$N:$N,$K:$K,DATA!$K:$K,">="&$C$3,DATA!$K:$K,"<="&$E$3) -> 0 | G18: =COUNTIFS(DATA!$P:$P,"=D", DATA!$F:$F,"=Trouble shooting",DATA!$N:$N,$K:$K,DATA!$K:$K,">="&$C$3,DATA!$K:$K,"<="&$E$3) -> 0 | H18: =IF(SUM(D18:G18)=0,"-",SUM(D18:E18)/SUM(D18:G18)) -> - | I18: =D18*10+E18 -> 0 | K18: ="*"&StaffList!B15&"*" -> *Cuong.dv*
A19: 12 | B19: =VLOOKUP(K19, StaffList!B:C,2,FALSE) -> Mai Văn Hoàng | C19: =COUNTIFS(DATA!$F:$F,"=Trouble shooting", DATA!$N:$N,$K:$K,DATA!$K:$K,">="&$C$3,DATA!$K:$K,"<="&$E$3) -> 0 | D19: =COUNTIFS(DATA!$P:$P,"=E", DATA!$F:$F,"=Trouble shooting",DATA!$N:$N,$K:$K,DATA!$K:$K,">="&$C$3,DATA!$K:$K,"<="&$E$3) -> 0 | E19: =COUNTIFS(DATA!$P:$P,"=S", DATA!$F:$F,"=Trouble shooting",DATA!$N:$N,$K:$K,DATA!$K:$K,">="&$C$3,DATA!$K:$K,"<="&$E$3) -> 0 | F19: =COUNTIFS(DATA!$P:$P,"=A", DATA!$F:$F,"=Trouble shooting",DATA!$N:$N,$K:$K,DATA!$K:$K,">="&$C$3,DATA!$K:$K,"<="&$E$3) -> 0 | G19: =COUNTIFS(DATA!$P:$P,"=D", DATA!$F:$F,"=Trouble shooting",DATA!$N:$N,$K:$K,DATA!$K:$K,">="&$C$3,DATA!$K:$K,"<="&$E$3) -> 0 | H19: =IF(SUM(D19:G19)=0,"-",SUM(D19:E19)/SUM(D19:G19)) -> - | I19: =D19*10+E19 -> 0 | K19: ="*"&StaffList!B16&"*" -> *Hoang.mv*
... A36: 29 | B36: =VLOOKUP(K36, StaffList!B:C,2,FALSE) -> Nguyễn Công Hoàng | C36: =COUNTIFS(DATA!$F:$F,"=Trouble shooting", DATA!$N:$N,$K:$K,DATA!$K:$K,">="&$C$3,DATA!$K:$K,"<="&$E$3) -> 0 | D36: =COUNTIFS(DATA!$P:$P,"=E", DATA!$F:$F,"=Trouble shooting",DATA!$N:$N,$K:$K,DATA!$K:$K,">="&$C$3,DATA!$K:$K,"<="&$E$3) -> 0 | E36: =COUNTIFS(DATA!$P:$P,"=S", DATA!$F:$F,"=Trouble shooting",DATA!$N:$N,$K:$K,DATA!$K:$K,">="&$C$3,DATA!$K:$K,"<="&$E$3) -> 0 | F36: =COUNTIFS(DATA!$P:$P,"=A", DATA!$F:$F,"=Trouble shooting",DATA!$N:$N,$K:$K,DATA!$K:$K,">="&$C$3,DATA!$K:$K,"<="&$E$3) -> 0 | G36: =COUNTIFS(DATA!$P:$P,"=D", DATA!$F:$F,"=Trouble shooting",DATA!$N:$N,$K:$K,DATA!$K:$K,">="&$C$3,DATA!$K:$K,"<="&$E$3) -> 0 | H36: =IF(SUM(D36:G36)=0,"-",SUM(D36:E36)/SUM(D36:G36)) -> - | I36: =D36*10+E36 -> 0 | K36: ="*"&StaffList!B33&"*" -> *Hoang.nc*
B37: TOTAL | C37: =SUM(C8:C36) -> 0 | D37: =SUM(D8:D36) -> 0 | E37: =SUM(E8:E36) -> 0 | F37: =SUM(F8:F36) -> 0 | G37: =SUM(G8:G36) -> 0 | H37: =IF(SUM(D37:G37)=0,"-",SUM(D37:E37)/SUM(D37:G37)) -> -

Sheet StaffList
A1: DANH SÁCH NHÂN SỰ DỰ ÁN
A2: Lưu ý: Cập nhật khi có nhân viên mới hoặc xóa đi khi có nhân viên nghỉ việc
A3: Thứ tự | B3: Viết tắt | C3: Họ và tên nhân viên | D3: Vị trí
A4: No. | B4: Short Name | C4: Full Name | D4: Position
A5: 1 | B5: Manh.lh | C5: Lê Hùng Mạnh
A6: 2 | B6: Dien.hd | C6: Hà Đình Diên
A7: 3 | B7: Hung.nm | C7: Nguyễn Mạnh Hùng
A8: 4 | B8: Hoang.v | C8: Vũ Hoàng
A9: 5 | B9: Hiep.hs | C9: Hồ Sỹ Hiệp
A10: 6 | B10: Thao.ct | C10: Chu Trọng Thao
A11: 7 | B11: Thuong.mv | C11: Mông Văn Thương
A12: 8 | B12: Dung.ct | C12: Chu Tiến Dũng
A13: 9 | B13: Phuc.vx | C13: Vũ Xuân Phúc
A14: 10 | B14: Thao.hv | C14: Hoàng Việt Thao
A15: 11 | B15: Cuong.dv | C15: Đỗ Văn Cường
A16: 12 | B16: Hoang.mv | C16: Mai Văn Hoàng
... A38: 34 | B38: Vinh.nv | C38: Nguyễn Văn Vịnh

Sheet DATA (For monthly bonus)
E1: PROJECT COMPLETED REPORT FOLLOW UP
B3: 1. Pending report (báo cáo chưa hoàn thiện) (P): Công việc chưa thực hiện được (do KH chưa sắp lịch, bộ phận chưa/quên sắp lịch)...hoặc thực hiện chưa xong/ Works haven't been done
A4: NOTE: | B4: 2. Missing report (báo cáo thiếu) (M): Công việc đã thực hiện (chưa nộp báo cáo về VP/ KH chưa ký/ mất báo cáo…)/ Works done but Report havent been submitted to Office
B5: 3. Cancel report: CV không thực hiện do KH hủy ko yêu cầu/ Works cancel because client not require
A6: Tên khách hàng | B6: Địa điểm thực hiện dịch vụ | C6: Mã số dự án | D6: Mã phụ dự án | E6: Tên dự án | F6: Thiết bị | G6: Tần suất | H6: Mã hiệu | I6: Số lg | J6: Phân loại | K6: Tính or miễn phí | L6: Kế hoạch Planed | N6: Thực tế Actual | P6: Tình trạng chung | Q6: Ý kiến của KH (nếu có) | R6: P.trách dự án | S6: Hành động khắc phục | T6: Mức hài lòng | U6: Ghi chú | V6: KG ĐÁNH GIÁ MỨC HÀI LÒNG KH | W6: Báo cáo chưa về văn phòng
A7: Customer name | B7: Service Location | C7: Project number | D7: Project subcode | E7: Project name | F7: Equipment | G7: Frequency | H7: Model | I7: Q.ty | J7: Classify | K7: Charger / Free service | L7: Ngày bắt đầu Start date | M7: Ngày kết thúc Finish date | N7: Ngày hoàn thành / ngày kí báo cáo Date signed report | O7: Ngày nhận báo cáo / Received report date | P7: General Status | Q7: Customer's comment (if any | R7: P.I.C | S7: Follow up action | T7: Satisfaction feedback | U7: Remarks
A8: 51 LE DAI HANH | B8: 51 Lê Đại Hành | C8: LDH-190228 | D8: LDH-190228 | E8: THAY THẾ ẮC QUI CHO MÁY PHÁT ĐIỆN | F8: Genset | G8: 1 times | I8: 1 Lot | J8: Services | K8: Charge | L8: 43533 | M8: =L8 -> 43533 | N8: 43533 | O8: 43533 | P8: Thay thế ắc quy cho máy phát điện Kiểm tra tổng máy phát điện, ATS Chạy test máy phát điện không tải & có tải => Cần thay thế dầu nhớt, phin lọc & nước làm mát cho máy => Tăng tần suất chạy test máy phát điện (không tải) định kỳ 2 lần/tháng (hiện tại 1 lần/tháng) -> Sau khi thay thế ắc quy, máy hoạt động bình thường | R8: Hieu.lv | U8: KH không đánh giá mức độ hài lòng
A9: 51 LE DAI HANH | B9: 51 Lê Đại Hành | C9: N/A | D9: N/A | E9: SỰ CỐ MẤT ĐIỆN KHU VỰC SIÊU THỊ | F9: Electric | G9: 1 times | I9: 1 Lot | J9: Trouble shooting | K9: Free | L9: 43789 | M9: 43789 | N9: 43789 | O9: 43789 | P9: Mất điện khu vực siêu thị tầng 1, hệ thống đèn chiếu sáng, tự động không mất điện Kiểm tra aptomat tầng 1, phát hiện aptomat tổng loại 63A (3 Pha), 1 pha có điện áp, 2 pha còn lại mất điện. Tiền hành thay aptomat do move bị kém Cần lại 1 pha vâng dòng quá cao (24A) Thiết bị đã hoạt động bình thường, dòng điện định mức đã trở lại bình thường Đã khuyến cáo khách hàng thay aptomat 1 pha = 3 pha | R9: Hieu.kv | T9: E
A10: ABB VIETNAM | B10: Km9 National Highway 1A, Hanoi | C10: AHN-200428 | D10: AHN-200428 | E10: BẢO TRÌ QUẠT THÔNG GIÓ CÔNG NGHIỆP HVLS | F10: Industrial fan | G10: 1 times | I10: 1 Lot | J10: Maintenance | K10: Charge | L10: 43970 | M10: =L10+45 -> 44015 | N10: 43981 | O10: 44003 | P10: Đã kiểm tra bảo trì 12 quạt thông gió công nghiệp Sau bảo trì các quạt hoạt động bình thường | R10: Dien.hd | T10: S
A11: ABB VIETNAM | B11: KCN Tiên Sơn, Bắc Ninh | C11: ABB-200715 | D11: ABB-200715 | E11: CUNG CẤP VÒNG BI QUẠT AHU | F11: AHU | G11: 1 times | I11: 1 | J11: Services | K11: Charge | L11: 44078 | M11: =L11 -> 44078 | N11: 44070 | O11: 44070 | P11: Cung cấp vòng bi cho quạt AHU | R11: Manh.lh | U11: Sử dụng mẫu Delivery note => kg có mục đánh giá mức độ hài lòng
A12: AEON MALL LONG BIÊN | B12: Cổ Linh, Long Biên, HN | C12: ALB-200429 | D12: ALB-200429 | E12: VỆ SINH ĐƯỜNG ỐNG CẤP NƯỚC SINH HOẠT | F12: Fresh water | G12: 1 times | I12: 1 Lot | J12: Services | K12: Charge | L12: 43966 | M12: =L12+60 -> 44026 | N12: 43975 | O12: 44000 | P12: Công việc đã hoàn thành | U12: Sử dụng mẫu BB nghiệm thu của KH nên kg có nội dung đánh giá hài lòng
A13: AEON MALL LONG BIÊN | B13: Cổ Linh, Long Biên, HN | C13: ALB-200729 | D13: ALB-200729 | E13: SỬA CHỮA RÒ RỈ ĐƯỜNG ỐNG NƯỚC SẠCH | F13: Fresh water | G13: 1 times | I13: 1 | J13: Services | K13: Charge | L13: 44042 | M13: =L13+3 -> 44045 | N13: 44042 | O13: 44043 | P13: - Đường ống nước sạch D150 vị trí WC số 2 bị rò rỉ nước do đường ống bị lệch -> Tắt bơm & khóa nước tầng 2, trục ống cần sửa chữa -> Xả nước tại nhà vệ sinh số 1 & nhà vệ sinh nhân viên -> Tháo cút D200 cấp nước cho TTTM -> Tiến hành tháo cút D150 vị trí rò rỉ -> Tháo lỏng các ubolt giữ cố định đường ống ngang -> Nới lỏng mặt bích trục ống dọc -> Căn chỉnh vuông góc, thay gioăng mới và gioăng cũ có hiện tượng bị biến dạng -> Bắt siết lại cút D150, siết lại mặt bích trục ống dọc, bắt lại các Ubolt giữ đường ống ngang -> Lắp lại cút D200 -> Chạy bơm áp suất 3,5bar -> theo dõi rò rỉ -> Vệ sinh khu vực sửa chữa => Sau khi sửa chữa, đường ống đã thẳng, không còn hiện tượng rò rỉ | R13: Hieu.kv | T13: S
A14: AEON MALL LONG BIÊN | B14: Cổ Linh, Long Biên, HN | C14: ALB-200429 | D14: ALB-200429 | E14: VỆ SINH ĐƯỜNG ỐNG CẤP NƯỚC SINH HOẠT | F14: Fresh water | G14: 1 times | I14: 1 | J14: Trouble shooting | K14: Free | L14: 44073 | M14: 44073 | N14: 44073 | O14: 44073 | P14: - Đường ống bị tắc nghẽn - Đồng ho đo áp nước không hiện áp - Nước ở vòi chảy nhỏ giọt & có cặn -> Tiến hành cắt ống cấp nước -> Sử dụng dây lò xo thông ống -> Lắp lại ống & tiến hành hàn nhiệt -> Sục lại đường ống bằng áp nước > 3kg => Nước chảy mạnh & không còn cặn bẩn | Q14: Nhà thầu làm việc cẩn thận, chu đáo. Dọn dẹp gọn gàng sau khi hoàn thành công việc | R14: Thiem.l, Ha.vd, Ton.nd | T14: E
A15: AEON MALL LONG BIÊN | B15: Cổ Linh, Long Biên, HN | C15: ALB-200810 | D15: ALB-200810 | E15: ĐO ĐẠC, ĐÁNH GIÁ VÀ ĐIỀU CHỈNH LƯU LƯỢNG GIÓ AHU-1-12 | F15: AHU | G15: 1 times | I15: 1 | J15: Services | K15: Charge | L15: 44094 | M15: 44099 | N15: 44088 | O15: 44097 | P15: - Lưu lượng gió cấp cho 1 số gian hàng thấp hơn bản vẽ hoàn công & không đồng đều -> Đo đạc lưu lượng gió AHU-1-12 (tại các điểm có chỉ số lưu lượng trên bản vẽ hoàn công) -> Tổng hợp số liệu, đánh giá lưu lượng gió AHU-1-12 so sánh với bản vẽ hoàn công & hiện trạng thực tế - > Điều chỉnh lưu lượng gió AHU-1-12 căn cứ theo bản vẽ hoàn công & có thể điều chỉnh theo y/c thực tế -> Cập nhật lưu lượng gió AHU-1-12 trên bản vẽ hoàn công => Lưu lượng gió tại các điểm đã căn chỉnh đạt yêu cầu | R15: Bang.ta, Hung.nm, Hieu.nq, Diem.l, Dong.hp | T15: E
A16: AEON MALL LONG BIÊN | B16: Cổ Linh, Long Biên, HN | C16: ALB-200429 | D16: ALB-200429 | E16: VỆ SINH ĐƯỜNG ỐNG CẤP NƯỚC SINH HOẠT | F16: Fresh water | G16: 1 times | I16: 1 | J16: Warranty | K16: Free | L16: 44082 | M16: 44083 | N16: 44082 | O16: 44083 | P16: Đường ống cấp nước chảy yếu -> nguyên nhân là do ống bị tắc, có rò rỉ nước ở cút -> Khóa nước tiến hành tháo dỡ đoạn ống nổi để làm vệ sinh, đoạn ống chìm thì dùng dây lò xo thông nghẽn -> Vệ sinh van 1 chiều -> Về rò rỉ nước: KH y/c thay mới zắc co ở sau van (đã bao gồm cả cút bị rò) => Áp nước về ban đầu, hệ thống h/đ bình thường => Đã thay thế bộ phận zắc co sau van bị rò theo y/c | Q16: Gian hàng hài lòng với cách làm việc của kỹ thuật SPS -> Sau khi thực hiện cv đã vệ sinh sạch sẽ | R16: Thiem.l, Hieu.nq, Ha.vd | T16: E
A17: AMC | B17: Nhà máy VinSmart, KCN Cao Láng - Hòa Lạc | C17: AMC-190222-Rev3 | D17: AMC-190222-Rev3 | E17: LẮP ĐẶT HỆ THỐNG GIÀN TREO VÀ BĂNG TẢI | F17: M&E | G17: 1 times | I17: 1 Lot | J17: Services | K17: Charge | L17: 43525 | M17: =L17+40 -> 43565 | N17: 43577 | O17: 43577 | P17: Rất cảm ơn anh em thi công tại công trường cùng đội ngũ kỹ thuật Support đã hoàn thành dự án tốt đẹp Tuy nhiên bên cạnh đó làm chưa có người kiểm tra giám sát xuyên suốt quá trình để đưa ra được biện pháp thi công phù hợp với tình hình thực tế (Mr. Diên Support) được ít hôm. Thiếu quản lý dẫn đến trong tổ có to tiếng với nhau | R17: quyen.h | T17: A
A18: AMC | B18: Nhà máy Meiko, KCN Thạch Thất, Hà Nội | C18: AMC-190215 | D18: AMC-190215 | E18: LẮP ĐẶT MÁY DUST COLLECTOR | F18: Dust collector | G18: 1 times | I18: 1 Lot | J18: Services | K18: Charge | L18: 43536 | M18: 43567 | N18: 43536 | O18: 43567 | P18: Tháo dỡ, di chuyển máy hút bụi vào vị trí. Kết nối, lắp đặt tại vị trí bệ máy | Q18: Chưa chuẩn bị tốt biện pháp thi công, chưa tuân thủ thời gian làm việc tốt tại công trường, trong quá trình làm việc CN chưa tập trung | R18: manh.lh | T18: A
A19: AMC | B19: Nhà máy Meiko, KCN Thạch Thất, Hà Nội | C19: AMC-190226-Rev2 | D19: AMC-190226-Rev2 | E19: CẤP NGUỒN CHO MÁY DUST COLLECTOR | F19: Dust collector | G19: 1 times | I19: 1 Lot | J19: Services | K19: Charge | L19: 43536 | M19: 43567 | N19: 43536 | O19: 43567 | P19: Cấp nguồn cho máy Dust Collector | Q19: Cần chú ý nhiều đến biện pháp thi công và an toàn trong quá trình thao tác | R19: manh.lh | T19: S
A20: AMC | B20: Nhà máy Meiko, KCN Thạch Thất, Hà Nội | C20: AMC-190215-VO | D20: AMC-190215-VO | E20: LẮP ĐẶT MÁY DUST COLLECTOR - PHÁT SINH | F20: Dust collector | G20: 1 times | I20: 1 Lot | J20: Services | K20: Charge | L20: 43536 | M20: 43565 | N20: 43536 | O20: 43565 | P20: Lắp đặt máy Dust collector phần phát sinh (lắp đặt cáp điện cho rotary valve, lắp đặt ống thép phụ kiện, khoan lỗ sesor, xoay máy Blower 03 => Công việc đã hoàn thành | T20: A
A21: BBP VIỆT NAM | B21: Vingroup, HN | C21: BBP-200715-Rev1 | D21: BBP-200715-Rev1 | E21: LẮP ĐẶT SENSOR VÀ THIẾT BỊ PHỤC VỤ ĐO KIỂM | F21: HVAC | G21: 1 times | I21: 1 | J21: Services | K21: Charge | L21: 44007 | M21: 44060 | N21: 44007 | O21: 44060 | P21: Lắp đặt sensor và thiết bị phục vụ đo kiểm | R21: Diem.l, Tan.nm | T21: S
A22: BBP VIỆT NAM | B22: JW Marriott Hotel HN | C22: BBP-210104 | D22: BBP-210104 | E22: LẮP ĐẶT SENSOR VÀ THIẾT BỊ PHỤC VỤ ĐO KIỂM | F22: HVAC | G22: 1 times | I22: 1 | J22: Services | K22: Charge | L22: 44081 | M22: 44088 | N22: 44081 | O22: 44088 | P22: Lắp đặt sensor & thiết bị phục vụ đo kiểm => CV đã hoàn thành | R22: Diem.l, Tan.nm, Thiem.l | T22: S
A23: BIBIHOME | B23: Số 17 ngõ 62 Đặng Văn Ngữ, Hà Nội | C23: BBH-200804 | D23: BBH-200804 | E23: SỬA CHỮA HỆ THỐNG ĐÈN CẦU THANG | F23: Lamp | G23: 1 times | I23: 1 | J23: Services | K23: Charge | L23: 44013 | M23: 44043 | N23: 44041 | O23: 44041 | P23: - Đèn cầu thang mất điện -> Ktra nguồn điện, công tắc đèn -> Dây nguồn cấp cho đèn cầu thang bị chập trong tường gây nhảy thiết bị bảo vệ => Cần đi lại dây mới cho đèn cầu thang | R23: Dien.hd | U23: KH không đánh giá mức độ hài lòng
A24: BIG C ARTEMIS | B24: 3 Lê Trọng Tấn, HN | C24: BAT-191230 | D24: BAT-191230 | E24: THAY THẾ DẦU NHỚT, PHIN LỌC, NƯỚC LÀM MÁT CHO MÁY PHÁT ĐIỆN | F24: Genset | G24: 1 times | I24: 1 Lot | J24: Services | K24: Charge | L24: 43878 | M24: =L24+30 -> 43908 | N24: 43904 | O24: 43904 | P24: Thay thế dầu nhớt, phin lọc, nước làm mát cho máy phát điện/ Replace Lub oil, filter, coolant water for Genset. Thiết bị hoạt động bình thường/ Genset works normally | R24: Hung2.nm, Thao.ct, Duc.nv | T24: S
A25: BIG C ARTEMIS | B25: 3 Lê Trọng Tấn, HN | C25: BAT-200331 | D25: BAT-200331 | E25: THAY THẾ UPS CỦA ATS | F25: ATS | G25: 1 times | I25: 1 Lot | J25: Services | K25: Charge | L25: 43921 | M25: =L25+8 -> 43929 | N25: 43921 | O25: 43921 | P25: Thay thế UPS của ATS UPS hoạt động bình thường | R25: Manh.lh | T25: E
A26: BIG C ARTEMIS | B26: 3 Lê Trọng Tấn, HN | C26: BAT-200429-Rev1 | D26: BAT-200429-Rev1 | E26: THAY THẾ BỘ ĐIỀU KHIỂN TỐC ĐỘ MÁY PHÁT ĐIỆN | F26: Genset | G26: 1 times | I26: 1 Lot | J26: Services | K26: Charge | L26: 43955 | M26: =L26+16 -> 43971 | N26: 43956 | O26: 43956 | P26: Bộ điều khiển tốc độ máy phát điện hỏng Thay thế bộ điều khiển máy phát điện Thiết bị hoạt động bình thường | R26: Hung2.nm, Hieu.kv | U26: KH không đánh giá mức độ hài lòng
A27: BIG C ARTEMIS | B27: 3 Lê Trọng Tấn, HN | C27: N/A | D27: N/A | E27: KIỂM TRA SỰ CỐ MÁY PHÁT ĐIỆN | F27: Genset | G27: 1 times | I27: 1 Lot | J27: Trouble shooting | K27: Free | L27: 43949 | M27: 43949 | N27: 43949 | O27: 43949 | P27: - Máy không hoạt động được - Kiểm tra nguồn điện DC - Kiểm tra Pickup - Kiểm tra bo Speed Controller, bị cháy XS-400B-03 - Thay bo điều tốc XS-400B-03 - Chạy máy kiểm tra, và theo dõi thêm | R27: Hung2.nm | U27: KH không đánh giá mức độ hài lòng
A28: BIG C ARTEMIS | B28: 3 Lê Trọng Tấn, HN | C28: N/A | D28: N/A | E28: Sự cố | F28: Genset | G28: 1 times | I28: 1 Lot | J28: Trouble shooting | K28: Free | L28: 43949 | M28: 43949 | N28: 43949 | O28: 43949 | P28: Máy không hoạt động được Kiểm tra nguồn điện DC Kiểm tra PVCKVP Kiểm tra bo SPRCO Controllrr, bị chấy XS-400B-03 Thay bo điều tốc XS-400B-03 Chạy máy kiểm tra, và theo dõi thêm | R28: Hung2.nm | U28: KH không đánh giá mức độ hài lòng
A29: BIG C BẮC GIANG | B29: Bắc Giang | C29: BBG-191230 | D29: BBG-191230 | E29: THAY THẾ DẦU NHỚT, PHIN LỌC, NƯỚC LÀM MÁT CHO MÁY PHÁT ĐIỆN | F29: Genset | G29: 1 times | I29: 1 Lot | J29: Services | K29: Charge | L29: 43866 | M29: =L29+32 -> 43898 | N29: 43890 | O29: 43890 | P29: Đã bàn giao đầy đủ số lượng theo hợp đồng | R29: Manh.lh | U29: Sử dụng form biên bản giao nhận và nghiệm thu
A30: BIG C BẮC GIANG | B30: Xã Tân Tiến, TP Bắc Giang, Bắc Giang | C30: BBG-200601 | D30: BBG-200601-GE-Y01 | E30: BẢO TRÌ MÁY PHÁT ĐIỆN | F30: Genset | G30: Y | I30: 1 | J30: Maintenance | K30: Charge | L30: 44013 | M30: 44042 | N30: 44036 | O30: 44036 | P30: MFĐ sau khi bảo dưỡng h/đ bình thường | R30: Hung2.nm, Hoang.v, Luan.dt | T30: S
A31: BIG C BẮC GIANG | B31: Xã Tân Tiến, TP Bắc Giang, Bắc Giang | C31: BBG-200601 | D31: BBG-200601-GE-Q01 | E31: BẢO TRÌ MÁY PHÁT ĐIỆN | F31: Genset | G31: Q | I31: 1 | J31: Maintenance | K31: Charge | L31: 44105 | M31: 44134 | N31: 44133 | O31: 44133 | P31: Sau khi bảo trì định kỳ, MFĐ h/đ bình thường | R31: Hung2.nm, Thuong.mv | T31: S
A32: BIG C BẮC GIANG | B32: Xã Tân Tiến, TP Bắc Giang, Bắc Giang | C32: BBG-200601 | D32: BBG-200601-GE-S01 | E32: BẢO TRÌ MÁY PHÁT ĐIỆN | F32: Genset | G32: S | I32: 1 | J32: Maintenance | K32: Charge | L32: 44197 | M32: 44226 | N32: 44204 | O32: 44204 | P32: Sau khi bảo trì định kỳ, MFĐ h/đ bình thường | R32: Hung2.nm, Tai.nt, Hieu.nq | T32: E
A33: BIG C BẮC GIANG | B33: Xã Tân Tiến, TP Bắc Giang, Bắc Giang | C33: BBG-200601 | D33: BBG-200601-GE-Q02 | E33: BẢO TRÌ MÁY PHÁT ĐIỆN | F33: Genset | G33: Q | I33: 1 | J33: Maintenance | K33: Charge | L33: 44287 | M33: 44316 | N33: 44303 | O33: 44303 | P33: Sau khi bảo trì định kỳ, MFĐ h/đ bình thường | R33: Hung2.nm, Hieu.nq | T33: S
A34: BIG C HẠ LONG | B34: Cột 5, Hồng Hà, Thành phố Hạ Long, Quảng Ninh | C34: BHL-200211 | D34: BHL-200211 | E34: THAY THẾ DẦU NHỚT, PHIN LỌC, NƯỚC LÀM MÁT CHO MÁY PHÁT ĐIỆN | F34: Genset | G34: 1 times | I34: 1 Lot | J34: Services | K34: Charge | L34: 43916 | M34: =L34+32 -> 43948 | N34: 43927 | O34: 43929 | P34: - Thay thế dầu nhớt, phin lọc, nước làm mát cho máy phát điện - Thu thập số liệu MPĐ 01: + Điện áp 400V + Dòng diện + Tần số 50Hz + Áp suất nhớt 5bar, nhiệt độ nước 40 độ - Thu thập số liệu MPĐ 02: + Điện áp 400V + Dòng điện + Tần số 50Hz + Áp suất dầu 5bar, nhiệt độ nước 40 độ - Thiết bị hoạt động bình thường - Thu thập dữ liệu MPĐ 01: + Điện áp 400V + Dòng điện 200A + Tần số 50Hz + Áp suất dầu 6,5bar + Nhiệt độ nước 60 độ - Thu thập dữ liệu MPĐ 02: + Điện áp 400V + Dòng điện 200A + Tần số 50Hz + Áp suất dầu 6,5bar + Nhiệt độ nước 60 độ - Nghiệm thu: Đã thực hiện theo các hạng muc vật tư bàn giao thay thế, còn 02 hạng mục chưa vật tư thay sau | R34: Hung2.nm, Hieu.kv, Luan.dt, Hoang.v | T34: S
A35: BIG C HẢI DƯƠNG | B35: Khu TTTM, Ngọc Châu, An Định, Nhị Châu, Hải Dương | C35: BHD-200601 | D35: BHD-200601-GE-Y01 | E35: BẢO TRÌ MÁY PHÁT ĐIỆN | F35: Genset | G35: Y | I35: 1 | J35: Maintenance | K35: Charge | L35: 44013 | M35: 44042 | N35: 44040 | O35: 44040 | P35: - Bơm nước có hiện tượng chảy nước -> cần theo dõi thêm - Giá đỡ đường ống dầu bị vỡ -> cần thay thế -> MFĐ h/d bình thường | R35: Hung2.nm, Luan.dt, Thiem.l | T35: A
A36: BIG C HẢI DƯƠNG | B36: Khu TTTM, Ngọc Châu, An Định, Nhị Châu, Hải Dương | C36: BHD-200601 | D36: BHD-200601-GE-Q01 | E36: BẢO TRÌ MÁY PHÁT ĐIỆN | F36: Genset | G36: Q | I36: 1 | J36: Maintenance | K36: Charge | L36: 44105 | M36: 44134 | N36: 44135 | O36: 44135 | P36: Sau khi bảo dưỡng định kỳ, hệ thống MFĐ h/đ bình thường | R36: Hung2.nm, Thuong.mv | U36: KH không đánh giá mức độ hài lòng
A37: BIG C HẢI DƯƠNG | B37: Khu TTTM, Ngọc Châu, An Định, Nhị Châu, Hải Dương | C37: BHD-200601 | D37: BHD-200601-GE-S01 | E37: BẢO TRÌ MÁY PHÁT ĐIỆN | F37: Genset | G37: S | I37: 1 | J37: Maintenance | K37: Charge | L37: 44197 | M37: 44226 | N37: 44207 | O37: 44207 | P37: Để MFĐ h/đ hiệu quả hơn cần thay giá đỡ đường ống nhiên liệu => Sau khi bảo dưỡng hệ thống MFĐ h/đ bình thường | R37: Hung2.nm, Hieu.nq, Tai.nt | T37: E
A38: BIG C HẢI DƯƠNG | B38: Khu TTTM, Ngọc Châu, An Định, Nhị Châu, Hải Dương | C38: BHD-200601 | D38: BHD-200601-GE-Q02 | E38: BẢO TRÌ MÁY PHÁT ĐIỆN | F38: Genset | G38: Q | I38: 1 | J38: Maintenance | K38: Charge | L38: 44287 | M38: 44316 | N38: 44310 | O38: 44310 | P38: - Giá đỡ đường ống nhiên liệu bị vỡ -> cần thay thế => Hệ thống MFĐ sau bảo dưỡng h/đ bình thường | R38: Hung2.nm, Hieu.nq | T38: S
A39: BIG C HẢI PHÒNG | B39: Lô 1/20, khu đô thị mới Ngã Năm - Sân bay Cát Bi, Phường Đằng Giang, Quận Ngô Quyền, TP Hải Phòng | C39: BHP-200601 | D39: BHP-200601-GE-Y01 | E39: BẢO TRÌ MÁY PHÁT ĐIỆN | F39: Genset | G39: Y | I39: 1 | J39: Maintenance | K39: Charge | L39: 44013 | M39: 44042 | N39: 44039 | O39: 44039 | P39: - Hở nắp két nước nên khi chạy máy phát, nước chảy ra ngoài - Bổ sung 60L nước -> MFĐ h/đ bình thường | R39: Hung2.nm, Luan.dt | T39: S
A40: BIG C HẢI PHÒNG | B40: Lô 1/20, khu đô thị mới Ngã Năm - Sân bay Cát Bi, Phường Đằng Giang, Quận Ngô Quyền, TP Hải Phòng | C40: BHP-200601 | D40: BHP-200601-GE-Q01 | E40: BẢO TRÌ MÁY PHÁT ĐIỆN | F40: Genset | G40: Q | I40: 1 | J40: Maintenance | K40: Charge | L40: 44105 | M40: 44134 | N40: 44134 | O40: 44134 | P40: Sau khi bảo trì định kỳ, MFĐ h/đ bình thường | R40: Hung2.nm, Thuong.mv | U40: KH không đánh giá mức độ hài lòng
A41: BIG C HẢI PHÒNG | B41: Lô 1/20, khu đô thị mới Ngã Năm - Sân bay Cát Bi, Phường Đằng Giang, Quận Ngô Quyền, TP Hải Phòng | C41: BHP-200601 | D41: BHP-200601-GE-Q02 | E41: BẢO TRÌ MÁY PHÁT ĐIỆN | F41: Genset | G41: Q | I41: 1 | J41: Maintenance | K41: Charge | L41: 44197 | M41: 44226 | N41: 44208 | O41: 44208 | P41: - Để đảm bảo MFĐ h/đ hiệu quả hơn & kg báo lỗi nhiệt độ thấp, cần kết nối hệ thống sấy nước cho MFĐ -> MFĐ h/đ bình thường - Hiện trạng phòng MFĐ có chuột -> đề nghị CĐT có phương án diệt chuột | Q41: Y/c sắp xếp thử tài vào lần bảo trì tiếp theo | R41: Hung2.nm, Tai.nt, Hieu.nq | T41: E
A42: BIG C HẢI PHÒNG | B42: Lô 1/20, khu đô thị mới Ngã Năm - Sân bay Cát Bi, Phường Đằng Giang, Quận Ngô Quyền, TP Hải Phòng | C42: BHP-200601 | D42: BHP-200601-GE-Q03 | E42: BẢO TRÌ MÁY PHÁT ĐIỆN | F42: Genset | G42: Q | I42: 1 | J42: Maintenance | K42: Charge | L42: 44287 | M42: 44316 | N42: 44309 | O42: 44309 | P42: - Có hiện tượng hao nước trong bình ắc quy -> cần theo dõi thêm => Sau khi bảo dưỡng, hệ thống MFĐ h/đ bình thường | R42: Hung2.nm, Tai.nt, Thuong.mv | U42: KH không đánh giá mức độ hài lòng
A43: BIG C HẢI PHÒNG | B43: Lô 1/20, khu đô thị mới Ngã Năm - Sân bay Cát Bi, Phường Đằng Giang, Quận Ngô Quyền, TP Hải Phòng | C43: N/A | D43: N/A | E43: SỰ CỐ | F43: Genset | G43: 1 times | I43: 1 | J43: Trouble shooting | K43: Free | L43: 44063 | M43: 44063 | N43: 44063 | O43: 44063 | P43: - Máy phát điện không mang được tải -> Ktra lọc tách nước, phát hiện gioăng không kín -> đã lắp bổ sung -> Chạy thử máy phát điện => Máy phát điện h/đ tự động, mang tải bình thường Dòng điện tải 884/829/852 A, điện áp 398,31/397,72/397,70 V | R43: Manh.lh, Hoang.v, Hung2.nm | T43: E
A44: BIG C LONG BIÊN | B44: Long Biên, HN | C44: BLB-191230 | D44: BLB-191230 | E44: THAY THẾ DẦU NHỚT, PHIN LỌC, NƯỚC LÀM MÁT CHO MÁY PHÁT ĐIỆN | F44: Genset | G44: 1 times | I44: 1 Lot | J44: Services | K44: Charge | L44: 43866 | M44: =L44+32 -> 43898 | N44: 43897 | O44: 43897 | P44: Đã thay thế dầu nhớt, phin lọc, nước làm mát cho máy phát điện Thiết bị hoạt động bình thường | R44: Hung2.nm, Dung.ct, Dung.nv | U44: Sử dụng mẫu Delivery note => kg có mục đánh giá mức độ hài lòng
A45: BIG C LONG BIÊN | B45: Long Biên, HN | C45: BLB-200601-2 | D45: BLB-200601-2 | E45: SỬA CHỮA BỘ ĐO MỨC BỒN DẦU | F45: Genset | G45: 1 times | I45: 1 Lot | J45: Services | K45: Charge | L45: 43983 | M45: =L45+16 -> 43999 | N45: 43987 | O45: 43987 | P45: Thay thế ống dây đo mức bồn dầu Chạy thử, bàn giao Hoàn thành | R45: Hung2.nm, Dung.ct | T45: E
A46: BIG C LONG BIÊN | B46: Long Biên, HN | C46: BLB-200601 | D46: BLB-200601-GE-Q01 | E46: BẢO TRÌ MÁY PHÁT ĐIỆN | F46: Genset | G46: Q | I46: 1 | J46: Maintenance | K46: Charge | L46: 44013 | M46: 44042 | N46: 44032 | O46: 44032 | P46: - Bộ điều khiển không hiển thị rõ thông số của MFĐ -> cần thay bộ điều khiển MFĐ -> MFĐ h/đ bình thường | R46: Hung2.nm, Luan.dt, Tan.nm | T46: A
A47: BIG C LONG BIÊN | B47: Long Biên, HN | C47: BLB-200601 | D47: BLB-200601-GE-Q02 | E47: BẢO TRÌ MÁY PHÁT ĐIỆN | F47: Genset | G47: Q | I47: 1 | J47: Maintenance | K47: Charge | L47: 44105 | M47: 44134 | N47: 44127 | O47: 44127 | P47: - Bảo dưỡng định kỳ năm + Bộ hiển thị mức nhiên liệu bồn dầu chính mất nguồn + Tủ ATS các cầu chì OFF không thấy 1 số thiết bị => MFĐ sau khi bảo dưỡng ở chế độ không tải h/đ bình thường | R47: Hung2.nm, Thuong.mv | U47: KH không đánh giá mức độ hài lòng
A48: BIG C LONG BIÊN | B48: Long Biên, HN | C48: BLB-200601 | D48: BLB-200601-GE-Y01 | E48: BẢO TRÌ MÁY PHÁT ĐIỆN | F48: Genset | G48: Y | I48: 1 | J48: Maintenance | K48: Charge | L48: 44197 | M48: 44226 | N48: 44200 | O48: 44200 | P48: - Đồng hồ hiển thị mức dầu bồn dầu ngầm bị lỗi -> cần sửa chữa thay thế - Tủ ATS kg h/đ ở chế độ tự động -> cần ktra sửa chữa => Sau khi bảo dưỡng, hệ thống MFĐ h/đ bình thường | R48: Hung2.nm, Hieu.nq, Tai.nt | T48: A
A49: BIG C LONG BIÊN | B49: Long Biên, HN | C49: BLB-200601 | D49: BLB-200601-GE-S01 | E49: BẢO TRÌ MÁY PHÁT ĐIỆN | F49: Genset | G49: S | I49: 1 | J49: Maintenance | K49: Charge | L49: 44287 | M49: 44316 | N49: 44295 | O49: 44295 | P49: Sau khi bảo dưỡng, hệ thống MFĐ h/đ bình thường | R49: Hung2.nm, Hieu.nq, Cuong.dv | T49: A
A50: BIG C LONG BIÊN | B50: Long Biên, HN | C50: N/A | D50: N/A | E50: SỰ CỐ | F50: Genset | G50: 1 times | I50: 1 | J50: Trouble shooting | K50: Free | L50: 44009 | M50: 44009 | N50: 44009 | O50: 44009 | P50: Màn hình máy phát điện không hiển thị thông số kỹ thuật -> Ktra hệ thống điện -> Vệ sinh bộ điều khiển máy phát điện => Bộ điều khiển hiển thị thông số mờ, không rõ => Cần thay bộ điều khiển mới | R50: Hung2.nm | T50: A
A51: BIG C MÊ LINH | B51: Tầng 1, TTTM Mê Linh Plaza, KM8 Cao Tốc Bắc Thăng Long - Nội Bài, Phường Quang Minh, Quận Mê Linh, HN | C51: BML-200601 | D51: BML-200601-GE-Q01 | E51: BẢO TRÌ MÁY PHÁT ĐIỆN | F51: Genset | G51: Q | I51: 1 | J51: Maintenance | K51: Charge | L51: 44013 | M51: 44042 | N51: 44033 | O51: 44033 | P51: - Có nước mưa đọng trong phòng máy phát điện - Giá đỡ đường ống nhiên liệu bị vỡ -> cần thay thế => MFĐ h/đ bình thường | Q51: Đề nghị báo giá đệm giảm chấn đỡ ống dầu cao áp | R51: Hung2.nm, Luan, Tan.nm | T51: S
A52: BIG C MÊ LINH | B52: Tầng 1, TTTM Mê Linh Plaza, KM8 Cao Tốc Bắc Thăng Long - Nội Bài, Phường Quang Minh, Quận Mê Linh, HN | C52: BML-200601 | D52: BML-200601-GE-Y01 | E52: BẢO TRÌ MÁY PHÁT ĐIỆN | F52: Genset | G52: Y | I52: 1 | J52: Maintenance | K52: Charge | L52: 44105 | M52: 44134 | N52: 44130 | O52: 44130 | P52: Sau khi bảo dưỡng, hệ thống MFĐ h/đ bình thường | R52: Hung2.nm, Thuong.mv, Dong.hp | T52: S
A53: BIG C MÊ LINH | B53: Tầng 1, TTTM Mê Linh Plaza, KM8 Cao Tốc Bắc Thăng Long - Nội Bài, Phường Quang Minh, Quận Mê Linh, HN | C53: BML-200601 | D53: BML-200601-GE-Q02 | E53: BẢO TRÌ MÁY PHÁT ĐIỆN | F53: Genset | G53: Q | I53: 1 | J53: Maintenance | K53: Charge | L53: 44197 | M53: 44226 | N53: 44201 | O53: 44201 | P53: Để MFĐ h/đ hiệu quả hơn cần: - Thay phớt bơm nước - Thay giá đỡ đường ống nhiên liệu - Thay bộ điều khiển ATS 400A => Sau khi bảo dưỡng hệ thống MFĐ h/đ bình thường | R53: Hung2.nm, Hieu.nq, Tai.nt | T53: S
A54: BIG C MÊ LINH | B54: Tầng 1, TTTM Mê Linh Plaza, KM8 Cao Tốc Bắc Thăng Long - Nội Bài, Phường Quang Minh, Quận Mê Linh, HN | C54: BML-200601 | D54: BML-200601-GE-S01 | E54: BẢO TRÌ MÁY PHÁT ĐIỆN | F54: Genset | G54: S | I54: 1 | J54: Maintenance | K54: Charge | L54: 44287 | M54: 44316 | N54: 44312 | O54: 44312 | P54: - Trong phòng MFĐ có nước mưa chảy từ ngoài vào -> cần xử lý che mái tôn bảo vệ => Sau khi bảo dưỡng, hệ thống MFĐ h/đ bình thường | R54: Hung2.nm, Hieu.nq, Cuong.dv | T54: S
A55: BIG C NINH BÌNH | B55: Trần Nhân Tông, Ninh Phú, Ninh Bình | C55: BNB-201026-Rev1 | D55: BNB-201026-Rev1 | E55: SỬA CHỮA MÁY PHÁT ĐIỆN | F55: Genset | G55: 1 times | I55: 1 | J55: Services | K55: Charge | L55: 44151 | M55: 44165 | N55: 44153 | O55: 44153 | P55: - Bộ sạc tự động kg cấp ra điện áp, điện áp ắc quy 24,5V - MFĐ chạy không ổn định tốc độ vòng tua -> Thay bộ sạc ắc quy 24V-10A -> Thay bộ điều tốc XS - 400B-O3 - Đo điện áp ắc quy khi máy dừng: 26.3V - Chạy MFĐ có tải: 1506 RPM, tần số 5HZ, điện áp 391/393/393, dòng điện 460A/470A/410A -> Hệ thống MFĐ h/đ bình thường | R55: Hung2.nm, Tan.nm, Diem.lv | T55: S
A56: BIG C THĂNG LONG | B56: 222 Trần Duy Hưng, Cầu Giấy, Hà Nội | C56: BTL-200716 | D56: BTL-200716 | E56: THAY THẾ KHỚP NỐI MỀM CỦA BƠM NHIÊN LIỆU MÁY PHÁT ĐIỆN P500-1 | F56: Genset | G56: 1 times | I56: 1 | J56: Services | K56: Charge | L56: 44013 | M56: 44043 | N56: 44033 | O56: 44033 | P56: Đã thay thế khớp nối mềm của bơm nhiên liệu MFĐ | S56: Hiep.hs, Dien.hd | T56: S | U56: Sử dụng mẫu Biên bản nghiệm thu - bàn giao của KH, không có mục đánh giá hài lòng
A57: BIG C VIỆT TRÌ | B57: Đường Nguyễn Tất Thành, P. Thanh Miếu, TP. Việt Trì, Phú Thọ | C57: BVT-200601 | D57: BVT-200601-GE-Y01 | E57: BẢO TRÌ MÁY PHÁT ĐIỆN | F57: Genset | G57: Y | I57: 1 | J57: Maintenance | K57: Charge | L57: 44013 | M57: 44042 | N57: 44035 | O57: 44035 | P57: - Trước khi bảo trì: Máy phát điện khó khởi động do tụt dầu nhiên liệu - Sau bảo trì: máy phát điện h/đ bình thường | R57: Hung2.nm, Hieu.nq, Tan.nm | T57: S
A58: BIG C VIỆT TRÌ | B58: Đường Nguyễn Tất Thành, P. Thanh Miếu, TP. Việt Trì, Phú Thọ | C58: BVT-200601 | D58: BVT-200601-GE-Q01 | E58: BẢO TRÌ MÁY PHÁT ĐIỆN | F58: Genset | G58: Q | I58: 1 | J58: Maintenance | K58: Charge | L58: 44105 | M58: 44134 | N58: 44132 | O58: 44132 | P58: - Sửa chữa van chặn, thay oring van chặn - Ktra tủ điều khiển -> cần thay thế van báo mức dầu thấp => Hệ thống MFĐ h/đ bình thường => Rò rỉ đường cấp dầu bơm tay lên téc 2000 L => Báo mức dầu lên téc 20.000L bị lỗi | R58: Hung2.nm, Thuong.mv | T58: S
A59: BIG C VIỆT TRÌ | B59: Đường Nguyễn Tất Thành, P. Thanh Miếu, TP. Việt Trì, Phú Thọ | C59: BVT-200601 | D59: BVT-200601-GE-S01 | E59: BẢO TRÌ MÁY PHÁT ĐIỆN | F59: Genset | G59: S | I59: 1 | J59: Maintenance | K59: Charge | L59: 44197 | M59: 44226 | N59: 44203 | O59: 44203 | P59: - Để đảm bảo hệ thống MFĐ h/đ ổn định hơn cần: + Sửa chữa, thay thế van báo mức dầu + Sửa chữa bơm dầu bằng tay + Sửa chữa hoặc thay thế đồng hồ mức dầu bình 20.000L + Thay van xả nước bầu lọc tách nước => Hệ thống MFĐ h/đ bình thường | R59: Hung2.nm, Hieu.nq, Tai.nt | T59: S
A60: BIG C VIỆT TRÌ | B60: Đường Nguyễn Tất Thành, P. Thanh Miếu, TP. Việt Trì, Phú Thọ | C60: BVT-200601 | D60: BVT-200601-GE-Q02 | E60: BẢO TRÌ MÁY PHÁT ĐIỆN | F60: Genset | G60: Q | I60: 1 | J60: Maintenance | K60: Charge | L60: 44287 | M60: 44316 | N60: 44302 | O60: 44302 | P60: - Bổ sung nước cất cho ắc quy - Ktra xác định nguyên nhân xử lý lỗi MFĐ khi có điện lưới trở lại mà không tự tắt máy - Để hệ thống h/đ tốt hơn, cần thay thế, sửa chữa đồng hồ báo mức dầu, phao báo mức dầu, bầu tách nước, bơm tay hở dầu => Sau khi bảo dưỡng, hệ thống MFĐ h/đ bình thường | R60: Hung2.nm, Hieu.nq, Vinh.dd | T60: S
A61: BIG C VĨNH PHÚC | B61: Phường Khai Quang, TP. Vĩnh Yên, Vĩnh Phúc | C61: BVP-200601 | D61: BVP-200601-GE-Y01 | E61: BẢO TRÌ MÁY PHÁT ĐIỆN | F61: Genset | G61: Y | I61: 1 | J61: Maintenance | K61: Charge | L61: 44013 | M61: 44042 | N61: 44034 | O61: 44034 | P61: - Giá đỡ đường ống dầu bị vỡ -> cần thay thế mới - MFĐ h/đ bình thường | Q61: Đề nghị nhà thầu gửi báo giá | R61: Hung2.nm, Thuong.mv | T61: S
A62: BIG C VĨNH PHÚC | B62: Phường Khai Quang, TP. Vĩnh Yên, Vĩnh Phúc | C62: BVP-200601 | D62: BVP-200601-GE-Q01 | E62: BẢO TRÌ MÁY PHÁT ĐIỆN | F62: Genset | G62: Q | I62: 1 | J62: Maintenance | K62: Charge | L62: 44105 | M62: 44134 | N62: 44131 | O62: 44131 | P62: - Xiết lại đường ống mềm đường nước do bị hở - Sau khi bảo dưỡng, hệ thống MFĐ h/đ bình thường | R62: Hung2.nm, Thuong.mv | T62: S
A63: BIG C VĨNH PHÚC | B63: Phường Khai Quang, TP. Vĩnh Yên, Vĩnh Phúc | C63: BVP-200601 | D63: BVP-200601-GE-S01 | E63: BẢO TRÌ MÁY PHÁT ĐIỆN | F63: Genset | G63: S | I63: 1 | J63: Maintenance | K63: Charge | L63: 44197 | M63: 44226 | N63: 44202 | O63: 44202 | P63: - Để MFĐ h/đ hiệu quả hơn cần thay thế giá đỡ đường ống dầu nhiên liệu. => Sau khi bảo dưỡng hệ thống MFĐ h/đ bình thường - Hướng gió tươi bị mục nát, có dấu hiệu phân chuột -> cần gia cố che chắn | Q63: Đề nghị SPS báo giá giá đỡ ống nhiên liệu để đc phê duyệt & thay thế sớm nhất - Sau khi bảo dưỡng, hệ thống h/đ bình thường | R63: Hung2.nm, Hieu.nq, Tai.nt | T63: S
A64: BIG C VĨNH PHÚC | B64: Phường Khai Quang, TP. Vĩnh Yên, Vĩnh Phúc | C64: BVP-200601 | D64: BVP-200601-GE-Q02 | E64: BẢO TRÌ MÁY PHÁT ĐIỆN | F64: Genset | G64: Q | I64: 1 | J64: Maintenance | K64: Charge | L64: 44287 | M64: 44316 | N64: 44301 | O64: 44301 | P64: - Hệ thống MFĐ h/đ bình thường - Giá đỡ đường ống nhiên liệu bị vỡ -> cần thay thế mới | R64: Hung2.nm, Hieu.nq | T64: S
A65: BỘ TƯ LỆNH THỦ ĐÔ | B65: Số 8 Phạm Hùng, Nam Từ Liêm, Hà Nội | C65: N/A | D65: N/A | E65: THANH DẪN ĐIỆN CHO HỆ ĐIỀU HÒA TẦNG 3 BỊ MẤT PHA | F65: Busway | G65: 1 times | I65: 1 Lot | J65: Trouble shooting | K65: Free | L65: 43737 | M65: 43737 | N65: 43737 | O65: 43737 | P65: Thanh dẫn điện cho hệ điều hòa tầng 3 bị mất pha => Kiểm tra Plug-in Box => Tiếp điểm và thanh cái bị đánh mòn do tiếp xúc kém => Đã vệ sinh tiếp điểm và thanh cái để hoạt động tạm thời => Cần có phương án kiểm tra bảo dưỡng để phát hiện kịp thời và thay thế những vị trí có nguy cơ sự cố | R65: Dien.hd, Hoang.v | T65: S
A66: BỘ TƯ LỆNH THỦ ĐÔ | B66: Số 8 Phạm Hùng, Nam Từ Liêm, Hà Nội | C66: N/A | D66: N/A | E66: SỰ CỐ THÀNH DẪN ĐIỆN CHO HỆ ĐIỀU HÒA TẦNG 3 BỊ MẤT PHANH | F66: Busway | G66: 1 times | I66: 1 Lot | J66: Trouble shooting | K66: Free | L66: 43737 | M66: 43737 | N66: 43737 | O66: 43737 | P66: Thanh dẫn điện cho hệ điều hòa tầng 3 bị mất phanh Kiểm tra Plug-in box -> tiếp điểm và thanh cài bị đánh mòn do tiếp xúc kém Đã vệ sinh tiếp điểm và thanh cài để hoạt động tạm thời => Cần có phương án kiểm tra bảo dưỡng để phát hiện kịp thời và thay thế những vị trí có nguy cơ sự cố | R66: Dien.hd, Hoang.v | T66: S
A67: BỘ TƯ LỆNH THỦ ĐÔ | B67: Số 8 Phạm Hùng, Nam Từ Liêm, Hà Nội | C67: BTD-190919-Rev1 | D67: BTD-190919-Rev1 | E67: Bảo trì hệ thống thanh dẫn điện | F67: Busway | G67: 1 times | I67: 1 Lot | J67: Services | K67: Charge | L67: 43755 | M67: =L67+30 -> 43785 | N67: 43764 | O67: 43772 | P67: Hệ thống Busway đã kiểm tra bảo dưỡng Có 18 thanh kẹp tiếp điểm tình trạng tiếp xúc kém cần thay thế Giá đỗ cố định hệ thống Busway tầng 1 có hiện tượng biến dạng cần sữa chữa thay thế | R67: Dien.hd, Ninh.tv, Hung.nm, Hieu.kv | T67: S
A68: BỘ TƯ LỆNH THỦ ĐÔ | B68: Số 8 Phạm Hùng, Nam Từ Liêm, Hà Nội | C68: BTD-191128 | D68: BTD-191128 | E68: BẢO TRÌ HỆ THỐNG THANH DẪN ĐIỆN | F68: Busway | G68: 1 times | I68: 1 Lot | J68: Services | K68: Charge | L68: 43805 | M68: =L68+60 -> 43865 | N68: 43764 | O68: 43772 | P68: Hệ thống buusway đã kiểm tra bảo dưỡng Có 18 thanh kẹp tiếp điểm tình trạng tiếp xúc kém cần thay thế Giá đỡ cố định hệ thống busway tầng 1 có hiện tượng biến dạng cần sửa chữa | R68: Dien.hd, Ninh.tv, Hung.nm, Hieu.kv | T68: S
A69: BỘ TƯ LỆNH THỦ ĐÔ | B69: Số 8 Phạm Hùng, Nam Từ Liêm, Hà Nội | C69: BTD-191128 | D69: BTD-191128 | E69: SỬA CHỮA HỆ THỐNG THANH DẪN ĐIỆN | F69: Busway | G69: 1 times | I69: 1 Lot | J69: Services | K69: Charge | L69: 43805 | M69: =L69+60 -> 43865 | N69: 43828 | O69: 43828 | P69: Sau khi thay thế kẹp busway hệ thống hoạt động bình thường Các hạng mục còn lại như: kẹp đôi, giá đỡ cố định, giá đỡ lò xo, khách hàng cân nhắc sửa chữa sớm để tránh sự cố ngoài mong muốn | R69: Dien.hd | T69: S
A70: BỘ TƯ LỆNH THỦ ĐÔ | B70: Số 8 Phạm Hùng, Nam Từ Liêm, Hà Nội | C70: N/A | D70: N/A | E70: SỰ CỐ MẤT PHA ĐIỆN | F70: Busway | G70: 1 times | I70: 1 Lot | J70: Services | K70: Free | L70: 43973 | M70: 43973 | N70: 43973 | O70: 43973 | P70: Điện tầng 1 tòa nhà A2 có hiện tượng mất pha Tháo hộp Plug in của thanh busway kiểm tra phát hiện kẹp thanh cái bị tiếp xúc kém. Đã thay kẹp mới (do khách hàng cung cấp) Hệ thống điện tầng 1 đã hoạt động bình thường | R70: Dien.hd, Dung.ct | T70: S
A71: BÙI THỊ XUÂN BUILDING | B71: 135 Bùi Thị Xuân, Hai Bà Trưng, Hà Nội | C71: TXB-191025-Rev2 | D71: TXB-191025-Rev2 | E71: BẢO TRÌ HỆ THỐNG TỦ ĐIỆN | F71: Electric | G71: Y | I71: 1 Lot | J71: Maintenance | K71: Charge | L71: 43797 | M71: 43800 | N71: 43797 | O71: 43800 | P71: Hệ thống tủ điện đã xuống cấp, cần sữa chữa hoặc thay thế tủ điện mới 02 tủ cấp nguồn cho điều hòa đang dùng tấm tôn che đậy Aptomat và thanh cài => không an toàn => cần thay thế bàng mica để đảm bảo an toàn cho con người và tránh chập cháy Tủ bơm nước sạch tầng hầm 2 cần thay thế tủ mới vì tủ quá cũ nát Khuyến cáo lắp thêm 01 Aptomat tổng bên trong tòa nhà, để tiện cho việc bảo trì sữa chữa và thay thế thiết bị Một số tủ có các đầu dây thừa, không biết dây đi đâu, không rõ cấp cho thiết bị nào => SPS đã cuốn băng dính và bó gọn lại Các tủ đã bảo trì và kiểm tra siết lại các điểm đấu nối tại các cầu đấu và các aptomat => Hiện tại hệ thống hoạt động bình thường. | R71: Hung.mn, Hiep.hs, Hoang.v | T71: S
A72: BÙI THỊ XUÂN BUILDING | B72: 135 Bùi Thị Xuân, Hai Bà Trưng, Hà Nội | C72: TXB-191214 | D72: TXB-191214 | E72: THAY THẾ MCCB CHO TỦ ĐIỆN TẦNG 5 | F72: MCCB | G72: 1 times | I72: 1 Lot | J72: Services | K72: Charge | L72: 43813 | M72: 43813 | N72: 43813 | O72: 43813 | P72: MCCB 3P 100A quá tải gây hỏng aptomat và đánh cháy đầu cos SPS đã tiến hành xử lý và thay mới MCCB 3P 100A mới, kẹp lại đầu cos Thiết bị hoạt động bình thường | R72: Dung.ta | T72: S
A73: BÙI THỊ XUÂN BUILDING | B73: 135 Bùi Thị Xuân, Hai Bà Trưng, Hà Nội | C73: TXB-191219-Rev1 | D73: TXB-191219-Rev1 | E73: THAY THẾ MIKA BẢO VỆ CHO TỦ ĐIỆN ĐIỀU HÒA | F73: AC | G73: 1 times | I73: 1 Lot | J73: Services | K73: Charge | L73: 43818 | M73: =L73+20 -> 43838 | N73: 43848 | O73: 43848 | P73: Thay thế Mika cho 2 tủ điện điều hòa => Hoàn thành công việc | R73: Hung2.nm, Hiep.hs | T73: S
A74: CENTRAL BUILDING | B74: 31 Hai Bà Trưng, Hoàn Kiếm, HN | C74: CBL-190912 | D74: CBL-190912 | E74: THAY THẾ ĐỒNG HỒ ĐO MỨC DẦU BỒN DẦU CHÍNH | F74: Genset | G74: 1 times | I74: 1 Lot | J74: Services | K74: Charge | L74: 43720 | M74: 43753 | N74: 43756 | O74: 43757 | P74: 1.Thay thế đồng hồ đo mức dầu bồn dầu chính 2.Chạy thử, bàn giao Nguồn cảnh báo Thấp < 10% Cao >90% => Đồng hồ mới thay hoạt động bình thường | R74: Manh.lh, Hieu.kv, Hung2.nm | T74: S
A75: CHUNG CƯ 282 LĨNH NAM | B75: 282 Lĩnh Nam, Hoàng Mai, Hà Nội | C75: 282-190518-Rev2 | D75: 282-190518-Rev2-FA-S01 | E75: BẢO TRÌ HỆ THỐNG PCCC | F75: Fire alarm | G75: S | I75: 1 Lot | J75: Maintenance | K75: Charge | L75: 43647 | M75: 43676 | N75: 43647 | O75: 43655 | P75: No1_ Đã kiểm tra bảo dưỡng các thiết bị đầu báo và tổ hợp chuông đèn; thay thế 08 đầu báo bị hỏng; sửa chữa các vị trí bị đứt dây các tầng 1,4,16; một số đèn báo bị hỏng cần thay thế (25VDC-5W); sửa một số lỗi của tủ báo cháy bọc gen cách điện cho dây bị hỏng vỏ cách điện; kiểm tra hoạt động của các thiết bị quạt hút, chuông đèn; hệ thống thang máy không có kết nối; với hệ thống báo cháy => Hệ thống báo cháy đã hết lỗi đang hoạt động bình thường No2_ Đã kiểm tra bảo dưỡng các thiết bị của hệ thiết bị của hệ thống báo cháy; sửa chữa các lỗi bị đứt dây tín hiệu tại các tầng 1,2,3,8,9,11,14,15; bọc gen cách điện cho dây tín hiệu trong tủ báo cháy; kiểm tra hoạt động của các thiết bị liên động: Quạt hút, chuông đèn (thang máy không có kết nối với hệ thống báo cháy); khu thương mại tầng 1 hiện không có dầu báo cháy (1 tổ hợp chuông đèn bị tháo ra đã bàn giao cho BQL); hệ thống báo cháy đã hết lỗi và hoạt động bình thường | R75: Dien.hd | T75: S
A76: CHUNG CƯ 282 LĨNH NAM | B76: 282 Lĩnh Nam, Hoàng Mai, Hà Nội | C76: 282-190518-Rev2 | D76: 282-190518-Rev2-FF-S01 | E76: BẢO TRÌ HỆ THỐNG PCCC | F76: Fire fighting | G76: S | I76: 1 Lot | J76: Maintenance | K76: Charge | L76: 43647 | M76: 43676 | N76: 43647 | O76: 43655 | P76: No1_Hệ thống bơm đã kiểm tra hoạt động bình thường No2_Hệ thống bơm đã kiểm tra hoạt động bình thường | R76: Dien.hd | T76: S
A77: CHUNG CƯ 282 LĨNH NAM | B77: 282 Lĩnh Nam, Hoàng Mai, Hà Nội | C77: 282-190518-Rev2 | D77: 282-190518-Rev2-VF-S01 | E77: BẢO TRÌ HỆ THỐNG PCCC | F77: Fan | G77: S | I77: 1 Lot | J77: Maintenance | K77: Charge | L77: 43647 | M77: 43676 | N77: 43647 | O77: 43655 | P77: No1_Quạt tăng áp đã kiểm tra hoạt động bình thường No2_Quạt tăng áp đã kiểm tra hoạt động bình thường | R77: Dien.hd | T77: S
A78: CHUNG CƯ 282 LĨNH NAM | B78: 282 Lĩnh Nam, Hoàng Mai, Hà Nội | C78: 282-200512-1 | D78: 282-200512-1-FA-S01 | E78: BẢO TRÌ HỆ THỐNG PCCC | F78: Fire alarm | G78: S | I78: 1 Lot | J78: Maintenance | K78: Charge | L78: 43984 | M78: 43992 | N78: 43984 | O78: 43992 | P78: Đã kiểm tra bảo trì hệ thống báo cháy Khu thương mại tầng 1 tòa nhà N02 thiếu 1 tổ hợp nút nhấn báo cháy cần bổ sung Tổng hợp 1 số thiết bị báo cháy đã kiểm tra: Đầu báo nhiệt: 57 Đầu báo khói: 200 Tổ hợp nút nhấn: 65 Tủ trung tâm: 02 Hệ thống sau bảo trì hoạt động bình thường | R78: Dien.hd, Hoang.v | T78: S | U78: Đợi thông tin từ BQL
A79: CHUNG CƯ 282 LĨNH NAM | B79: 282 Lĩnh Nam, Hoàng Mai, Hà Nội | C79: 282-200512-1 | D79: 282-200512-1-FF-S01 | E79: BẢO TRÌ HỆ THỐNG PCCC | F79: Fire fighting | G79: S | I79: 1 Lot | J79: Maintenance | K79: Charge | L79: 43984 | M79: 43994 | N79: 43984 | O79: 43994 | P79: Hệ thống bơm cứu hỏa đã kiểm tra bảo dưỡng. Hệ thống hoạt động bình thường '1 số đèn báo của tủ điều khiển hỏng đã thay thế | R79: Dien.hd, Hoang.v | T79: S | U79: Đợi thông tin từ BQL
A80: CHUNG CƯ 282 LĨNH NAM | B80: 282 Lĩnh Nam, Hoàng Mai, Hà Nội | C80: 282-200512-1 | D80: 282-200512-1-VF-S01 | E80: BẢO TRÌ HỆ THỐNG PCCC | F80: Fan | G80: S | I80: 1 Lot | J80: Maintenance | K80: Charge | L80: 43994 | M80: 43994 | N80: 43994 | O80: 43994 | P80: Hệ thống quạt ép gió cầu thang đã kiểm tra bảo dưỡng hoạt động bình thường Cần lắp đặt bổ sung thêm lưới bảo vệ cho lồng quạt để đảm bảo an toàn | R80: Dien.hd, Hoang.v, Hieu.nq | T80: S | U80: Đợi thông tin từ BQL
A81: CHUNG CƯ 282 LĨNH NAM | B81: 282 Lĩnh Nam, Hoàng Mai, Hà Nội | C81: 282-190711-Rev4 | D81: 282-190711-Rev4 | E81: LẮP ĐẶT HỆ THỐNG BÁO CHÁY CHO KHU THƯƠNG MẠI TẦNG 1 NHÀ NO2 | F81: Fire alarm | G81: 1 times | I81: 1 Lot | J81: Services | K81: Charge | L81: 43738 | M81: 43748 | N81: 43754 | O81: 43754 | P81: 1.Lắp đặt hệ thống báo cháy cho khu thương mại tầng 1 nhà N02 => chạy thử, bàn giao *Đã hoàn thành công việc lắp đặt *Đã kết nối với hệ thống chung => Hệ thống hoạt động bình thường | R81: Hung.nm | T81: S
A82: CHUNG CƯ 282 LĨNH NAM | B82: 282 Lĩnh Nam, Hoàng Mai, Hà Nội | C82: N/A | D82: N/A | E82: SỰ CỐ HỆ THỐNG BÁO CHÁY BÁO LỖI TẠI TỦ | F82: Fire alarm | G82: 1 times | I82: 1 Lot | J82: Trouble shooting | K82: Free | L82: 43875 | M82: 43875 | N82: 43875 | O82: 43875 | P82: Hệ thống báo cháy báo lỗi tại tủ -> Kiểm tra tình trạng tủ điều khiển phát hiện 1 điện trở cuối nguồn bị hỏng đã thay thế => Tủ báo cháy hoạt động bình thường | R82: Dien.hd | U82: KH không đánh giá mức độ hài lòng
A83: CHUNG CƯ 282 LĨNH NAM | B83: 282 Lĩnh Nam, Hoàng Mai, Hà Nội | C83: N/A | D83: N/A | E83: SỰ CỐ BÁO CHÁY | F83: Fire alarm | G83: 1 times | I83: 1 Lot | J83: Survey | K83: Free | L83: 43957 | M83: 43957 | N83: 43957 | O83: 43957 | P83: Nút nhấn báo cháy tầng 1 kho vật tư điện không kich hoạt được. SPS đã kiểm tra phát hiện nút nhấn bị cháy hỏng không kích hoạt được, đã tháo tạm nút nhấn trên mái xuống lắp tạm vào để kho vật tư thiết bị điện hoạt động lại bình thường Nút nhấn hoạt động bình thường | R83: Hung.nm | T83: S
A84: CHUNG CƯ 282 LĨNH NAM | B84: 282 Lĩnh Nam, Hoàng Mai, Hà Nội | C84: 282-200512-2 | D84: 282-200512-2-FA | E84: BẢO TRÌ HỆ THỐNG PCCC | F84: Fire alarm | G84: 1 times | I84: 1 | J84: Maintenance | K84: Charge | L84: 44166 | M84: =EOMONTH(L84,0) -> 44196 | N84: 44193 | O84: 44203 | P84: - Đã ktra bảo trì hệ thống báo cháy cả 2 tháp N01 & N02 -> Hệ thống h/đ bình thường 1. Tòa nhà N01: - Tầng 6 hỏng 1 đầu báo khói, đã thay thế đầu báo mới (sảnh thang máy) - 90% các tổ hợp báo cháy tại các tầng thiếu & cháy bun đèn -> cần lắp bổ sung & thay thế bun đèn mới 2. Tòa nhà N02: - Tầng 2 sảnh thang máy hỏng 1 đầu báo khói -> đã thay thế đầu báo mới - Tầng 9: cửa phòng 903 hỏng 1 đầu báo khói -> đã thay thế đầu báo mới - Tầng 15: hỏng 1 bun đèn -> cần thay thế - Tầng 4: thiếu 2 bun đèn -> cần thay thế => Tổng số thiết bị đã bảo trì cả 2 tòa: 63 đầu báo nhiệt, 194 đầu báo khói, 66 tổ hợp nút nhấn, 02 tủ điều khiển trung tâm | R84: Hung.nm, Cuong.dv, Diem.lv, Hoang.v | T84: S
A85: CHUNG CƯ 282 LĨNH NAM | B85: 282 Lĩnh Nam, Hoàng Mai, Hà Nội | C85: 282-200512-2 | D85: 282-200512-2-FF | E85: BẢO TRÌ HỆ THỐNG PCCC | F85: Fire fighting | G85: 1 times | I85: 1 | J85: Maintenance | K85: Charge | L85: 44166 | M85: =EOMONTH(L85,0) -> 44196 | N85: 44193 | O85: 44203 | P85: Hệ thống chữa cháy h/đ bình thường - Tháp N01: bơm bù áp vòng bi kêu to, có hiện tượng rò rỉ phớt trục -> cần thay thế vòng bi & phớt bơm | R85: Hung.nm, Cuong.dv, Diem.lv | T85: S
A86: CHUNG CƯ 282 LĨNH NAM | B86: 282 Lĩnh Nam, Hoàng Mai, Hà Nội | C86: 282-200512-2 | D86: 282-200512-2-VF | E86: BẢO TRÌ HỆ THỐNG PCCC | F86: Pressure fan, exhaust fan | G86: 1 times | I86: 1 | J86: Maintenance | K86: Charge | L86: 44166 | M86: =EOMONTH(L86,0) -> 44196 | N86: 44193 | O86: 44203 | P86: Hệ thống quạt hút khói h/đ bình thường - Tháp N01: cổ bạt mềm của quạt đã rách nát -> cần thay thế cổ bạt mới - Tháp N02: tủ điều khiển kg có chức năng chạy bằng tay, chỉ chạy đc tự động do tủ báo cháy điều khiển -> cần lắp thêm chuyển mạch, nút nhấn để tiện cho việc chạy thử & test quạt | R86: Hung.nm, Cuong.dv, Diem.lv | T86: S
A87: CHUNG CƯ N07 (B2 & B3) DỊCH VỌNG | B87: Thành Thái, Dịch Vọng, Cầu Giấy, Hà Nội | C87: N07-190806 | D87: N07-190806 | E87: BẢO TRÌ, ĐÁNH GIÁ HỆ THỐNG BÁO CHÁY | F87: Fire alarm | I87: 1 Lot | J87: Maintenance | K87: Charge | L87: 43701 | M87: =L87+60 -> 43761 | N87: 43717 | O87: 43780 | P87: Trạng thái hệ thống trước khi bảo trì: tủ FACP đã rút nguồn, ngưng hoạt động. Quá trình bảo trì: Tủ FACP đã được thay mới. Tủ FACP hiển thị rất nhiều lỗi trouble do nhiều zone đang báo lỗi thiếu thiết bị EOL, hoặc bị cắt bỏ dây dẫn đến không kết nối được với EOL, hoặc EOL bị hỏng. Một số đường dây bị nhiễu tín hiệu, hoặc đấu nối không đúng chuẩn, đo chân dương chiều đi và chân âm chiều về vẫn có nguồn mặc dù đã tách 2 dây chiều về tại tủ, dấn đến kích hoạt báo cháy giả. Một số tầng, dây tín hiệu bị tháo khỏi đầu báo. SPS đã kết nối lại. Tủ FACP sau khi kiểm tra phần mềm, phát hiện nhiều thiết bị đã bị xóa khỏi hệ thống. Một module điều khiển còi đèn từ tầng 12-15 bị tháo bỏ hoàn toàn, không tìm thấy dây tín hiệu để đấu lại. Đang để trong tủ module trên mái. Một module có địa chỉ 2, zone 6, loop 1 trong phòng bơm tầng hầm B2 khi kiểm tra lại có chú thích liên động còi đèn. Cần cập nhật địa chỉ và tên cho các thiết bị. Có 10 tấm kính của nút ấn báo cháy bị vỡ, nằm ngoài hợp đồng, cần thay thế. Sau căn hộ 1006 đang tháo bỏ dây cấp đến đầu báo do chập dây. Tầng 19, 18, 17, 13, 12, 9, 8, 4: thiểu module EOL. Tầng 21 và 2: thiếu module EOL cho module giám sát công tắc dòng chảy. Tầng 12: đầu báo trong căn hộ đang báo cháy giả, cần kiểm tra khoanh vùng sự cố. O857 Tầng 11 và 6: đang bị sụt áp chập dây đầu báo trong căn hộ. Đang cách ly khỏi hệ thống. Tầng 18 bị báo lỗi chạm đất, đã cách ly khỏi hệ thống. Tầng 1: các đầu báo thuộc module địa chỉ 8, loop 1, zone 1 đang cách ly module khỏi hệ thống do khi lắp vào bị kích hoạt báo cháy giả. Có 12/20 tầng, chuông báo cháy bị lắp ngược cơ khí, một số vị trí bị đấu ngược cực tính điện dẫn đến không kêu được. SPS đã sửa cho chuông hoạt động bình thường. O370 Liên động đến các hệ thống khác: Liên động báo cháy đến thang máy, quạt ép gió cầu thang hoạt động tốt. Nguồn cấp cho hệ thống chuông đèn và liên động báo cháy với quạt ép gió, thang máy, tủ điện phân phối không có acquy dự phòng, nếu mất điện thì các hệ thống này sẽ mất tác dụng. Đã bàn giao cho đại diện khách hàng 55 đầu báo khói hỏng và 23 đầu báo nhiệt hỏng. Các vị trí đầu báo tốt, không tiếp cận để bảo trì được do căn hộ cải tạo bịt kín, chưa vào được, mất nguồn cấp, mất đầu báo được mô tả trong bảng kê trước và sau khi bảo trì đính kèm. Trạng thái chung của hệ thống sau khi bảo trì: Tủ FACP đang báo: 0 cháy, 2 tiền báo động, 11 lỗi | R87: Manh.lh, Hung.nm, Hoang.v, Hiep.hs, Thuong.mv | T87: S
A88: CNC VINA | B88: Lô CN6, Trung tâm phát triển cụm công nghiệp, Bắc Từ Liêm, HN | C88: CNV-190702 | D88: CNV-190702 | E88: BẢO TRÌ VÀ SỬA CHỮA ĐIỀU HÒA | F88: AC | G88: 1 times | I88: 1 Lot | J88: Services | K88: Charge | L88: 43644 | M88: 43652 | N88: 43644 | O88: 43652 | P88: Điều hòa 1 số phòng kém mát, Bảo trì 17 máy điều hòa cục bộ, tháo dỡ 4 máy điều hòa, lắp đặt 3 máy điều hòa => 17 máy điều hòa hoạt động bình thường; có 8 máy điều hòa ở các phòng (P. Điều khiển tầng 1, phòng họp tầng 2, phòng kế toán tầng 3, phòng thiết kế cơ 2 máy, phòng server tầng 1, phòng hội trường tầng 4, phòng mua bán ở xưởng, bảo ôn cần chạy lại ống đồng và bảo ôn Yêu cầu báo giá thay bảo ôn ống đồng theo list kê trên | R88: Hiep.hs | T88: S
A89: CNC VINA | B89: Lô CN6, Trung tâm phát triển cụm công nghiệp, Bắc Từ Liêm, HN | C89: CNV-200603 | D89: CNV-200603 | E89: CÁC SỬA CHỮA NHỎ | F89: AC | G89: 1 times | I89: 1 Lot | J89: Trouble shooting | K89: Charge | L89: 43670 | M89: 43670 | N89: 43670 | O89: 43670 | P89: Máy nén điều hòa tầng 2 phòng mua bán không hoạt động => Kiểm tra phát hiện tụ của máy nén hỏng, thay tụ mới cho máy nén => Sau khi thực hiện điều hòa hoạt động bình thường | R89: ton.nd | T89: S
A90: CNC VINA | B90: Lô CN6, Trung tâm phát triển cụm công nghiệp, Bắc Từ Liêm, HN | C90: CNV-190909 | D90: CNV-190909 | E90: THAY THẾ ĐIỀU HÒA PHÒNG SERVER TẦNG 1 | F90: AC | G90: 1 times | I90: 1 Lot | J90: Services | K90: Charge | L90: 43717 | M90: =L90+9 -> 43726 | N90: 43722 | O90: 43722 | P90: Tháo 02 điều hòa: 1 máy tầng 4, 1 máy tầng 1,; Lắp đặt chạy thử và bàn giao 1 máy ở tầng 1 phòng Server => Máy lắp đặt hoạt động bình thường | R90: Hiep.hs, Ton.nd, Thuong.mv | T90: S
A91: CNC VINA | B91: Lô CN6, Trung tâm phát triển cụm công nghiệp, Bắc Từ Liêm, HN | C91: N/A | D91: N/A | E91: MÁY NÉN PHÒNG SERVER KHÔNG HOẠT ĐỘNG | F91: AC | G91: 1 times | I91: 1 Lot | J91: Trouble shooting | K91: Free | L91: 43715 | M91: =L91 -> 43715 | N91: 43715 | O91: =N91 -> 43715 | P91: Máy nén không chạy => Kiểm tra cuộn dây máy nén bị chạm vỏ => Máy nén bị hỏng, cần thay thế | R91: Ton.nd | T91: S
A92: CNC VINA | B92: Lô CN6, Trung tâm phát triển cụm công nghiệp, Bắc Từ Liêm, HN | C92: N/A | D92: N/A | E92: SỰ CỐ ĐIỀU HÒA CHẢY NƯỚC | F92: AC | G92: 1 times | I92: 1 Lot | J92: Trouble shooting | K92: Free | L92: 43759 | M92: 43759 | N92: 43759 | O92: 43759 | P92: *Điều hòa chảy nước ở giàn lạnh *Đường ống nước thải kê lên chân giá cục nóng bị văng giữa ống -> xử lý đường ống nước thải, thông ống => Sau khi xử lý xong đường ống nước ngưng đã thoát nước bình thường | R92: Ton.nd | T92: S
A93: CNC Vina | B93: Lô CN6, Trung tâm phát triển cụm công nghiệp, Bắc Từ Liêm, HN | C93: CNV-200410 | D93: CNV-200410 | E93: BẢO TRÌ HỆ THỐNG ĐIỀU HÒA | F93: AC | G93: 1 times | I93: 1 Lot | J93: Services | K93: Charge | L93: 43980 | M93: 43982 | N93: 43980 | O93: 43982 | P93: Đã xử lý 1 ống nước ngưng AC tầng 3 bị chuột cắn Bảo trì thêm 03 điều hòa giải nhiệt tủ điện DMG bảo trì thêm 1 chiller và 1 điều hòa một cục Điều hòa 1 cục không đủ công suất giải nhiệt cho tủ điện, cần thay thế điều hòa công suất lớn hơn | R93: Hiep.hs | T93: S
A94: CNC Vina | B94: Lô CN6, Trung tâm phát triển cụm công nghiệp, Bắc Từ Liêm, HN | C94: CNV-200410 | D94: CNV-200410 | E94: BẢO TRÌ HỆ THỐNG ĐIỀU HÒA | F94: AC | G94: 1 times | I94: 1 Lot | J94: Services | K94: Free | L94: 43983 | M94: 43983 | N94: 43983 | O94: 43983 | P94: Điều hòa bị kêu ở dàn lạnh Kiểm tra nguyên nhân kêu Kiểm tra và tra dầu bạc quạt dàn lạnh Hiện tại đã hết kêu, để chạy ổn định cần thay bạc mới | R94: Hiep.hs | T94: S
A95: CNC Vina | B95: Lô CN6, Trung tâm phát triển cụm công nghiệp, Bắc Từ Liêm, HN | C95: CNV-200603 | D95: CNV-200603 | E95: CÁC SỬA CHỮA NHỎ | F95: Other | G95: 1 times | I95: 1 Lot | J95: Services | K95: Charge | L95: 43985 | M95: 43985 | N95: 43985 | O95: 43985 | P95: Điều hòa không mát Kiểm tra phát hiện tụ của máy nén hỏng Thay tụ mới cho máy nén Sau khi sửa chửa xong điều hòa hoạt động bình thường | R95: Ton.nd | T95: S
A96: CNC VINA | B96: Số 9 ngõ 21, Lê Văn Lương, Hà Nội | C96: CNV-200602 | D96: CNV-200602 | E96: KIỂM TRA ĐIỀU HÒA NHÀ MR.VĂN | F96: AC | G96: 1 times | I96: 1 Lot | J96: Services | K96: Charge | L96: 43984 | M96: =L96+6 -> 43990 | N96: 43988 | O96: 43988 | T96: S
A97: CNC VINA | B97: Lô CN6, Trung tâm phát triển cụm công nghiệp, Bắc Từ Liêm, HN | C97: N/A | D97: N/A | E97: KIỂM TRA ĐIỀU HÒA | F97: AC | G97: 1 times | I97: 1 Lot | J97: Services | K97: Free | L97: 43990 | M97: 43990 | N97: 43990 | O97: 43990 | P97: Điều hòa CNC 09 không chạy Kiểm tra phát hiện quạt giải nhiệt bị hỏng Cần thay điều hòa mới loại 2 quạt riêng biệt nối ống gió vào cánh kẻ | R97: Ton.nd | T97: S
A98: CNC VINA | B98: Lô CN6, Trung tâm phát triển cụm công nghiệp, Bắc Từ Liêm, HN | C98: CNV-200806 | D98: CNV-200806 | E98: CÁC SỬA CHỮA NHỎ | F98: AC | G98: 1 times | I98: 1 Lot | J98: Services | K98: Charge | L98: 44011 | M98: 44011 | N98: 44011 | O98: 44011 | P98: -Điều hòa chạy lúc bị ngắt -Kiểm tra phát hiện tụ điện cho máy nén bị hỏng -Thay tụ điện mới cho máy nén -Sau khi sửa chữa xong điều hòa hoạt động bình thường | R98: Ton.nd, Dung.ct | T98: S
A99: CNC VINA | B99: Lô CN6, Trung tâm phát triển cụm công nghiệp, Bắc Từ Liêm, HN | C99: CNV-200806 | D99: CNV-200806 | E99: CÁC SỬA CHỮA NHỎ | F99: AC | G99: 1 times | I99: 1 | J99: Services | K99: Charge | L99: 44032 | M99: 44032 | N99: 44032 | O99: 44032 | P99: Điều hòa Phòng sản xuất tầng 1 chạy không mát -> Ktra điều hòa -> điều hòa bị hỏng tụ máy nén -> Thay tụ mới, chạy thử kiểm tra => Điều hòa h/đ bình thường, cần theo dõi thêm | R99: Hiep.hs | T99: S
A100: CNC VINA | B100: Lô CN6, Trung tâm phát triển cụm công nghiệp, Bắc Từ Liêm, HN | C100: CNV-200806 | D100: CNV-200806 | E100: CÁC SỬA CHỮA NHỎ | F100: AC | G100: 1 times | I100: 1 | J100: Services | K100: Charge | L100: 44056 | M100: 44056 | N100: 44056 | O100: 44056 | P100: Điều hòa hành lang tầng 2 - Điều hòa bị bắn nước từ cửa gió ra và có tiếng kêu trong dàn lạnh -> Ktra điều hòa thiếu gas, hỏng tụ quạt dàn lạnh -> Nạp bổ sung gas, ktra điểm hở, siết lại zăc co, thay tụ quạt dàn lạnh, chạy và theo dõi => Điều hòa đã h/đ bình thường | R100: Hiep.hs, Hieu.nq | T100: S
A101: CNC VINA | B101: Lô CN6, Trung tâm phát triển cụm công nghiệp, Bắc Từ Liêm, HN | C101: CNV-200806 | D101: CNV-200806 | E101: CÁC SỬA CHỮA NHỎ | F101: AC | G101: 1 times | I101: 1 | J101: Services | K101: Charge | L101: 44058 | M101: 44058 | N101: 44058 | O101: 44058 | P101: Điều hòa tầng 2 chảy nước ->Vệ sinh thông tắc đường ống thoát nước => Hệ thống điều hòa h/đ bình thường | R101: Tan.nm, Hung2.nm | T101: S
...

Sheet General (For monthly bonus)
G1: CHỈ SỐ HÀI LÒNG CỦA KHÁCH HÀNG | N1: Prepared by: | O1: Hang.ntt
G2: Customer Satisfaction Report | N2: Checked by: | O2: Phuc.vx
A3: SPS SERVICES.,JSC | F3: YEAR: | G3: 2023 | N3: Updated to: | O3: =TODAY() -> 46004
B4: Công thức trung gian lọc ra ngày cuối tháng | D4: 31 | E4: =DAY(EOMONTH(DATE(G3,E5,1),0)) -> 28 | F4: 31 | G4: 30 | H4: 31 | I4: 30 | J4: 31 | K4: 31 | L4: 30 | M4: 31 | N4: 30 | O4: 31
B5: THÁNG / MONTH | C5: Phân loại | D5: 1 | E5: 2 | F5: 3 | G5: 4 | H5: 5 | I5: 6 | J5: 7 | K5: 8 | L5: 9 | M5: 10 | N5: 11 | O5: 12 | P5: TOTAL | Q5: %
A6: REPORT | B6: SỐ BÁO CÁO THEO KẾ HOẠCH NUMBER OF REPORTS AS SCHEDULED | D6: =COUNTIFS('DATA (For monthly bonus)'!$M:$M,">="&DATE($G$3,D$5,1),'DATA (For monthly bonus)'!$M:$M,"<="&DATE($G$3,D$5,D$4)) -> 46 | E6: =COUNTIFS('DATA (For monthly bonus)'!$M:$M,">="&DATE($G$3,E$5,1),'DATA (For monthly bonus)'!$M:$M,"<="&DATE($G$3,E$5,E$4)) -> 77 | F6: =COUNTIFS('DATA (For monthly bonus)'!$M:$M,">="&DATE($G$3,F$5,1),'DATA (For monthly bonus)'!$M:$M,"<="&DATE($G$3,F$5,F$4)) -> 65 | G6: =COUNTIFS('DATA (For monthly bonus)'!$M:$M,">="&DATE($G$3,G$5,1),'DATA (For monthly bonus)'!$M:$M,"<="&DATE($G$3,G$5,G$4)) -> 53 | H6: =COUNTIFS('DATA (For monthly bonus)'!$M:$M,">="&DATE($G$3,H$5,1),'DATA (For monthly bonus)'!$M:$M,"<="&DATE($G$3,H$5,H$4)) -> 76 | I6: =COUNTIFS('DATA (For monthly bonus)'!$M:$M,">="&DATE($G$3,I$5,1),'DATA (For monthly bonus)'!$M:$M,"<="&DATE($G$3,I$5,I$4)) -> 40 | J6: =COUNTIFS('DATA (For monthly bonus)'!$M:$M,">="&DATE($G$3,J$5,1),'DATA (For monthly bonus)'!$M:$M,"<="&DATE($G$3,J$5,J$4)) -> 13 | K6: =COUNTIFS('DATA (For monthly bonus)'!$M:$M,">="&DATE($G$3,K$5,1),'DATA (For monthly bonus)'!$M:$M,"<="&DATE($G$3,K$5,K$4)) -> 31 | ... O6: =COUNTIFS('DATA (For monthly bonus)'!$M:$M,">="&DATE($G$3,O$5,1),'DATA (For monthly bonus)'!$M:$M,"<="&DATE($G$3,O$5,O$4)) -> 15 | P6: =SUM(D6:O6) -> 498 | Q6: 1
B7: SỐ BÁO CÁO ĐÃ NHẬN VỀ RECEIVED REPORTS | D7: =COUNTIFS('DATA (For monthly bonus)'!$O:$O,">0",'DATA (For monthly bonus)'!$M:$M,">="&DATE($G$3,D$5,1),'DATA (For monthly bonus)'!$M:$M,"<="&DATE($G$3,D$5,D$4)) -> 38 | E7: =COUNTIFS('DATA (For monthly bonus)'!$O:$O,">0",'DATA (For monthly bonus)'!$M:$M,">="&DATE($G$3,E$5,1),'DATA (For monthly bonus)'!$M:$M,"<="&DATE($G$3,E$5,E$4)) -> 1 | F7: =COUNTIFS('DATA (For monthly bonus)'!$O:$O,">0",'DATA (For monthly bonus)'!$M:$M,">="&DATE($G$3,F$5,1),'DATA (For monthly bonus)'!$M:$M,"<="&DATE($G$3,F$5,F$4)) -> 0 | G7: =COUNTIFS('DATA (For monthly bonus)'!$O:$O,">0",'DATA (For monthly bonus)'!$M:$M,">="&DATE($G$3,G$5,1),'DATA (For monthly bonus)'!$M:$M,"<="&DATE($G$3,G$5,G$4)) -> 0 | H7: =COUNTIFS('DATA (For monthly bonus)'!$O:$O,">0",'DATA (For monthly bonus)'!$M:$M,">="&DATE($G$3,H$5,1),'DATA (For monthly bonus)'!$M:$M,"<="&DATE($G$3,H$5,H$4)) -> 0 | I7: =COUNTIFS('DATA (For monthly bonus)'!$O:$O,">0",'DATA (For monthly bonus)'!$M:$M,">="&DATE($G$3,I$5,1),'DATA (For monthly bonus)'!$M:$M,"<="&DATE($G$3,I$5,I$4)) -> 0 | J7: =COUNTIFS('DATA (For monthly bonus)'!$O:$O,">0",'DATA (For monthly bonus)'!$M:$M,">="&DATE($G$3,J$5,1),'DATA (For monthly bonus)'!$M:$M,"<="&DATE($G$3,J$5,J$4)) -> 0 | K7: =COUNTIFS('DATA (For monthly bonus)'!$O:$O,">0",'DATA (For monthly bonus)'!$M:$M,">="&DATE($G$3,K$5,1),'DATA (For monthly bonus)'!$M:$M,"<="&DATE($G$3,K$5,K$4)) -> 0 | ... O7: =COUNTIFS('DATA (For monthly bonus)'!$O:$O,">0",'DATA (For monthly bonus)'!$M:$M,">="&DATE($G$3,O$5,1),'DATA (For monthly bonus)'!$M:$M,"<="&DATE($G$3,O$5,O$4)) -> 0 | P7: =SUM(D7:O7) -> 39 | Q7: =P7/P6 -> 0.078313253
B8: SỐ HẠNG MỤC CHƯA HOÀN THÀNH PENDING ITEMS | D8: =IF(TODAY()>DATE($G$3,D5,D4),D6-D7,0) -> 8 | E8: =IF(TODAY()>DATE($G$3,E5,E4),E6-E7,0) -> 76 | F8: =IF(TODAY()>DATE($G$3,F5,F4),F6-F7,0) -> 65 | G8: =IF(TODAY()>DATE($G$3,G5,G4),G6-G7,0) -> 53 | H8: =IF(TODAY()>DATE($G$3,H5,H4),H6-H7,0) -> 76 | I8: =IF(TODAY()>DATE($G$3,I5,I4),I6-I7,0) -> 40 | J8: =IF(TODAY()>DATE($G$3,J5,J4),J6-J7,0) -> 13 | K8: =IF(TODAY()>DATE($G$3,K5,K4),K6-K7,0) -> 31 | ... O8: =IF(TODAY()>DATE($G$3,O5,O4),O6-O7,0) -> 15 | P8: =SUM(D8:O8) -> 459 | Q8: =P8/P7 -> 11.769231
A9: CLIENT FEED BACK | B9: SỐ BÁO CÁO CÓ PHẢN HỒI KHÁCH HÀNG NUMBER OF REPORTS WITH CUSTOMER'S FEED BACK | D9: =SUM(D10:D13) -> 37 | E9: =SUM(E10:E13) -> 1 | F9: =SUM(F10:F13) -> 0 | G9: =SUM(G10:G13) -> 0 | H9: =SUM(H10:H13) -> 0 | I9: =SUM(I10:I13) -> 0 | J9: =SUM(J10:J13) -> 0 | K9: =SUM(K10:K13) -> 0 | ... O9: =SUM(O10:O13) -> 0 | P9: =SUM(D9:O9) -> 38 | Q9: =P9/P7 -> 0.97435897
B10: RẤT HÀI LÒNG EXCEEDED SATISFY | C10: E | D10: =COUNTIFS('DATA (For monthly bonus)'!$T:$T,"=E",'DATA (For monthly bonus)'!$O:$O,">="&DATE($G$3,D$5,1),'DATA (For monthly bonus)'!$O:$O,"<="&DATE($G$3,D$5,D$4)) -> 12 | E10: =COUNTIFS('DATA (For monthly bonus)'!$T:$T,"=E",'DATA (For monthly bonus)'!$O:$O,">="&DATE($G$3,E$5,1),'DATA (For monthly bonus)'!$O:$O,"<="&DATE($G$3,E$5,E$4)) -> 1 | F10: =COUNTIFS('DATA (For monthly bonus)'!$T:$T,"=E",'DATA (For monthly bonus)'!$O:$O,">="&DATE($G$3,F$5,1),'DATA (For monthly bonus)'!$O:$O,"<="&DATE($G$3,F$5,F$4)) -> 0 | G10: =COUNTIFS('DATA (For monthly bonus)'!$T:$T,"=E",'DATA (For monthly bonus)'!$O:$O,">="&DATE($G$3,G$5,1),'DATA (For monthly bonus)'!$O:$O,"<="&DATE($G$3,G$5,G$4)) -> 0 | H10: =COUNTIFS('DATA (For monthly bonus)'!$T:$T,"=E",'DATA (For monthly bonus)'!$O:$O,">="&DATE($G$3,H$5,1),'DATA (For monthly bonus)'!$O:$O,"<="&DATE($G$3,H$5,H$4)) -> 0 | I10: =COUNTIFS('DATA (For monthly bonus)'!$T:$T,"=E",'DATA (For monthly bonus)'!$O:$O,">="&DATE($G$3,I$5,1),'DATA (For monthly bonus)'!$O:$O,"<="&DATE($G$3,I$5,I$4)) -> 0 | J10: =COUNTIFS('DATA (For monthly bonus)'!$T:$T,"=E",'DATA (For monthly bonus)'!$O:$O,">="&DATE($G$3,J$5,1),'DATA (For monthly bonus)'!$O:$O,"<="&DATE($G$3,J$5,J$4)) -> 0 | K10: =COUNTIFS('DATA (For monthly bonus)'!$T:$T,"=E",'DATA (For monthly bonus)'!$O:$O,">="&DATE($G$3,K$5,1),'DATA (For monthly bonus)'!$O:$O,"<="&DATE($G$3,K$5,K$4)) -> 0 | ... O10: =COUNTIFS('DATA (For monthly bonus)'!$T:$T,"=E",'DATA (For monthly bonus)'!$O:$O,">="&DATE($G$3,O$5,1),'DATA (For monthly bonus)'!$O:$O,"<="&DATE($G$3,O$5,O$4)) -> 0 | P10: =SUM(D10:O10) -> 13 | Q10: =P10/$P$9 -> 0.34210526
B11: HÀI LÒNG SATISFIED | C11: S | D11: =COUNTIFS('DATA (For monthly bonus)'!$T:$T,"=S",'DATA (For monthly bonus)'!$O:$O,">="&DATE($G$3,D$5,1),'DATA (For monthly bonus)'!$O:$O,"<="&DATE($G$3,D$5,D$4)) -> 25 | E11: =COUNTIFS('DATA (For monthly bonus)'!$T:$T,"=S",'DATA (For monthly bonus)'!$O:$O,">="&DATE($G$3,E$5,1),'DATA (For monthly bonus)'!$O:$O,"<="&DATE($G$3,E$5,E$4)) -> 0 | F11: =COUNTIFS('DATA (For monthly bonus)'!$T:$T,"=S",'DATA (For monthly bonus)'!$O:$O,">="&DATE($G$3,F$5,1),'DATA (For monthly bonus)'!$O:$O,"<="&DATE($G$3,F$5,F$4)) -> 0 | G11: =COUNTIFS('DATA (For monthly bonus)'!$T:$T,"=S",'DATA (For monthly bonus)'!$O:$O,">="&DATE($G$3,G$5,1),'DATA (For monthly bonus)'!$O:$O,"<="&DATE($G$3,G$5,G$4)) -> 0 | H11: =COUNTIFS('DATA (For monthly bonus)'!$T:$T,"=S",'DATA (For monthly bonus)'!$O:$O,">="&DATE($G$3,H$5,1),'DATA (For monthly bonus)'!$O:$O,"<="&DATE($G$3,H$5,H$4)) -> 0 | I11: =COUNTIFS('DATA (For monthly bonus)'!$T:$T,"=S",'DATA (For monthly bonus)'!$O:$O,">="&DATE($G$3,I$5,1),'DATA (For monthly bonus)'!$O:$O,"<="&DATE($G$3,I$5,I$4)) -> 0 | J11: =COUNTIFS('DATA (For monthly bonus)'!$T:$T,"=S",'DATA (For monthly bonus)'!$O:$O,">="&DATE($G$3,J$5,1),'DATA (For monthly bonus)'!$O:$O,"<="&DATE($G$3,J$5,J$4)) -> 0 | K11: =COUNTIFS('DATA (For monthly bonus)'!$T:$T,"=S",'DATA (For monthly bonus)'!$O:$O,">="&DATE($G$3,K$5,1),'DATA (For monthly bonus)'!$O:$O,"<="&DATE($G$3,K$5,K$4)) -> 0 | ... O11: =COUNTIFS('DATA (For monthly bonus)'!$T:$T,"=S",'DATA (For monthly bonus)'!$O:$O,">="&DATE($G$3,O$5,1),'DATA (For monthly bonus)'!$O:$O,"<="&DATE($G$3,O$5,O$4)) -> 0 | P11: =SUM(D11:O11) -> 25 | Q11: =P11/$P$9 -> 0.65789474
B12: CHẤP NHẬN ACCEPTABLE | C12: A | D12: =COUNTIFS('DATA (For monthly bonus)'!$T:$T,"=A",'DATA (For monthly bonus)'!$O:$O,">="&DATE($G$3,D$5,1),'DATA (For monthly bonus)'!$O:$O,"<="&DATE($G$3,D$5,D$4)) -> 0 | E12: =COUNTIFS('DATA (For monthly bonus)'!$T:$T,"=A",'DATA (For monthly bonus)'!$O:$O,">="&DATE($G$3,E$5,1),'DATA (For monthly bonus)'!$O:$O,"<="&DATE($G$3,E$5,E$4)) -> 0 | F12: =COUNTIFS('DATA (For monthly bonus)'!$T:$T,"=A",'DATA (For monthly bonus)'!$O:$O,">="&DATE($G$3,F$5,1),'DATA (For monthly bonus)'!$O:$O,"<="&DATE($G$3,F$5,F$4)) -> 0 | G12: =COUNTIFS('DATA (For monthly bonus)'!$T:$T,"=A",'DATA (For monthly bonus)'!$O:$O,">="&DATE($G$3,G$5,1),'DATA (For monthly bonus)'!$O:$O,"<="&DATE($G$3,G$5,G$4)) -> 0 | H12: =COUNTIFS('DATA (For monthly bonus)'!$T:$T,"=A",'DATA (For monthly bonus)'!$O:$O,">="&DATE($G$3,H$5,1),'DATA (For monthly bonus)'!$O:$O,"<="&DATE($G$3,H$5,H$4)) -> 0 | I12: =COUNTIFS('DATA (For monthly bonus)'!$T:$T,"=A",'DATA (For monthly bonus)'!$O:$O,">="&DATE($G$3,I$5,1),'DATA (For monthly bonus)'!$O:$O,"<="&DATE($G$3,I$5,I$4)) -> 0 | J12: =COUNTIFS('DATA (For monthly bonus)'!$T:$T,"=A",'DATA (For monthly bonus)'!$O:$O,">="&DATE($G$3,J$5,1),'DATA (For monthly bonus)'!$O:$O,"<="&DATE($G$3,J$5,J$4)) -> 0 | K12: =COUNTIFS('DATA (For monthly bonus)'!$T:$T,"=A",'DATA (For monthly bonus)'!$O:$O,">="&DATE($G$3,K$5,1),'DATA (For monthly bonus)'!$O:$O,"<="&DATE($G$3,K$5,K$4)) -> 0 | ... O12: =COUNTIFS('DATA (For monthly bonus)'!$T:$T,"=A",'DATA (For monthly bonus)'!$O:$O,">="&DATE($G$3,O$5,1),'DATA (For monthly bonus)'!$O:$O,"<="&DATE($G$3,O$5,O$4)) -> 0 | P12: =SUM(D12:O12) -> 0 | Q12: =P12/$P$9 -> 0
B13: KHÔNG HÀI LÒNG DISSATISFIED | C13: D | D13: =COUNTIFS('DATA (For monthly bonus)'!$T:$T,"=D",'DATA (For monthly bonus)'!$O:$O,">="&DATE($G$3,D$5,1),'DATA (For monthly bonus)'!$O:$O,"<="&DATE($G$3,D$5,D$4)) -> 0 | E13: =COUNTIFS('DATA (For monthly bonus)'!$T:$T,"=D",'DATA (For monthly bonus)'!$O:$O,">="&DATE($G$3,E$5,1),'DATA (For monthly bonus)'!$O:$O,"<="&DATE($G$3,E$5,E$4)) -> 0 | F13: =COUNTIFS('DATA (For monthly bonus)'!$T:$T,"=D",'DATA (For monthly bonus)'!$O:$O,">="&DATE($G$3,F$5,1),'DATA (For monthly bonus)'!$O:$O,"<="&DATE($G$3,F$5,F$4)) -> 0 | G13: =COUNTIFS('DATA (For monthly bonus)'!$T:$T,"=D",'DATA (For monthly bonus)'!$O:$O,">="&DATE($G$3,G$5,1),'DATA (For monthly bonus)'!$O:$O,"<="&DATE($G$3,G$5,G$4)) -> 0 | H13: =COUNTIFS('DATA (For monthly bonus)'!$T:$T,"=D",'DATA (For monthly bonus)'!$O:$O,">="&DATE($G$3,H$5,1),'DATA (For monthly bonus)'!$O:$O,"<="&DATE($G$3,H$5,H$4)) -> 0 | I13: =COUNTIFS('DATA (For monthly bonus)'!$T:$T,"=D",'DATA (For monthly bonus)'!$O:$O,">="&DATE($G$3,I$5,1),'DATA (For monthly bonus)'!$O:$O,"<="&DATE($G$3,I$5,I$4)) -> 0 | J13: =COUNTIFS('DATA (For monthly bonus)'!$T:$T,"=D",'DATA (For monthly bonus)'!$O:$O,">="&DATE($G$3,J$5,1),'DATA (For monthly bonus)'!$O:$O,"<="&DATE($G$3,J$5,J$4)) -> 0 | K13: =COUNTIFS('DATA (For monthly bonus)'!$T:$T,"=D",'DATA (For monthly bonus)'!$O:$O,">="&DATE($G$3,K$5,1),'DATA (For monthly bonus)'!$O:$O,"<="&DATE($G$3,K$5,K$4)) -> 0 | ... O13: =COUNTIFS('DATA (For monthly bonus)'!$T:$T,"=D",'DATA (For monthly bonus)'!$O:$O,">="&DATE($G$3,O$5,1),'DATA (For monthly bonus)'!$O:$O,"<="&DATE($G$3,O$5,O$4)) -> 0 | P13: =SUM(D13:O13) -> 0 | Q13: =P13/$P$9 -> 0
A14: PERCENTAGE | B14: MỤC TIÊU MỨC ĐỘ HÀI LÒNG TARGET OF SATISFIED LEVEL | D14: 0.95 | E14: =$D$14 -> 0.95 | F14: =$D$14 -> 0.95 | G14: =$D$14 -> 0.95 | H14: =$D$14 -> 0.95 | I14: =$D$14 -> 0.95 | J14: =$D$14 -> 0.95 | K14: =$D$14 -> 0.95 | L14: =$D$14 -> 0.95 | ... P14: =$D$14 -> 0.95
B15: % MỨC ĐỘ HÀI LÒNG PERCENTAGE OF SATISFIED LEVEL | D15: =IF(D9>0,(D11+D10)/D9,"") -> 1 | E15: =IF(E9>0,(E11+E10)/E9,"") -> 1 | F15: =IF(F9>0,(F11+F10)/F9,"") | G15: =IF(G9>0,(G11+G10)/G9,"") | H15: =IF(H9>0,(H11+H10)/H9,"") | I15: =IF(I9>0,(I11+I10)/I9,"") | J15: =IF(J9>0,(J11+J10)/J9,"") | K15: =IF(K9>0,(K11+K10)/K9,"") | ... P15: =IF(P9>0,(P11+P10)/P9,"") -> 1
P16: =P15 -> 1

Sheet Monthly Staff Satisfaction (2)
C1: CHỈ SỐ HÀI LÒNG CỦA KHÁCH HÀNG ĐỐI VỚI NHÂN VIÊN
A2: SPS SERVICES.,JSC | C2: ASSESSMENT OF CUSTOMER SATISFACTION FOR EACH EMPLOYEES
B3: Từ ngày / From date: | C3: 44927 | D3: Tới / To: | E3: =EOMONTH(C3,0) -> 44957 | H3: Reported by: Hang.ntt
A4: Ghi chú: Số báo cáo một dịch vụ bằng tổng số người thực tế đi làm dịch vụ đó. Báo cáo không bao gồm thực tập sinh hoặc thầu phụ
A6: TT | B6: Tên nhân viên | C6: Tổng số báo cáo có phản hồi | D6: Rất hài lòng | E6: Hài lòng | F6: Chấp nhận | G6: Không hài lòng | H6: Điểm để so sánh | J6: Ký kiệu trung gian cho công thức tự động
A7: No | B7: Full Name | C7: Total report wt feedback | D7: Exceeded satisfy (E) | E7: Satisfied (S) | F7: Acceptable (A) | G7: Dissatisfied (D) | H7: Rating (Ex10+Sx1) | J7: Name for calculator
A8: 1 | B8: =VLOOKUP(J8, StaffList!B:C,2,FALSE) -> Lê Hùng Mạnh | C8: =SUM(D8:G8) -> 2 | D8: =COUNTIFS('DATA (For monthly bonus)'!$T:$T,"=E", 'DATA (For monthly bonus)'!$R:$R,$J:$J,'DATA (For monthly bonus)'!$O:$O,">="&$C$3,'DATA (For monthly bonus)'!$O:$O,"<="&$E$3) -> 1 | E8: =COUNTIFS('DATA (For monthly bonus)'!$T:$T,"=S", 'DATA (For monthly bonus)'!$R:$R,$J:$J,'DATA (For monthly bonus)'!$O:$O,">="&$C$3,'DATA (For monthly bonus)'!$O:$O,"<="&$E$3) -> 1 | F8: =COUNTIFS('DATA (For monthly bonus)'!$T:$T,"=A",'DATA (For monthly bonus)'!$R:$R,$J:$J,'DATA (For monthly bonus)'!$O:$O,">="&$C$3,'DATA (For monthly bonus)'!$O:$O,"<="&$E$3) -> 0 | G8: =COUNTIFS('DATA (For monthly bonus)'!$T:$T,"=D",'DATA (For monthly bonus)'!$R:$R,$J:$J,'DATA (For monthly bonus)'!$O:$O,">="&$C$3,'DATA (For monthly bonus)'!$O:$O,"<="&$E$3) -> 0 | H8: =D8*10+E8 -> 11 | J8: ="*"&StaffList!B5&"*" -> *Manh.lh*
A9: 2 | B9: =VLOOKUP(J9, StaffList!B:C,2,FALSE) -> Hà Đình Diên | C9: =SUM(D9:G9) -> 2 | D9: =COUNTIFS('DATA (For monthly bonus)'!$T:$T,"=E", 'DATA (For monthly bonus)'!$R:$R,$J:$J,'DATA (For monthly bonus)'!$O:$O,">="&$C$3,'DATA (For monthly bonus)'!$O:$O,"<="&$E$3) -> 2 | E9: =COUNTIFS('DATA (For monthly bonus)'!$T:$T,"=S", 'DATA (For monthly bonus)'!$R:$R,$J:$J,'DATA (For monthly bonus)'!$O:$O,">="&$C$3,'DATA (For monthly bonus)'!$O:$O,"<="&$E$3) -> 0 | F9: =COUNTIFS('DATA (For monthly bonus)'!$T:$T,"=A",'DATA (For monthly bonus)'!$R:$R,$J:$J,'DATA (For monthly bonus)'!$O:$O,">="&$C$3,'DATA (For monthly bonus)'!$O:$O,"<="&$E$3) -> 0 | G9: =COUNTIFS('DATA (For monthly bonus)'!$T:$T,"=D",'DATA (For monthly bonus)'!$R:$R,$J:$J,'DATA (For monthly bonus)'!$O:$O,">="&$C$3,'DATA (For monthly bonus)'!$O:$O,"<="&$E$3) -> 0 | H9: =D9*10+E9 -> 20 | J9: ="*"&StaffList!B6&"*" -> *Dien.hd*
A10: 3 | B10: =VLOOKUP(J10, StaffList!B:C,2,FALSE) -> Nguyễn Mạnh Hùng | C10: =SUM(D10:G10) -> 1 | D10: =COUNTIFS('DATA (For monthly bonus)'!$T:$T,"=E", 'DATA (For monthly bonus)'!$R:$R,$J:$J,'DATA (For monthly bonus)'!$O:$O,">="&$C$3,'DATA (For monthly bonus)'!$O:$O,"<="&$E$3) -> 0 | E10: =COUNTIFS('DATA (For monthly bonus)'!$T:$T,"=S", 'DATA (For monthly bonus)'!$R:$R,$J:$J,'DATA (For monthly bonus)'!$O:$O,">="&$C$3,'DATA (For monthly bonus)'!$O:$O,"<="&$E$3) -> 1 | F10: =COUNTIFS('DATA (For monthly bonus)'!$T:$T,"=A",'DATA (For monthly bonus)'!$R:$R,$J:$J,'DATA (For monthly bonus)'!$O:$O,">="&$C$3,'DATA (For monthly bonus)'!$O:$O,"<="&$E$3) -> 0 | G10: =COUNTIFS('DATA (For monthly bonus)'!$T:$T,"=D",'DATA (For monthly bonus)'!$R:$R,$J:$J,'DATA (For monthly bonus)'!$O:$O,">="&$C$3,'DATA (For monthly bonus)'!$O:$O,"<="&$E$3) -> 0 | H10: =D10*10+E10 -> 1 | J10: ="*"&StaffList!B7&"*" -> *Hung.nm*
A11: 4 | B11: =VLOOKUP(J11, StaffList!B:C,2,FALSE) -> #REF! | C11: =SUM(D11:G11) -> 0 | D11: =COUNTIFS('DATA (For monthly bonus)'!$T:$T,"=E", 'DATA (For monthly bonus)'!$R:$R,$J:$J,'DATA (For monthly bonus)'!$O:$O,">="&$C$3,'DATA (For monthly bonus)'!$O:$O,"<="&$E$3) -> 0 | E11: =COUNTIFS('DATA (For monthly bonus)'!$T:$T,"=S", 'DATA (For monthly bonus)'!$R:$R,$J:$J,'DATA (For monthly bonus)'!$O:$O,">="&$C$3,'DATA (For monthly bonus)'!$O:$O,"<="&$E$3) -> 0 | F11: =COUNTIFS('DATA (For monthly bonus)'!$T:$T,"=A",'DATA (For monthly bonus)'!$R:$R,$J:$J,'DATA (For monthly bonus)'!$O:$O,">="&$C$3,'DATA (For monthly bonus)'!$O:$O,"<="&$E$3) -> 0 | G11: =COUNTIFS('DATA (For monthly bonus)'!$T:$T,"=D",'DATA (For monthly bonus)'!$R:$R,$J:$J,'DATA (For monthly bonus)'!$O:$O,">="&$C$3,'DATA (For monthly bonus)'!$O:$O,"<="&$E$3) -> 0 | H11: =D11*10+E11 -> 0 | J11: ="*"&StaffList!#REF!&"*" -> #REF!
